Workbook
Name Ạ2: Portfolio!$AI$49
Name RPT: Report!$C$2
Name Yesterday: Report!$C$3

Sheet Log
A1: Ngày | B1: Log | C1: PIC
B2: Tạo file và các bảng query | C2: thaottp14
B3: Tạo code VBA và bảng lưu trữ rating lên 53 | C3: thaottp14
A4: 46157 | B4: Sửa query, sửa bảng tham chiếu do thay đổi folder | C4: thaottp14
A5: 46157 | B5: Thêm tenor, tenor ảnh hưởng call put | C5: thaottp14
A6: 46157 | B6: Thêm đối ứng, và tính lại tỷ lệ cho deal đối ứng | C6: thaottp14

Sheet Report
A1: STT | B1: Indicator | C1: Values | G1: 1. Thay đổi rating
A2: 1 | B2: RptDate | C2: 46268 | G2: Issuer code | H2: Issuer name | I2: New Rating FI | J2: Last Rating | K2: New Date Rating | L2: Last Date Rating
A3: 2 | B3: Raw data | C3: ="\\filesrv01.msb.com.vn\06.Khoi Quan Ly Rui Ro\02.Trung Tam QLRR Thi Truong\02.Phong GSRRTT\05.Report\01.Daily report\"&TEXT(RPT,"yyyy.mm.dd")&"\00.Input\00.Raw_Data.xlsm" -> \\filesrv01.msb.com.vn\06.Khoi Quan Ly Rui Ro\02.Trung Tam QLRR Thi Truong\02.Phong GSRRTT\05.Report\01.Daily report\2026.09.03\00.Input\00.Raw_Data.xlsm | G3: =_xlfn.XLOOKUP(H3,Rating!A:A,Rating!B:B,"",0) | H3: {=IFERROR(_xlfn._xlws.FILTER(Rating!A:A,Rating!N:N="Yes"),"")} | I3: =_xlfn.XLOOKUP(H3,Rating!A:A,Rating!D:D,"",0) | J3: =_xlfn.XLOOKUP(H4,Rating!S:S,Rating!U:U,"",0) -> 0 | K3: 46182
A4: 3 | B4: Tool FIBond | C4: ="\\filesrv01.msb.com.vn\06.Khoi Quan Ly Rui Ro\02.Trung Tam QLRR Thi Truong\02.Phong GSRRTT\05.Report\01.Daily Report\"&TEXT(RPT,"yyyy.mm.dd")&"\BOND\02.FI Bond\01.RptTool_FIBond_"&TEXT(RPT,"yyyy.mm.dd")&".xlsb" -> \\filesrv01.msb.com.vn\06.Khoi Quan Ly Rui Ro\02.Trung Tam QLRR Thi Truong\02.Phong GSRRTT\05.Report\01.Daily Report\2026.09.03\BOND\02.FI Bond\01.RptTool_FIBond_2026.09.03.xlsb | G4: =_xlfn.XLOOKUP(H4,Rating!A:A,Rating!B:B,"",0) -> 0 | I4: =_xlfn.XLOOKUP(H4,Rating!A:A,Rating!D:D,"",0) -> 0 | J4: =_xlfn.XLOOKUP(H4,Rating!S:S,Rating!U:U,"",0) -> 0 | K4: =_xlfn.XLOOKUP(H4,Rating!A:A,Rating!E:E,"",0) -> 0
A5: 4 | B5: Rating | C5: ="\\filesrv01.msb.com.vn\06.Khoi Quan Ly Rui Ro\02.Trung Tam QLRR Thi Truong\02.Phong GSRRTT\05.Report\02.Monthly Report\06. Bond Monthly\03.FIBond_Internal rating\Input\"&YEAR(RPT)&"\FI rating và External rating_"&TEXT(RPT,"yyyy.mm")&".xlsx" -> \\filesrv01.msb.com.vn\06.Khoi Quan Ly Rui Ro\02.Trung Tam QLRR Thi Truong\02.Phong GSRRTT\05.Report\02.Monthly Report\06. Bond Monthly\03.FIBond_Internal rating\Input\2026\FI rating và External rating_2026.09.xlsx
A6: 5 | B6: RPBOD3 | C6: ="\\filesrv01.msb.com.vn\06.Khoi Quan Ly Rui Ro\02.Trung Tam QLRR Thi Truong\02.Phong GSRRTT\05.Report\01.Daily report\"&TEXT(RPT,"yyyy.mm.dd")&"\00.Input\02.Kondor\RPBOD_B003.xlsx" -> \\filesrv01.msb.com.vn\06.Khoi Quan Ly Rui Ro\02.Trung Tam QLRR Thi Truong\02.Phong GSRRTT\05.Report\01.Daily report\2026.09.03\00.Input\02.Kondor\RPBOD_B003.xlsx
A7: 6 | B7: Backup | C7: ="\\filesrv01.msb.com.vn\06.Khoi Quan Ly Rui Ro\02.Trung Tam QLRR Thi Truong\02.Phong GSRRTT\05.Report\02.Monthly Report\06. Bond Monthly\03.FIBond_Internal rating\Backup\01.FIBond_Rating_"&TEXT(RPT,"yyyy.mm")&".xlsb" -> \\filesrv01.msb.com.vn\06.Khoi Quan Ly Rui Ro\02.Trung Tam QLRR Thi Truong\02.Phong GSRRTT\05.Report\02.Monthly Report\06. Bond Monthly\03.FIBond_Internal rating\Backup\01.FIBond_Rating_2026.09.xlsb
A8: 7 | B8: Tháng | C8: =MONTH(RPT-30) -> 8
A9: 8 | B9: Năm | C9: =YEAR(RPT-30) -> 2026 | G9: 2. Thay đổi ngày review, giữ nguyên rating (chủ yếu do đến tần suất review định kỳ 1 lần/năm)
A10: 9 | B10: Check | C10: =IF(AND(Portfolio!D10=Portfolio!B24,Portfolio!D10=Portfolio_by_issuer[[#Totals],[Total Amount]],Portfolio!D10=Portfolio!B24),"OK","CHECK") -> CHECK | G10: Issuer code | H10: Issuer name | I10: Rating FI | J10: New Date Rating | K10: Last Date Rating
A11: 10 | B11: FNRP BB MSB | C11: ="\\filesrv01.msb.com.vn\06.Khoi Quan Ly Rui Ro\02.Trung Tam QLRR Thi Truong\02.Phong GSRRTT\05.Report\01.Daily Report\"&TEXT(RPT,"yyyy.mm.dd")&"\00.Input\01.DataFile53\BondAllBS2BK.BondsSynthetic.csv" -> \\filesrv01.msb.com.vn\06.Khoi Quan Ly Rui Ro\02.Trung Tam QLRR Thi Truong\02.Phong GSRRTT\05.Report\01.Daily Report\2026.09.03\00.Input\01.DataFile53\BondAllBS2BK.BondsSynthetic.csv | G11: =_xlfn.XLOOKUP(H11,Rating!A:A,Rating!B:B,"",0) -> PBVN | H11: {=_xlfn._xlws.FILTER(Rating!A:A, (Rating!L:L="No") * (Rating!M:M="Yes"))} -> NGAN HANG TNHH MTV PUBLIC VN | I11: =_xlfn.XLOOKUP(H11,Rating!A:A,Rating!D:D,"",0) -> BB | J11: =_xlfn.XLOOKUP(H11,Rating!A:A,Rating!E:E,"",0) -> 46237 | K11: =_xlfn.XLOOKUP(H11,Rating!S:S,Rating!V:V,"",0) -> 45782
A12: 11 | B12: Tỷ giá | C12: 298.3522 | G12: =_xlfn.XLOOKUP(H12,Rating!A:A,Rating!B:B,"",0) -> SGTT | H12: NGAN HANG TMCP SAI GON TAI LOC | I12: =_xlfn.XLOOKUP(H12,Rating!A:A,Rating!D:D,"",0) -> A | J12: =_xlfn.XLOOKUP(H12,Rating!A:A,Rating!E:E,"",0) -> 46253 | K12: =_xlfn.XLOOKUP(H12,Rating!S:S,Rating!V:V,"",0) -> 0
G13: =_xlfn.XLOOKUP(H13,Rating!A:A,Rating!B:B,"",0) -> VNDIRECT | H13: CONG TY CP CHUNG KHOAN VNDIRECT | I13: =_xlfn.XLOOKUP(H13,Rating!A:A,Rating!D:D,"",0) -> AAA | J13: =_xlfn.XLOOKUP(H13,Rating!A:A,Rating!E:E,"",0) -> 46216 | K13: =_xlfn.XLOOKUP(H13,Rating!S:S,Rating!V:V,"",0) -> 45460
G14: =_xlfn.XLOOKUP(H14,Rating!A:A,Rating!B:B,"",0) -> PINETREE | H14: CONG TY CP CHUNG KHOAN PINETREE | I14: =_xlfn.XLOOKUP(H14,Rating!A:A,Rating!D:D,"",0) -> BBB | J14: =_xlfn.XLOOKUP(H14,Rating!A:A,Rating!E:E,"",0) -> 46231 | K14: =_xlfn.XLOOKUP(H14,Rating!S:S,Rating!V:V,"",0) -> 45866
G15: =_xlfn.XLOOKUP(H15,Rating!A:A,Rating!B:B,"",0) -> 0 | I15: =_xlfn.XLOOKUP(H15,Rating!A:A,Rating!D:D,"",0) -> 0 | J15: =_xlfn.XLOOKUP(H15,Rating!A:A,Rating!E:E,"",0) -> 0 | K15: =_xlfn.XLOOKUP(H15,Rating!S:S,Rating!V:V,"",0) -> 0
G16: =_xlfn.XLOOKUP(H16,Rating!A:A,Rating!B:B,"",0) -> 0 | I16: =_xlfn.XLOOKUP(H16,Rating!A:A,Rating!D:D,"",0) -> 0 | J16: =_xlfn.XLOOKUP(H16,Rating!A:A,Rating!E:E,"",0) -> 0 | K16: =_xlfn.XLOOKUP(H16,Rating!S:S,Rating!V:V,"",0) -> 0
G22: 3. Issuer mới được xếp hạng hoặc bị xóa xếp hạng
G23: Issuer code | H23: Issuer name | I23: Loại hình DN | J23: FI Rating | K23: Ngày xếp hạng | L23: Tổ chức xếp hạng | O23: Ngày xếp hạng
L24: Fitch | M24: Moody's | N24: S&P | O24: Fitch | P24: Moody's | Q24: S&P
G25: =_xlfn.XLOOKUP(H25,Rating!A:A,Rating!B:B,"",0) | H25: {=IFERROR(_xlfn._xlws.FILTER(Rating!A:A,Rating!N:N="Yes"),"")} | I25: =_xlfn.XLOOKUP(H25,Rating!A:A,Rating!C:C,"",0) | J25: =_xlfn.XLOOKUP(H25,Rating!A:A,Rating!D:D,"",0) | K25: 46182 | L25: =_xlfn.XLOOKUP(H25,Rating!A:A,Rating!F:F,"",0) | M25: =_xlfn.XLOOKUP(H25,Rating!A:A,Rating!H:H,"",0) | N25: =_xlfn.XLOOKUP(H25,Rating!A:A,Rating!J:J,"",0) | O25: =_xlfn.XLOOKUP(H25,Rating!A:A,Rating!G:G,"-",0) -> - | P25: =_xlfn.XLOOKUP(H25,Rating!A:A,Rating!I:I,"",0) | Q25: =_xlfn.XLOOKUP(H25,Rating!A:A,Rating!K:K,"",0)
G26: =_xlfn.XLOOKUP(H26,Rating!A:A,Rating!B:B,"",0) -> 0 | I26: =_xlfn.XLOOKUP(H26,Rating!A:A,Rating!C:C,"",0) -> 0 | J26: =_xlfn.XLOOKUP(H26,Rating!A:A,Rating!D:D,"",0) -> 0 | K26: =_xlfn.XLOOKUP(H26,Rating!A:A,Rating!E:E,"",0) -> 0 | L26: =_xlfn.XLOOKUP(H26,Rating!A:A,Rating!F:F,"",0) -> 0 | M26: =_xlfn.XLOOKUP(H26,Rating!A:A,Rating!H:H,"",0) -> 0 | N26: =_xlfn.XLOOKUP(H26,Rating!A:A,Rating!J:J,"",0) -> 0 | O26: =_xlfn.XLOOKUP(H26,Rating!A:A,Rating!G:G,"",0) -> 0 | P26: =_xlfn.XLOOKUP(H26,Rating!A:A,Rating!I:I,"",0) -> 0 | Q26: =_xlfn.XLOOKUP(H26,Rating!A:A,Rating!K:K,"",0) -> 0
L27: =_xlfn.XLOOKUP(H27,Rating!A:A,Rating!F:F,"",0) -> 0 | M27: =_xlfn.XLOOKUP(H27,Rating!A:A,Rating!H:H,"",0) -> 0 | N27: =_xlfn.XLOOKUP(H27,Rating!A:A,Rating!J:J,"",0) -> 0 | O27: =_xlfn.XLOOKUP(H27,Rating!A:A,Rating!G:G,"",0) -> 0 | P27: =_xlfn.XLOOKUP(H27,Rating!A:A,Rating!I:I,"",0) -> 0 | Q27: =_xlfn.XLOOKUP(H27,Rating!A:A,Rating!K:K,"",0) -> 0
L28: =_xlfn.XLOOKUP(H28,Rating!A:A,Rating!F:F,"",0) -> 0 | M28: =_xlfn.XLOOKUP(H28,Rating!A:A,Rating!H:H,"",0) -> 0 | N28: =_xlfn.XLOOKUP(H28,Rating!A:A,Rating!J:J,"",0) -> 0 | O28: =_xlfn.XLOOKUP(H28,Rating!A:A,Rating!G:G,"",0) -> 0 | P28: =_xlfn.XLOOKUP(H28,Rating!A:A,Rating!I:I,"",0) -> 0 | Q28: =_xlfn.XLOOKUP(H28,Rating!A:A,Rating!K:K,"",0) -> 0
L29: =_xlfn.XLOOKUP(H29,Rating!A:A,Rating!F:F,"",0) -> 0 | M29: =_xlfn.XLOOKUP(H29,Rating!A:A,Rating!H:H,"",0) -> 0 | N29: =_xlfn.XLOOKUP(H29,Rating!A:A,Rating!J:J,"",0) -> 0 | O29: =_xlfn.XLOOKUP(H29,Rating!A:A,Rating!G:G,"",0) -> 0 | P29: =_xlfn.XLOOKUP(H29,Rating!A:A,Rating!I:I,"",0) -> 0 | Q29: =_xlfn.XLOOKUP(H29,Rating!A:A,Rating!K:K,"",0) -> 0

Sheet Portfolio
A1: Internal Rating | B1: Haircut in Normal | C1: Haircut in Stress | D1: Sau khi điều chỉnh rating | G1: Trước khi điều chỉnh rating | J1: Outstandings By issuers | K1: Issuer | L1: Total Amount | M1: Rating | N1: Review Date | O1: Fitch Rating | P1: Moody Rating | Q1: S&P Rating | R1: Tỷ lệ lũy kế | S1: Last rating | T1: Tỷ lệ lũy kế | V1: Outstandings By bond | W1: Issuer | X1: Issuer_Name | Y1: Bond_Code | Z1: Tenor | AA1: Tenor (c/p) | AB1: Rating | AC1: Review Date | AD1: Fitch Rating | AE1: Moody Rating | AF1: S&P Rating | AG1: Total Amount | AH1: Tỷ lệ lũy kế | AI1: Amount adj đối ứng | AJ1: Tỷ lệ lũy kế | AK1: Tenor (ca/pu) | AM1: Row Labels | AN1: Sum of Total Amount | AP1: Row Labels | AQ1: Sum of Total Amount
D2: Bond Oustanding | E2: Tỷ lệ lũy kế | F2: Tỷ lệ lũy kế adj đối ứng | G2: Bond Oustanding | H2: Tỷ lệ lũy kế | J2: Tỷ lệ this rate | K2: VBAH | L2: 3000 | M2: AAA | N2: 46203 | P2: Ba2 | R2: =Portfolio_by_issuer[[#This Row],[Total Amount]]/Portfolio_by_issuer[[#Totals],[Total Amount]] -> 0.081679114 | S2: =_xlfn.XLOOKUP(Portfolio_by_issuer[[#This Row],[Issuer]],Rating!T:T,Rating!U:U,,0) -> AAA | T2: =Portfolio_by_issuer[[#This Row],[Total Amount]]/Portfolio_by_issuer[[#Totals],[Total Amount]] -> 0.081679114 | W2: HCVN | X2: CONG TY TAI CHINH TNHH MTV HOME CREDIT VN | Y2: HCVCD180926 | Z2: <1M | AB2: AAA | AC2: 46128 | AG2: 50 | AH2: =AG2/Portfolio_by_bond[[#Totals],[Total Amount]] -> 0.0013613364 | AI2: =Portfolio_by_bond[[#This Row],[Total Amount]]-_xlfn.XLOOKUP(Portfolio_by_bond[[#This Row],[Bond_Code]],'Ref'!F:F,'Ref'!G:G,0,0) -> 50 | AJ2: =AI2/(SUM(AI:AI)/2) -> 0.0017328851 | AK2: =IF(AA2="",Z2,AA2) -> <1M | AM2: <1M | AN2: 3350 | AP2: <1M | AQ2: 3350
A3: AAA | B3: 0.2 | C3: 0.19 | D3: =SUMIFS(L:L,M:M,A3) -> 8765 | E3: =_xlfn.MAXIFS(T:T,M:M,A3) -> 0.23863914 | F3: =SUMIFS(AI:AI,AB:AB,A3)/(SUM(AI:AI)/2) -> 0.30377476 | G3: =SUMIFS(L:L,S:S,A3) -> 8765 | H3: =_xlfn.MAXIFS(T:T,S:S,A3) -> 0.23863914 | J3: =_xlfn.MAXIFS(R:R,M:M,"BBB") -> 0.79991068 | K3: TCBV-HO | L3: 2300 | M3: AAA | N3: 46211 | R3: =R2+Portfolio_by_issuer[[#This Row],[Total Amount]]/Portfolio_by_issuer[[#Totals],[Total Amount]] -> 0.14429977 | S3: =_xlfn.XLOOKUP(Portfolio_by_issuer[[#This Row],[Issuer]],Rating!T:T,Rating!U:U,,0) -> AAA | T3: =T2+Portfolio_by_issuer[[#This Row],[Total Amount]]/Portfolio_by_issuer[[#Totals],[Total Amount]] -> 0.14429977 | W3: HCVN | X3: CONG TY TAI CHINH TNHH MTV HOME CREDIT VN | Y3: HCVCD231026 | Z3: 1-3M | AB3: AAA | AC3: 46128 | AG3: 200 | AH3: =AH2+AG3/Portfolio_by_bond[[#Totals],[Total Amount]] -> 0.006806682 | AI3: =Portfolio_by_bond[[#This Row],[Total Amount]]-_xlfn.XLOOKUP(Portfolio_by_bond[[#This Row],[Bond_Code]],'Ref'!F:F,'Ref'!G:G,0,0) -> 200 | AJ3: =AJ2+AI3/(SUM(AI:AI)/2) -> 0.0086644257 | AK3: =IF(AA3="",Z3,AA3) -> 1-3M | AM3: 1-2Y | AN3: 700 | AP3: 1-2Y | AQ3: 1700
A4: AA | B4: 0.2 | C4: 0.2 | D4: =SUMIFS(L:L,M:M,A4) -> 6344.6106 | E4: =_xlfn.MAXIFS(T:T,M:M,A4) -> 0.41137987 | F4: =F3+SUMIFS(AI:AI,AB:AB,A4)/(SUM(AI:AI)/2) -> 0.47167784 | G4: =SUMIFS(L:L,S:S,A4) -> 6344.6106 | H4: =_xlfn.MAXIFS(T:T,S:S,A4) -> 0.41137987 | J4: Tỷ lệ last rate | K4: HCVN | L4: 2250 | M4: AAA | N4: 46128 | R4: =R3+Portfolio_by_issuer[[#This Row],[Total Amount]]/Portfolio_by_issuer[[#Totals],[Total Amount]] -> 0.2055591 | S4: =_xlfn.XLOOKUP(Portfolio_by_issuer[[#This Row],[Issuer]],Rating!T:T,Rating!U:U,,0) -> AAA | T4: =T3+Portfolio_by_issuer[[#This Row],[Total Amount]]/Portfolio_by_issuer[[#Totals],[Total Amount]] -> 0.2055591 | W4: HCVN | X4: CONG TY TAI CHINH TNHH MTV HOME CREDIT VN | Y4: HCVNCD190427 | Z4: 6M-1Y | AB4: AAA | AC4: 46128 | AG4: 400 | AH4: =AH3+AG4/Portfolio_by_bond[[#Totals],[Total Amount]] -> 0.017697373 | AI4: =Portfolio_by_bond[[#This Row],[Total Amount]]-_xlfn.XLOOKUP(Portfolio_by_bond[[#This Row],[Bond_Code]],'Ref'!F:F,'Ref'!G:G,0,0) -> 400 | AJ4: =AJ3+AI4/(SUM(AI:AI)/2) -> 0.022527507 | AK4: =IF(AA4="",Z4,AA4) -> 6M-1Y | AM4: 1-3M | AN4: 7950 | AP4: 1-3M | AQ4: 7950
A5: A | B5: 0.2 | C5: 0.23 | D5: =SUMIFS(L:L,M:M,A5) -> 8200 | E5: =_xlfn.MAXIFS(T:T,M:M,A5) -> 0.63463611 | F5: =F4+SUMIFS(AI:AI,AB:AB,A5)/(SUM(AI:AI)/2) -> 0.755871 | G5: =SUMIFS(L:L,S:S,A5) -> 8200 | H5: =_xlfn.MAXIFS(T:T,S:S,A5) -> 0.63463611 | J5: =_xlfn.MAXIFS(T:T,S:S,"BBB") -> 0.79991068 | K5: MCSB | L5: 1215 | M5: AAA | N5: 46136 | O5: BB | P5: Ba2 | R5: =R4+Portfolio_by_issuer[[#This Row],[Total Amount]]/Portfolio_by_issuer[[#Totals],[Total Amount]] -> 0.23863914 | S5: =_xlfn.XLOOKUP(Portfolio_by_issuer[[#This Row],[Issuer]],Rating!T:T,Rating!U:U,,0) -> AAA | T5: =T4+Portfolio_by_issuer[[#This Row],[Total Amount]]/Portfolio_by_issuer[[#Totals],[Total Amount]] -> 0.23863914 | W5: HCVN | X5: CONG TY TAI CHINH TNHH MTV HOME CREDIT VN | Y5: HCV12502 | Z5: 6M-1Y | AB5: AAA | AC5: 46128 | AG5: 400 | AH5: =AH4+AG5/Portfolio_by_bond[[#Totals],[Total Amount]] -> 0.028588064 | AI5: =Portfolio_by_bond[[#This Row],[Total Amount]]-_xlfn.XLOOKUP(Portfolio_by_bond[[#This Row],[Bond_Code]],'Ref'!F:F,'Ref'!G:G,0,0) -> 400 | AJ5: =AJ4+AI5/(SUM(AI:AI)/2) -> 0.036390588 | AK5: =IF(AA5="",Z5,AA5) -> 6M-1Y | AM5: 2-3Y | AN5: 3000 | AP5: 3-6M | AQ5: 3172
A6: BBB | B6: 0.2 | C6: 0.26 | D6: =SUMIFS(L:L,M:M,A6) -> 6070.3854 | E6: =_xlfn.MAXIFS(T:T,M:M,A6) -> 0.79991068 | F6: =F5+SUMIFS(AI:AI,AB:AB,A6)/(SUM(AI:AI)/2) -> 0.77319985 | G6: =SUMIFS(L:L,S:S,A6) -> 6070.3854 | H6: =_xlfn.MAXIFS(T:T,S:S,A6) -> 0.79991068 | K6: HDBV | L6: 2697.6106 | M6: AA | N6: 46022 | P6: B1 | R6: =R5+Portfolio_by_issuer[[#This Row],[Total Amount]]/Portfolio_by_issuer[[#Totals],[Total Amount]] -> 0.31208529 | S6: =_xlfn.XLOOKUP(Portfolio_by_issuer[[#This Row],[Issuer]],Rating!T:T,Rating!U:U,,0) -> AA | T6: =T5+Portfolio_by_issuer[[#This Row],[Total Amount]]/Portfolio_by_issuer[[#Totals],[Total Amount]] -> 0.31208529 | W6: HCVN | X6: CONG TY TAI CHINH TNHH MTV HOME CREDIT VN | Y6: HCVL12606 | Z6: 1-2Y | AB6: AAA | AC6: 46128 | AG6: 200 | AH6: =AH5+AG6/Portfolio_by_bond[[#Totals],[Total Amount]] -> 0.03403341 | AI6: =Portfolio_by_bond[[#This Row],[Total Amount]]-_xlfn.XLOOKUP(Portfolio_by_bond[[#This Row],[Bond_Code]],'Ref'!F:F,'Ref'!G:G,0,0) -> 200 | AJ6: =AJ5+AI6/(SUM(AI:AI)/2) -> 0.043322128 | AK6: =IF(AA6="",Z6,AA6) -> 1-2Y | AM6: 3-6M | AN6: 3172 | AP6: 6M-1Y | AQ6: 17986.711
A7: BB | B7: 0.2 | C7: 0.36 | D7: =SUMIFS(L:L,M:M,A7) -> 5850 | E7: =_xlfn.MAXIFS(T:T,M:M,A7) -> 0.95918495 | F7: =F6+SUMIFS(AI:AI,AB:AB,A7)/(SUM(AI:AI)/2) -> 0.97594741 | G7: =SUMIFS(L:L,S:S,A7) -> 5850 | H7: =_xlfn.MAXIFS(T:T,S:S,A7) -> 0.95918495 | K7: ACBV | L7: 1400 | M7: AA | N7: 46203 | O7: BB- | P7: Ba3 | R7: =R6+Portfolio_by_issuer[[#This Row],[Total Amount]]/Portfolio_by_issuer[[#Totals],[Total Amount]] -> 0.35020221 | S7: =_xlfn.XLOOKUP(Portfolio_by_issuer[[#This Row],[Issuer]],Rating!T:T,Rating!U:U,,0) -> AA | T7: =T6+Portfolio_by_issuer[[#This Row],[Total Amount]]/Portfolio_by_issuer[[#Totals],[Total Amount]] -> 0.35020221 | W7: HCVN | X7: CONG TY TAI CHINH TNHH MTV HOME CREDIT VN | Y7: HCV12602 | Z7: 2-3Y | AB7: AAA | AC7: 46128 | AG7: 1000 | AH7: =AH6+AG7/Portfolio_by_bond[[#Totals],[Total Amount]] -> 0.061260138 | AI7: =Portfolio_by_bond[[#This Row],[Total Amount]]-_xlfn.XLOOKUP(Portfolio_by_bond[[#This Row],[Bond_Code]],'Ref'!F:F,'Ref'!G:G,0,0) -> 1000 | AJ7: =AJ6+AI7/(SUM(AI:AI)/2) -> 0.077979831 | AK7: =IF(AA7="",Z7,AA7) -> 2-3Y | AM7: 5-7Y | AN7: 3897.6106 | AP7: 2-3Y | AQ7: 1000
A8: B | B8: 0.2 | C8: 0.52 | D8: =SUMIFS(L:L,M:M,A8) -> 1000 | E8: 0.98 | F8: 0.99 | G8: =SUMIFS(L:L,S:S,A8) -> 1000 | H8: 0.99 | K8: LVBT | L8: 1000 | M8: AA | N8: 46199 | P8: Ba3 | R8: =R7+Portfolio_by_issuer[[#This Row],[Total Amount]]/Portfolio_by_issuer[[#Totals],[Total Amount]] -> 0.37742858 | S8: =_xlfn.XLOOKUP(Portfolio_by_issuer[[#This Row],[Issuer]],Rating!T:T,Rating!U:U,,0) -> AA | T8: =T7+Portfolio_by_issuer[[#This Row],[Total Amount]]/Portfolio_by_issuer[[#Totals],[Total Amount]] -> 0.37742858 | W8: MCSB | X8: NGAN HANG TMCP QUAN DOI | Y8: MBBOND2027 | Z8: 1-2Y | AB8: AAA | AC8: 46136 | AD8: BB | AE8: Ba2 | AG8: 500 | AH8: =AH7+AG8/Portfolio_by_bond[[#Totals],[Total Amount]] -> 0.074873502 | AI8: =Portfolio_by_bond[[#This Row],[Total Amount]]-_xlfn.XLOOKUP(Portfolio_by_bond[[#This Row],[Bond_Code]],'Ref'!F:F,'Ref'!G:G,0,0) -> 500 | AJ8: =AJ7+AI8/(SUM(AI:AI)/2) -> 0.095308683 | AK8: =IF(AA8="",Z8,AA8) -> 1-2Y | AM8: 6M-1Y | AN8: 14089.1 | AP8: 3-5Y | AQ8: 569.90402
A9: D | B9: 0.2 | C9: 0.52 | D9: =SUMIFS(L:L,M:M,A9) -> 499.1 | E9: 1 | F9: 1 | G9: =SUMIFS(L:L,S:S,A9) -> 499.1 | H9: 1 | K9: TC_DIENLUC | L9: 847 | M9: AA | N9: 46164 | P9: B2 | R9: =R8+Portfolio_by_issuer[[#This Row],[Total Amount]]/Portfolio_by_issuer[[#Totals],[Total Amount]] -> 0.40048932 | S9: =_xlfn.XLOOKUP(Portfolio_by_issuer[[#This Row],[Issuer]],Rating!T:T,Rating!U:U,,0) -> AA | T9: =T8+Portfolio_by_issuer[[#This Row],[Total Amount]]/Portfolio_by_issuer[[#Totals],[Total Amount]] -> 0.40048932 | W9: MCSB | X9: NGAN HANG TMCP QUAN DOI | Y9: MBBCD040227 | Z9: 3-6M | AB9: AAA | AC9: 46136 | AD9: BB | AE9: Ba2 | AG9: 715 | AH9: =AH8+AG9/Portfolio_by_bond[[#Totals],[Total Amount]] -> 0.094340613 | AI9: =Portfolio_by_bond[[#This Row],[Total Amount]]-_xlfn.XLOOKUP(Portfolio_by_bond[[#This Row],[Bond_Code]],'Ref'!F:F,'Ref'!G:G,0,0) -> 715 | AJ9: =AJ8+AI9/(SUM(AI:AI)/2) -> 0.12008894 | AK9: =IF(AA9="",Z9,AA9) -> 3-6M | AM9: 3-5Y | AN9: 569.90402 | AP9: 5-7Y | AQ9: 1000
A10: Grand Total | D10: =SUM(D3:D9) -> 36729.096 | E10: =E9 -> 1 | F10: =F9 -> 1 | G10: =SUM(G3:G9) -> 36729.096 | H10: =H9 -> 1 | K10: VPVN | L10: 400 | M10: AA | N10: 46142 | P10: Ba3 | R10: =R9+Portfolio_by_issuer[[#This Row],[Total Amount]]/Portfolio_by_issuer[[#Totals],[Total Amount]] -> 0.41137987 | S10: =_xlfn.XLOOKUP(Portfolio_by_issuer[[#This Row],[Issuer]],Rating!T:T,Rating!U:U,,0) -> AA | T10: =T9+Portfolio_by_issuer[[#This Row],[Total Amount]]/Portfolio_by_issuer[[#Totals],[Total Amount]] -> 0.41137987 | W10: TCBV-HO | X10: NGAN HANG TMCP KY THUONG VN | Y10: TCBCD0251226 | Z10: 3-6M | AB10: AAA | AC10: 46211 | AG10: 300 | AH10: =AH9+AG10/Portfolio_by_bond[[#Totals],[Total Amount]] -> 0.10250863 | AI10: =Portfolio_by_bond[[#This Row],[Total Amount]]-_xlfn.XLOOKUP(Portfolio_by_bond[[#This Row],[Bond_Code]],'Ref'!F:F,'Ref'!G:G,0,0) -> 300 | AJ10: =AJ9+AI10/(SUM(AI:AI)/2) -> 0.13048625 | AK10: =IF(AA10="",Z10,AA10) -> 3-6M | AM10: Grand Total | AN10: 36728.615 | AP10: Grand Total | AQ10: 36728.615
K11: SGTT | L11: 3700 | M11: A | N11: 46253 | O11: BB- | P11: B1 | R11: =R10+Portfolio_by_issuer[[#This Row],[Total Amount]]/Portfolio_by_issuer[[#Totals],[Total Amount]] -> 0.51211744 | S11: =_xlfn.XLOOKUP(Portfolio_by_issuer[[#This Row],[Issuer]],Rating!T:T,Rating!U:U,,0) -> A | T11: =T10+Portfolio_by_issuer[[#This Row],[Total Amount]]/Portfolio_by_issuer[[#Totals],[Total Amount]] -> 0.51211744 | W11: TCBV-HO | X11: NGAN HANG TMCP KY THUONG VN | Y11: TCB12603 | Z11: 2-3Y | AA11: 6M-1Y | AB11: AAA | AC11: 46211 | AG11: 2000 | AH11: =AH10+AG11/Portfolio_by_bond[[#Totals],[Total Amount]] -> 0.15696209 | AI11: =Portfolio_by_bond[[#This Row],[Total Amount]]-_xlfn.XLOOKUP(Portfolio_by_bond[[#This Row],[Bond_Code]],'Ref'!F:F,'Ref'!G:G,0,0) -> 2000 | AJ11: =AJ10+AI11/(SUM(AI:AI)/2) -> 0.19980166 | AK11: =IF(AA11="",Z11,AA11) -> 6M-1Y
K12: SABH | L12: 3000 | M12: A | N12: 46141 | O12: B+ | P12: B2 | R12: =R11+Portfolio_by_issuer[[#This Row],[Total Amount]]/Portfolio_by_issuer[[#Totals],[Total Amount]] -> 0.59379655 | S12: =_xlfn.XLOOKUP(Portfolio_by_issuer[[#This Row],[Issuer]],Rating!T:T,Rating!U:U,,0) -> A | T12: =T11+Portfolio_by_issuer[[#This Row],[Total Amount]]/Portfolio_by_issuer[[#Totals],[Total Amount]] -> 0.59379655 | W12: VBAH | X12: NGAN HANG NONG NGHIEP VA PHAT TRIEN NONG THON | Y12: VBA12503 | Z12: 6M-1Y | AB12: AAA | AC12: 46203 | AE12: Ba2 | AG12: 3000 | AH12: =AH11+AG12/Portfolio_by_bond[[#Totals],[Total Amount]] -> 0.23864227 | AI12: =Portfolio_by_bond[[#This Row],[Total Amount]]-_xlfn.XLOOKUP(Portfolio_by_bond[[#This Row],[Bond_Code]],'Ref'!F:F,'Ref'!G:G,0,0) -> 3000 | AJ12: =AJ11+AI12/(SUM(AI:AI)/2) -> 0.30377476 | AK12: =IF(AA12="",Z12,AA12) -> 6M-1Y
A13: Tenor | B13: Amount | C13: Amount (c/p) | K13: SHBV | L13: 1500 | M13: A | N13: 46211 | O13: BB- | P13: B1 | R13: =R12+Portfolio_by_issuer[[#This Row],[Total Amount]]/Portfolio_by_issuer[[#Totals],[Total Amount]] -> 0.63463611 | S13: =_xlfn.XLOOKUP(Portfolio_by_issuer[[#This Row],[Issuer]],Rating!T:T,Rating!U:U,,0) -> A | T13: =T12+Portfolio_by_issuer[[#This Row],[Total Amount]]/Portfolio_by_issuer[[#Totals],[Total Amount]] -> 0.63463611 | W13: ACBV | X13: NGAN HANG TMCP A CHAU | Y13: ACBCD140127 | Z13: 3-6M | AB13: AA | AC13: 46203 | AD13: BB- | AE13: Ba3 | AG13: 300 | AH13: =AH12+AG13/Portfolio_by_bond[[#Totals],[Total Amount]] -> 0.24681029 | AI13: =Portfolio_by_bond[[#This Row],[Total Amount]]-_xlfn.XLOOKUP(Portfolio_by_bond[[#This Row],[Bond_Code]],'Ref'!F:F,'Ref'!G:G,0,0) -> 300 | AJ13: =AJ12+AI13/(SUM(AI:AI)/2) -> 0.31417208 | AK13: =IF(AA13="",Z13,AA13) -> 3-6M
K14: NABV | L14: 3000 | M14: BBB | N14: 46146 | O14: B+ | R14: =R13+Portfolio_by_issuer[[#This Row],[Total Amount]]/Portfolio_by_issuer[[#Totals],[Total Amount]] -> 0.71631522 | S14: =_xlfn.XLOOKUP(Portfolio_by_issuer[[#This Row],[Issuer]],Rating!T:T,Rating!U:U,,0) -> BBB | T14: =T13+Portfolio_by_issuer[[#This Row],[Total Amount]]/Portfolio_by_issuer[[#Totals],[Total Amount]] -> 0.71631522 | W14: ACBV | X14: NGAN HANG TMCP A CHAU | Y14: ACBCD090427 | Z14: 6M-1Y | AB14: AA | AC14: 46203 | AD14: BB- | AE14: Ba3 | AG14: 200 | AH14: =AH13+AG14/Portfolio_by_bond[[#Totals],[Total Amount]] -> 0.25225563 | AI14: =Portfolio_by_bond[[#This Row],[Total Amount]]-_xlfn.XLOOKUP(Portfolio_by_bond[[#This Row],[Bond_Code]],'Ref'!F:F,'Ref'!G:G,0,0) -> 200 | AJ14: =AJ13+AI14/(SUM(AI:AI)/2) -> 0.32110362 | AK14: =IF(AA14="",Z14,AA14) -> 6M-1Y
A15: <1M | B15: =_xlfn.XLOOKUP(A15,AM:AM,AN:AN,0,0) -> 3350 | C15: =_xlfn.XLOOKUP(A15,AP:AP,AQ:AQ,0,0) -> 3350 | K15: OCBV | L15: 2500 | M15: BBB | N15: 46206 | P15: Ba3 | R15: =R14+Portfolio_by_issuer[[#This Row],[Total Amount]]/Portfolio_by_issuer[[#Totals],[Total Amount]] -> 0.78438115 | S15: =_xlfn.XLOOKUP(Portfolio_by_issuer[[#This Row],[Issuer]],Rating!T:T,Rating!U:U,,0) -> BBB | T15: =T14+Portfolio_by_issuer[[#This Row],[Total Amount]]/Portfolio_by_issuer[[#Totals],[Total Amount]] -> 0.78438115 | W15: ACBV | X15: NGAN HANG TMCP A CHAU | Y15: ACBCD190127 | Z15: 3-6M | AB15: AA | AC15: 46203 | AD15: BB- | AE15: Ba3 | AG15: 400 | AH15: =AH14+AG15/Portfolio_by_bond[[#Totals],[Total Amount]] -> 0.26314633 | AI15: =Portfolio_by_bond[[#This Row],[Total Amount]]-_xlfn.XLOOKUP(Portfolio_by_bond[[#This Row],[Bond_Code]],'Ref'!F:F,'Ref'!G:G,0,0) -> 400 | AJ15: =AJ14+AI15/(SUM(AI:AI)/2) -> 0.3349667 | AK15: =IF(AA15="",Z15,AA15) -> 3-6M
A16: 1-3M | B16: =_xlfn.SINGLE(_xlfn.XLOOKUP(A16,AM:AM,AN:AN,0,0)) -> 7950 | C16: =_xlfn.SINGLE(_xlfn.XLOOKUP(A16,AP:AP,AQ:AQ,0,0)) -> 7950 | K16: MFKR | L16: 570.38538 | M16: BBB | O16: B | P16: B3 | Q16: B+ | R16: =R15+Portfolio_by_issuer[[#This Row],[Total Amount]]/Portfolio_by_issuer[[#Totals],[Total Amount]] -> 0.79991068 | S16: =_xlfn.XLOOKUP(Portfolio_by_issuer[[#This Row],[Issuer]],Rating!T:T,Rating!U:U,,0) -> BBB | T16: =T15+Portfolio_by_issuer[[#This Row],[Total Amount]]/Portfolio_by_issuer[[#Totals],[Total Amount]] -> 0.79991068 | W16: ACBV | X16: NGAN HANG TMCP A CHAU | Y16: ACBCD021226 | Z16: 1-3M | AB16: AA | AC16: 46203 | AD16: BB- | AE16: Ba3 | AG16: 500 | AH16: =AH15+AG16/Portfolio_by_bond[[#Totals],[Total Amount]] -> 0.27675969 | AI16: =Portfolio_by_bond[[#This Row],[Total Amount]]-_xlfn.XLOOKUP(Portfolio_by_bond[[#This Row],[Bond_Code]],'Ref'!F:F,'Ref'!G:G,0,0) -> 500 | AJ16: =AJ15+AI16/(SUM(AI:AI)/2) -> 0.35229555 | AK16: =IF(AA16="",Z16,AA16) -> 1-3M
A17: 3-6M | B17: =_xlfn.SINGLE(_xlfn.XLOOKUP(A17,AM:AM,AN:AN,0,0)) -> 3172 | C17: =_xlfn.SINGLE(_xlfn.XLOOKUP(A17,AP:AP,AQ:AQ,0,0)) -> 3172 | K17: VIETBANK | L17: 2500 | M17: BB | N17: 46128 | R17: =R16+Portfolio_by_issuer[[#This Row],[Total Amount]]/Portfolio_by_issuer[[#Totals],[Total Amount]] -> 0.8679766 | S17: =_xlfn.XLOOKUP(Portfolio_by_issuer[[#This Row],[Issuer]],Rating!T:T,Rating!U:U,,0) -> BB | T17: =T16+Portfolio_by_issuer[[#This Row],[Total Amount]]/Portfolio_by_issuer[[#Totals],[Total Amount]] -> 0.8679766 | W17: HDBV | X17: NGAN HANG TMCP PHAT TRIEN TP HO CHI MINH | Y17: HDB125011 | Z17: 5-7Y | AA17: 6M-1Y | AB17: AA | AC17: 46022 | AE17: B1 | AG17: 397.6106 | AH17: =AH16+AG17/Portfolio_by_bond[[#Totals],[Total Amount]] -> 0.28758533 | AI17: =Portfolio_by_bond[[#This Row],[Total Amount]]-_xlfn.XLOOKUP(Portfolio_by_bond[[#This Row],[Bond_Code]],'Ref'!F:F,'Ref'!G:G,0,0) -> 397.6106 | AJ17: =AJ16+AI17/(SUM(AI:AI)/2) -> 0.36607582 | AK17: =IF(AA17="",Z17,AA17) -> 6M-1Y
A18: 6M-1Y | B18: =_xlfn.SINGLE(_xlfn.XLOOKUP(A18,AM:AM,AN:AN,0,0)) -> 14089.1 | C18: =_xlfn.SINGLE(_xlfn.XLOOKUP(A18,AP:AP,AQ:AQ,0,0)) -> 17986.711 | K18: EIBV | L18: 1500 | M18: BB | N18: 46190 | Q18: B+ | R18: =R17+Portfolio_by_issuer[[#This Row],[Total Amount]]/Portfolio_by_issuer[[#Totals],[Total Amount]] -> 0.90881616 | S18: =_xlfn.XLOOKUP(Portfolio_by_issuer[[#This Row],[Issuer]],Rating!T:T,Rating!U:U,,0) -> BB | T18: =T17+Portfolio_by_issuer[[#This Row],[Total Amount]]/Portfolio_by_issuer[[#Totals],[Total Amount]] -> 0.90881616 | W18: HDBV | X18: NGAN HANG TMCP PHAT TRIEN TP HO CHI MINH | Y18: HDB12M261126 | Z18: 1-3M | AB18: AA | AC18: 46022 | AE18: B1 | AG18: 1500 | AH18: =AH17+AG18/Portfolio_by_bond[[#Totals],[Total Amount]] -> 0.32842542 | AI18: =Portfolio_by_bond[[#This Row],[Total Amount]]-_xlfn.XLOOKUP(Portfolio_by_bond[[#This Row],[Bond_Code]],'Ref'!F:F,'Ref'!G:G,0,0) -> 0 | AJ18: =AJ17+AI18/(SUM(AI:AI)/2) -> 0.36607582 | AK18: =IF(AA18="",Z18,AA18) -> 1-3M
A19: 1-2Y | B19: =_xlfn.SINGLE(_xlfn.XLOOKUP(A19,AM:AM,AN:AN,0,0)) -> 700 | C19: =_xlfn.SINGLE(_xlfn.XLOOKUP(A19,AP:AP,AQ:AQ,0,0)) -> 1700 | K19: TC_SHINSEI | L19: 1000 | M19: BB | N19: 45747 | O19: B+ | R19: =R18+Portfolio_by_issuer[[#This Row],[Total Amount]]/Portfolio_by_issuer[[#Totals],[Total Amount]] -> 0.93604253 | S19: =_xlfn.XLOOKUP(Portfolio_by_issuer[[#This Row],[Issuer]],Rating!T:T,Rating!U:U,,0) -> BB | T19: =T18+Portfolio_by_issuer[[#This Row],[Total Amount]]/Portfolio_by_issuer[[#Totals],[Total Amount]] -> 0.93604253 | W19: HDBV | X19: NGAN HANG TMCP PHAT TRIEN TP HO CHI MINH | Y19: HDB1CD031126 | Z19: 1-3M | AB19: AA | AC19: 46022 | AE19: B1 | AG19: 800 | AH19: =AH18+AG19/Portfolio_by_bond[[#Totals],[Total Amount]] -> 0.3502068 | AI19: =Portfolio_by_bond[[#This Row],[Total Amount]]-_xlfn.XLOOKUP(Portfolio_by_bond[[#This Row],[Bond_Code]],'Ref'!F:F,'Ref'!G:G,0,0) -> 800 | AJ19: =AJ18+AI19/(SUM(AI:AI)/2) -> 0.39380198 | AK19: =IF(AA19="",Z19,AA19) -> 1-3M
A20: 2-3Y | B20: =_xlfn.SINGLE(_xlfn.XLOOKUP(A20,AM:AM,AN:AN,0,0)) -> 3000 | C20: =_xlfn.SINGLE(_xlfn.XLOOKUP(A20,AP:AP,AQ:AQ,0,0)) -> 1000 | K20: VABV | L20: 600 | M20: BB | N20: 45792 | O20: B+ | P20: B2 | R20: =R19+Portfolio_by_issuer[[#This Row],[Total Amount]]/Portfolio_by_issuer[[#Totals],[Total Amount]] -> 0.95237835 | S20: =_xlfn.XLOOKUP(Portfolio_by_issuer[[#This Row],[Issuer]],Rating!T:T,Rating!U:U,,0) -> BB | T20: =T19+Portfolio_by_issuer[[#This Row],[Total Amount]]/Portfolio_by_issuer[[#Totals],[Total Amount]] -> 0.95237835 | W20: LVBT | X20: NGAN HANG TMCP LOC PHAT VN | Y20: LPB12407 | Z20: <1M | AA20: <1M | AB20: AA | AC20: 46199 | AE20: Ba3 | AG20: 1000 | AH20: =AH19+AG20/Portfolio_by_bond[[#Totals],[Total Amount]] -> 0.37743353 | AI20: =Portfolio_by_bond[[#This Row],[Total Amount]]-_xlfn.XLOOKUP(Portfolio_by_bond[[#This Row],[Bond_Code]],'Ref'!F:F,'Ref'!G:G,0,0) -> 1000 | AJ20: =AJ19+AI20/(SUM(AI:AI)/2) -> 0.42845968 | AK20: =IF(AA20="",Z20,AA20) -> <1M
A21: 3-5Y | B21: =_xlfn.SINGLE(_xlfn.XLOOKUP(A21,AM:AM,AN:AN,0,0)) -> 569.90402 | C21: =_xlfn.SINGLE(_xlfn.XLOOKUP(A21,AP:AP,AQ:AQ,0,0)) -> 569.90402 | K21: VCCB | L21: 250 | M21: BB | N21: 46209 | O21: B+ | R21: =R20+Portfolio_by_issuer[[#This Row],[Total Amount]]/Portfolio_by_issuer[[#Totals],[Total Amount]] -> 0.95918495 | S21: =_xlfn.XLOOKUP(Portfolio_by_issuer[[#This Row],[Issuer]],Rating!T:T,Rating!U:U,,0) -> BB | T21: =T20+Portfolio_by_issuer[[#This Row],[Total Amount]]/Portfolio_by_issuer[[#Totals],[Total Amount]] -> 0.95918495 | W21: TC_DIENLUC | X21: CONG TY TAI CHINH CO PHAN DIEN LUC | Y21: EVNFC160427 | Z21: 6M-1Y | AB21: AA | AC21: 46164 | AE21: B2 | AG21: 300 | AH21: =AH20+AG21/Portfolio_by_bond[[#Totals],[Total Amount]] -> 0.38560155 | AI21: =Portfolio_by_bond[[#This Row],[Total Amount]]-_xlfn.XLOOKUP(Portfolio_by_bond[[#This Row],[Bond_Code]],'Ref'!F:F,'Ref'!G:G,0,0) -> 300 | AJ21: =AJ20+AI21/(SUM(AI:AI)/2) -> 0.43885699 | AK21: =IF(AA21="",Z21,AA21) -> 6M-1Y
A22: 5-7Y | B22: =_xlfn.SINGLE(_xlfn.XLOOKUP(A22,AM:AM,AN:AN,0,0)) -> 3897.6106 | C22: =_xlfn.SINGLE(_xlfn.XLOOKUP(A22,AP:AP,AQ:AQ,0,0)) -> 1000 | K22: PVFC | L22: 1000 | M22: B | N22: 46218 | R22: =R21+Portfolio_by_issuer[[#This Row],[Total Amount]]/Portfolio_by_issuer[[#Totals],[Total Amount]] -> 0.98641132 | S22: =_xlfn.XLOOKUP(Portfolio_by_issuer[[#This Row],[Issuer]],Rating!T:T,Rating!U:U,,0) -> B | T22: =T21+Portfolio_by_issuer[[#This Row],[Total Amount]]/Portfolio_by_issuer[[#Totals],[Total Amount]] -> 0.98641132 | W22: TC_DIENLUC | X22: CONG TY TAI CHINH CO PHAN DIEN LUC | Y22: EVNFC260427 | Z22: 6M-1Y | AB22: AA | AC22: 46164 | AE22: B2 | AG22: 100 | AH22: =AH21+AG22/Portfolio_by_bond[[#Totals],[Total Amount]] -> 0.38832422 | AI22: =Portfolio_by_bond[[#This Row],[Total Amount]]-_xlfn.XLOOKUP(Portfolio_by_bond[[#This Row],[Bond_Code]],'Ref'!F:F,'Ref'!G:G,0,0) -> 100 | AJ22: =AJ21+AI22/(SUM(AI:AI)/2) -> 0.44232277 | AK22: =IF(AA22="",Z22,AA22) -> 6M-1Y
A23: >7Y | B23: =_xlfn.SINGLE(_xlfn.XLOOKUP(A23,AM:AM,AN:AN,0,0)) -> 0 | C23: =_xlfn.SINGLE(_xlfn.XLOOKUP(A23,AP:AP,AQ:AQ,0,0)) -> 0 | K23: OJBV | L23: 499.1 | M23: D | R23: =R22+Portfolio_by_issuer[[#This Row],[Total Amount]]/Portfolio_by_issuer[[#Totals],[Total Amount]] -> 1 | S23: =_xlfn.XLOOKUP(Portfolio_by_issuer[[#This Row],[Issuer]],Rating!T:T,Rating!U:U,,0) -> D | T23: =T22+Portfolio_by_issuer[[#This Row],[Total Amount]]/Portfolio_by_issuer[[#Totals],[Total Amount]] -> 1 | W23: TC_DIENLUC | X23: CONG TY TAI CHINH CO PHAN DIEN LUC | Y23: EVNFC170527 | Z23: 6M-1Y | AB23: AA | AC23: 46164 | AE23: B2 | AG23: 390 | AH23: =AH22+AG23/Portfolio_by_bond[[#Totals],[Total Amount]] -> 0.39894264 | AI23: =Portfolio_by_bond[[#This Row],[Total Amount]]-_xlfn.XLOOKUP(Portfolio_by_bond[[#This Row],[Bond_Code]],'Ref'!F:F,'Ref'!G:G,0,0) -> 390 | AJ23: =AJ22+AI23/(SUM(AI:AI)/2) -> 0.45583927 | AK23: =IF(AA23="",Z23,AA23) -> 6M-1Y
A24: Total | B24: =SUM(B15:B23) -> 36728.615 | C24: =SUM(C15:C23) -> 36728.615 | K24: Total | L24: =SUBTOTAL(109,Portfolio_by_issuer[Total Amount]) -> 36729.096 | W24: TC_DIENLUC | X24: CONG TY TAI CHINH CO PHAN DIEN LUC | Y24: EVNFC010227 | Z24: 3-6M | AB24: AA | AC24: 46164 | AE24: B2 | AG24: 57 | AH24: =AH23+AG24/Portfolio_by_bond[[#Totals],[Total Amount]] -> 0.40049457 | AI24: =Portfolio_by_bond[[#This Row],[Total Amount]]-_xlfn.XLOOKUP(Portfolio_by_bond[[#This Row],[Bond_Code]],'Ref'!F:F,'Ref'!G:G,0,0) -> 57 | AJ24: =AJ23+AI24/(SUM(AI:AI)/2) -> 0.45781476 | AK24: =IF(AA24="",Z24,AA24) -> 3-6M
W25: VPVN | X25: NGAN HANG TMCP VIET NAM THINH VUONG | Y25: VPBCD080427 | Z25: 6M-1Y | AB25: AA | AC25: 46142 | AE25: Ba3 | AG25: 400 | AH25: =AH24+AG25/Portfolio_by_bond[[#Totals],[Total Amount]] -> 0.41138526 | AI25: =Portfolio_by_bond[[#This Row],[Total Amount]]-_xlfn.XLOOKUP(Portfolio_by_bond[[#This Row],[Bond_Code]],'Ref'!F:F,'Ref'!G:G,0,0) -> 400 | AJ25: =AJ24+AI25/(SUM(AI:AI)/2) -> 0.47167784 | AK25: =IF(AA25="",Z25,AA25) -> 6M-1Y
W26: SABH | X26: NGAN HANG TMCP NAM A | Y26: NABCD041226 | Z26: 3-6M | AB26: A | AC26: 46141 | AD26: B+ | AE26: B2 | AG26: 1000 | AH26: =AH25+AG26/Portfolio_by_bond[[#Totals],[Total Amount]] -> 0.43861199 | AI26: =Portfolio_by_bond[[#This Row],[Total Amount]]-_xlfn.XLOOKUP(Portfolio_by_bond[[#This Row],[Bond_Code]],'Ref'!F:F,'Ref'!G:G,0,0) -> 1000 | AJ26: =AJ25+AI26/(SUM(AI:AI)/2) -> 0.50633554 | AK26: =IF(AA26="",Z26,AA26) -> 3-6M
W27: SABH | X27: NGAN HANG TMCP NAM A | Y27: NABCD200527 | Z27: 6M-1Y | AB27: A | AC27: 46141 | AD27: B+ | AE27: B2 | AG27: 2000 | AH27: =AH26+AG27/Portfolio_by_bond[[#Totals],[Total Amount]] -> 0.49306544 | AI27: =Portfolio_by_bond[[#This Row],[Total Amount]]-_xlfn.XLOOKUP(Portfolio_by_bond[[#This Row],[Bond_Code]],'Ref'!F:F,'Ref'!G:G,0,0) -> 2000 | AJ27: =AJ26+AI27/(SUM(AI:AI)/2) -> 0.57565095 | AK27: =IF(AA27="",Z27,AA27) -> 6M-1Y
W28: SHBV | X28: NGAN HANG TMCP SAI GON HA NOI | Y28: SHBL12601 | Z28: 5-7Y | AB28: A | AC28: 46211 | AD28: BB- | AE28: B1 | AG28: 1000 | AH28: =AH27+AG28/Portfolio_by_bond[[#Totals],[Total Amount]] -> 0.52029217 | AI28: =Portfolio_by_bond[[#This Row],[Total Amount]]-_xlfn.XLOOKUP(Portfolio_by_bond[[#This Row],[Bond_Code]],'Ref'!F:F,'Ref'!G:G,0,0) -> 1000 | AJ28: =AJ27+AI28/(SUM(AI:AI)/2) -> 0.61030865 | AK28: =IF(AA28="",Z28,AA28) -> 5-7Y
W29: SHBV | X29: NGAN HANG TMCP SAI GON HA NOI | Y29: SHB12503 | Z29: 5-7Y | AA29: 6M-1Y | AB29: A | AC29: 46211 | AD29: BB- | AE29: B1 | AG29: 500 | AH29: =AH28+AG29/Portfolio_by_bond[[#Totals],[Total Amount]] -> 0.53390553 | AI29: =Portfolio_by_bond[[#This Row],[Total Amount]]-_xlfn.XLOOKUP(Portfolio_by_bond[[#This Row],[Bond_Code]],'Ref'!F:F,'Ref'!G:G,0,0) -> 500 | AJ29: =AJ28+AI29/(SUM(AI:AI)/2) -> 0.6276375 | AK29: =IF(AA29="",Z29,AA29) -> 6M-1Y
W30: NABV | X30: NGAN HANG TMCP BAC A | Y30: BAB12603 | Z30: 6M-1Y | AA30: 6M-1Y | AB30: BBB | AC30: 46146 | AD30: B+ | AG30: 1000 | AH30: =AH29+AG30/Portfolio_by_bond[[#Totals],[Total Amount]] -> 0.56113226 | AI30: =Portfolio_by_bond[[#This Row],[Total Amount]]-_xlfn.XLOOKUP(Portfolio_by_bond[[#This Row],[Bond_Code]],'Ref'!F:F,'Ref'!G:G,0,0) -> 0 | AJ30: =AJ29+AI30/(SUM(AI:AI)/2) -> 0.6276375 | AK30: =IF(AA30="",Z30,AA30) -> 6M-1Y
W31: NABV | X31: NGAN HANG TMCP BAC A | Y31: BAB12601 | Z31: 6M-1Y | AA31: 6M-1Y | AB31: BBB | AC31: 46146 | AD31: B+ | AG31: 2000 | AH31: =AH30+AG31/Portfolio_by_bond[[#Totals],[Total Amount]] -> 0.61558572 | AI31: =Portfolio_by_bond[[#This Row],[Total Amount]]-_xlfn.XLOOKUP(Portfolio_by_bond[[#This Row],[Bond_Code]],'Ref'!F:F,'Ref'!G:G,0,0) -> 0 | AJ31: =AJ30+AI31/(SUM(AI:AI)/2) -> 0.6276375 | AK31: =IF(AA31="",Z31,AA31) -> 6M-1Y
W32: OCBV | X32: NGAN HANG TMCP PHUONG DONG | Y32: OCBCD241126 | Z32: 1-3M | AB32: BBB | AC32: 46206 | AE32: Ba3 | AG32: 2000 | AH32: =AH31+AG32/Portfolio_by_bond[[#Totals],[Total Amount]] -> 0.67003917 | AI32: =Portfolio_by_bond[[#This Row],[Total Amount]]-_xlfn.XLOOKUP(Portfolio_by_bond[[#This Row],[Bond_Code]],'Ref'!F:F,'Ref'!G:G,0,0) -> 0 | AJ32: =AJ31+AI32/(SUM(AI:AI)/2) -> 0.6276375 | AK32: =IF(AA32="",Z32,AA32) -> 1-3M
W33: OCBV | X33: NGAN HANG TMCP PHUONG DONG | Y33: OCBCD281026 | Z33: 1-3M | AB33: BBB | AC33: 46206 | AE33: Ba3 | AG33: 500 | AH33: =AH32+AG33/Portfolio_by_bond[[#Totals],[Total Amount]] -> 0.68365254 | AI33: =Portfolio_by_bond[[#This Row],[Total Amount]]-_xlfn.XLOOKUP(Portfolio_by_bond[[#This Row],[Bond_Code]],'Ref'!F:F,'Ref'!G:G,0,0) -> 500 | AJ33: =AJ32+AI33/(SUM(AI:AI)/2) -> 0.64496635 | AK33: =IF(AA33="",Z33,AA33) -> 1-3M
W34: EIBV | X34: NGAN HANG TMCP XUAT NHAP KHAU VN | Y34: EIBCD291026 | Z34: 1-3M | AB34: BB | AC34: 46190 | AF34: B+ | AG34: 500 | AH34: =AH33+AG34/Portfolio_by_bond[[#Totals],[Total Amount]] -> 0.6972659 | AI34: =Portfolio_by_bond[[#This Row],[Total Amount]]-_xlfn.XLOOKUP(Portfolio_by_bond[[#This Row],[Bond_Code]],'Ref'!F:F,'Ref'!G:G,0,0) -> 500 | AJ34: =AJ33+AI34/(SUM(AI:AI)/2) -> 0.6622952 | AK34: =IF(AA34="",Z34,AA34) -> 1-3M
W35: EIBV | X35: NGAN HANG TMCP XUAT NHAP KHAU VN | Y35: EIBCD240926 | Z35: <1M | AB35: BB | AC35: 46190 | AF35: B+ | AG35: 1000 | AH35: =AH34+AG35/Portfolio_by_bond[[#Totals],[Total Amount]] -> 0.72449263 | AI35: =Portfolio_by_bond[[#This Row],[Total Amount]]-_xlfn.XLOOKUP(Portfolio_by_bond[[#This Row],[Bond_Code]],'Ref'!F:F,'Ref'!G:G,0,0) -> 1000 | AJ35: =AJ34+AI35/(SUM(AI:AI)/2) -> 0.69695291 | AK35: =IF(AA35="",Z35,AA35) -> <1M
W36: TC_SHINSEI | X36: CONG TY TAI CHINH TNHH MB SHINSEI | Y36: MCCD240327 | Z36: 6M-1Y | AB36: BB | AC36: 45747 | AD36: B+ | AG36: 400 | AH36: =AH35+AG36/Portfolio_by_bond[[#Totals],[Total Amount]] -> 0.73538332 | AI36: =Portfolio_by_bond[[#This Row],[Total Amount]]-_xlfn.XLOOKUP(Portfolio_by_bond[[#This Row],[Bond_Code]],'Ref'!F:F,'Ref'!G:G,0,0) -> 400 | AJ36: =AJ35+AI36/(SUM(AI:AI)/2) -> 0.71081599 | AK36: =IF(AA36="",Z36,AA36) -> 6M-1Y
W37: TC_SHINSEI | X37: CONG TY TAI CHINH TNHH MB SHINSEI | Y37: MSF12404 | Z37: 3-6M | AB37: BB | AC37: 45747 | AD37: B+ | AG37: 400 | AH37: =AH36+AG37/Portfolio_by_bond[[#Totals],[Total Amount]] -> 0.74627401 | AI37: =Portfolio_by_bond[[#This Row],[Total Amount]]-_xlfn.XLOOKUP(Portfolio_by_bond[[#This Row],[Bond_Code]],'Ref'!F:F,'Ref'!G:G,0,0) -> 400 | AJ37: =AJ36+AI37/(SUM(AI:AI)/2) -> 0.72467907 | AK37: =IF(AA37="",Z37,AA37) -> 3-6M
W38: TC_SHINSEI | X38: CONG TY TAI CHINH TNHH MB SHINSEI | Y38: MCCD060827 | Z38: 6M-1Y | AB38: BB | AC38: 45747 | AD38: B+ | AG38: 200 | AH38: =AH37+AG38/Portfolio_by_bond[[#Totals],[Total Amount]] -> 0.75171936 | AI38: =Portfolio_by_bond[[#This Row],[Total Amount]]-_xlfn.XLOOKUP(Portfolio_by_bond[[#This Row],[Bond_Code]],'Ref'!F:F,'Ref'!G:G,0,0) -> 200 | AJ38: =AJ37+AI38/(SUM(AI:AI)/2) -> 0.73161061 | AK38: =IF(AA38="",Z38,AA38) -> 6M-1Y
W39: VABV | X39: NGAN HANG TMCP VIET A | Y39: VABCD190827 | Z39: 6M-1Y | AB39: BB | AC39: 45792 | AD39: B+ | AE39: B2 | AG39: 600 | AH39: =AH38+AG39/Portfolio_by_bond[[#Totals],[Total Amount]] -> 0.76805539 | AI39: =Portfolio_by_bond[[#This Row],[Total Amount]]-_xlfn.XLOOKUP(Portfolio_by_bond[[#This Row],[Bond_Code]],'Ref'!F:F,'Ref'!G:G,0,0) -> 600 | AJ39: =AJ38+AI39/(SUM(AI:AI)/2) -> 0.75240523 | AK39: =IF(AA39="",Z39,AA39) -> 6M-1Y
W40: VCCB | X40: NGAN HANG TMCP BAN VIET | Y40: VCCB1Y301026 | Z40: 1-3M | AB40: BB | AC40: 46209 | AD40: B+ | AG40: 250 | AH40: =AH39+AG40/Portfolio_by_bond[[#Totals],[Total Amount]] -> 0.77486208 | AI40: =Portfolio_by_bond[[#This Row],[Total Amount]]-_xlfn.XLOOKUP(Portfolio_by_bond[[#This Row],[Bond_Code]],'Ref'!F:F,'Ref'!G:G,0,0) -> 250 | AJ40: =AJ39+AI40/(SUM(AI:AI)/2) -> 0.76106966 | AK40: =IF(AA40="",Z40,AA40) -> 1-3M
W41: VIETBANK | X41: NGAN HANG TMCP VIET NAM THUONG TIN | Y41: VBB1Y130527 | Z41: 6M-1Y | AB41: BB | AC41: 46128 | AG41: 200 | AH41: =AH40+AG41/Portfolio_by_bond[[#Totals],[Total Amount]] -> 0.78030742 | AI41: =Portfolio_by_bond[[#This Row],[Total Amount]]-_xlfn.XLOOKUP(Portfolio_by_bond[[#This Row],[Bond_Code]],'Ref'!F:F,'Ref'!G:G,0,0) -> 200 | AJ41: =AJ40+AI41/(SUM(AI:AI)/2) -> 0.7680012 | AK41: =IF(AA41="",Z41,AA41) -> 6M-1Y
W42: VIETBANK | X42: NGAN HANG TMCP VIET NAM THUONG TIN | Y42: VBBCD180527 | Z42: 6M-1Y | AB42: BB | AC42: 46128 | AG42: 900 | AH42: =AH41+AG42/Portfolio_by_bond[[#Totals],[Total Amount]] -> 0.80481148 | AI42: =Portfolio_by_bond[[#This Row],[Total Amount]]-_xlfn.XLOOKUP(Portfolio_by_bond[[#This Row],[Bond_Code]],'Ref'!F:F,'Ref'!G:G,0,0) -> 900 | AJ42: =AJ41+AI42/(SUM(AI:AI)/2) -> 0.79919313 | AK42: =IF(AA42="",Z42,AA42) -> 6M-1Y
W43: VIETBANK | X43: NGAN HANG TMCP VIET NAM THUONG TIN | Y43: VBB1Y180527 | Z43: 6M-1Y | AB43: BB | AC43: 46128 | AG43: 400 | AH43: =AH42+AG43/Portfolio_by_bond[[#Totals],[Total Amount]] -> 0.81570217 | AI43: =Portfolio_by_bond[[#This Row],[Total Amount]]-_xlfn.XLOOKUP(Portfolio_by_bond[[#This Row],[Bond_Code]],'Ref'!F:F,'Ref'!G:G,0,0) -> 400 | AJ43: =AJ42+AI43/(SUM(AI:AI)/2) -> 0.81305621 | AK43: =IF(AA43="",Z43,AA43) -> 6M-1Y
W44: VIETBANK | X44: NGAN HANG TMCP VIET NAM THUONG TIN | Y44: VBB1Y301126 | Z44: 1-3M | AB44: BB | AC44: 46128 | AG44: 200 | AH44: =AH43+AG44/Portfolio_by_bond[[#Totals],[Total Amount]] -> 0.82114751 | AI44: =Portfolio_by_bond[[#This Row],[Total Amount]]-_xlfn.XLOOKUP(Portfolio_by_bond[[#This Row],[Bond_Code]],'Ref'!F:F,'Ref'!G:G,0,0) -> 200 | AJ44: =AJ43+AI44/(SUM(AI:AI)/2) -> 0.81998775 | AK44: =IF(AA44="",Z44,AA44) -> 1-3M
W45: VIETBANK | X45: NGAN HANG TMCP VIET NAM THUONG TIN | Y45: VBB1Y061026 | Z45: 1-3M | AB45: BB | AC45: 46128 | AG45: 500 | AH45: =AH44+AG45/Portfolio_by_bond[[#Totals],[Total Amount]] -> 0.83476088 | AI45: =Portfolio_by_bond[[#This Row],[Total Amount]]-_xlfn.XLOOKUP(Portfolio_by_bond[[#This Row],[Bond_Code]],'Ref'!F:F,'Ref'!G:G,0,0) -> 500 | AJ45: =AJ44+AI45/(SUM(AI:AI)/2) -> 0.8373166 | AK45: =IF(AA45="",Z45,AA45) -> 1-3M
W46: VIETBANK | X46: NGAN HANG TMCP VIET NAM THUONG TIN | Y46: VBB1Y090926 | Z46: <1M | AB46: BB | AC46: 46128 | AG46: 300 | AH46: =AH45+AG46/Portfolio_by_bond[[#Totals],[Total Amount]] -> 0.8429289 | AI46: =Portfolio_by_bond[[#This Row],[Total Amount]]-_xlfn.XLOOKUP(Portfolio_by_bond[[#This Row],[Bond_Code]],'Ref'!F:F,'Ref'!G:G,0,0) -> 300 | AJ46: =AJ45+AI46/(SUM(AI:AI)/2) -> 0.84771391 | AK46: =IF(AA46="",Z46,AA46) -> <1M
W47: MFKR | X47: KOMPANION BANK CLOSED JOINT STOCK COMPANY | Y47: GBA05310713 | Z47: 3-5Y | AA47: 3-5Y | AB47: B | AG47: 189.30842 | AH47: =AH46+AG47/Portfolio_by_bond[[#Totals],[Total Amount]] -> 0.84808315 | AI47: =Portfolio_by_bond[[#This Row],[Total Amount]]-_xlfn.XLOOKUP(Portfolio_by_bond[[#This Row],[Bond_Code]],'Ref'!F:F,'Ref'!G:G,0,0) -> 189.30842 | AJ47: =AJ46+AI47/(SUM(AI:AI)/2) -> 0.85427491 | AK47: =IF(AA47="",Z47,AA47) -> 3-5Y
W48: MFKR | X48: KOMPANION BANK CLOSED JOINT STOCK COMPANY | Y48: GBA05310727 | Z48: 3-5Y | AA48: 3-5Y | AB48: B | AG48: 380.5956 | AH48: =AH47+AG55/Portfolio_by_bond[[#Totals],[Total Amount]] -> 0.87530987 | AI48: =Portfolio_by_bond[[#This Row],[Total Amount]]-_xlfn.XLOOKUP(Portfolio_by_bond[[#This Row],[Bond_Code]],'Ref'!F:F,'Ref'!G:G,0,0) -> 380.5956 | AJ48: =AJ47+AI48/(SUM(AI:AI)/2) -> 0.86746548 | AK48: =IF(AA48="",Z48,AA48) -> 3-5Y
W49: OJBV | X49: NGAN HANG THUONG MAI TNHH MTV DAI DUONG | Y49: MBVCD2180827 | Z49: 6M-1Y | AB49: D | AG49: 39.1 | AH49: =AH48+AG56/Portfolio_by_bond[[#Totals],[Total Amount]] -> 1.8753099 | AI49: =Portfolio_by_bond[[#This Row],[Total Amount]]-_xlfn.XLOOKUP(Portfolio_by_bond[[#This Row],[Bond_Code]],'Ref'!F:F,'Ref'!G:G,0,0) -> 39.1 | AJ49: =AJ48+AI49/(SUM(AI:AI)/2) -> 0.86882059 | AK49: =IF(AA49="",Z49,AA49) -> 6M-1Y
W50: OJBV | X50: NGAN HANG THUONG MAI TNHH MTV DAI DUONG | Y50: MBVCD180827 | Z50: 6M-1Y | AB50: D | AG50: 460 | AH50: =AH49+AG57/Portfolio_by_bond[[#Totals],[Total Amount]] -> 1.8753099 | AI50: =Portfolio_by_bond[[#This Row],[Total Amount]]-_xlfn.XLOOKUP(Portfolio_by_bond[[#This Row],[Bond_Code]],'Ref'!F:F,'Ref'!G:G,0,0) -> 460 | AJ50: =AJ49+AI50/(SUM(AI:AI)/2) -> 0.88476314 | AK50: =IF(AA50="",Z50,AA50) -> 6M-1Y
W51: PVFC | X51: NGAN HANG TMCP DAI CHUNG VN | Y51: PCB12601 | Z51: 5-7Y | AA51: 1-2Y | AB51: B | AC51: 46218 | AG51: 1000 | AH51: =AH50+AG58/Portfolio_by_bond[[#Totals],[Total Amount]] -> 1.8753099 | AI51: =Portfolio_by_bond[[#This Row],[Total Amount]]-_xlfn.XLOOKUP(Portfolio_by_bond[[#This Row],[Bond_Code]],'Ref'!F:F,'Ref'!G:G,0,0) -> 1000 | AJ51: =AJ50+AI51/(SUM(AI:AI)/2) -> 0.91942084 | AK51: =IF(AA51="",Z51,AA51) -> 1-2Y
W52: SGTT | X52: NGAN HANG TMCP SAI GON THUONG TIN | Y52: STBCD050827 | Z52: 6M-1Y | AB52: A | AG52: 700 | AH52: =AH51+AG59/Portfolio_by_bond[[#Totals],[Total Amount]] -> 1.8753099 | AI52: =Portfolio_by_bond[[#This Row],[Total Amount]]-_xlfn.XLOOKUP(Portfolio_by_bond[[#This Row],[Bond_Code]],'Ref'!F:F,'Ref'!G:G,0,0) -> 700 | AJ52: =AJ51+AI52/(SUM(AI:AI)/2) -> 0.94368123 | AK52: =IF(AA52="",Z52,AA52) -> 6M-1Y
W53: SGTT | X53: NGAN HANG TMCP SAI GON THUONG TIN | Y53: STBCD061126 | Z53: 1-3M | AB53: A | AG53: 1000 | AH53: =AH52+AG60/Portfolio_by_bond[[#Totals],[Total Amount]] -> 1.8753099 | AI53: =Portfolio_by_bond[[#This Row],[Total Amount]]-_xlfn.XLOOKUP(Portfolio_by_bond[[#This Row],[Bond_Code]],'Ref'!F:F,'Ref'!G:G,0,0) -> 1000 | AJ53: =AJ52+AI53/(SUM(AI:AI)/2) -> 0.97833894 | AK53: =IF(AA53="",Z53,AA53) -> 1-3M
W54: SGTT | X54: NGAN HANG TMCP SAI GON THUONG TIN | Y54: STB1Y230926 | Z54: <1M | AB54: A | AG54: 1000 | AH54: =AH53+AG61/Portfolio_by_bond[[#Totals],[Total Amount]] -> 1.8753099 | AI54: =Portfolio_by_bond[[#This Row],[Total Amount]]-_xlfn.XLOOKUP(Portfolio_by_bond[[#This Row],[Bond_Code]],'Ref'!F:F,'Ref'!G:G,0,0) -> 1000 | AJ54: =AJ53+AI54/(SUM(AI:AI)/2) -> 1.0129966 | AK54: =IF(AA54="",Z54,AA54) -> <1M
W55: SGTT | X55: NGAN HANG TMCP SAI GON THUONG TIN | Y55: STBL12609 | Z55: 5-7Y | AA55: 6M-1Y | AB55: A | AG55: 1000 | AH55: =AH54+AG62/Portfolio_by_bond[[#Totals],[Total Amount]] -> 1.8753099 | AI55: =Portfolio_by_bond[[#This Row],[Total Amount]]-_xlfn.XLOOKUP(Portfolio_by_bond[[#This Row],[Bond_Code]],'Ref'!F:F,'Ref'!G:G,0,0) -> 1000 | AJ55: =AJ54+AI55/(SUM(AI:AI)/2) -> 1.0476543 | AK55: =IF(AA55="",Z55,AA55) -> 6M-1Y
W56: Total | AG56: =SUBTOTAL(109,Portfolio_by_bond[Total Amount]) -> 36728.615 | AI56: =SUM(AI9:AI55) -> 27478.615

Sheet Rating
A1: CPTY_NAME | B1: CPTY_CODE_ISSUER | C1: CPTY_TYPE | D1: FI_RATING | E1: FI_RATING_DATE | F1: FITCH_RATING | G1: FITCH_RATING_DATE | H1: MOODY_RATING | I1: MOODY_RATING_DATE | J1: SP_RATING | K1: SP_RATING_DATE | L1: Change Rating | M1: Chang rv date | N1: New Rating | P1: His | Q1: Month | R1: Year | S1: CptyName | T1: CptyCode | U1: FiRating | V1: FiRatingDate
A2: ZUERCHER KANTONAL BANK | B2: ZKB | C2: NHNN | D2: AAA | F2: AAA | H2: A1 | L2: =IF(OR(CtpyRating[[#This Row],[FI_RATING]]="",_xlfn.XLOOKUP(CtpyRating[[#This Row],[CPTY_NAME]],S:S,U:U,"",0)=CtpyRating[[#This Row],[FI_RATING]],CtpyRating[[#This Row],[New Rating]]="Yes"),"No","Yes") -> No | M2: =IF(OR(CtpyRating[[#This Row],[FI_RATING_DATE]]="",CtpyRating[[#This Row],[FI_RATING_DATE]]=_xlfn.XLOOKUP(CtpyRating[[#This Row],[CPTY_NAME]],S:S,V:V,"",0),CtpyRating[[#This Row],[New Rating]]="Yes"),"No","Yes") -> No | N2: =IF(AND(CtpyRating[[#This Row],[FI_RATING]]<>"",_xlfn.XLOOKUP(CtpyRating[[#This Row],[CPTY_NAME]],S:S,U:U,"",0)=""),"Yes","No") -> No | Q2: 8 | R2: 2026 | S2: NGAN HANG PHAT TRIEN VN | T2: VDB | U2: BB | V2: 45820
A3: WOORI BANK | B3: HVHB-VN | C3: NHNN | F3: A | G3: 45807 | H3: A1 | I3: 45889 | L3: =IF(OR(CtpyRating[[#This Row],[FI_RATING]]="",_xlfn.XLOOKUP(CtpyRating[[#This Row],[CPTY_NAME]],S:S,U:U,"",0)=CtpyRating[[#This Row],[FI_RATING]],CtpyRating[[#This Row],[New Rating]]="Yes"),"No","Yes") -> No | M3: =IF(OR(CtpyRating[[#This Row],[FI_RATING_DATE]]="",CtpyRating[[#This Row],[FI_RATING_DATE]]=_xlfn.XLOOKUP(CtpyRating[[#This Row],[CPTY_NAME]],S:S,V:V,"",0),CtpyRating[[#This Row],[New Rating]]="Yes"),"No","Yes") -> No | N3: =IF(AND(CtpyRating[[#This Row],[FI_RATING]]<>"",_xlfn.XLOOKUP(CtpyRating[[#This Row],[CPTY_NAME]],S:S,U:U,"",0)=""),"Yes","No") -> No | Q3: 8 | R3: 2026 | S3: NGAN HANG NONG NGHIEP VA PHAT TRIEN NONG THON | T3: VBAH | U3: AAA | V3: 46203
A4: WELLS FARGO NA | B4: WAHK-LDON | C4: NHNN | F4: AA- | G4: 45793 | H4: Aa2 | I4: 45978 | L4: =IF(OR(CtpyRating[[#This Row],[FI_RATING]]="",_xlfn.XLOOKUP(CtpyRating[[#This Row],[CPTY_NAME]],S:S,U:U,"",0)=CtpyRating[[#This Row],[FI_RATING]],CtpyRating[[#This Row],[New Rating]]="Yes"),"No","Yes") -> No | M4: =IF(OR(CtpyRating[[#This Row],[FI_RATING_DATE]]="",CtpyRating[[#This Row],[FI_RATING_DATE]]=_xlfn.XLOOKUP(CtpyRating[[#This Row],[CPTY_NAME]],S:S,V:V,"",0),CtpyRating[[#This Row],[New Rating]]="Yes"),"No","Yes") -> No | N4: =IF(AND(CtpyRating[[#This Row],[FI_RATING]]<>"",_xlfn.XLOOKUP(CtpyRating[[#This Row],[CPTY_NAME]],S:S,U:U,"",0)=""),"Yes","No") -> No | Q4: 8 | R4: 2026 | S4: NGAN HANG TMCP SAI GON HA NOI | T4: SHBV | U4: A | V4: 46211
A5: UNITED OVERSEA BANK LIMITED | B5: UOB_SING | C5: NHNN | H5: Aa1 | I5: 45979 | L5: =IF(OR(CtpyRating[[#This Row],[FI_RATING]]="",_xlfn.XLOOKUP(CtpyRating[[#This Row],[CPTY_NAME]],S:S,U:U,"",0)=CtpyRating[[#This Row],[FI_RATING]],CtpyRating[[#This Row],[New Rating]]="Yes"),"No","Yes") -> No | M5: =IF(OR(CtpyRating[[#This Row],[FI_RATING_DATE]]="",CtpyRating[[#This Row],[FI_RATING_DATE]]=_xlfn.XLOOKUP(CtpyRating[[#This Row],[CPTY_NAME]],S:S,V:V,"",0),CtpyRating[[#This Row],[New Rating]]="Yes"),"No","Yes") -> No | N5: =IF(AND(CtpyRating[[#This Row],[FI_RATING]]<>"",_xlfn.XLOOKUP(CtpyRating[[#This Row],[CPTY_NAME]],S:S,U:U,"",0)=""),"Yes","No") -> No | Q5: 8 | R5: 2026 | S5: NGAN HANG TMCP PHUONG DONG | T5: OCBV | U5: BBB | V5: 46206
A6: TRUNG TAM THONG TIN Y TE QUOC GIA | C6: LHK | D6: AAA | L6: =IF(OR(CtpyRating[[#This Row],[FI_RATING]]="",_xlfn.XLOOKUP(CtpyRating[[#This Row],[CPTY_NAME]],S:S,U:U,"",0)=CtpyRating[[#This Row],[FI_RATING]],CtpyRating[[#This Row],[New Rating]]="Yes"),"No","Yes") -> No | M6: =IF(OR(CtpyRating[[#This Row],[FI_RATING_DATE]]="",CtpyRating[[#This Row],[FI_RATING_DATE]]=_xlfn.XLOOKUP(CtpyRating[[#This Row],[CPTY_NAME]],S:S,V:V,"",0),CtpyRating[[#This Row],[New Rating]]="Yes"),"No","Yes") -> No | N6: =IF(AND(CtpyRating[[#This Row],[FI_RATING]]<>"",_xlfn.XLOOKUP(CtpyRating[[#This Row],[CPTY_NAME]],S:S,U:U,"",0)=""),"Yes","No") -> No | Q6: 8 | R6: 2026 | S6: NGAN HANG TMCP SAI GON | T6: SCBV | U6: CC | V6: 44781
A7: TONG CONG TY CP TAI BAO HIEM HA NOI | B7: TCT_TBHPVI | C7: CTBH | D7: A | E7: 45853 | L7: =IF(OR(CtpyRating[[#This Row],[FI_RATING]]="",_xlfn.XLOOKUP(CtpyRating[[#This Row],[CPTY_NAME]],S:S,U:U,"",0)=CtpyRating[[#This Row],[FI_RATING]],CtpyRating[[#This Row],[New Rating]]="Yes"),"No","Yes") -> No | M7: =IF(OR(CtpyRating[[#This Row],[FI_RATING_DATE]]="",CtpyRating[[#This Row],[FI_RATING_DATE]]=_xlfn.XLOOKUP(CtpyRating[[#This Row],[CPTY_NAME]],S:S,V:V,"",0),CtpyRating[[#This Row],[New Rating]]="Yes"),"No","Yes") -> No | N7: =IF(AND(CtpyRating[[#This Row],[FI_RATING]]<>"",_xlfn.XLOOKUP(CtpyRating[[#This Row],[CPTY_NAME]],S:S,U:U,"",0)=""),"Yes","No") -> No | Q7: 8 | R7: 2026 | S7: NGAN HANG TMCP QUOC DAN | T7: NCBV | U7: D | V7: 45730
A8: TONG CONG TY CP BAO MINH | B8: TCT_CPBM | C8: CTBH | D8: AAA | E8: 45981 | L8: =IF(OR(CtpyRating[[#This Row],[FI_RATING]]="",_xlfn.XLOOKUP(CtpyRating[[#This Row],[CPTY_NAME]],S:S,U:U,"",0)=CtpyRating[[#This Row],[FI_RATING]],CtpyRating[[#This Row],[New Rating]]="Yes"),"No","Yes") -> No | M8: =IF(OR(CtpyRating[[#This Row],[FI_RATING_DATE]]="",CtpyRating[[#This Row],[FI_RATING_DATE]]=_xlfn.XLOOKUP(CtpyRating[[#This Row],[CPTY_NAME]],S:S,V:V,"",0),CtpyRating[[#This Row],[New Rating]]="Yes"),"No","Yes") -> No | N8: =IF(AND(CtpyRating[[#This Row],[FI_RATING]]<>"",_xlfn.XLOOKUP(CtpyRating[[#This Row],[CPTY_NAME]],S:S,U:U,"",0)=""),"Yes","No") -> No | Q8: 8 | R8: 2026 | S8: NGAN HANG TMCP DONG NAM A | T8: SEAV | U8: A | V8: 45919
A9: THE SIAM COMMERCIAL BANK PUBLIC COMPANY LIMITED | B9: SIAMBANK | C9: NHNN | F9: BBB | G9: 45929 | H9: Baa1 | I9: 45995 | L9: =IF(OR(CtpyRating[[#This Row],[FI_RATING]]="",_xlfn.XLOOKUP(CtpyRating[[#This Row],[CPTY_NAME]],S:S,U:U,"",0)=CtpyRating[[#This Row],[FI_RATING]],CtpyRating[[#This Row],[New Rating]]="Yes"),"No","Yes") -> No | M9: =IF(OR(CtpyRating[[#This Row],[FI_RATING_DATE]]="",CtpyRating[[#This Row],[FI_RATING_DATE]]=_xlfn.XLOOKUP(CtpyRating[[#This Row],[CPTY_NAME]],S:S,V:V,"",0),CtpyRating[[#This Row],[New Rating]]="Yes"),"No","Yes") -> No | N9: =IF(AND(CtpyRating[[#This Row],[FI_RATING]]<>"",_xlfn.XLOOKUP(CtpyRating[[#This Row],[CPTY_NAME]],S:S,U:U,"",0)=""),"Yes","No") -> No | Q9: 8 | R9: 2026 | S9: NGAN HANG TMCP KIEN LONG | T9: KIENLONG | U9: BBB | V9: 45929
A10: THE GOVERNOR AND COMPANY OF THE BANK OF IRELAND | B10: IRELANDBANK | C10: NHNN | F10: A+ | G10: 46183 | H10: Aa3 | I10: 46133 | L10: =IF(OR(CtpyRating[[#This Row],[FI_RATING]]="",_xlfn.XLOOKUP(CtpyRating[[#This Row],[CPTY_NAME]],S:S,U:U,"",0)=CtpyRating[[#This Row],[FI_RATING]],CtpyRating[[#This Row],[New Rating]]="Yes"),"No","Yes") -> No | M10: =IF(OR(CtpyRating[[#This Row],[FI_RATING_DATE]]="",CtpyRating[[#This Row],[FI_RATING_DATE]]=_xlfn.XLOOKUP(CtpyRating[[#This Row],[CPTY_NAME]],S:S,V:V,"",0),CtpyRating[[#This Row],[New Rating]]="Yes"),"No","Yes") -> No | N10: =IF(AND(CtpyRating[[#This Row],[FI_RATING]]<>"",_xlfn.XLOOKUP(CtpyRating[[#This Row],[CPTY_NAME]],S:S,U:U,"",0)=""),"Yes","No") -> No | Q10: 8 | R10: 2026 | S10: NGAN HANG TMCP DAI CHUNG VN | T10: PVFC | U10: B | V10: 46218
A11: THE BANK OF NEW YORK MELLON | B11: BNYM | C11: NHNN | F11: AA | G11: 45730 | H11: Aa1 | I11: 45978 | L11: =IF(OR(CtpyRating[[#This Row],[FI_RATING]]="",_xlfn.XLOOKUP(CtpyRating[[#This Row],[CPTY_NAME]],S:S,U:U,"",0)=CtpyRating[[#This Row],[FI_RATING]],CtpyRating[[#This Row],[New Rating]]="Yes"),"No","Yes") -> No | M11: =IF(OR(CtpyRating[[#This Row],[FI_RATING_DATE]]="",CtpyRating[[#This Row],[FI_RATING_DATE]]=_xlfn.XLOOKUP(CtpyRating[[#This Row],[CPTY_NAME]],S:S,V:V,"",0),CtpyRating[[#This Row],[New Rating]]="Yes"),"No","Yes") -> No | N11: =IF(AND(CtpyRating[[#This Row],[FI_RATING]]<>"",_xlfn.XLOOKUP(CtpyRating[[#This Row],[CPTY_NAME]],S:S,U:U,"",0)=""),"Yes","No") -> No | Q11: 8 | R11: 2026 | S11: NGAN HANG TMCP TIEN PHONG | T11: TPBH | U11: A
A12: TCT TAI BAO HIEM QUOC GIA VN | B12: VINARE | C12: CTBH | D12: CC | L12: =IF(OR(CtpyRating[[#This Row],[FI_RATING]]="",_xlfn.XLOOKUP(CtpyRating[[#This Row],[CPTY_NAME]],S:S,U:U,"",0)=CtpyRating[[#This Row],[FI_RATING]],CtpyRating[[#This Row],[New Rating]]="Yes"),"No","Yes") -> No | M12: =IF(OR(CtpyRating[[#This Row],[FI_RATING_DATE]]="",CtpyRating[[#This Row],[FI_RATING_DATE]]=_xlfn.XLOOKUP(CtpyRating[[#This Row],[CPTY_NAME]],S:S,V:V,"",0),CtpyRating[[#This Row],[New Rating]]="Yes"),"No","Yes") -> No | N12: =IF(AND(CtpyRating[[#This Row],[FI_RATING]]<>"",_xlfn.XLOOKUP(CtpyRating[[#This Row],[CPTY_NAME]],S:S,U:U,"",0)=""),"Yes","No") -> No | Q12: 8 | R12: 2026 | S12: NGAN HANG TMCP NAM A | T12: SABH | U12: A | V12: 46141
A13: TCT CP TAI BAO HIEM PVI | B13: TBH_PVI | C13: CTBH | D13: CC | L13: =IF(OR(CtpyRating[[#This Row],[FI_RATING]]="",_xlfn.XLOOKUP(CtpyRating[[#This Row],[CPTY_NAME]],S:S,U:U,"",0)=CtpyRating[[#This Row],[FI_RATING]],CtpyRating[[#This Row],[New Rating]]="Yes"),"No","Yes") -> No | M13: =IF(OR(CtpyRating[[#This Row],[FI_RATING_DATE]]="",CtpyRating[[#This Row],[FI_RATING_DATE]]=_xlfn.XLOOKUP(CtpyRating[[#This Row],[CPTY_NAME]],S:S,V:V,"",0),CtpyRating[[#This Row],[New Rating]]="Yes"),"No","Yes") -> No | N13: =IF(AND(CtpyRating[[#This Row],[FI_RATING]]<>"",_xlfn.XLOOKUP(CtpyRating[[#This Row],[CPTY_NAME]],S:S,U:U,"",0)=""),"Yes","No") -> No | Q13: 8 | R13: 2026 | S13: NGAN HANG TMCP VIET A | T13: VABV | U13: BB | V13: 45792
A14: TCT CP BAO HIEM BUU DIEN PTI | B14: BH_BUUDIEN | C14: CTBH | D14: AAA | E14: 45917 | L14: =IF(OR(CtpyRating[[#This Row],[FI_RATING]]="",_xlfn.XLOOKUP(CtpyRating[[#This Row],[CPTY_NAME]],S:S,U:U,"",0)=CtpyRating[[#This Row],[FI_RATING]],CtpyRating[[#This Row],[New Rating]]="Yes"),"No","Yes") -> No | M14: =IF(OR(CtpyRating[[#This Row],[FI_RATING_DATE]]="",CtpyRating[[#This Row],[FI_RATING_DATE]]=_xlfn.XLOOKUP(CtpyRating[[#This Row],[CPTY_NAME]],S:S,V:V,"",0),CtpyRating[[#This Row],[New Rating]]="Yes"),"No","Yes") -> No | N14: =IF(AND(CtpyRating[[#This Row],[FI_RATING]]<>"",_xlfn.XLOOKUP(CtpyRating[[#This Row],[CPTY_NAME]],S:S,U:U,"",0)=""),"Yes","No") -> No | Q14: 8 | R14: 2026 | S14: NGAN HANG TMCP BAN VIET | T14: VCCB | U14: BB | V14: 46209
A15: TCT CP BAO HIEM BAO LONG | B15: BAOLONG | C15: CTBH | D15: CCC+ | L15: =IF(OR(CtpyRating[[#This Row],[FI_RATING]]="",_xlfn.XLOOKUP(CtpyRating[[#This Row],[CPTY_NAME]],S:S,U:U,"",0)=CtpyRating[[#This Row],[FI_RATING]],CtpyRating[[#This Row],[New Rating]]="Yes"),"No","Yes") -> No | M15: =IF(OR(CtpyRating[[#This Row],[FI_RATING_DATE]]="",CtpyRating[[#This Row],[FI_RATING_DATE]]=_xlfn.XLOOKUP(CtpyRating[[#This Row],[CPTY_NAME]],S:S,V:V,"",0),CtpyRating[[#This Row],[New Rating]]="Yes"),"No","Yes") -> No | N15: =IF(AND(CtpyRating[[#This Row],[FI_RATING]]<>"",_xlfn.XLOOKUP(CtpyRating[[#This Row],[CPTY_NAME]],S:S,U:U,"",0)=""),"Yes","No") -> No | Q15: 8 | R15: 2026 | S15: NGAN HANG TMCP SAI GON CONG THUONG | T15: SGCT | U15: CCC | V15: 46157
A16: TCT BAO VIET NHAN THO | B16: BAOVIETLIF | C16: CTBH | D16: D | L16: =IF(OR(CtpyRating[[#This Row],[FI_RATING]]="",_xlfn.XLOOKUP(CtpyRating[[#This Row],[CPTY_NAME]],S:S,U:U,"",0)=CtpyRating[[#This Row],[FI_RATING]],CtpyRating[[#This Row],[New Rating]]="Yes"),"No","Yes") -> No | M16: =IF(OR(CtpyRating[[#This Row],[FI_RATING_DATE]]="",CtpyRating[[#This Row],[FI_RATING_DATE]]=_xlfn.XLOOKUP(CtpyRating[[#This Row],[CPTY_NAME]],S:S,V:V,"",0),CtpyRating[[#This Row],[New Rating]]="Yes"),"No","Yes") -> No | N16: =IF(AND(CtpyRating[[#This Row],[FI_RATING]]<>"",_xlfn.XLOOKUP(CtpyRating[[#This Row],[CPTY_NAME]],S:S,U:U,"",0)=""),"Yes","No") -> No | Q16: 8 | R16: 2026 | S16: NGAN HANG TMCP BAC A | T16: NABV | U16: BBB | V16: 46146
A17: TCT BAO HIEM PVI | B17: PVI | C17: CTBH | D17: AAA | E17: 45961 | L17: =IF(OR(CtpyRating[[#This Row],[FI_RATING]]="",_xlfn.XLOOKUP(CtpyRating[[#This Row],[CPTY_NAME]],S:S,U:U,"",0)=CtpyRating[[#This Row],[FI_RATING]],CtpyRating[[#This Row],[New Rating]]="Yes"),"No","Yes") -> No | M17: =IF(OR(CtpyRating[[#This Row],[FI_RATING_DATE]]="",CtpyRating[[#This Row],[FI_RATING_DATE]]=_xlfn.XLOOKUP(CtpyRating[[#This Row],[CPTY_NAME]],S:S,V:V,"",0),CtpyRating[[#This Row],[New Rating]]="Yes"),"No","Yes") -> No | N17: =IF(AND(CtpyRating[[#This Row],[FI_RATING]]<>"",_xlfn.XLOOKUP(CtpyRating[[#This Row],[CPTY_NAME]],S:S,U:U,"",0)=""),"Yes","No") -> No | Q17: 8 | R17: 2026 | S17: NGAN HANG TMCP BAO VIET | T17: BVBH | U17: CC | V17: 46189
A18: TCT BAO HIEM PJICO | B18: BH_PJICO | C18: CTBH | D18: CCC+ | L18: =IF(OR(CtpyRating[[#This Row],[FI_RATING]]="",_xlfn.XLOOKUP(CtpyRating[[#This Row],[CPTY_NAME]],S:S,U:U,"",0)=CtpyRating[[#This Row],[FI_RATING]],CtpyRating[[#This Row],[New Rating]]="Yes"),"No","Yes") -> No | M18: =IF(OR(CtpyRating[[#This Row],[FI_RATING_DATE]]="",CtpyRating[[#This Row],[FI_RATING_DATE]]=_xlfn.XLOOKUP(CtpyRating[[#This Row],[CPTY_NAME]],S:S,V:V,"",0),CtpyRating[[#This Row],[New Rating]]="Yes"),"No","Yes") -> No | N18: =IF(AND(CtpyRating[[#This Row],[FI_RATING]]<>"",_xlfn.XLOOKUP(CtpyRating[[#This Row],[CPTY_NAME]],S:S,U:U,"",0)=""),"Yes","No") -> No | Q18: 8 | R18: 2026 | S18: NGAN HANG LIEN DOANH VIET NGA | T18: VRB | U18: BB | V18: 44326
A19: TCT BAO HIEM BAO VIET | B19: BH_BAOVIET | C19: CTBH | D19: D | L19: =IF(OR(CtpyRating[[#This Row],[FI_RATING]]="",_xlfn.XLOOKUP(CtpyRating[[#This Row],[CPTY_NAME]],S:S,U:U,"",0)=CtpyRating[[#This Row],[FI_RATING]],CtpyRating[[#This Row],[New Rating]]="Yes"),"No","Yes") -> No | M19: =IF(OR(CtpyRating[[#This Row],[FI_RATING_DATE]]="",CtpyRating[[#This Row],[FI_RATING_DATE]]=_xlfn.XLOOKUP(CtpyRating[[#This Row],[CPTY_NAME]],S:S,V:V,"",0),CtpyRating[[#This Row],[New Rating]]="Yes"),"No","Yes") -> No | N19: =IF(AND(CtpyRating[[#This Row],[FI_RATING]]<>"",_xlfn.XLOOKUP(CtpyRating[[#This Row],[CPTY_NAME]],S:S,U:U,"",0)=""),"Yes","No") -> No | Q19: 8 | R19: 2026 | S19: NGAN HANG TNHH MTV PUBLIC VN | T19: PBVN | U19: BB | V19: 45782
A20: TAP DOAN BAO VIET | B20: TD_BAOVIET | C20: CTBH | D20: CCC+ | L20: =IF(OR(CtpyRating[[#This Row],[FI_RATING]]="",_xlfn.XLOOKUP(CtpyRating[[#This Row],[CPTY_NAME]],S:S,U:U,"",0)=CtpyRating[[#This Row],[FI_RATING]],CtpyRating[[#This Row],[New Rating]]="Yes"),"No","Yes") -> No | M20: =IF(OR(CtpyRating[[#This Row],[FI_RATING_DATE]]="",CtpyRating[[#This Row],[FI_RATING_DATE]]=_xlfn.XLOOKUP(CtpyRating[[#This Row],[CPTY_NAME]],S:S,V:V,"",0),CtpyRating[[#This Row],[New Rating]]="Yes"),"No","Yes") -> No | N20: =IF(AND(CtpyRating[[#This Row],[FI_RATING]]<>"",_xlfn.XLOOKUP(CtpyRating[[#This Row],[CPTY_NAME]],S:S,U:U,"",0)=""),"Yes","No") -> No | Q20: 8 | R20: 2026 | S20: NGAN HANG TNHH MTV CIMB VN | T20: CIMB-VN | U20: BB | V20: 46169
A21: TAIPEI FUBON COMMERCIAL BANK | C21: NHNN | H21: A1 | I21: 45827 | L21: =IF(OR(CtpyRating[[#This Row],[FI_RATING]]="",_xlfn.XLOOKUP(CtpyRating[[#This Row],[CPTY_NAME]],S:S,U:U,"",0)=CtpyRating[[#This Row],[FI_RATING]],CtpyRating[[#This Row],[New Rating]]="Yes"),"No","Yes") -> No | M21: =IF(OR(CtpyRating[[#This Row],[FI_RATING_DATE]]="",CtpyRating[[#This Row],[FI_RATING_DATE]]=_xlfn.XLOOKUP(CtpyRating[[#This Row],[CPTY_NAME]],S:S,V:V,"",0),CtpyRating[[#This Row],[New Rating]]="Yes"),"No","Yes") -> No | N21: =IF(AND(CtpyRating[[#This Row],[FI_RATING]]<>"",_xlfn.XLOOKUP(CtpyRating[[#This Row],[CPTY_NAME]],S:S,U:U,"",0)=""),"Yes","No") -> No | Q21: 8 | R21: 2026 | S21: NGAN HANG TNHH INDOVINA | T21: IVB | U21: B | V21: 46183
A22: SUMITOMO MITSUI BANKING CORPORATION | B22: SMHN | C22: NHNN | F22: A | G22: 45945 | H22: A1 | I22: 45979 | L22: =IF(OR(CtpyRating[[#This Row],[FI_RATING]]="",_xlfn.XLOOKUP(CtpyRating[[#This Row],[CPTY_NAME]],S:S,U:U,"",0)=CtpyRating[[#This Row],[FI_RATING]],CtpyRating[[#This Row],[New Rating]]="Yes"),"No","Yes") -> No | M22: =IF(OR(CtpyRating[[#This Row],[FI_RATING_DATE]]="",CtpyRating[[#This Row],[FI_RATING_DATE]]=_xlfn.XLOOKUP(CtpyRating[[#This Row],[CPTY_NAME]],S:S,V:V,"",0),CtpyRating[[#This Row],[New Rating]]="Yes"),"No","Yes") -> No | N22: =IF(AND(CtpyRating[[#This Row],[FI_RATING]]<>"",_xlfn.XLOOKUP(CtpyRating[[#This Row],[CPTY_NAME]],S:S,U:U,"",0)=""),"Yes","No") -> No | Q22: 8 | R22: 2026 | S22: CONG TY TAI CHINH CO PHAN DIEN LUC | T22: TC_DIENLUC | U22: AA | V22: 46164
A23: STANDARD CHARTERED BANK | B23: SCHN-LD | C23: NHNN | H23: Aa1 | I23: 45985 | L23: =IF(OR(CtpyRating[[#This Row],[FI_RATING]]="",_xlfn.XLOOKUP(CtpyRating[[#This Row],[CPTY_NAME]],S:S,U:U,"",0)=CtpyRating[[#This Row],[FI_RATING]],CtpyRating[[#This Row],[New Rating]]="Yes"),"No","Yes") -> No | M23: =IF(OR(CtpyRating[[#This Row],[FI_RATING_DATE]]="",CtpyRating[[#This Row],[FI_RATING_DATE]]=_xlfn.XLOOKUP(CtpyRating[[#This Row],[CPTY_NAME]],S:S,V:V,"",0),CtpyRating[[#This Row],[New Rating]]="Yes"),"No","Yes") -> No | N23: =IF(AND(CtpyRating[[#This Row],[FI_RATING]]<>"",_xlfn.XLOOKUP(CtpyRating[[#This Row],[CPTY_NAME]],S:S,U:U,"",0)=""),"Yes","No") -> No | Q23: 8 | R23: 2026 | S23: NGAN HANG TMCP VIET NAM THUONG TIN | T23: VIETBANK | U23: BB | V23: 46128
A24: SAXO BANK A/S | B24: SAXOBANK | C24: NHNN | J24: A- | K24: 45820 | L24: =IF(OR(CtpyRating[[#This Row],[FI_RATING]]="",_xlfn.XLOOKUP(CtpyRating[[#This Row],[CPTY_NAME]],S:S,U:U,"",0)=CtpyRating[[#This Row],[FI_RATING]],CtpyRating[[#This Row],[New Rating]]="Yes"),"No","Yes") -> No | M24: =IF(OR(CtpyRating[[#This Row],[FI_RATING_DATE]]="",CtpyRating[[#This Row],[FI_RATING_DATE]]=_xlfn.XLOOKUP(CtpyRating[[#This Row],[CPTY_NAME]],S:S,V:V,"",0),CtpyRating[[#This Row],[New Rating]]="Yes"),"No","Yes") -> No | N24: =IF(AND(CtpyRating[[#This Row],[FI_RATING]]<>"",_xlfn.XLOOKUP(CtpyRating[[#This Row],[CPTY_NAME]],S:S,U:U,"",0)=""),"Yes","No") -> No | Q24: 8 | R24: 2026 | S24: NGAN HANG TMCP LOC PHAT VN | T24: LVBT | U24: AA | V24: 46199
A25: RAIFFEISEN BANK INTERNATIONAL | B25: RBI | C25: NHNN | D25: BBB | H25: A3 | J25: A- | L25: =IF(OR(CtpyRating[[#This Row],[FI_RATING]]="",_xlfn.XLOOKUP(CtpyRating[[#This Row],[CPTY_NAME]],S:S,U:U,"",0)=CtpyRating[[#This Row],[FI_RATING]],CtpyRating[[#This Row],[New Rating]]="Yes"),"No","Yes") -> No | M25: =IF(OR(CtpyRating[[#This Row],[FI_RATING_DATE]]="",CtpyRating[[#This Row],[FI_RATING_DATE]]=_xlfn.XLOOKUP(CtpyRating[[#This Row],[CPTY_NAME]],S:S,V:V,"",0),CtpyRating[[#This Row],[New Rating]]="Yes"),"No","Yes") -> No | N25: =IF(AND(CtpyRating[[#This Row],[FI_RATING]]<>"",_xlfn.XLOOKUP(CtpyRating[[#This Row],[CPTY_NAME]],S:S,U:U,"",0)=""),"Yes","No") -> No | Q25: 8 | R25: 2026 | S25: NGAN HANG TMCP VIET NAM THINH VUONG | T25: VPVN | U25: AA | V25: 46142
A26: QUOC GIA KYRGYZ REPUBLIC | B26: MFKR | C26: QG | D26: BBB | F26: B | G26: 46132 | H26: B3 | I26: 45849 | J26: B+ | K26: 45744 | L26: No | M26: =IF(OR(CtpyRating[[#This Row],[FI_RATING_DATE]]="",CtpyRating[[#This Row],[FI_RATING_DATE]]=_xlfn.XLOOKUP(CtpyRating[[#This Row],[CPTY_NAME]],S:S,V:V,"",0),CtpyRating[[#This Row],[New Rating]]="Yes"),"No","Yes") -> No | N26: No | Q26: 8 | R26: 2026 | S26: NGAN HANG TMCP NGOAI THUONG VN | T26: VCBH | U26: AAA | V26: 46196
A27: PHONGSAVANH BANK LIMITED | B27: PHONGSAVANH | C27: NHNN | D27: D | E27: 45875 | L27: =IF(OR(CtpyRating[[#This Row],[FI_RATING]]="",_xlfn.XLOOKUP(CtpyRating[[#This Row],[CPTY_NAME]],S:S,U:U,"",0)=CtpyRating[[#This Row],[FI_RATING]],CtpyRating[[#This Row],[New Rating]]="Yes"),"No","Yes") -> No | M27: =IF(OR(CtpyRating[[#This Row],[FI_RATING_DATE]]="",CtpyRating[[#This Row],[FI_RATING_DATE]]=_xlfn.XLOOKUP(CtpyRating[[#This Row],[CPTY_NAME]],S:S,V:V,"",0),CtpyRating[[#This Row],[New Rating]]="Yes"),"No","Yes") -> No | N27: =IF(AND(CtpyRating[[#This Row],[FI_RATING]]<>"",_xlfn.XLOOKUP(CtpyRating[[#This Row],[CPTY_NAME]],S:S,U:U,"",0)=""),"Yes","No") -> No | Q27: 8 | R27: 2026 | S27: NGAN HANG TMCP DAU TU VA PHAT TRIEN VN | T27: BIDV | U27: AAA
A28: NONGHYUP BANK | B28: NONGHYUP | C28: NHNN | F28: A | G28: 45952 | H28: Aa3 | I28: 45953 | L28: =IF(OR(CtpyRating[[#This Row],[FI_RATING]]="",_xlfn.XLOOKUP(CtpyRating[[#This Row],[CPTY_NAME]],S:S,U:U,"",0)=CtpyRating[[#This Row],[FI_RATING]],CtpyRating[[#This Row],[New Rating]]="Yes"),"No","Yes") -> No | M28: =IF(OR(CtpyRating[[#This Row],[FI_RATING_DATE]]="",CtpyRating[[#This Row],[FI_RATING_DATE]]=_xlfn.XLOOKUP(CtpyRating[[#This Row],[CPTY_NAME]],S:S,V:V,"",0),CtpyRating[[#This Row],[New Rating]]="Yes"),"No","Yes") -> No | N28: =IF(AND(CtpyRating[[#This Row],[FI_RATING]]<>"",_xlfn.XLOOKUP(CtpyRating[[#This Row],[CPTY_NAME]],S:S,U:U,"",0)=""),"Yes","No") -> No | Q28: 8 | R28: 2026 | S28: NGAN HANG TMCP CONG THUONG VN | T28: ICBV | U28: AAA | V28: 45859
A29: NGAN HANG TNHH MTV WOORI VIET NAM | B29: HVHB-VN | C29: Local Bank | D29: AA | E29: 46197 | L29: =IF(OR(CtpyRating[[#This Row],[FI_RATING]]="",_xlfn.XLOOKUP(CtpyRating[[#This Row],[CPTY_NAME]],S:S,U:U,"",0)=CtpyRating[[#This Row],[FI_RATING]],CtpyRating[[#This Row],[New Rating]]="Yes"),"No","Yes") -> No | M29: =IF(OR(CtpyRating[[#This Row],[FI_RATING_DATE]]="",CtpyRating[[#This Row],[FI_RATING_DATE]]=_xlfn.XLOOKUP(CtpyRating[[#This Row],[CPTY_NAME]],S:S,V:V,"",0),CtpyRating[[#This Row],[New Rating]]="Yes"),"No","Yes") -> No | N29: =IF(AND(CtpyRating[[#This Row],[FI_RATING]]<>"",_xlfn.XLOOKUP(CtpyRating[[#This Row],[CPTY_NAME]],S:S,U:U,"",0)=""),"Yes","No") -> No | Q29: 8 | R29: 2026 | S29: NGAN HANG TMCP QUAN DOI | T29: MCSB | U29: AAA | V29: 46136
A30: NGAN HANG TNHH MTV VIET NAM HIEN DAI | C30: Local Bank | D30: D | L30: =IF(OR(CtpyRating[[#This Row],[FI_RATING]]="",_xlfn.XLOOKUP(CtpyRating[[#This Row],[CPTY_NAME]],S:S,U:U,"",0)=CtpyRating[[#This Row],[FI_RATING]],CtpyRating[[#This Row],[New Rating]]="Yes"),"No","Yes") -> No | M30: =IF(OR(CtpyRating[[#This Row],[FI_RATING_DATE]]="",CtpyRating[[#This Row],[FI_RATING_DATE]]=_xlfn.XLOOKUP(CtpyRating[[#This Row],[CPTY_NAME]],S:S,V:V,"",0),CtpyRating[[#This Row],[New Rating]]="Yes"),"No","Yes") -> No | N30: =IF(AND(CtpyRating[[#This Row],[FI_RATING]]<>"",_xlfn.XLOOKUP(CtpyRating[[#This Row],[CPTY_NAME]],S:S,U:U,"",0)=""),"Yes","No") -> No | Q30: 8 | R30: 2026 | S30: NGAN HANG TMCP KY THUONG VN | T30: TCBV-HO | U30: AAA | V30: 46211
A31: NGAN HANG TNHH MTV UNITED OVERSEAS BANK VN | B31: UOB_SING | C31: Local Bank | D31: BBB | E31: 45912 | L31: =IF(OR(CtpyRating[[#This Row],[FI_RATING]]="",_xlfn.XLOOKUP(CtpyRating[[#This Row],[CPTY_NAME]],S:S,U:U,"",0)=CtpyRating[[#This Row],[FI_RATING]],CtpyRating[[#This Row],[New Rating]]="Yes"),"No","Yes") -> No | M31: =IF(OR(CtpyRating[[#This Row],[FI_RATING_DATE]]="",CtpyRating[[#This Row],[FI_RATING_DATE]]=_xlfn.XLOOKUP(CtpyRating[[#This Row],[CPTY_NAME]],S:S,V:V,"",0),CtpyRating[[#This Row],[New Rating]]="Yes"),"No","Yes") -> No | N31: =IF(AND(CtpyRating[[#This Row],[FI_RATING]]<>"",_xlfn.XLOOKUP(CtpyRating[[#This Row],[CPTY_NAME]],S:S,U:U,"",0)=""),"Yes","No") -> No | Q31: 8 | R31: 2026 | S31: NGAN HANG TMCP XUAT NHAP KHAU VN | T31: EIBV | U31: BB | V31: 46190
A32: NGAN HANG TNHH MTV STANDARD CHARTERED VN | B32: SCHN-VN | C32: Local Bank | D32: A | E32: 46197 | F32: BB+ | G32: 45974 | L32: =IF(OR(CtpyRating[[#This Row],[FI_RATING]]="",_xlfn.XLOOKUP(CtpyRating[[#This Row],[CPTY_NAME]],S:S,U:U,"",0)=CtpyRating[[#This Row],[FI_RATING]],CtpyRating[[#This Row],[New Rating]]="Yes"),"No","Yes") -> No | M32: =IF(OR(CtpyRating[[#This Row],[FI_RATING_DATE]]="",CtpyRating[[#This Row],[FI_RATING_DATE]]=_xlfn.XLOOKUP(CtpyRating[[#This Row],[CPTY_NAME]],S:S,V:V,"",0),CtpyRating[[#This Row],[New Rating]]="Yes"),"No","Yes") -> No | N32: =IF(AND(CtpyRating[[#This Row],[FI_RATING]]<>"",_xlfn.XLOOKUP(CtpyRating[[#This Row],[CPTY_NAME]],S:S,U:U,"",0)=""),"Yes","No") -> No | Q32: 8 | R32: 2026 | S32: NGAN HANG TMCP SAI GON TAI LOC | T32: SGTT | U32: A
A33: NGAN HANG TNHH MTV SO VIKKI | C33: Local Bank | D33: D | L33: =IF(OR(CtpyRating[[#This Row],[FI_RATING]]="",_xlfn.XLOOKUP(CtpyRating[[#This Row],[CPTY_NAME]],S:S,U:U,"",0)=CtpyRating[[#This Row],[FI_RATING]],CtpyRating[[#This Row],[New Rating]]="Yes"),"No","Yes") -> No | M33: =IF(OR(CtpyRating[[#This Row],[FI_RATING_DATE]]="",CtpyRating[[#This Row],[FI_RATING_DATE]]=_xlfn.XLOOKUP(CtpyRating[[#This Row],[CPTY_NAME]],S:S,V:V,"",0),CtpyRating[[#This Row],[New Rating]]="Yes"),"No","Yes") -> No | N33: =IF(AND(CtpyRating[[#This Row],[FI_RATING]]<>"",_xlfn.XLOOKUP(CtpyRating[[#This Row],[CPTY_NAME]],S:S,U:U,"",0)=""),"Yes","No") -> No | Q33: 8 | R33: 2026 | S33: NGAN HANG TMCP A CHAU | T33: ACBV | U33: AA | V33: 46203
A34: NGAN HANG TNHH MTV SHINHAN VN | B34: SHHC | C34: Local Bank | D34: AA | E34: 46119 | L34: =IF(OR(CtpyRating[[#This Row],[FI_RATING]]="",_xlfn.XLOOKUP(CtpyRating[[#This Row],[CPTY_NAME]],S:S,U:U,"",0)=CtpyRating[[#This Row],[FI_RATING]],CtpyRating[[#This Row],[New Rating]]="Yes"),"No","Yes") -> No | M34: =IF(OR(CtpyRating[[#This Row],[FI_RATING_DATE]]="",CtpyRating[[#This Row],[FI_RATING_DATE]]=_xlfn.XLOOKUP(CtpyRating[[#This Row],[CPTY_NAME]],S:S,V:V,"",0),CtpyRating[[#This Row],[New Rating]]="Yes"),"No","Yes") -> No | N34: =IF(AND(CtpyRating[[#This Row],[FI_RATING]]<>"",_xlfn.XLOOKUP(CtpyRating[[#This Row],[CPTY_NAME]],S:S,U:U,"",0)=""),"Yes","No") -> No | Q34: 8 | R34: 2026 | S34: NGAN HANG TMCP QUOC TE | T34: VIBH | U34: BBB
A35: NGAN HANG TNHH MTV PUBLIC VN | B35: PBVN | C35: Local Bank | D35: BB | E35: 46237 | L35: =IF(OR(CtpyRating[[#This Row],[FI_RATING]]="",_xlfn.XLOOKUP(CtpyRating[[#This Row],[CPTY_NAME]],S:S,U:U,"",0)=CtpyRating[[#This Row],[FI_RATING]],CtpyRating[[#This Row],[New Rating]]="Yes"),"No","Yes") -> No | M35: =IF(OR(CtpyRating[[#This Row],[FI_RATING_DATE]]="",CtpyRating[[#This Row],[FI_RATING_DATE]]=_xlfn.XLOOKUP(CtpyRating[[#This Row],[CPTY_NAME]],S:S,V:V,"",0),CtpyRating[[#This Row],[New Rating]]="Yes"),"No","Yes") -> Yes | N35: =IF(AND(CtpyRating[[#This Row],[FI_RATING]]<>"",_xlfn.XLOOKUP(CtpyRating[[#This Row],[CPTY_NAME]],S:S,U:U,"",0)=""),"Yes","No") -> No | Q35: 8 | R35: 2026 | S35: NGAN HANG TMCP PHAT TRIEN TP HO CHI MINH | T35: HDBV | U35: AA | V35: 46022
A36: NGAN HANG TNHH MTV HSBC VN | B36: HSHC-VN | C36: Local Bank | D36: AA- | L36: =IF(OR(CtpyRating[[#This Row],[FI_RATING]]="",_xlfn.XLOOKUP(CtpyRating[[#This Row],[CPTY_NAME]],S:S,U:U,"",0)=CtpyRating[[#This Row],[FI_RATING]],CtpyRating[[#This Row],[New Rating]]="Yes"),"No","Yes") -> No | M36: =IF(OR(CtpyRating[[#This Row],[FI_RATING_DATE]]="",CtpyRating[[#This Row],[FI_RATING_DATE]]=_xlfn.XLOOKUP(CtpyRating[[#This Row],[CPTY_NAME]],S:S,V:V,"",0),CtpyRating[[#This Row],[New Rating]]="Yes"),"No","Yes") -> No | N36: =IF(AND(CtpyRating[[#This Row],[FI_RATING]]<>"",_xlfn.XLOOKUP(CtpyRating[[#This Row],[CPTY_NAME]],S:S,U:U,"",0)=""),"Yes","No") -> No | Q36: 8 | R36: 2026 | S36: NGAN HANG TMCP AN BINH | T36: ABBV | U36: BBB | V36: 46172
A37: NGAN HANG TNHH MTV HONG LEONG VN | B37: HLBV-VN | C37: Local Bank | D37: AAA | E37: 46227 | L37: =IF(OR(CtpyRating[[#This Row],[FI_RATING]]="",_xlfn.XLOOKUP(CtpyRating[[#This Row],[CPTY_NAME]],S:S,U:U,"",0)=CtpyRating[[#This Row],[FI_RATING]],CtpyRating[[#This Row],[New Rating]]="Yes"),"No","Yes") -> No | M37: =IF(OR(CtpyRating[[#This Row],[FI_RATING_DATE]]="",CtpyRating[[#This Row],[FI_RATING_DATE]]=_xlfn.XLOOKUP(CtpyRating[[#This Row],[CPTY_NAME]],S:S,V:V,"",0),CtpyRating[[#This Row],[New Rating]]="Yes"),"No","Yes") -> No | N37: =IF(AND(CtpyRating[[#This Row],[FI_RATING]]<>"",_xlfn.XLOOKUP(CtpyRating[[#This Row],[CPTY_NAME]],S:S,U:U,"",0)=""),"Yes","No") -> No | Q37: 8 | R37: 2026 | S37: CONG TY TAI CHINH CO PHAN TIN VIET | T37: CFCV | U37: A | V37: 46140
A38: NGAN HANG TNHH MTV CIMB VN | B38: CIMB-VN | C38: Local Bank | D38: BB | E38: 46169 | L38: =IF(OR(CtpyRating[[#This Row],[FI_RATING]]="",_xlfn.XLOOKUP(CtpyRating[[#This Row],[CPTY_NAME]],S:S,U:U,"",0)=CtpyRating[[#This Row],[FI_RATING]],CtpyRating[[#This Row],[New Rating]]="Yes"),"No","Yes") -> No | M38: =IF(OR(CtpyRating[[#This Row],[FI_RATING_DATE]]="",CtpyRating[[#This Row],[FI_RATING_DATE]]=_xlfn.XLOOKUP(CtpyRating[[#This Row],[CPTY_NAME]],S:S,V:V,"",0),CtpyRating[[#This Row],[New Rating]]="Yes"),"No","Yes") -> No | N38: =IF(AND(CtpyRating[[#This Row],[FI_RATING]]<>"",_xlfn.XLOOKUP(CtpyRating[[#This Row],[CPTY_NAME]],S:S,U:U,"",0)=""),"Yes","No") -> No | Q38: 8 | R38: 2026 | S38: TCT CP BAO HIEM BUU DIEN PTI | T38: BH_BUUDIEN | U38: AAA | V38: 45917
A39: NGAN HANG TNHH MTV ANZ VN | B39: ANZF-VN | C39: Local Bank | D39: A | E39: 46196 | F39: BB+ | G39: 45974 | L39: =IF(OR(CtpyRating[[#This Row],[FI_RATING]]="",_xlfn.XLOOKUP(CtpyRating[[#This Row],[CPTY_NAME]],S:S,U:U,"",0)=CtpyRating[[#This Row],[FI_RATING]],CtpyRating[[#This Row],[New Rating]]="Yes"),"No","Yes") -> No | M39: =IF(OR(CtpyRating[[#This Row],[FI_RATING_DATE]]="",CtpyRating[[#This Row],[FI_RATING_DATE]]=_xlfn.XLOOKUP(CtpyRating[[#This Row],[CPTY_NAME]],S:S,V:V,"",0),CtpyRating[[#This Row],[New Rating]]="Yes"),"No","Yes") -> No | N39: =IF(AND(CtpyRating[[#This Row],[FI_RATING]]<>"",_xlfn.XLOOKUP(CtpyRating[[#This Row],[CPTY_NAME]],S:S,U:U,"",0)=""),"Yes","No") -> No | Q39: 8 | R39: 2026 | S39: TCT BAO HIEM PJICO | T39: BH_PJICO | U39: CCC+
A40: NGAN HANG TNHH INDOVINA | B40: IVB | C40: Local Bank | D40: B | E40: 46183 | L40: =IF(OR(CtpyRating[[#This Row],[FI_RATING]]="",_xlfn.XLOOKUP(CtpyRating[[#This Row],[CPTY_NAME]],S:S,U:U,"",0)=CtpyRating[[#This Row],[FI_RATING]],CtpyRating[[#This Row],[New Rating]]="Yes"),"No","Yes") -> No | M40: =IF(OR(CtpyRating[[#This Row],[FI_RATING_DATE]]="",CtpyRating[[#This Row],[FI_RATING_DATE]]=_xlfn.XLOOKUP(CtpyRating[[#This Row],[CPTY_NAME]],S:S,V:V,"",0),CtpyRating[[#This Row],[New Rating]]="Yes"),"No","Yes") -> No | N40: =IF(AND(CtpyRating[[#This Row],[FI_RATING]]<>"",_xlfn.XLOOKUP(CtpyRating[[#This Row],[CPTY_NAME]],S:S,U:U,"",0)=""),"Yes","No") -> No | Q40: 8 | R40: 2026 | S40: CONG TY BAO HIEM LIEN HIEP UIC | T40: BH_LIENHIE | U40: BBB | V40: 45936
A41: NGAN HANG TNHH CONG THUONG VIET NAM TAI LAO | B41: ICBV-LAO | C41: NHNN | D41: D | L41: =IF(OR(CtpyRating[[#This Row],[FI_RATING]]="",_xlfn.XLOOKUP(CtpyRating[[#This Row],[CPTY_NAME]],S:S,U:U,"",0)=CtpyRating[[#This Row],[FI_RATING]],CtpyRating[[#This Row],[New Rating]]="Yes"),"No","Yes") -> No | M41: =IF(OR(CtpyRating[[#This Row],[FI_RATING_DATE]]="",CtpyRating[[#This Row],[FI_RATING_DATE]]=_xlfn.XLOOKUP(CtpyRating[[#This Row],[CPTY_NAME]],S:S,V:V,"",0),CtpyRating[[#This Row],[New Rating]]="Yes"),"No","Yes") -> No | N41: =IF(AND(CtpyRating[[#This Row],[FI_RATING]]<>"",_xlfn.XLOOKUP(CtpyRating[[#This Row],[CPTY_NAME]],S:S,U:U,"",0)=""),"Yes","No") -> No | Q41: 8 | R41: 2026 | S41: CONG TY CP TAP DOAN BAO HIEM DBV | U41: BBB
A42: NGAN HANG TMCP XUAT NHAP KHAU VN | B42: EIBV | C42: Local Bank | D42: BB | E42: 46190 | J42: B+ | K42: 46128 | L42: =IF(OR(CtpyRating[[#This Row],[FI_RATING]]="",_xlfn.XLOOKUP(CtpyRating[[#This Row],[CPTY_NAME]],S:S,U:U,"",0)=CtpyRating[[#This Row],[FI_RATING]],CtpyRating[[#This Row],[New Rating]]="Yes"),"No","Yes") -> No | M42: =IF(OR(CtpyRating[[#This Row],[FI_RATING_DATE]]="",CtpyRating[[#This Row],[FI_RATING_DATE]]=_xlfn.XLOOKUP(CtpyRating[[#This Row],[CPTY_NAME]],S:S,V:V,"",0),CtpyRating[[#This Row],[New Rating]]="Yes"),"No","Yes") -> No | N42: =IF(AND(CtpyRating[[#This Row],[FI_RATING]]<>"",_xlfn.XLOOKUP(CtpyRating[[#This Row],[CPTY_NAME]],S:S,U:U,"",0)=""),"Yes","No") -> No | Q42: 8 | R42: 2026 | S42: TCT TAI BAO HIEM QUOC GIA VN | T42: VINARE | U42: CC
A43: NGAN HANG TMCP VIET NAM THUONG TIN | B43: VIETBANK | C43: Local Bank | D43: BB | E43: 46128 | L43: =IF(OR(CtpyRating[[#This Row],[FI_RATING]]="",_xlfn.XLOOKUP(CtpyRating[[#This Row],[CPTY_NAME]],S:S,U:U,"",0)=CtpyRating[[#This Row],[FI_RATING]],CtpyRating[[#This Row],[New Rating]]="Yes"),"No","Yes") -> No | M43: =IF(OR(CtpyRating[[#This Row],[FI_RATING_DATE]]="",CtpyRating[[#This Row],[FI_RATING_DATE]]=_xlfn.XLOOKUP(CtpyRating[[#This Row],[CPTY_NAME]],S:S,V:V,"",0),CtpyRating[[#This Row],[New Rating]]="Yes"),"No","Yes") -> No | N43: =IF(AND(CtpyRating[[#This Row],[FI_RATING]]<>"",_xlfn.XLOOKUP(CtpyRating[[#This Row],[CPTY_NAME]],S:S,U:U,"",0)=""),"Yes","No") -> No | Q43: 8 | R43: 2026 | S43: CONG TY TNHH BAO HIEM NHAN THO PREVOIR | T43: PREVOIR | U43: D
A44: NGAN HANG TMCP VIET NAM THINH VUONG | B44: VPVN | C44: Local Bank | D44: AA | E44: 46142 | H44: Ba3 | I44: 45768 | L44: =IF(OR(CtpyRating[[#This Row],[FI_RATING]]="",_xlfn.XLOOKUP(CtpyRating[[#This Row],[CPTY_NAME]],S:S,U:U,"",0)=CtpyRating[[#This Row],[FI_RATING]],CtpyRating[[#This Row],[New Rating]]="Yes"),"No","Yes") -> No | M44: =IF(OR(CtpyRating[[#This Row],[FI_RATING_DATE]]="",CtpyRating[[#This Row],[FI_RATING_DATE]]=_xlfn.XLOOKUP(CtpyRating[[#This Row],[CPTY_NAME]],S:S,V:V,"",0),CtpyRating[[#This Row],[New Rating]]="Yes"),"No","Yes") -> No | N44: =IF(AND(CtpyRating[[#This Row],[FI_RATING]]<>"",_xlfn.XLOOKUP(CtpyRating[[#This Row],[CPTY_NAME]],S:S,U:U,"",0)=""),"Yes","No") -> No | Q44: 8 | R44: 2026 | S44: TONG CONG TY CP BAO MINH | T44: TCT_CPBM | U44: AAA | V44: 45981
A45: NGAN HANG TMCP VIET A | B45: VABV | C45: Local Bank | D45: BB | E45: 45792 | F45: B+ | G45: 45896 | H45: B2 | I45: 45329 | L45: =IF(OR(CtpyRating[[#This Row],[FI_RATING]]="",_xlfn.XLOOKUP(CtpyRating[[#This Row],[CPTY_NAME]],S:S,U:U,"",0)=CtpyRating[[#This Row],[FI_RATING]],CtpyRating[[#This Row],[New Rating]]="Yes"),"No","Yes") -> No | M45: =IF(OR(CtpyRating[[#This Row],[FI_RATING_DATE]]="",CtpyRating[[#This Row],[FI_RATING_DATE]]=_xlfn.XLOOKUP(CtpyRating[[#This Row],[CPTY_NAME]],S:S,V:V,"",0),CtpyRating[[#This Row],[New Rating]]="Yes"),"No","Yes") -> No | N45: =IF(AND(CtpyRating[[#This Row],[FI_RATING]]<>"",_xlfn.XLOOKUP(CtpyRating[[#This Row],[CPTY_NAME]],S:S,U:U,"",0)=""),"Yes","No") -> No | Q45: 8 | R45: 2026 | S45: TAP DOAN BAO VIET | T45: TD_BAOVIET | U45: CCC+
A46: NGAN HANG TMCP TIEN PHONG | B46: TPBH | C46: Local Bank | D46: A | H46: B1 | I46: 45923 | L46: =IF(OR(CtpyRating[[#This Row],[FI_RATING]]="",_xlfn.XLOOKUP(CtpyRating[[#This Row],[CPTY_NAME]],S:S,U:U,"",0)=CtpyRating[[#This Row],[FI_RATING]],CtpyRating[[#This Row],[New Rating]]="Yes"),"No","Yes") -> No | M46: =IF(OR(CtpyRating[[#This Row],[FI_RATING_DATE]]="",CtpyRating[[#This Row],[FI_RATING_DATE]]=_xlfn.XLOOKUP(CtpyRating[[#This Row],[CPTY_NAME]],S:S,V:V,"",0),CtpyRating[[#This Row],[New Rating]]="Yes"),"No","Yes") -> No | N46: =IF(AND(CtpyRating[[#This Row],[FI_RATING]]<>"",_xlfn.XLOOKUP(CtpyRating[[#This Row],[CPTY_NAME]],S:S,U:U,"",0)=""),"Yes","No") -> No | Q46: 8 | R46: 2026 | S46: TCT BAO VIET NHAN THO | T46: BAOVIETLIF | U46: D
A47: NGAN HANG TMCP THINH VUONG VA PHAT TRIEN | B47: PGBV-HO | C47: Local Bank | D47: B | E47: 45835 | L47: =IF(OR(CtpyRating[[#This Row],[FI_RATING]]="",_xlfn.XLOOKUP(CtpyRating[[#This Row],[CPTY_NAME]],S:S,U:U,"",0)=CtpyRating[[#This Row],[FI_RATING]],CtpyRating[[#This Row],[New Rating]]="Yes"),"No","Yes") -> No | M47: =IF(OR(CtpyRating[[#This Row],[FI_RATING_DATE]]="",CtpyRating[[#This Row],[FI_RATING_DATE]]=_xlfn.XLOOKUP(CtpyRating[[#This Row],[CPTY_NAME]],S:S,V:V,"",0),CtpyRating[[#This Row],[New Rating]]="Yes"),"No","Yes") -> No | N47: =IF(AND(CtpyRating[[#This Row],[FI_RATING]]<>"",_xlfn.XLOOKUP(CtpyRating[[#This Row],[CPTY_NAME]],S:S,U:U,"",0)=""),"Yes","No") -> No | Q47: 8 | R47: 2026 | S47: TCT BAO HIEM BAO VIET | T47: BH_BAOVIET | U47: D
A48: NGAN HANG TMCP SAI GON TAI LOC | B48: SGTT | C48: Local Bank | D48: A | E48: 46253 | F48: BB- | G48: 46140 | H48: B1 | I48: 45979 | L48: =IF(OR(CtpyRating[[#This Row],[FI_RATING]]="",_xlfn.XLOOKUP(CtpyRating[[#This Row],[CPTY_NAME]],S:S,U:U,"",0)=CtpyRating[[#This Row],[FI_RATING]],CtpyRating[[#This Row],[New Rating]]="Yes"),"No","Yes") -> No | M48: =IF(OR(CtpyRating[[#This Row],[FI_RATING_DATE]]="",CtpyRating[[#This Row],[FI_RATING_DATE]]=_xlfn.XLOOKUP(CtpyRating[[#This Row],[CPTY_NAME]],S:S,V:V,"",0),CtpyRating[[#This Row],[New Rating]]="Yes"),"No","Yes") -> Yes | N48: =IF(AND(CtpyRating[[#This Row],[FI_RATING]]<>"",_xlfn.XLOOKUP(CtpyRating[[#This Row],[CPTY_NAME]],S:S,U:U,"",0)=""),"Yes","No") -> No | Q48: 8 | R48: 2026 | S48: CONG TY CP PVI | T48: PVI | U48: D
A49: NGAN HANG TMCP SAI GON HA NOI | B49: SHBV | C49: Local Bank | D49: A | E49: 46211 | F49: BB- | G49: 45967 | H49: B1 | I49: 46133 | L49: =IF(OR(CtpyRating[[#This Row],[FI_RATING]]="",_xlfn.XLOOKUP(CtpyRating[[#This Row],[CPTY_NAME]],S:S,U:U,"",0)=CtpyRating[[#This Row],[FI_RATING]],CtpyRating[[#This Row],[New Rating]]="Yes"),"No","Yes") -> No | M49: =IF(OR(CtpyRating[[#This Row],[FI_RATING_DATE]]="",CtpyRating[[#This Row],[FI_RATING_DATE]]=_xlfn.XLOOKUP(CtpyRating[[#This Row],[CPTY_NAME]],S:S,V:V,"",0),CtpyRating[[#This Row],[New Rating]]="Yes"),"No","Yes") -> No | N49: =IF(AND(CtpyRating[[#This Row],[FI_RATING]]<>"",_xlfn.XLOOKUP(CtpyRating[[#This Row],[CPTY_NAME]],S:S,U:U,"",0)=""),"Yes","No") -> No | Q49: 8 | R49: 2026 | S49: CONG TY TNHH BAO HIEM NHAN THO ACE | T49: BH_ACE | U49: D
A50: NGAN HANG TMCP SAI GON CONG THUONG | B50: SGCT | C50: Local Bank | D50: CCC | E50: 46157 | L50: =IF(OR(CtpyRating[[#This Row],[FI_RATING]]="",_xlfn.XLOOKUP(CtpyRating[[#This Row],[CPTY_NAME]],S:S,U:U,"",0)=CtpyRating[[#This Row],[FI_RATING]],CtpyRating[[#This Row],[New Rating]]="Yes"),"No","Yes") -> No | M50: =IF(OR(CtpyRating[[#This Row],[FI_RATING_DATE]]="",CtpyRating[[#This Row],[FI_RATING_DATE]]=_xlfn.XLOOKUP(CtpyRating[[#This Row],[CPTY_NAME]],S:S,V:V,"",0),CtpyRating[[#This Row],[New Rating]]="Yes"),"No","Yes") -> No | N50: =IF(AND(CtpyRating[[#This Row],[FI_RATING]]<>"",_xlfn.XLOOKUP(CtpyRating[[#This Row],[CPTY_NAME]],S:S,U:U,"",0)=""),"Yes","No") -> No | Q50: 8 | R50: 2026 | S50: CONG TY TNHH BAO HIEM NHAN THO AIA | T50: BH_AIA | U50: D
A51: NGAN HANG TMCP SAI GON | B51: SCBV | C51: Local Bank | D51: CC | E51: 44781 | L51: =IF(OR(CtpyRating[[#This Row],[FI_RATING]]="",_xlfn.XLOOKUP(CtpyRating[[#This Row],[CPTY_NAME]],S:S,U:U,"",0)=CtpyRating[[#This Row],[FI_RATING]],CtpyRating[[#This Row],[New Rating]]="Yes"),"No","Yes") -> No | M51: =IF(OR(CtpyRating[[#This Row],[FI_RATING_DATE]]="",CtpyRating[[#This Row],[FI_RATING_DATE]]=_xlfn.XLOOKUP(CtpyRating[[#This Row],[CPTY_NAME]],S:S,V:V,"",0),CtpyRating[[#This Row],[New Rating]]="Yes"),"No","Yes") -> No | N51: =IF(AND(CtpyRating[[#This Row],[FI_RATING]]<>"",_xlfn.XLOOKUP(CtpyRating[[#This Row],[CPTY_NAME]],S:S,U:U,"",0)=""),"Yes","No") -> No | Q51: 8 | R51: 2026 | S51: CONG TY TNHH BAO HIEM NHAN THO CATHAY | T51: BH_CATHAY | U51: D
A52: NGAN HANG TMCP QUOC TE | B52: VIBH | C52: Local Bank | D52: BBB | H52: Ba3 | L52: =IF(OR(CtpyRating[[#This Row],[FI_RATING]]="",_xlfn.XLOOKUP(CtpyRating[[#This Row],[CPTY_NAME]],S:S,U:U,"",0)=CtpyRating[[#This Row],[FI_RATING]],CtpyRating[[#This Row],[New Rating]]="Yes"),"No","Yes") -> No | M52: =IF(OR(CtpyRating[[#This Row],[FI_RATING_DATE]]="",CtpyRating[[#This Row],[FI_RATING_DATE]]=_xlfn.XLOOKUP(CtpyRating[[#This Row],[CPTY_NAME]],S:S,V:V,"",0),CtpyRating[[#This Row],[New Rating]]="Yes"),"No","Yes") -> No | N52: =IF(AND(CtpyRating[[#This Row],[FI_RATING]]<>"",_xlfn.XLOOKUP(CtpyRating[[#This Row],[CPTY_NAME]],S:S,U:U,"",0)=""),"Yes","No") -> No | Q52: 8 | R52: 2026 | S52: CONG TY TNHH BAO HIEM NHAN THO DAI-ICHI VN | T52: BH_DAICHI | U52: D
A53: NGAN HANG TMCP QUOC DAN | B53: NCBV | C53: Local Bank | D53: D | E53: 45730 | L53: =IF(OR(CtpyRating[[#This Row],[FI_RATING]]="",_xlfn.XLOOKUP(CtpyRating[[#This Row],[CPTY_NAME]],S:S,U:U,"",0)=CtpyRating[[#This Row],[FI_RATING]],CtpyRating[[#This Row],[New Rating]]="Yes"),"No","Yes") -> No | M53: =IF(OR(CtpyRating[[#This Row],[FI_RATING_DATE]]="",CtpyRating[[#This Row],[FI_RATING_DATE]]=_xlfn.XLOOKUP(CtpyRating[[#This Row],[CPTY_NAME]],S:S,V:V,"",0),CtpyRating[[#This Row],[New Rating]]="Yes"),"No","Yes") -> No | N53: =IF(AND(CtpyRating[[#This Row],[FI_RATING]]<>"",_xlfn.XLOOKUP(CtpyRating[[#This Row],[CPTY_NAME]],S:S,U:U,"",0)=""),"Yes","No") -> No | Q53: 8 | R53: 2026 | S53: CONG TY TNHH BAO HIEM NHAN THO FUBON | T53: BH_FUBON | U53: AAA
A54: NGAN HANG TMCP QUAN DOI | B54: MCSB | C54: Local Bank | D54: AAA | E54: 46136 | F54: BB | G54: 45967 | H54: Ba2 | I54: 46147 | L54: =IF(OR(CtpyRating[[#This Row],[FI_RATING]]="",_xlfn.XLOOKUP(CtpyRating[[#This Row],[CPTY_NAME]],S:S,U:U,"",0)=CtpyRating[[#This Row],[FI_RATING]],CtpyRating[[#This Row],[New Rating]]="Yes"),"No","Yes") -> No | M54: =IF(OR(CtpyRating[[#This Row],[FI_RATING_DATE]]="",CtpyRating[[#This Row],[FI_RATING_DATE]]=_xlfn.XLOOKUP(CtpyRating[[#This Row],[CPTY_NAME]],S:S,V:V,"",0),CtpyRating[[#This Row],[New Rating]]="Yes"),"No","Yes") -> No | N54: =IF(AND(CtpyRating[[#This Row],[FI_RATING]]<>"",_xlfn.XLOOKUP(CtpyRating[[#This Row],[CPTY_NAME]],S:S,U:U,"",0)=""),"Yes","No") -> No | Q54: 8 | R54: 2026 | S54: CONG TY TNHH BAO HIEM HANWHA LIFE VN | T54: BH_HANWHA | U54: D
A55: NGAN HANG TMCP PHUONG DONG | B55: OCBV | C55: Local Bank | D55: BBB | E55: 46206 | H55: Ba3 | I55: 45540 | L55: =IF(OR(CtpyRating[[#This Row],[FI_RATING]]="",_xlfn.XLOOKUP(CtpyRating[[#This Row],[CPTY_NAME]],S:S,U:U,"",0)=CtpyRating[[#This Row],[FI_RATING]],CtpyRating[[#This Row],[New Rating]]="Yes"),"No","Yes") -> No | M55: =IF(OR(CtpyRating[[#This Row],[FI_RATING_DATE]]="",CtpyRating[[#This Row],[FI_RATING_DATE]]=_xlfn.XLOOKUP(CtpyRating[[#This Row],[CPTY_NAME]],S:S,V:V,"",0),CtpyRating[[#This Row],[New Rating]]="Yes"),"No","Yes") -> No | N55: =IF(AND(CtpyRating[[#This Row],[FI_RATING]]<>"",_xlfn.XLOOKUP(CtpyRating[[#This Row],[CPTY_NAME]],S:S,U:U,"",0)=""),"Yes","No") -> No | Q55: 8 | R55: 2026 | S55: CONG TY TNHH MANULIFE VN | T55: BH_MANUL | U55: D
A56: NGAN HANG TMCP PHAT TRIEN TP HO CHI MINH | B56: HDBV | C56: Local Bank | D56: AA | E56: 46022 | H56: B1 | I56: 46133 | L56: =IF(OR(CtpyRating[[#This Row],[FI_RATING]]="",_xlfn.XLOOKUP(CtpyRating[[#This Row],[CPTY_NAME]],S:S,U:U,"",0)=CtpyRating[[#This Row],[FI_RATING]],CtpyRating[[#This Row],[New Rating]]="Yes"),"No","Yes") -> No | M56: =IF(OR(CtpyRating[[#This Row],[FI_RATING_DATE]]="",CtpyRating[[#This Row],[FI_RATING_DATE]]=_xlfn.XLOOKUP(CtpyRating[[#This Row],[CPTY_NAME]],S:S,V:V,"",0),CtpyRating[[#This Row],[New Rating]]="Yes"),"No","Yes") -> No | N56: =IF(AND(CtpyRating[[#This Row],[FI_RATING]]<>"",_xlfn.XLOOKUP(CtpyRating[[#This Row],[CPTY_NAME]],S:S,U:U,"",0)=""),"Yes","No") -> No | Q56: 8 | R56: 2026 | S56: CONG TY TNHH BAO HIEM NHAN THO SUN LIFE VN | T56: SUNLIFE | U56: D
A57: NGAN HANG TMCP NGOAI THUONG VN | B57: VCBH | C57: Local Bank | D57: AAA | E57: 46196 | F57: BB+ | G57: 45964 | H57: Ba2 | I57: 46147 | J57: BB+ | K57: 45894 | L57: =IF(OR(CtpyRating[[#This Row],[FI_RATING]]="",_xlfn.XLOOKUP(CtpyRating[[#This Row],[CPTY_NAME]],S:S,U:U,"",0)=CtpyRating[[#This Row],[FI_RATING]],CtpyRating[[#This Row],[New Rating]]="Yes"),"No","Yes") -> No | M57: =IF(OR(CtpyRating[[#This Row],[FI_RATING_DATE]]="",CtpyRating[[#This Row],[FI_RATING_DATE]]=_xlfn.XLOOKUP(CtpyRating[[#This Row],[CPTY_NAME]],S:S,V:V,"",0),CtpyRating[[#This Row],[New Rating]]="Yes"),"No","Yes") -> No | N57: =IF(AND(CtpyRating[[#This Row],[FI_RATING]]<>"",_xlfn.XLOOKUP(CtpyRating[[#This Row],[CPTY_NAME]],S:S,U:U,"",0)=""),"Yes","No") -> No | Q57: 8 | R57: 2026 | S57: CONG TY TNHH BAO HIEM TONG HOP GROUPAMA VN | T57: GROUPAMA | U57: D
A58: NGAN HANG TMCP NAM A | B58: SABH | C58: Local Bank | D58: A | E58: 46141 | F58: B+ | G58: 46078 | H58: B2 | I58: 46065 | L58: =IF(OR(CtpyRating[[#This Row],[FI_RATING]]="",_xlfn.XLOOKUP(CtpyRating[[#This Row],[CPTY_NAME]],S:S,U:U,"",0)=CtpyRating[[#This Row],[FI_RATING]],CtpyRating[[#This Row],[New Rating]]="Yes"),"No","Yes") -> No | M58: =IF(OR(CtpyRating[[#This Row],[FI_RATING_DATE]]="",CtpyRating[[#This Row],[FI_RATING_DATE]]=_xlfn.XLOOKUP(CtpyRating[[#This Row],[CPTY_NAME]],S:S,V:V,"",0),CtpyRating[[#This Row],[New Rating]]="Yes"),"No","Yes") -> No | N58: =IF(AND(CtpyRating[[#This Row],[FI_RATING]]<>"",_xlfn.XLOOKUP(CtpyRating[[#This Row],[CPTY_NAME]],S:S,U:U,"",0)=""),"Yes","No") -> No | Q58: 8 | R58: 2026 | S58: CONG TY TNHH BAO HIEM PHI NHAN THO FUBON VN | T58: FUBON | U58: D
A59: NGAN HANG TMCP LOC PHAT VN | B59: LVBT | C59: Local Bank | D59: AA | E59: 46199 | H59: Ba3 | I59: 45979 | L59: =IF(OR(CtpyRating[[#This Row],[FI_RATING]]="",_xlfn.XLOOKUP(CtpyRating[[#This Row],[CPTY_NAME]],S:S,U:U,"",0)=CtpyRating[[#This Row],[FI_RATING]],CtpyRating[[#This Row],[New Rating]]="Yes"),"No","Yes") -> No | M59: =IF(OR(CtpyRating[[#This Row],[FI_RATING_DATE]]="",CtpyRating[[#This Row],[FI_RATING_DATE]]=_xlfn.XLOOKUP(CtpyRating[[#This Row],[CPTY_NAME]],S:S,V:V,"",0),CtpyRating[[#This Row],[New Rating]]="Yes"),"No","Yes") -> No | N59: =IF(AND(CtpyRating[[#This Row],[FI_RATING]]<>"",_xlfn.XLOOKUP(CtpyRating[[#This Row],[CPTY_NAME]],S:S,U:U,"",0)=""),"Yes","No") -> No | Q59: 8 | R59: 2026 | S59: TCT CP BAO HIEM BAO LONG | T59: BAOLONG | U59: CCC+
A60: NGAN HANG TMCP KY THUONG VN | B60: TCBV-HO | C60: Local Bank | D60: AAA | E60: 46211 | L60: =IF(OR(CtpyRating[[#This Row],[FI_RATING]]="",_xlfn.XLOOKUP(CtpyRating[[#This Row],[CPTY_NAME]],S:S,U:U,"",0)=CtpyRating[[#This Row],[FI_RATING]],CtpyRating[[#This Row],[New Rating]]="Yes"),"No","Yes") -> No | M60: =IF(OR(CtpyRating[[#This Row],[FI_RATING_DATE]]="",CtpyRating[[#This Row],[FI_RATING_DATE]]=_xlfn.XLOOKUP(CtpyRating[[#This Row],[CPTY_NAME]],S:S,V:V,"",0),CtpyRating[[#This Row],[New Rating]]="Yes"),"No","Yes") -> No | N60: =IF(AND(CtpyRating[[#This Row],[FI_RATING]]<>"",_xlfn.XLOOKUP(CtpyRating[[#This Row],[CPTY_NAME]],S:S,U:U,"",0)=""),"Yes","No") -> No | Q60: 8 | R60: 2026 | S60: CONG TY CP BAO HIEM TOAN CAU GIC | T60: GIC | U60: D
A61: NGAN HANG TMCP KIEN LONG | B61: KIENLONG | C61: Local Bank | D61: BBB | E61: 45929 | L61: =IF(OR(CtpyRating[[#This Row],[FI_RATING]]="",_xlfn.XLOOKUP(CtpyRating[[#This Row],[CPTY_NAME]],S:S,U:U,"",0)=CtpyRating[[#This Row],[FI_RATING]],CtpyRating[[#This Row],[New Rating]]="Yes"),"No","Yes") -> No | M61: =IF(OR(CtpyRating[[#This Row],[FI_RATING_DATE]]="",CtpyRating[[#This Row],[FI_RATING_DATE]]=_xlfn.XLOOKUP(CtpyRating[[#This Row],[CPTY_NAME]],S:S,V:V,"",0),CtpyRating[[#This Row],[New Rating]]="Yes"),"No","Yes") -> No | N61: =IF(AND(CtpyRating[[#This Row],[FI_RATING]]<>"",_xlfn.XLOOKUP(CtpyRating[[#This Row],[CPTY_NAME]],S:S,U:U,"",0)=""),"Yes","No") -> No | Q61: 8 | R61: 2026 | S61: CONG TY CP BAO HIEM HUNG VUONG | T61: CP_BHHV | U61: D
A62: NGAN HANG TMCP DONG NAM A | B62: SEAV | C62: Local Bank | D62: A | E62: 45919 | H62: Ba3 | I62: 45932 | L62: =IF(OR(CtpyRating[[#This Row],[FI_RATING]]="",_xlfn.XLOOKUP(CtpyRating[[#This Row],[CPTY_NAME]],S:S,U:U,"",0)=CtpyRating[[#This Row],[FI_RATING]],CtpyRating[[#This Row],[New Rating]]="Yes"),"No","Yes") -> No | M62: =IF(OR(CtpyRating[[#This Row],[FI_RATING_DATE]]="",CtpyRating[[#This Row],[FI_RATING_DATE]]=_xlfn.XLOOKUP(CtpyRating[[#This Row],[CPTY_NAME]],S:S,V:V,"",0),CtpyRating[[#This Row],[New Rating]]="Yes"),"No","Yes") -> No | N62: =IF(AND(CtpyRating[[#This Row],[FI_RATING]]<>"",_xlfn.XLOOKUP(CtpyRating[[#This Row],[CPTY_NAME]],S:S,U:U,"",0)=""),"Yes","No") -> No | Q62: 8 | R62: 2026 | S62: CONG TY TNHH BAO HIEM NHAN THO GENERALI VN | T62: GENERALI | U62: D
A63: NGAN HANG TMCP DAU TU VA PHAT TRIEN VN | B63: BIDV | C63: Local Bank | D63: AAA | H63: Ba2 | I63: 46147 | L63: =IF(OR(CtpyRating[[#This Row],[FI_RATING]]="",_xlfn.XLOOKUP(CtpyRating[[#This Row],[CPTY_NAME]],S:S,U:U,"",0)=CtpyRating[[#This Row],[FI_RATING]],CtpyRating[[#This Row],[New Rating]]="Yes"),"No","Yes") -> No | M63: =IF(OR(CtpyRating[[#This Row],[FI_RATING_DATE]]="",CtpyRating[[#This Row],[FI_RATING_DATE]]=_xlfn.XLOOKUP(CtpyRating[[#This Row],[CPTY_NAME]],S:S,V:V,"",0),CtpyRating[[#This Row],[New Rating]]="Yes"),"No","Yes") -> No | N63: =IF(AND(CtpyRating[[#This Row],[FI_RATING]]<>"",_xlfn.XLOOKUP(CtpyRating[[#This Row],[CPTY_NAME]],S:S,U:U,"",0)=""),"Yes","No") -> No | Q63: 8 | R63: 2026 | S63: CONG TY TNHH QLQ EASTSPRING INVESTMENT | T63: QLQ_EAST | U63: AAA
A64: NGAN HANG TMCP DAI CHUNG VN | B64: PVFC | C64: Local Bank | D64: B | E64: 46218 | L64: =IF(OR(CtpyRating[[#This Row],[FI_RATING]]="",_xlfn.XLOOKUP(CtpyRating[[#This Row],[CPTY_NAME]],S:S,U:U,"",0)=CtpyRating[[#This Row],[FI_RATING]],CtpyRating[[#This Row],[New Rating]]="Yes"),"No","Yes") -> No | M64: =IF(OR(CtpyRating[[#This Row],[FI_RATING_DATE]]="",CtpyRating[[#This Row],[FI_RATING_DATE]]=_xlfn.XLOOKUP(CtpyRating[[#This Row],[CPTY_NAME]],S:S,V:V,"",0),CtpyRating[[#This Row],[New Rating]]="Yes"),"No","Yes") -> No | N64: =IF(AND(CtpyRating[[#This Row],[FI_RATING]]<>"",_xlfn.XLOOKUP(CtpyRating[[#This Row],[CPTY_NAME]],S:S,U:U,"",0)=""),"Yes","No") -> No | Q64: 8 | R64: 2026 | S64: CONG TY CP CHUNG KHOAN BAO VIET | T64: BVS | U64: A | V64: 45930
A65: NGAN HANG TMCP CONG THUONG VN | B65: ICBV | C65: Local Bank | D65: AAA | E65: 45859 | F65: BB+ | G65: 45964 | H65: Ba2 | I65: 46044 | L65: =IF(OR(CtpyRating[[#This Row],[FI_RATING]]="",_xlfn.XLOOKUP(CtpyRating[[#This Row],[CPTY_NAME]],S:S,U:U,"",0)=CtpyRating[[#This Row],[FI_RATING]],CtpyRating[[#This Row],[New Rating]]="Yes"),"No","Yes") -> No | M65: =IF(OR(CtpyRating[[#This Row],[FI_RATING_DATE]]="",CtpyRating[[#This Row],[FI_RATING_DATE]]=_xlfn.XLOOKUP(CtpyRating[[#This Row],[CPTY_NAME]],S:S,V:V,"",0),CtpyRating[[#This Row],[New Rating]]="Yes"),"No","Yes") -> No | N65: =IF(AND(CtpyRating[[#This Row],[FI_RATING]]<>"",_xlfn.XLOOKUP(CtpyRating[[#This Row],[CPTY_NAME]],S:S,U:U,"",0)=""),"Yes","No") -> No | Q65: 8 | R65: 2026 | S65: CONG TY CP CHUNG KHOAN SSI | T65: SSI | U65: AAA | V65: 46174
A66: NGAN HANG TMCP BAO VIET | B66: BVBH | C66: Local Bank | D66: CC | E66: 46189 | L66: =IF(OR(CtpyRating[[#This Row],[FI_RATING]]="",_xlfn.XLOOKUP(CtpyRating[[#This Row],[CPTY_NAME]],S:S,U:U,"",0)=CtpyRating[[#This Row],[FI_RATING]],CtpyRating[[#This Row],[New Rating]]="Yes"),"No","Yes") -> No | M66: =IF(OR(CtpyRating[[#This Row],[FI_RATING_DATE]]="",CtpyRating[[#This Row],[FI_RATING_DATE]]=_xlfn.XLOOKUP(CtpyRating[[#This Row],[CPTY_NAME]],S:S,V:V,"",0),CtpyRating[[#This Row],[New Rating]]="Yes"),"No","Yes") -> No | N66: =IF(AND(CtpyRating[[#This Row],[FI_RATING]]<>"",_xlfn.XLOOKUP(CtpyRating[[#This Row],[CPTY_NAME]],S:S,U:U,"",0)=""),"Yes","No") -> No | Q66: 8 | R66: 2026 | S66: CONG TY CP CHUNG KHOAN AGRIBANK | T66: AGRISECO
A67: NGAN HANG TMCP BAN VIET | B67: VCCB | C67: Local Bank | D67: BB | E67: 46209 | F67: B+ | G67: 46198 | L67: =IF(OR(CtpyRating[[#This Row],[FI_RATING]]="",_xlfn.XLOOKUP(CtpyRating[[#This Row],[CPTY_NAME]],S:S,U:U,"",0)=CtpyRating[[#This Row],[FI_RATING]],CtpyRating[[#This Row],[New Rating]]="Yes"),"No","Yes") -> No | M67: =IF(OR(CtpyRating[[#This Row],[FI_RATING_DATE]]="",CtpyRating[[#This Row],[FI_RATING_DATE]]=_xlfn.XLOOKUP(CtpyRating[[#This Row],[CPTY_NAME]],S:S,V:V,"",0),CtpyRating[[#This Row],[New Rating]]="Yes"),"No","Yes") -> No | N67: =IF(AND(CtpyRating[[#This Row],[FI_RATING]]<>"",_xlfn.XLOOKUP(CtpyRating[[#This Row],[CPTY_NAME]],S:S,U:U,"",0)=""),"Yes","No") -> No | Q67: 8 | R67: 2026 | S67: CONG TY TNHH CHUNG KHOAN NGAN HANG TMCP NGOAI THUONG VN | T67: VCBS | U67: AAA | V67: 46192
A68: NGAN HANG TMCP BAC A | B68: NABV | C68: Local Bank | D68: BBB | E68: 46146 | F68: B+ | G68: 45954 | L68: =IF(OR(CtpyRating[[#This Row],[FI_RATING]]="",_xlfn.XLOOKUP(CtpyRating[[#This Row],[CPTY_NAME]],S:S,U:U,"",0)=CtpyRating[[#This Row],[FI_RATING]],CtpyRating[[#This Row],[New Rating]]="Yes"),"No","Yes") -> No | M68: =IF(OR(CtpyRating[[#This Row],[FI_RATING_DATE]]="",CtpyRating[[#This Row],[FI_RATING_DATE]]=_xlfn.XLOOKUP(CtpyRating[[#This Row],[CPTY_NAME]],S:S,V:V,"",0),CtpyRating[[#This Row],[New Rating]]="Yes"),"No","Yes") -> No | N68: =IF(AND(CtpyRating[[#This Row],[FI_RATING]]<>"",_xlfn.XLOOKUP(CtpyRating[[#This Row],[CPTY_NAME]],S:S,U:U,"",0)=""),"Yes","No") -> No | Q68: 8 | R68: 2026 | S68: CONG TY CP CHUNG KHOAN BIDV | T68: BSI | U68: AAA | V68: 46150
A69: NGAN HANG TMCP AN BINH | B69: ABBV | C69: Local Bank | D69: BBB | E69: 46172 | H69: B2 | I69: 46066 | L69: =IF(OR(CtpyRating[[#This Row],[FI_RATING]]="",_xlfn.XLOOKUP(CtpyRating[[#This Row],[CPTY_NAME]],S:S,U:U,"",0)=CtpyRating[[#This Row],[FI_RATING]],CtpyRating[[#This Row],[New Rating]]="Yes"),"No","Yes") -> No | M69: =IF(OR(CtpyRating[[#This Row],[FI_RATING_DATE]]="",CtpyRating[[#This Row],[FI_RATING_DATE]]=_xlfn.XLOOKUP(CtpyRating[[#This Row],[CPTY_NAME]],S:S,V:V,"",0),CtpyRating[[#This Row],[New Rating]]="Yes"),"No","Yes") -> No | N69: =IF(AND(CtpyRating[[#This Row],[FI_RATING]]<>"",_xlfn.XLOOKUP(CtpyRating[[#This Row],[CPTY_NAME]],S:S,U:U,"",0)=""),"Yes","No") -> No | Q69: 8 | R69: 2026 | S69: CONG TY CP CHUNG KHOAN NGAN HANG CONG THUONG VN | T69: CTS | U69: A | V69: 45922
A70: NGAN HANG TMCP A CHAU | B70: ACBV | C70: Local Bank | D70: AA | E70: 46203 | F70: BB- | G70: 45967 | H70: Ba3 | I70: 46147 | L70: =IF(OR(CtpyRating[[#This Row],[FI_RATING]]="",_xlfn.XLOOKUP(CtpyRating[[#This Row],[CPTY_NAME]],S:S,U:U,"",0)=CtpyRating[[#This Row],[FI_RATING]],CtpyRating[[#This Row],[New Rating]]="Yes"),"No","Yes") -> No | M70: =IF(OR(CtpyRating[[#This Row],[FI_RATING_DATE]]="",CtpyRating[[#This Row],[FI_RATING_DATE]]=_xlfn.XLOOKUP(CtpyRating[[#This Row],[CPTY_NAME]],S:S,V:V,"",0),CtpyRating[[#This Row],[New Rating]]="Yes"),"No","Yes") -> No | N70: =IF(AND(CtpyRating[[#This Row],[FI_RATING]]<>"",_xlfn.XLOOKUP(CtpyRating[[#This Row],[CPTY_NAME]],S:S,U:U,"",0)=""),"Yes","No") -> No | Q70: 8 | R70: 2026 | S70: CONG TY CP CHUNG KHOAN VNDIRECT | T70: VNDIRECT | U70: AAA | V70: 45460
A71: NGAN HANG THUONG MAI TNHH MTV XAY DUNG VN | B71: GTBV | C71: Local Bank | L71: =IF(OR(CtpyRating[[#This Row],[FI_RATING]]="",_xlfn.XLOOKUP(CtpyRating[[#This Row],[CPTY_NAME]],S:S,U:U,"",0)=CtpyRating[[#This Row],[FI_RATING]],CtpyRating[[#This Row],[New Rating]]="Yes"),"No","Yes") -> No | M71: =IF(OR(CtpyRating[[#This Row],[FI_RATING_DATE]]="",CtpyRating[[#This Row],[FI_RATING_DATE]]=_xlfn.XLOOKUP(CtpyRating[[#This Row],[CPTY_NAME]],S:S,V:V,"",0),CtpyRating[[#This Row],[New Rating]]="Yes"),"No","Yes") -> No | N71: =IF(AND(CtpyRating[[#This Row],[FI_RATING]]<>"",_xlfn.XLOOKUP(CtpyRating[[#This Row],[CPTY_NAME]],S:S,U:U,"",0)=""),"Yes","No") -> No | Q71: 8 | R71: 2026 | S71: CONG TY CP CHUNG KHOAN KB VN | T71: KBS | U71: A
A72: NGAN HANG PHAT TRIEN VN | B72: VDB | C72: Local Bank | D72: BB | E72: 45820 | L72: =IF(OR(CtpyRating[[#This Row],[FI_RATING]]="",_xlfn.XLOOKUP(CtpyRating[[#This Row],[CPTY_NAME]],S:S,U:U,"",0)=CtpyRating[[#This Row],[FI_RATING]],CtpyRating[[#This Row],[New Rating]]="Yes"),"No","Yes") -> No | M72: =IF(OR(CtpyRating[[#This Row],[FI_RATING_DATE]]="",CtpyRating[[#This Row],[FI_RATING_DATE]]=_xlfn.XLOOKUP(CtpyRating[[#This Row],[CPTY_NAME]],S:S,V:V,"",0),CtpyRating[[#This Row],[New Rating]]="Yes"),"No","Yes") -> No | N72: =IF(AND(CtpyRating[[#This Row],[FI_RATING]]<>"",_xlfn.XLOOKUP(CtpyRating[[#This Row],[CPTY_NAME]],S:S,U:U,"",0)=""),"Yes","No") -> No | Q72: 8 | R72: 2026 | S72: CONG TY TNHH CHUNG KHOAN ACB | T72: ACBS | U72: AAA | V72: 45940
A73: NGAN HANG NONG NGHIEP VA PHAT TRIEN NONG THON | B73: VBAH | C73: Local Bank | D73: AAA | E73: 46203 | H73: Ba2 | I73: 46147 | L73: =IF(OR(CtpyRating[[#This Row],[FI_RATING]]="",_xlfn.XLOOKUP(CtpyRating[[#This Row],[CPTY_NAME]],S:S,U:U,"",0)=CtpyRating[[#This Row],[FI_RATING]],CtpyRating[[#This Row],[New Rating]]="Yes"),"No","Yes") -> No | M73: =IF(OR(CtpyRating[[#This Row],[FI_RATING_DATE]]="",CtpyRating[[#This Row],[FI_RATING_DATE]]=_xlfn.XLOOKUP(CtpyRating[[#This Row],[CPTY_NAME]],S:S,V:V,"",0),CtpyRating[[#This Row],[New Rating]]="Yes"),"No","Yes") -> No | N73: =IF(AND(CtpyRating[[#This Row],[FI_RATING]]<>"",_xlfn.XLOOKUP(CtpyRating[[#This Row],[CPTY_NAME]],S:S,U:U,"",0)=""),"Yes","No") -> No | Q73: 8 | R73: 2026 | S73: CONG TY CP CHUNG KHOAN VIETCAP | T73: VIETCAP | U73: AAA
A74: NGAN HANG NGOAI THUONG LAO | B74: BCEL | C74: NHNN | D74: BBB | E74: 45217 | L74: =IF(OR(CtpyRating[[#This Row],[FI_RATING]]="",_xlfn.XLOOKUP(CtpyRating[[#This Row],[CPTY_NAME]],S:S,U:U,"",0)=CtpyRating[[#This Row],[FI_RATING]],CtpyRating[[#This Row],[New Rating]]="Yes"),"No","Yes") -> No | M74: =IF(OR(CtpyRating[[#This Row],[FI_RATING_DATE]]="",CtpyRating[[#This Row],[FI_RATING_DATE]]=_xlfn.XLOOKUP(CtpyRating[[#This Row],[CPTY_NAME]],S:S,V:V,"",0),CtpyRating[[#This Row],[New Rating]]="Yes"),"No","Yes") -> No | N74: =IF(AND(CtpyRating[[#This Row],[FI_RATING]]<>"",_xlfn.XLOOKUP(CtpyRating[[#This Row],[CPTY_NAME]],S:S,U:U,"",0)=""),"Yes","No") -> No | Q74: 8 | R74: 2026 | S74: CONG TY CP CHUNG KHOAN NHAT BAN | T74: JSI
A75: NGAN HANG LIEN DOANH VIET NGA | B75: VRB | C75: Local Bank | D75: BB | E75: 44326 | L75: =IF(OR(CtpyRating[[#This Row],[FI_RATING]]="",_xlfn.XLOOKUP(CtpyRating[[#This Row],[CPTY_NAME]],S:S,U:U,"",0)=CtpyRating[[#This Row],[FI_RATING]],CtpyRating[[#This Row],[New Rating]]="Yes"),"No","Yes") -> No | M75: =IF(OR(CtpyRating[[#This Row],[FI_RATING_DATE]]="",CtpyRating[[#This Row],[FI_RATING_DATE]]=_xlfn.XLOOKUP(CtpyRating[[#This Row],[CPTY_NAME]],S:S,V:V,"",0),CtpyRating[[#This Row],[New Rating]]="Yes"),"No","Yes") -> No | N75: =IF(AND(CtpyRating[[#This Row],[FI_RATING]]<>"",_xlfn.XLOOKUP(CtpyRating[[#This Row],[CPTY_NAME]],S:S,U:U,"",0)=""),"Yes","No") -> No | Q75: 8 | R75: 2026 | S75: CONG TY CP CHUNG KHOAN PHUONG NAM | T75: FNS
A76: NGAN HANG DAU TU VA PHAT TRIEN CAMPUCHIA | B76: BIDC | C76: NHNN | D76: CCC | E76: 46227 | L76: =IF(OR(CtpyRating[[#This Row],[FI_RATING]]="",_xlfn.XLOOKUP(CtpyRating[[#This Row],[CPTY_NAME]],S:S,U:U,"",0)=CtpyRating[[#This Row],[FI_RATING]],CtpyRating[[#This Row],[New Rating]]="Yes"),"No","Yes") -> No | M76: =IF(OR(CtpyRating[[#This Row],[FI_RATING_DATE]]="",CtpyRating[[#This Row],[FI_RATING_DATE]]=_xlfn.XLOOKUP(CtpyRating[[#This Row],[CPTY_NAME]],S:S,V:V,"",0),CtpyRating[[#This Row],[New Rating]]="Yes"),"No","Yes") -> No | N76: =IF(AND(CtpyRating[[#This Row],[FI_RATING]]<>"",_xlfn.XLOOKUP(CtpyRating[[#This Row],[CPTY_NAME]],S:S,U:U,"",0)=""),"Yes","No") -> No | Q76: 8 | R76: 2026 | S76: CONG TY TNHH QLQ DAI-ICHI LIFE VN | T76: QLQ_DAICHI | U76: AA
A77: NGAN HANG CATHAY UNITED BANK CO.LTD | B77: CATHAY | C77: NHNN | H77: A1 | I77: 46199 | J77: A | K77: 44687 | L77: =IF(OR(CtpyRating[[#This Row],[FI_RATING]]="",_xlfn.XLOOKUP(CtpyRating[[#This Row],[CPTY_NAME]],S:S,U:U,"",0)=CtpyRating[[#This Row],[FI_RATING]],CtpyRating[[#This Row],[New Rating]]="Yes"),"No","Yes") -> No | M77: =IF(OR(CtpyRating[[#This Row],[FI_RATING_DATE]]="",CtpyRating[[#This Row],[FI_RATING_DATE]]=_xlfn.XLOOKUP(CtpyRating[[#This Row],[CPTY_NAME]],S:S,V:V,"",0),CtpyRating[[#This Row],[New Rating]]="Yes"),"No","Yes") -> No | N77: =IF(AND(CtpyRating[[#This Row],[FI_RATING]]<>"",_xlfn.XLOOKUP(CtpyRating[[#This Row],[CPTY_NAME]],S:S,U:U,"",0)=""),"Yes","No") -> No | Q77: 8 | R77: 2026 | S77: CONG TY TNHH QLQ MANULIFE VN | T77: QLQ_MANUL | U77: AAA
A78: MUFG BANK, LTD | B78: MUFG | C78: NHNN | F78: A | G78: 45945 | H78: A1 | I78: 45979 | L78: =IF(OR(CtpyRating[[#This Row],[FI_RATING]]="",_xlfn.XLOOKUP(CtpyRating[[#This Row],[CPTY_NAME]],S:S,U:U,"",0)=CtpyRating[[#This Row],[FI_RATING]],CtpyRating[[#This Row],[New Rating]]="Yes"),"No","Yes") -> No | M78: =IF(OR(CtpyRating[[#This Row],[FI_RATING_DATE]]="",CtpyRating[[#This Row],[FI_RATING_DATE]]=_xlfn.XLOOKUP(CtpyRating[[#This Row],[CPTY_NAME]],S:S,V:V,"",0),CtpyRating[[#This Row],[New Rating]]="Yes"),"No","Yes") -> No | N78: =IF(AND(CtpyRating[[#This Row],[FI_RATING]]<>"",_xlfn.XLOOKUP(CtpyRating[[#This Row],[CPTY_NAME]],S:S,U:U,"",0)=""),"Yes","No") -> No | Q78: 8 | R78: 2026 | S78: CONG TY CP QLQ PVI | T78: PVICAP | U78: B-
A79: MONEYCORP BANK LIMITED | B79: MONEYCORP | C79: NHNN | D79: D | L79: =IF(OR(CtpyRating[[#This Row],[FI_RATING]]="",_xlfn.XLOOKUP(CtpyRating[[#This Row],[CPTY_NAME]],S:S,U:U,"",0)=CtpyRating[[#This Row],[FI_RATING]],CtpyRating[[#This Row],[New Rating]]="Yes"),"No","Yes") -> No | M79: =IF(OR(CtpyRating[[#This Row],[FI_RATING_DATE]]="",CtpyRating[[#This Row],[FI_RATING_DATE]]=_xlfn.XLOOKUP(CtpyRating[[#This Row],[CPTY_NAME]],S:S,V:V,"",0),CtpyRating[[#This Row],[New Rating]]="Yes"),"No","Yes") -> No | N79: =IF(AND(CtpyRating[[#This Row],[FI_RATING]]<>"",_xlfn.XLOOKUP(CtpyRating[[#This Row],[CPTY_NAME]],S:S,U:U,"",0)=""),"Yes","No") -> No | Q79: 8 | R79: 2026 | S79: CONG TY TNHH QLQ BAO VIET | T79: BAOVIETCAP | U79: AAA | V79: 45903
A80: MIZUHO BANK | B80: MHCV | C80: NHNN | H80: A1 | I80: 45979 | L80: =IF(OR(CtpyRating[[#This Row],[FI_RATING]]="",_xlfn.XLOOKUP(CtpyRating[[#This Row],[CPTY_NAME]],S:S,U:U,"",0)=CtpyRating[[#This Row],[FI_RATING]],CtpyRating[[#This Row],[New Rating]]="Yes"),"No","Yes") -> No | M80: =IF(OR(CtpyRating[[#This Row],[FI_RATING_DATE]]="",CtpyRating[[#This Row],[FI_RATING_DATE]]=_xlfn.XLOOKUP(CtpyRating[[#This Row],[CPTY_NAME]],S:S,V:V,"",0),CtpyRating[[#This Row],[New Rating]]="Yes"),"No","Yes") -> No | N80: =IF(AND(CtpyRating[[#This Row],[FI_RATING]]<>"",_xlfn.XLOOKUP(CtpyRating[[#This Row],[CPTY_NAME]],S:S,U:U,"",0)=""),"Yes","No") -> No | Q80: 8 | R80: 2026 | S80: CONG TY CP QLQ DAU TU MB | T80: MBCAP | U80: D
A81: MASHREQ BANK PSC | B81: MASHREQ-DB | C81: NHNN | F81: A | G81: 46163 | H81: A3 | I81: 46196 | J81: A | K81: 45043 | L81: =IF(OR(CtpyRating[[#This Row],[FI_RATING]]="",_xlfn.XLOOKUP(CtpyRating[[#This Row],[CPTY_NAME]],S:S,U:U,"",0)=CtpyRating[[#This Row],[FI_RATING]],CtpyRating[[#This Row],[New Rating]]="Yes"),"No","Yes") -> No | M81: =IF(OR(CtpyRating[[#This Row],[FI_RATING_DATE]]="",CtpyRating[[#This Row],[FI_RATING_DATE]]=_xlfn.XLOOKUP(CtpyRating[[#This Row],[CPTY_NAME]],S:S,V:V,"",0),CtpyRating[[#This Row],[New Rating]]="Yes"),"No","Yes") -> No | N81: =IF(AND(CtpyRating[[#This Row],[FI_RATING]]<>"",_xlfn.XLOOKUP(CtpyRating[[#This Row],[CPTY_NAME]],S:S,U:U,"",0)=""),"Yes","No") -> No | Q81: 8 | R81: 2026 | S81: CONG TY CP QLQ TIN PHAT | T81: QLQ_TINPHA | U81: D
A82: MALDIVES MONETARY AUTHORITY | B82: MMA | C82: NHNN | L82: =IF(OR(CtpyRating[[#This Row],[FI_RATING]]="",_xlfn.XLOOKUP(CtpyRating[[#This Row],[CPTY_NAME]],S:S,U:U,"",0)=CtpyRating[[#This Row],[FI_RATING]],CtpyRating[[#This Row],[New Rating]]="Yes"),"No","Yes") -> No | M82: =IF(OR(CtpyRating[[#This Row],[FI_RATING_DATE]]="",CtpyRating[[#This Row],[FI_RATING_DATE]]=_xlfn.XLOOKUP(CtpyRating[[#This Row],[CPTY_NAME]],S:S,V:V,"",0),CtpyRating[[#This Row],[New Rating]]="Yes"),"No","Yes") -> No | N82: =IF(AND(CtpyRating[[#This Row],[FI_RATING]]<>"",_xlfn.XLOOKUP(CtpyRating[[#This Row],[CPTY_NAME]],S:S,U:U,"",0)=""),"Yes","No") -> No | Q82: 8 | R82: 2026 | S82: CONG TY TNHH QLQ SSI | T82: QLQ_SSI | U82: AA
A83: MALAYAN BANKING BERHAD | B83: MAYBANK | C83: NHNN | H83: A3 | I83: 45854 | L83: =IF(OR(CtpyRating[[#This Row],[FI_RATING]]="",_xlfn.XLOOKUP(CtpyRating[[#This Row],[CPTY_NAME]],S:S,U:U,"",0)=CtpyRating[[#This Row],[FI_RATING]],CtpyRating[[#This Row],[New Rating]]="Yes"),"No","Yes") -> No | M83: =IF(OR(CtpyRating[[#This Row],[FI_RATING_DATE]]="",CtpyRating[[#This Row],[FI_RATING_DATE]]=_xlfn.XLOOKUP(CtpyRating[[#This Row],[CPTY_NAME]],S:S,V:V,"",0),CtpyRating[[#This Row],[New Rating]]="Yes"),"No","Yes") -> No | N83: =IF(AND(CtpyRating[[#This Row],[FI_RATING]]<>"",_xlfn.XLOOKUP(CtpyRating[[#This Row],[CPTY_NAME]],S:S,U:U,"",0)=""),"Yes","No") -> No | Q83: 8 | R83: 2026 | S83: CONG TY QLQ DRAGON CAPITAL | T83: DRAGONCAP | U83: D
A84: KOOKMIN BANK | B84: KBHQ | C84: NHNN | F84: A | G84: 46010 | H84: Aa3 | I84: 45779 | L84: =IF(OR(CtpyRating[[#This Row],[FI_RATING]]="",_xlfn.XLOOKUP(CtpyRating[[#This Row],[CPTY_NAME]],S:S,U:U,"",0)=CtpyRating[[#This Row],[FI_RATING]],CtpyRating[[#This Row],[New Rating]]="Yes"),"No","Yes") -> No | M84: =IF(OR(CtpyRating[[#This Row],[FI_RATING_DATE]]="",CtpyRating[[#This Row],[FI_RATING_DATE]]=_xlfn.XLOOKUP(CtpyRating[[#This Row],[CPTY_NAME]],S:S,V:V,"",0),CtpyRating[[#This Row],[New Rating]]="Yes"),"No","Yes") -> No | N84: =IF(AND(CtpyRating[[#This Row],[FI_RATING]]<>"",_xlfn.XLOOKUP(CtpyRating[[#This Row],[CPTY_NAME]],S:S,U:U,"",0)=""),"Yes","No") -> No | Q84: 8 | R84: 2026 | S84: CONG TY TNHH MTV QLQ NH TMCP CONG THUONG VN | T84: VTBC | U84: BB-
A85: KOMPANION BANK CLOSED JOINT STOCK COMPANY | C85: NHNN | D85: BBB | E85: 46182 | L85: =IF(OR(CtpyRating[[#This Row],[FI_RATING]]="",_xlfn.XLOOKUP(CtpyRating[[#This Row],[CPTY_NAME]],S:S,U:U,"",0)=CtpyRating[[#This Row],[FI_RATING]],CtpyRating[[#This Row],[New Rating]]="Yes"),"No","Yes") -> No | M85: =IF(OR(CtpyRating[[#This Row],[FI_RATING_DATE]]="",CtpyRating[[#This Row],[FI_RATING_DATE]]=_xlfn.XLOOKUP(CtpyRating[[#This Row],[CPTY_NAME]],S:S,V:V,"",0),CtpyRating[[#This Row],[New Rating]]="Yes"),"No","Yes") -> No | N85: =IF(AND(CtpyRating[[#This Row],[FI_RATING]]<>"",_xlfn.XLOOKUP(CtpyRating[[#This Row],[CPTY_NAME]],S:S,U:U,"",0)=""),"Yes","No") -> No | Q85: 8 | R85: 2026 | S85: CONG TY QLQ VINACAPITAL | T85: QLQ_VNCAP | U85: A | V85: 44503
A86: KEB HANA BANK | B86: HANA-HCM | C86: NHNN | H86: Aa3 | I86: 45855 | L86: =IF(OR(CtpyRating[[#This Row],[FI_RATING]]="",_xlfn.XLOOKUP(CtpyRating[[#This Row],[CPTY_NAME]],S:S,U:U,"",0)=CtpyRating[[#This Row],[FI_RATING]],CtpyRating[[#This Row],[New Rating]]="Yes"),"No","Yes") -> No | M86: =IF(OR(CtpyRating[[#This Row],[FI_RATING_DATE]]="",CtpyRating[[#This Row],[FI_RATING_DATE]]=_xlfn.XLOOKUP(CtpyRating[[#This Row],[CPTY_NAME]],S:S,V:V,"",0),CtpyRating[[#This Row],[New Rating]]="Yes"),"No","Yes") -> No | N86: =IF(AND(CtpyRating[[#This Row],[FI_RATING]]<>"",_xlfn.XLOOKUP(CtpyRating[[#This Row],[CPTY_NAME]],S:S,U:U,"",0)=""),"Yes","No") -> No | Q86: 8 | R86: 2026 | S86: CONG TY CP QLQ DAU TU VN (VFM) | T86: QLQ_VFM | U86: AA
A87: KBC BANK | B87: KBC | C87: NHNN | F87: A+ | G87: 45981 | H87: Aa3 | I87: 45979 | L87: =IF(OR(CtpyRating[[#This Row],[FI_RATING]]="",_xlfn.XLOOKUP(CtpyRating[[#This Row],[CPTY_NAME]],S:S,U:U,"",0)=CtpyRating[[#This Row],[FI_RATING]],CtpyRating[[#This Row],[New Rating]]="Yes"),"No","Yes") -> No | M87: =IF(OR(CtpyRating[[#This Row],[FI_RATING_DATE]]="",CtpyRating[[#This Row],[FI_RATING_DATE]]=_xlfn.XLOOKUP(CtpyRating[[#This Row],[CPTY_NAME]],S:S,V:V,"",0),CtpyRating[[#This Row],[New Rating]]="Yes"),"No","Yes") -> No | N87: =IF(AND(CtpyRating[[#This Row],[FI_RATING]]<>"",_xlfn.XLOOKUP(CtpyRating[[#This Row],[CPTY_NAME]],S:S,U:U,"",0)=""),"Yes","No") -> No | Q87: 8 | R87: 2026 | S87: CONG TY CP QLQ VINAWEALTH | T87: QLQ_VINAWE | U87: D
A88: KASIKORNBANK PUBLIC COMPANY LIMITED | B88: KASIKORNBANK | C88: NHNN | F88: BBB | G88: 46181 | H88: Baa1 | I88: 46181 | J88: BBB | K88: 44641 | L88: =IF(OR(CtpyRating[[#This Row],[FI_RATING]]="",_xlfn.XLOOKUP(CtpyRating[[#This Row],[CPTY_NAME]],S:S,U:U,"",0)=CtpyRating[[#This Row],[FI_RATING]],CtpyRating[[#This Row],[New Rating]]="Yes"),"No","Yes") -> No | M88: =IF(OR(CtpyRating[[#This Row],[FI_RATING_DATE]]="",CtpyRating[[#This Row],[FI_RATING_DATE]]=_xlfn.XLOOKUP(CtpyRating[[#This Row],[CPTY_NAME]],S:S,V:V,"",0),CtpyRating[[#This Row],[New Rating]]="Yes"),"No","Yes") -> No | N88: =IF(AND(CtpyRating[[#This Row],[FI_RATING]]<>"",_xlfn.XLOOKUP(CtpyRating[[#This Row],[CPTY_NAME]],S:S,U:U,"",0)=""),"Yes","No") -> No | Q88: 8 | R88: 2026 | S88: NGAN HANG TNHH MTV HSBC VN | T88: HSHC-VN | U88: AA-
A89: JP MORGAN CHASE BANK N.A | B89: JPMORGAN | C89: NHNN | F89: AA | G89: 45811 | H89: Aa1 | I89: 45978 | J89: AA- | K89: 45611 | L89: =IF(OR(CtpyRating[[#This Row],[FI_RATING]]="",_xlfn.XLOOKUP(CtpyRating[[#This Row],[CPTY_NAME]],S:S,U:U,"",0)=CtpyRating[[#This Row],[FI_RATING]],CtpyRating[[#This Row],[New Rating]]="Yes"),"No","Yes") -> No | M89: =IF(OR(CtpyRating[[#This Row],[FI_RATING_DATE]]="",CtpyRating[[#This Row],[FI_RATING_DATE]]=_xlfn.XLOOKUP(CtpyRating[[#This Row],[CPTY_NAME]],S:S,V:V,"",0),CtpyRating[[#This Row],[New Rating]]="Yes"),"No","Yes") -> No | N89: =IF(AND(CtpyRating[[#This Row],[FI_RATING]]<>"",_xlfn.XLOOKUP(CtpyRating[[#This Row],[CPTY_NAME]],S:S,U:U,"",0)=""),"Yes","No") -> No | Q89: 8 | R89: 2026 | S89: NGAN HANG TNHH MTV STANDARD CHARTERED VN | T89: SCHN-VN | U89: A | V89: 46197
A90: INTERNATIONAL INVESTMENT BANK | B90: IIB | C90: NHNN | F90: A- | H90: A3 | J90: A- | L90: =IF(OR(CtpyRating[[#This Row],[FI_RATING]]="",_xlfn.XLOOKUP(CtpyRating[[#This Row],[CPTY_NAME]],S:S,U:U,"",0)=CtpyRating[[#This Row],[FI_RATING]],CtpyRating[[#This Row],[New Rating]]="Yes"),"No","Yes") -> No | M90: =IF(OR(CtpyRating[[#This Row],[FI_RATING_DATE]]="",CtpyRating[[#This Row],[FI_RATING_DATE]]=_xlfn.XLOOKUP(CtpyRating[[#This Row],[CPTY_NAME]],S:S,V:V,"",0),CtpyRating[[#This Row],[New Rating]]="Yes"),"No","Yes") -> No | N90: =IF(AND(CtpyRating[[#This Row],[FI_RATING]]<>"",_xlfn.XLOOKUP(CtpyRating[[#This Row],[CPTY_NAME]],S:S,U:U,"",0)=""),"Yes","No") -> No | Q90: 8 | R90: 2026 | S90: NGAN HANG TNHH MTV ANZ VN | T90: ANZF-VN | U90: A | V90: 46196
A91: INDUSTRIAL BANK OF KOREA | B91: IBK | C91: NHNN | F91: AA- | G91: 45952 | H91: Aa2 | I91: 45992 | L91: =IF(OR(CtpyRating[[#This Row],[FI_RATING]]="",_xlfn.XLOOKUP(CtpyRating[[#This Row],[CPTY_NAME]],S:S,U:U,"",0)=CtpyRating[[#This Row],[FI_RATING]],CtpyRating[[#This Row],[New Rating]]="Yes"),"No","Yes") -> No | M91: =IF(OR(CtpyRating[[#This Row],[FI_RATING_DATE]]="",CtpyRating[[#This Row],[FI_RATING_DATE]]=_xlfn.XLOOKUP(CtpyRating[[#This Row],[CPTY_NAME]],S:S,V:V,"",0),CtpyRating[[#This Row],[New Rating]]="Yes"),"No","Yes") -> No | N91: =IF(AND(CtpyRating[[#This Row],[FI_RATING]]<>"",_xlfn.XLOOKUP(CtpyRating[[#This Row],[CPTY_NAME]],S:S,U:U,"",0)=""),"Yes","No") -> No | Q91: 8 | R91: 2026 | S91: NGAN HANG TNHH MTV WOORI VIET NAM | T91: HVHB-VN | U91: AA | V91: 46197
A92: INDUSTRIAL AND COMMERCIAL BANK OF CHINA | B92: ICBC | C92: NHNN | F92: A | G92: 46045 | H92: A1 | I92: 46140 | L92: =IF(OR(CtpyRating[[#This Row],[FI_RATING]]="",_xlfn.XLOOKUP(CtpyRating[[#This Row],[CPTY_NAME]],S:S,U:U,"",0)=CtpyRating[[#This Row],[FI_RATING]],CtpyRating[[#This Row],[New Rating]]="Yes"),"No","Yes") -> No | M92: =IF(OR(CtpyRating[[#This Row],[FI_RATING_DATE]]="",CtpyRating[[#This Row],[FI_RATING_DATE]]=_xlfn.XLOOKUP(CtpyRating[[#This Row],[CPTY_NAME]],S:S,V:V,"",0),CtpyRating[[#This Row],[New Rating]]="Yes"),"No","Yes") -> No | N92: =IF(AND(CtpyRating[[#This Row],[FI_RATING]]<>"",_xlfn.XLOOKUP(CtpyRating[[#This Row],[CPTY_NAME]],S:S,U:U,"",0)=""),"Yes","No") -> No | Q92: 8 | R92: 2026 | S92: NGAN HANG TNHH MTV SHINHAN VN | T92: SHHC | U92: AA | V92: 46119
A93: HUA NAN BANK | B93: HUANAN | C93: NHNN | H93: A2 | I93: 45960 | L93: =IF(OR(CtpyRating[[#This Row],[FI_RATING]]="",_xlfn.XLOOKUP(CtpyRating[[#This Row],[CPTY_NAME]],S:S,U:U,"",0)=CtpyRating[[#This Row],[FI_RATING]],CtpyRating[[#This Row],[New Rating]]="Yes"),"No","Yes") -> No | M93: =IF(OR(CtpyRating[[#This Row],[FI_RATING_DATE]]="",CtpyRating[[#This Row],[FI_RATING_DATE]]=_xlfn.XLOOKUP(CtpyRating[[#This Row],[CPTY_NAME]],S:S,V:V,"",0),CtpyRating[[#This Row],[New Rating]]="Yes"),"No","Yes") -> No | N93: =IF(AND(CtpyRating[[#This Row],[FI_RATING]]<>"",_xlfn.XLOOKUP(CtpyRating[[#This Row],[CPTY_NAME]],S:S,U:U,"",0)=""),"Yes","No") -> No | Q93: 8 | R93: 2026 | S93: NGAN HANG TNHH MTV UNITED OVERSEAS BANK VN | T93: UOB_SING | U93: BBB | V93: 45912
A94: HSBC BANK | B94: HSHC-VN | C94: NHNN | F94: AA- | G94: 45888 | H94: A1 | I94: 45979 | L94: =IF(OR(CtpyRating[[#This Row],[FI_RATING]]="",_xlfn.XLOOKUP(CtpyRating[[#This Row],[CPTY_NAME]],S:S,U:U,"",0)=CtpyRating[[#This Row],[FI_RATING]],CtpyRating[[#This Row],[New Rating]]="Yes"),"No","Yes") -> No | M94: =IF(OR(CtpyRating[[#This Row],[FI_RATING_DATE]]="",CtpyRating[[#This Row],[FI_RATING_DATE]]=_xlfn.XLOOKUP(CtpyRating[[#This Row],[CPTY_NAME]],S:S,V:V,"",0),CtpyRating[[#This Row],[New Rating]]="Yes"),"No","Yes") -> No | N94: =IF(AND(CtpyRating[[#This Row],[FI_RATING]]<>"",_xlfn.XLOOKUP(CtpyRating[[#This Row],[CPTY_NAME]],S:S,U:U,"",0)=""),"Yes","No") -> No | Q94: 8 | R94: 2026 | S94: NGAN HANG TNHH MTV HONG LEONG VN | T94: HLBV-VN | U94: AAA | V94: 46227
A95: HONG LEONG BANK BERHAD | B95: HLBV-VN | C95: NHNN | F95: BBB+ | G95: 45855 | H95: A3 | I95: 45608 | L95: =IF(OR(CtpyRating[[#This Row],[FI_RATING]]="",_xlfn.XLOOKUP(CtpyRating[[#This Row],[CPTY_NAME]],S:S,U:U,"",0)=CtpyRating[[#This Row],[FI_RATING]],CtpyRating[[#This Row],[New Rating]]="Yes"),"No","Yes") -> No | M95: =IF(OR(CtpyRating[[#This Row],[FI_RATING_DATE]]="",CtpyRating[[#This Row],[FI_RATING_DATE]]=_xlfn.XLOOKUP(CtpyRating[[#This Row],[CPTY_NAME]],S:S,V:V,"",0),CtpyRating[[#This Row],[New Rating]]="Yes"),"No","Yes") -> No | N95: =IF(AND(CtpyRating[[#This Row],[FI_RATING]]<>"",_xlfn.XLOOKUP(CtpyRating[[#This Row],[CPTY_NAME]],S:S,U:U,"",0)=""),"Yes","No") -> No | Q95: 8 | R95: 2026 | S95: THE BANK OF NEW YORK MELLON | T95: BNYM
A96: GUANGXI BEIBU GULF BANK CO., LTD | B96: GUANGXI | C96: NHNN | D96: AA | E96: 45965 | L96: =IF(OR(CtpyRating[[#This Row],[FI_RATING]]="",_xlfn.XLOOKUP(CtpyRating[[#This Row],[CPTY_NAME]],S:S,U:U,"",0)=CtpyRating[[#This Row],[FI_RATING]],CtpyRating[[#This Row],[New Rating]]="Yes"),"No","Yes") -> No | M96: =IF(OR(CtpyRating[[#This Row],[FI_RATING_DATE]]="",CtpyRating[[#This Row],[FI_RATING_DATE]]=_xlfn.XLOOKUP(CtpyRating[[#This Row],[CPTY_NAME]],S:S,V:V,"",0),CtpyRating[[#This Row],[New Rating]]="Yes"),"No","Yes") -> No | N96: =IF(AND(CtpyRating[[#This Row],[FI_RATING]]<>"",_xlfn.XLOOKUP(CtpyRating[[#This Row],[CPTY_NAME]],S:S,U:U,"",0)=""),"Yes","No") -> No | Q96: 8 | R96: 2026 | S96: ESUN COMMERCIAL BANK | T96: ESUN
A97: FIRST COMMERCIAL BANK | B97: FCBV-HN | C97: NHNN | H97: A1 | I97: 46094 | J97: A | K97: 44687 | L97: =IF(OR(CtpyRating[[#This Row],[FI_RATING]]="",_xlfn.XLOOKUP(CtpyRating[[#This Row],[CPTY_NAME]],S:S,U:U,"",0)=CtpyRating[[#This Row],[FI_RATING]],CtpyRating[[#This Row],[New Rating]]="Yes"),"No","Yes") -> No | M97: =IF(OR(CtpyRating[[#This Row],[FI_RATING_DATE]]="",CtpyRating[[#This Row],[FI_RATING_DATE]]=_xlfn.XLOOKUP(CtpyRating[[#This Row],[CPTY_NAME]],S:S,V:V,"",0),CtpyRating[[#This Row],[New Rating]]="Yes"),"No","Yes") -> No | N97: =IF(AND(CtpyRating[[#This Row],[FI_RATING]]<>"",_xlfn.XLOOKUP(CtpyRating[[#This Row],[CPTY_NAME]],S:S,U:U,"",0)=""),"Yes","No") -> No | Q97: 8 | R97: 2026 | S97: BNP PARIBAS SA | T97: BPHM-SA
A98: ESUN COMMERCIAL BANK | B98: ESUN | C98: NHNN | H98: A1 | I98: 45972 | J98: A | K98: 44687 | L98: =IF(OR(CtpyRating[[#This Row],[FI_RATING]]="",_xlfn.XLOOKUP(CtpyRating[[#This Row],[CPTY_NAME]],S:S,U:U,"",0)=CtpyRating[[#This Row],[FI_RATING]],CtpyRating[[#This Row],[New Rating]]="Yes"),"No","Yes") -> No | M98: =IF(OR(CtpyRating[[#This Row],[FI_RATING_DATE]]="",CtpyRating[[#This Row],[FI_RATING_DATE]]=_xlfn.XLOOKUP(CtpyRating[[#This Row],[CPTY_NAME]],S:S,V:V,"",0),CtpyRating[[#This Row],[New Rating]]="Yes"),"No","Yes") -> No | N98: =IF(AND(CtpyRating[[#This Row],[FI_RATING]]<>"",_xlfn.XLOOKUP(CtpyRating[[#This Row],[CPTY_NAME]],S:S,U:U,"",0)=""),"Yes","No") -> No | Q98: 8 | R98: 2026 | S98: CTBC BANK | T98: CTBC-HCM
A99: DEVELOPMENT BANK OF SINGAPORE | B99: DBS | C99: NHNN | F99: AA- | G99: 45791 | H99: Aa1 | I99: 45979 | L99: =IF(OR(CtpyRating[[#This Row],[FI_RATING]]="",_xlfn.XLOOKUP(CtpyRating[[#This Row],[CPTY_NAME]],S:S,U:U,"",0)=CtpyRating[[#This Row],[FI_RATING]],CtpyRating[[#This Row],[New Rating]]="Yes"),"No","Yes") -> No | M99: =IF(OR(CtpyRating[[#This Row],[FI_RATING_DATE]]="",CtpyRating[[#This Row],[FI_RATING_DATE]]=_xlfn.XLOOKUP(CtpyRating[[#This Row],[CPTY_NAME]],S:S,V:V,"",0),CtpyRating[[#This Row],[New Rating]]="Yes"),"No","Yes") -> No | N99: =IF(AND(CtpyRating[[#This Row],[FI_RATING]]<>"",_xlfn.XLOOKUP(CtpyRating[[#This Row],[CPTY_NAME]],S:S,U:U,"",0)=""),"Yes","No") -> No | Q99: 8 | R99: 2026 | S99: CHINA CONSTRUCTION BANK CORPORATION | T99: CCB
A100: DEUTSCHE BANK AG | B100: DBHC | C100: NHNN | H100: A1 | I100: 46072 | L100: =IF(OR(CtpyRating[[#This Row],[FI_RATING]]="",_xlfn.XLOOKUP(CtpyRating[[#This Row],[CPTY_NAME]],S:S,U:U,"",0)=CtpyRating[[#This Row],[FI_RATING]],CtpyRating[[#This Row],[New Rating]]="Yes"),"No","Yes") -> No | M100: =IF(OR(CtpyRating[[#This Row],[FI_RATING_DATE]]="",CtpyRating[[#This Row],[FI_RATING_DATE]]=_xlfn.XLOOKUP(CtpyRating[[#This Row],[CPTY_NAME]],S:S,V:V,"",0),CtpyRating[[#This Row],[New Rating]]="Yes"),"No","Yes") -> No | N100: =IF(AND(CtpyRating[[#This Row],[FI_RATING]]<>"",_xlfn.XLOOKUP(CtpyRating[[#This Row],[CPTY_NAME]],S:S,U:U,"",0)=""),"Yes","No") -> No | Q100: 8 | R100: 2026 | S100: CITI BANK NA | T100: CITIBANK
...

Sheet Cpty
A1: CPTY_CODE_ISSUER | B1: CPTY_CODE_ISSUER_Name
A2: VDB | B2: NGAN HANG PHAT TRIEN VN
A3: VBAH | B3: NGAN HANG NONG NGHIEP VA PHAT TRIEN NONG THON
A4: SHBV | B4: NGAN HANG TMCP SAI GON HA NOI
A5: OCBV | B5: NGAN HANG TMCP PHUONG DONG
A6: SCBV | B6: NGAN HANG TMCP SAI GON
A7: NCBV | B7: NGAN HANG TMCP QUOC DAN
A8: SEAV | B8: NGAN HANG TMCP DONG NAM A
A9: KIENLONG | B9: NGAN HANG TMCP KIEN LONG
A10: PVFC | B10: NGAN HANG TMCP DAI CHUNG VN
A11: TPBH | B11: NGAN HANG TMCP TIEN PHONG
A12: SABH | B12: NGAN HANG TMCP NAM A
... A194: VPBS | B194: CONG TY CP CHUNG KHOAN VPBANK

Sheet Ref
A1: Tenor chuẩn | B1: Chặn dưới | C1: Chặn trên | E1: Đối ứng | F1: Bonds_ShortName | G1: FaceAmount | J1: Currency | K1: Duration_range | L1: Security Name | M1: Type of Instr. | N1: Mat. Date | O1: Open Pos | P1: Price | Q1: Clean Price | R1: QUANTITY | S1: Nominal | T1: Avg Price | U1: MARKET_VALUE | V1: Cpn Rate | W1: Accr Int | X1: Cpn Cumul | Y1: Cpn Reinvested | Z1: Cost of Carry | AA1: Yield Mat | AB1: Mod Dur | AC1: DURATION | AD1: Cnvx. | AE1: Cnvx. Value | AF1: BPV (K) | AG1: Theta (K) | AH1: REALIZED_CUR | AI1: UNREALIZED_CUR | AJ1: P/L Clean Price | AK1: P/L Currency | AL1: P/L Local | AM1: P/L Report | AN1: avg yield | AP1: Ccy | AQ1: Rate | AR1: RateDate | AS1: Source | AU1: Issuer | AV1: Rating
A2: <1M | B2: 0 | C2: 30 | F2: OCBCD241126 | G2: =2000000000000/10^9 -> 2000 | J2: SOM KYRGYZSTAN | K2: 3 yrs <= duration < 5 yrs | L2: GBA05310713 | M2: GOVBOND | N2: 13/07/2031 | O2: Buy | P2: 71.272 | Q2: 71 | R2: 6372854 | S2: 637285400 | T2: 68.57 | U2: 4.5420605e+08 | V2: 6 | W2: 1 | X2: 0 | Y2: 0 | Z2: -6838768.2 | AA2: 14.42 | AB2: 3.8342754 | AC2: 4.1107267 | AD2: 18.16938 | AE2: 83.50813 | AF2: -176.2268 | AG2: 173.936 | AH2: 0 | AI2: 17219452 | AJ2: 17219452 | AK2: 17219452 | AL2: 5.1374612e+09 | AM2: 5.1374612e+09 | AN2: 15.2 | AP2: KGS | AQ2: 300.1927 | AR2: 46237 | AU2: MFKR | AV2: B
A3: 1-3M | B3: 31 | C3: 90 | F3: BAB12601 | G3: 2000 | J3: SOM KYRGYZSTAN | K3: 3 yrs <= duration < 5 yrs | L3: GBA05310727 | M3: GOVBOND | N3: 27/07/2031 | O3: Buy | P3: 71.069 | Q3: 71 | R3: 12745000 | S3: 1274500000 | T3: 68.57 | U3: 905774405 | V3: 6 | W3: 1 | X3: 0 | Y3: 0 | Z3: -10145245 | AA3: 14.44 | AB3: 3.8687806 | AC3: 4.1481065 | AD3: 18.452465 | AE3: 168.59478 | AF3: -353.47917 | AG3: 346.21 | AH3: 0 | AI3: 31849755 | AJ3: 31849755 | AK3: 31849755 | AL3: 9.5024445e+09 | AM3: 9.5024445e+09 | AN3: 15.2
A4: 3-6M | B4: 91 | C4: 180 | F4: BAB12603 | G4: 1000
A5: 6M-1Y | B5: 181 | C5: 365 | F5: HDB12M261126 | G5: 1500
A6: 1-2Y | B6: 366 | C6: 730
A7: 2-3Y | B7: 731 | C7: 1095
A8: 3-5Y | B8: 1096 | C8: 1825
A9: 5-7Y | B9: 1826 | C9: 2555
A10: >7Y | B10: 2556 | C10: 100000
