Workbook
Name BOND.1: Code!$D$3
Name BOND.10: Code!$D$12
Name BOND.11: Code!$D$13
Name BOND.12: Code!$D$14
Name BOND.13: Code!$D$15
Name BOND.2: Code!$D$4
Name BOND.3: Code!$D$5
Name BOND.4: Code!$D$6
Name BOND.5: Code!$D$7
Name BOND.6: Code!$D$8
Name BOND.7: Code!$D$9
Name BOND.8: Code!$D$10
Name BOND.9: Code!$D$11
Name Lastmonth: 'Run Tool'!$B$4
Name Lastquater: 'Run Tool'!$B$8
Name Lastweek: 'Run Tool'!$B$6
Name Lastyear: 'Run Tool'!$B$5
Name May53.: Code!$A$1
Name MK.1: Code!$D$16
Name MK.2: Code!$D$17
Name MK.3: Code!$D$18
Name MK.4: Code!$D$19
Name RPT: 'Run Tool'!$B$2
Name RPT_LR: 'Run Tool'!$B$12
Name RPT_LR1: 'Run Tool'!$B$13
Name Yesterday: 'Run Tool'!$B$3

Sheet Run Tool
A1: Item | B1: Values | D1: Check | E1: Value | G1: Comment
A2: Rpt Date | B2: 46290 | D2: Có dữ liệu Bond ngày báo cáo chưa? | E2: =IF( AND(DATEVALUE(BOND!A4)=RPT,DATEVALUE(BOND!G4)=RPT,DATEVALUE(BOND!M4)=RPT,DATEVALUE(BOND!R4)=RPT,DATEVALUE(BOND!X4)=RPT,DATEVALUE(BOND!X4)=RPT,DATEVALUE(BOND!AC4)=RPT,DATEVALUE(BOND!AH4)=RPT,DATEVALUE(BOND!AN4)=RPT,DATEVALUE(BOND!AS4)=RPT,DATEVALUE(BOND!BB4)=RPT,DATEVALUE(BOND!BF4)=RPT,DATEVALUE(BOND!BJ4)=RPT,BOND!AX4=RPT_LR),"OK","CHECK") -> CHECK | G2: Executive Msg | H2: Executive Messages: (1) Chỉ số lỗ MtM của danh mục Bond Trading giữ mức 1.634 tỷ. Nếu yield tăng thêm 1 bps (~0.01%) ở tất cả các kỳ hạn, mức lỗ sẽ gia tăng thêm 11 tỷ. (2) Trạng thái danh mục GBond duy trì mức 17.513 tỷ - 88% hạn mức; Trạng thái danh mục FIBond & CD (bao gồm cả TPCP nước ngoài Kyrgyzstan) duy trì mức 39.414 tỷ - 88% hạn mức. (3) Lãi suất LNH kỳ ON tiếp tục giảm xuống 0.7% trong khi các kỳ dài hơn từ 1W-1M vẫn quanh mức 5-6%. Lưu ý rủi ro lỗ NIM vẫn tiềm ẩn do lãi suất có khả năng biến động mạnh. (4) Khe hở thanh khoản lũy kế - Gap 3M đang ở mức -25,2k tỷ, có xu hướng tăng chiều âm trong tháng 9, chủ yếu do giảm cho vay LNH kì 1-3M trong khi tăng huy động LNH kì dưới 3M
A3: Yesterday | B3: =WORKDAY(B2,-1,0) -> 46289 | D3: Có dữ liệu Market info ngày báo cáo chưa? | E3: =IF(AND(Market!A4=RPT,Market!E4=RPT,Market!I4=RPT,Market!M4=RPT),"OK","CHECK") -> CHECK | G3: Tiêu đề 1 | H3: Phân tách lại danh mục TD và BK GovBond
A4: Last month | B4: 46262 | C4: =WORKDAY(EOMONTH(RPT,-1)+1, -1) -> 46265 | D4: Có dữ liệu QLHS chưa? | E4: =IF(MAX(BOND!BN:BN)=Lastmonth,"OK","CHECK") -> OK | G4: Nội dung 1 | H4: Kể từ ngày báo cáo 10/08/2026, QLRR đã điều chỉnh danh mục Trading và Banking book theo bóc tách lại phần Danh mục Banking Gbond phù hợp với số vốn được Pool tài trợ 12k tỷ) từ DCM. Theo đó: (1) Danh mục theo mệnh giá của Trading book và Banking book tương ứng là: 17.413 tỷ và 10.848 tỷ. (2) Ngay tại thời điểm bóc tách lại (10/08), Lỗ MtM của danh mục Trading điều chỉnh tăng thêm 23 tỷ.
A5: last Year | B5: 45657 | D5: ItD của Trading Bond (limit 400 tỷ) | E5: =-SUMIFS(BOND!$AA:$AA,BOND!$Z:$Z,"",BOND!$X:$X,RPT) -> 1633.9373 | F5: =E5+SUMIFS(BOND!$AA:$AA,BOND!$Z:$Z,"",BOND!$X:$X,Yesterday) -> -0.36099488 | G5: Tiêu đề 2 | H5: Thay đổi ngưỡng mục tiêu bộ đệm thanh khoản
A6: Last week | B6: =RPT-WEEKDAY(RPT)-1 -> 46283 | D6: Trạng thái danh mục FIBond&CD (limit 44k, warning 40k) | E6: =SUMIFS(BOND!$AQ:$AQ,BOND!$AN:$AN,RPT) -> 39414.405 | F6: =E6-SUMIFS(BOND!$AQ:$AQ,BOND!$AN:$AN,Yesterday) -> -0.44888721 | G6: Nội dung 2 | H6: Sau bóc tách lại danh mục TD & BK, ngưỡng mục tiêu bộ đệm thanh khoản điều chỉnh từ 11.440 tỷ về 10.400 tỷ. QLRR lưu ý: (1) Banking Gbond dự phòng cần được sử dụng/tối ưu có chọn lọc trong điều kiện bình thường, nhằm tránh làm suy giảm năng lực ứng phó khi thị trường xuất hiện cú sốc nguồn vốn.
A7: Available bond | B7: ="\\filesrv01.msb.com.vn\06.Khoi Quan Ly Rui Ro\02.Trung Tam QLRR Thi Truong\03.Phong QLRRTK\Daily Report\LR_"&TEXT(RPT_LR,"yyyy.mm.dd")&"\MCO Report\Available bond_v5_"&TEXT(RPT_LR,"yyyy.mm.dd")&".xlsm" -> \\filesrv01.msb.com.vn\06.Khoi Quan Ly Rui Ro\02.Trung Tam QLRR Thi Truong\03.Phong QLRRTK\Daily Report\LR_2026.09.28\MCO Report\Available bond_v5_2026.09.28.xlsm | D7: Bộ đệm thanh khoản Available Bond | E7: =ROUND(SUMIFS(BOND!$AZ:$AZ,BOND!AY:AY,"Face_HLA",BOND!AX:AX,RPT_LR),0) -> 10769 | F7: =ROUND(SUMIFS(BOND!$AZ:$AZ,BOND!$AY:$AY,"Face_HLA",BOND!$AX:$AX,RPT_LR)-SUMIFS(BOND!$AZ:$AZ,BOND!$AY:$AY,"Face_HLA",BOND!$AX:$AX,RPT_LR1),0) -> -4560 | G7: Tiêu đề 3 | H7: Giám sát tình trạng NGOẠI LỆ vượt hạn mức lỗ mtm
A8: Last quarter | B8: 46203 | D8: Hạn mức bộ đệm thanh khoản | E8: =Executive!D78 -> 10300 | F8: =E7/E8 -> 1.045534 | G8: Nội dung 3 | H8: Danh mục Trading Gbond hiện ghi nhận lỗ MtM quanh 1.640 tỷ đồng (xu hướng tăng gần đây do yield tăng liên tục tuần qua) trên quy mô trạng thái rủi ro 17.413 tỷ đồng, vượt hạn mức 400 tỷ đồng và đang trong quá trình phê duyệt ngoại lệ. => QLRR khuyến nghị FI/DCM duy trì báo cáo định kỳ cấp có thẩm quyền, vẫn tiếp tục tìm kiếm các biện pháp giảm thiểu/xử lý lỗ và kiểm soát không để rủi ro tiếp tục gia tăng; báo cáo xin ý kiến cấp có thẩm quyền trong t/h phát sinh các nhân tố có thể làm leo thang đáng kể tình trạng lỗ mtm.
A9: QLHS | B9: \\filesrv01.msb.com.vn\06.Khoi Quan Ly Rui Ro\02.Trung Tam QLRR Thi Truong\02.Phong GSRRTT\05.Report\01.Daily Report\03. QLHS & VTC\00.Summary_EXCO FI.xlsx | D9: Trạng thái GovBond Trading | E9: =Executive!D19 -> 17513 | F9: =E9/20000 -> 0.87565 | G9: Tiêu đề 4 | H9: Rủi ro LỖ KÉP tiếp tục là ÁP LỰC CHÍNH
A10: BS FI | B10: ="\\filesrv01.msb.com.vn\06.Khoi Quan Ly Rui Ro\02.Trung Tam QLRR Thi Truong\03.Phong QLRRTK\Daily Report\LR_"&TEXT(RPT_LR,"yyyy.mm.dd")&"\MCO Report\BalanceSheet_FI_v2_"&TEXT(RPT_LR,"yyyy.mm.dd")&".xlsm" -> \\filesrv01.msb.com.vn\06.Khoi Quan Ly Rui Ro\02.Trung Tam QLRR Thi Truong\03.Phong QLRRTK\Daily Report\LR_2026.09.28\MCO Report\BalanceSheet_FI_v2_2026.09.28.xlsm | G10: Nội dung 4 | H10: Trong bối cảnh lợi suất trái phiếu tăng từ đầu tháng và chi phí vốn duy trì ở mức cao, các danh mục Banking Gbond, FIBond và Trading Gbond đang chịu đồng thời hai áp lực: lỗ đánh giá lại MtM và suy giảm NIM => Đây không chỉ là rủi ro thị trường ngắn hạn, mà là vấn đề cần được cân nhắc trong chiến lược phân bổ bảng cân đối (danh quy mô DM đầu tư) và tối ưu hiệu quả vốn.
A11: File csv | B11: ="\\filesrv01.msb.com.vn\06.Khoi Quan Ly Rui Ro\02.Trung Tam QLRR Thi Truong\02.Phong GSRRTT\05.Report\01.Daily Report\"&TEXT(RPT,"yyyy.mm.dd")&"\DAILY MR REPORT\Import_data.csv" -> \\filesrv01.msb.com.vn\06.Khoi Quan Ly Rui Ro\02.Trung Tam QLRR Thi Truong\02.Phong GSRRTT\05.Report\01.Daily Report\2026.09.25\DAILY MR REPORT\Import_data.csv | G11: Note | H11: Hệ thống tài trợ 12k tỷ để dự phòng thanh khoản cho kịch bản rút tiền gửi, tương ứng 10.848 tỷ theo mệnh giá.
A12: Reportdate LR | B12: =TODAY()-1 -> 46293
A13: Reportdate LR-1 | B13: =IF(WEEKDAY(RPT_LR)=1,RPT_LR-3,RPT_LR-1) -> 46292
A14: Daily tool | B14: ="Daily market risk report_"&TEXT(RPT,"yyyy.mm.dd")&".xlsb" -> Daily market risk report_2026.09.25.xlsb

Sheet Log
A1: RPT | B1: Nội dung | C1: PIC
A2: 45495 | B2: Bổ sung trạng thái đồng CNY | C2: tranglt38
A3: 45525 | B3: Bổ sung công thức On/off BS | C3: tranglt38
A4: 45554 | B4: Bổ sung note dự phóng vốn MR bộ SBV theo mục tiêu CAR | C4: tranglt38
A5: 45555 | B5: Bổ sung ngày kịch bản VaR Bond | C5: tranglt38
A6: 45587 | B6: Sửa lại công thức biến động yield kịch bản BB 95% do đang refer nhầm sang ngày của kịch bản TB 95% | C6: tranglt38
A7: 45604 | B7: Sử dụng công thức để sort kịch bản VaR thay cho việc vào sort tay; bỏ các doublecheck không cần thiết cho việc sort tay do không cần sort tay nữa. | C7: tranglt38
A8: 45623 | B8: Sửa lại bảng group tenor, đổi kì hạn <1M thành 0-1M Sửa công thức ghi nhận trạng thái IR kì hạn ON trong bảng trạng thái IR của FXDR (bổ sung bao gồm ON và Today tại bảng FX) | C8: tranglt38
A9: 45630 | B9: Sửa công thức PV01 Bond TB (công thức ngày T-1 và M-1 đang tham chiếu sai ngày) | C9: tranglt38
A10: 45636 | B10: Sửa công thức VaR Bond Bổ sung ngày kịch bản cho VaR FXDR Bổ sung các chỉ số VaR 99 cho Bond và FXDR (sửa code lấy dữ liệu + bổ sung trên bảng trình bày) | C10: tranglt38
A11: 45311 | B11: Bổ sung kịch bản Bond sum 10D | C11: tranglt38
A12: 45335 | B12: Sửa công thức trạng thái IR sản phẩm forward các kì dài hơn ON do tham chiếu sai cột group tenor | C12: tranglt38
A13: 45709 | B13: Thêm input vốn tự có trong input sheet FX, thêm công thức tính hạn mức trạng thái FX | C13: thaottp14
... A18: 45790 | B18: Sửa công thức tính biến động gapls kì 3-5Y tại kịch bản cho FXDR | C18: tranglt38
A19: 45806 | B19: Không chạy được báo cáo daily do mất kết nối tới server 53 - IT đổi IP của các thành viên trong phòng --> không gửi báo cáo
A20: 45820 | B20: Bổ sung hạn mức NTK/Tổng trạng thái | C20: tranglt38
A21: 45841 | B21: Bổ sung chú giải tác động yếu tố rủi ro tới danh mục | C21: tranglt38
A22: 45852 | B22: Bổ sung số liệu và chart PnL theo QLHS cho Bond và FXDR | C22: tranglt38
A23: 45854 | B23: Bổ sung 3 hạn mức BB Bond còn thiếu | C23: tranglt38
A24: 45855 | B24: Thêm hạn mức pos banking bond 17,000 | C24: thaottp14
A25: 45859 | B25: Kéo thêm dữ liệu FIBond, bổ sung hạn mức mới | C25: tranglt38
A26: 45869 | B26: Sửa lại các link đường dẫn do chuyển ổ chung toàn hàng | C26: tranglt38
A27: 45880 | B27: Sửa lại code kéo chỉ số tập trung của bond banking | C27: tranglt38
A28: 45896 | B28: Sửa code itd unrealized pnl của bond do bond điều chỉnh itd unrealized pnl cho công nợ KH | C28: tranglt38
A29: 45946 | B29: Sửa code vốn để kéo thêm vốn option. Bổ sung trình bày vốn option cả 2 bộ sổ | C29: tranglt38
A30: 45951 | B30: Bổ sung lại tính toán trigger và rule đèn cảnh báo. Bổ sung doublecheck các chỉ số vượt trigger 80% limit | C30: tranglt38
A31: 45978 | B31: Thêm bảng connection dữ liệu trạng thái USD theo sản phẩm | C31: thaottp14
... A42: 46259 | B42: Sửa lại công thức trong import từ công thức của AI | C42: thaottp14

Sheet Import
A1: Date | B1: Key | C1: Value | D1: Group: AI Module | E1: Description | F1: How to use
A2: =RPT -> 46290 | B2: moduleNav_aiRecommend | C2: ='AI module'!B2 -> Góc tham khảo: AI sẽ nói gì về MLIR hôm nay :)? | D2: AI Module | E2: Tên tab menu module AI | F2: Sửa cột Value rồi import sheet Data Import vào HTML. Các key format dùng giá trị CSS như #RRGGBB, px, số độ đậm, hoặc font-family.
A3: =RPT -> 46290 | B3: aiRecommendModuleTitle | C3: ='AI module'!B3 -> AI khuyến nghị hành động trong ngày | D3: AI Module | E3: Tên module AI
A4: =RPT -> 46290 | B4: aiRecommendModuleDesc | C4: ='AI module'!B4 -> Tự động rà soát dữ liệu hiện có sau import để tạo checklist ngắn gọn theo từng góc nhìn quản trị. | D4: AI Module | E4: Mô tả module AI
A5: =RPT -> 46290 | B5: aiRecommendModuleBadge | C5: ='AI module'!B5 -> Market Risk AI | D5: AI Module | E5: Badge nhỏ trong module AI
A6: =RPT -> 46290 | B6: aiRecommendTitle | C6: ='AI module'!B6 -> What does AI recommend for risk Today? | D6: AI Module | E6: Tiêu đề chính trước khi gen checklist
A7: =RPT -> 46290 | B7: aiRecommendDisclaimerHtml | C7: ='AI module'!B7 -> <b>Disclaimer:</b> Đây là nội dung gen tự động từ AI, chỉ để người đọc trải nghiệm và tham khảo thông tin gợi ý/lưu ý từ góc nhìn của AI. Không phải là khuyến nghị chính thức của QLRRTT&TK | D7: AI Module | E7: Nội dung disclaimer; HTML chỉ bôi đỏ/đậm chữ Disclaimer nếu HTML có CSS tương ứng
A8: =RPT -> 46290 | B8: aiRecommendSubtitle | C8: ='AI module'!B8 -> Mỗi lần bấm Generate, module sẽ rà soát lại dữ liệu đang hiển thị về Trading Gbond, MtM, Banking Gbond, Bond&CD-FI, Market II, thị trường và OMO để tạo checklist mới, không dùng lại checklist đã lưu trước đó. | D8: AI Module | E8: Subtitle module AI
A9: =RPT -> 46290 | B9: aiRecommendBackButton | C9: ='AI module'!B9 -> Back | D9: AI Module | E9: Nút quay lại checklist trước
A10: =RPT -> 46290 | B10: aiRecommendViewLeadership | C10: ='AI module'!B10 -> View lãnh đạo | D10: AI Module | E10: Tên view lãnh đạo
A11: =RPT -> 46290 | B11: aiRecommendViewSupervision | C11: ='AI module'!B11 -> View giám sát/khuyến nghị | D11: AI Module | E11: Tên view giám sát/khuyến nghị
A12: =RPT -> 46290 | B12: aiRecommendViewExecution | C12: ='AI module'!B12 -> View đơn vị thực hiện | D12: AI Module | E12: Tên view đơn vị thực hiện
A13: =RPT -> 46290 | B13: aiRecommendClearButton | C13: ='AI module'!B13 -> Xóa checklist hiện tại | D13: AI Module | E13: Nút xóa checklist hiện tại
A14: =RPT -> 46290 | B14: aiRecommendGenerateButton | C14: ='AI module'!B14 -> Generate new risk recommendation | D14: AI Module | E14: Nút gen checklist mới
... A51: =RPT -> 46290 | B51: importQualityStatusDone | C51: ='AI module'!B51 -> Done | D51: Import AI Check | E51: Trạng thái lỗi đã hết sau lần scan lại
A52: =RPT -> 46290 | B52: Key | C52: Value | D52: Module: Thông tin chung | E52: Group | F52: Note
A53: =RPT -> 46290 | B53: moduleNavLabel | C53: ='Module name'!B2 -> Menu báo cáo | D53: Thông tin chung | E53: Tên module | F53: Label thanh menu module
A54: =RPT -> 46290 | B54: moduleNav_executive | C54: ='Module name'!B3 -> Executive Messages | D54: Thông tin chung | E54: Tên module | F54: Tên tab module Executive Messages
A55: =RPT -> 46290 | B55: moduleNav_detailPortfolio | C55: ='Module name'!B4 -> Thông tin chi tiết Danh mục | D55: Thông tin chung | E55: Tên module | F55: Tên tab module Thông tin chi tiết Danh mục
A56: =RPT -> 46290 | B56: moduleNav_market | C56: ='Module name'!B5 -> Thông tin thị trường | D56: Thông tin chung | E56: Tên module | F56: Tên tab module Thông tin thị trường
A57: =RPT -> 46290 | B57: moduleNav_marketII | C57: ='Module name'!B6 -> Cơ cấu dòng tiền thanh khoản - Market II | D57: Thông tin chung | E57: Tên module | F57: Tên tab module Cơ cấu dòng tiền Market II
A58: =RPT -> 46290 | B58: moduleNav_import | C58: ='Module name'!B7 -> 🔒 Import Data | D58: Thông tin chung | E58: Tên module | F58: Tên tab module Import Data
A59: =RPT -> 46290 | B59: moduleNav_print | C59: ='Module name'!B8 -> In / PDF | D59: Thông tin chung | E59: Tên module | F59: Tên nút In / PDF trên thanh menu
A60: =RPT -> 46290 | B60: Key | C60: Value | D60: Module: Executive | E60: Section | F60: Field/Label
A61: =RPT -> 46290 | B61: reportDate | C61: =_xlfn.XLOOKUP(B61,Executive!B:B,Executive!D:D,,0) -> 46290 | D61: Executive Messages | E61: Header | F61: Tiêu đề module Executive
A62: =RPT -> 46290 | B62: reportMainTitle | C62: =_xlfn.XLOOKUP(B62,Executive!B:B,Executive!D:D,,0) -> Market & Liquidity Risk Report (Market II) | D62: Executive Messages
A63: =RPT -> 46290 | B63: reportSubtitle | C63: =_xlfn.XLOOKUP(B63,Executive!B:B,Executive!D:D,,0) -> Rủi ro thị trường - thanh khoản | Danh mục Gbond Banking Book & Trading Book | Theo dõi MtM, PV01, NIM và tín hiệu thị trường | D63: Executive Messages
A64: =RPT -> 46290 | B64: moduleExecutiveTitle | C64: =_xlfn.XLOOKUP(B64,Executive!B:B,Executive!D:D,,0) -> Executive Messages: (1) Chỉ số lỗ MtM của danh mục Bond Trading giữ mức 1.634 tỷ. Nếu yield tăng thêm 1 bps (~0.01%) ở tất cả các kỳ hạn, mức lỗ sẽ gia tăng thêm 11 tỷ. (2) Trạng thái danh mục GBond duy trì mức 17.513 tỷ - 88% hạn mức; Trạng thái danh mục FIBond & CD (bao gồm cả TPCP nước ngoài Kyrgyzstan) duy trì mức 39.414 tỷ - 88% hạn mức. (3) Lãi suất LNH kỳ ON tiếp tục giảm xuống 0.7% trong khi các kỳ dài hơn từ 1W-1M vẫn quanh mức 5-6%. Lưu ý rủi ro lỗ NIM vẫn tiềm ẩn do lãi suất có khả năng biến động mạnh. (4) Khe hở thanh khoản lũy kế - Gap 3M đang ở mức -25,2k tỷ, có xu hướng tăng chiều âm trong tháng 9, chủ yếu do giảm cho vay LNH kì 1-3M trong khi tăng huy động LNH kì dưới 3M | D64: Executive Messages | E64: Header | F64: Tiêu đề module Executive
A65: =RPT -> 46290 | B65: moduleExecutiveStatus | C65: =_xlfn.XLOOKUP(B65,Executive!B:B,Executive!D:D,,0) -> NGOẠI LỆ HẠN MỨC LỖ MtM & RỦI RO LỖ KÉP | D65: Executive Messages | E65: Header | F65: Trạng thái module Executive
A66: =RPT -> 46290 | B66: executiveMessageSectionTitle | C66: =_xlfn.XLOOKUP(B66,Executive!B:B,Executive!D:D,,0) -> 1. Thông điệp trọng tâm | D66: Executive Messages | E66: Thông điệp trọng tâm | F66: Tiêu đề section
A67: =RPT -> 46290 | B67: msg1Title | C67: =_xlfn.XLOOKUP(B67,Executive!B:B,Executive!D:D,,0) -> Phân tách lại danh mục TD và BK GovBond | D67: Executive Messages | E67: Thông điệp trọng tâm | F67: Tiêu đề 1
A68: =RPT -> 46290 | B68: msg1Body | C68: =_xlfn.XLOOKUP(B68,Executive!B:B,Executive!D:D,,0) -> Kể từ ngày báo cáo 10/08/2026, QLRR đã điều chỉnh danh mục Trading và Banking book theo bóc tách lại phần Danh mục Banking Gbond phù hợp với số vốn được Pool tài trợ 12k tỷ) từ DCM. Theo đó: (1) Danh mục theo mệnh giá của Trading book và Banking book tương ứng là: 17.413 tỷ và 10.848 tỷ. (2) Ngay tại thời điểm bóc tách lại (10/08), Lỗ MtM của danh mục Trading điều chỉnh tăng thêm 23 tỷ. | D68: Executive Messages | E68: Thông điệp trọng tâm | F68: Nội dung 1
A69: =RPT -> 46290 | B69: msg2Title | C69: =_xlfn.XLOOKUP(B69,Executive!B:B,Executive!D:D,,0) -> Thay đổi ngưỡng mục tiêu bộ đệm thanh khoản | D69: Executive Messages | E69: Thông điệp trọng tâm | F69: Tiêu đề 2
A70: =RPT -> 46290 | B70: msg2Body | C70: =_xlfn.XLOOKUP(B70,Executive!B:B,Executive!D:D,,0) -> Sau bóc tách lại danh mục TD & BK, ngưỡng mục tiêu bộ đệm thanh khoản điều chỉnh từ 11.440 tỷ về 10.400 tỷ. QLRR lưu ý: (1) Banking Gbond dự phòng cần được sử dụng/tối ưu có chọn lọc trong điều kiện bình thường, nhằm tránh làm suy giảm năng lực ứng phó khi thị trường xuất hiện cú sốc nguồn vốn. | D70: Executive Messages | E70: Thông điệp trọng tâm | F70: Nội dung 2
A71: =RPT -> 46290 | B71: msg3Title | C71: =_xlfn.XLOOKUP(B71,Executive!B:B,Executive!D:D,,0) -> Giám sát tình trạng NGOẠI LỆ vượt hạn mức lỗ mtm | D71: Executive Messages | E71: Thông điệp trọng tâm | F71: Tiêu đề 3
A72: =RPT -> 46290 | B72: msg3Body | C72: =_xlfn.XLOOKUP(B72,Executive!B:B,Executive!D:D,,0) -> Danh mục Trading Gbond hiện ghi nhận lỗ MtM quanh 1.640 tỷ đồng (xu hướng tăng gần đây do yield tăng liên tục tuần qua) trên quy mô trạng thái rủi ro 17.413 tỷ đồng, vượt hạn mức 400 tỷ đồng và đang trong quá trình phê duyệt ngoại lệ. => QLRR khuyến nghị FI/DCM duy trì báo cáo định kỳ cấp có thẩm quyền, vẫn tiếp tục tìm kiếm các biện pháp giảm thiểu/xử lý lỗ và kiểm soát không để rủi ro tiếp tục gia tăng; báo cáo xin ý kiến cấp có thẩm quyền trong t/h phát sinh các nhân tố có thể làm leo thang đáng kể tình trạng lỗ mtm. | D72: Executive Messages | E72: Thông điệp trọng tâm | F72: Nội dung 3
A73: =RPT -> 46290 | B73: msg4Title | C73: =_xlfn.XLOOKUP(B73,Executive!B:B,Executive!D:D,,0) -> Rủi ro LỖ KÉP tiếp tục là ÁP LỰC CHÍNH | D73: Executive Messages | E73: Thông điệp trọng tâm | F73: Tiêu đề 4
A74: =RPT -> 46290 | B74: msg4Body | C74: =_xlfn.XLOOKUP(B74,Executive!B:B,Executive!D:D,,0) -> Trong bối cảnh lợi suất trái phiếu tăng từ đầu tháng và chi phí vốn duy trì ở mức cao, các danh mục Banking Gbond, FIBond và Trading Gbond đang chịu đồng thời hai áp lực: lỗ đánh giá lại MtM và suy giảm NIM => Đây không chỉ là rủi ro thị trường ngắn hạn, mà là vấn đề cần được cân nhắc trong chiến lược phân bổ bảng cân đối (danh quy mô DM đầu tư) và tối ưu hiệu quả vốn. | D74: Executive Messages | E74: Thông điệp trọng tâm | F74: Nội dung 4
A75: =RPT -> 46290 | B75: executiveGbondSectionTitle | C75: =_xlfn.XLOOKUP(B75,Executive!B:B,Executive!D:D,,0) -> Tình hình rủi ro Danh mục Trái phiếu chính phủ | D75: Executive Messages | E75: KPI Gbond | F75: Tiêu đề nhóm
A76: =RPT -> 46290 | B76: tradingCardTitle | C76: =_xlfn.XLOOKUP(B76,Executive!B:B,Executive!D:D,,0) -> Trading Book chịu rủi ro thị trường | D76: Executive Messages | E76: Trading Book | F76: Tiêu đề card
A77: =RPT -> 46290 | B77: tradingStatus | D77: Executive Messages | E77: Trading Book | F77: Status
A78: =RPT -> 46290 | B78: tradingExposure | C78: =_xlfn.XLOOKUP(B78,Executive!B:B,Executive!D:D,,0) -> 17513 | D78: Executive Messages | E78: Trading Book | F78: Giá trị
A79: =RPT -> 46290 | B79: tradingExposureChange | C79: =_xlfn.XLOOKUP(B79,Executive!B:B,Executive!D:D,,0) -> 0 | D79: Executive Messages | E79: Trading Book | F79: +/-
A80: =RPT -> 46290 | B80: tradingPortfolioRateLabel | C80: =_xlfn.XLOOKUP(B80,Executive!B:B,Executive!D:D,,0) -> Lãi suất DM: | D80: Executive Messages | E80: Trading Book | F80: Label lãi suất
A81: =RPT -> 46290 | B81: tradingPortfolioRate | C81: =_xlfn.XLOOKUP(B81,Executive!B:B,Executive!D:D,,0) -> 0.030511557 | D81: Executive Messages | E81: Trading Book | F81: Lãi suất DM
A82: =RPT -> 46290 | B82: pendingTradeAmount | C82: =_xlfn.XLOOKUP(B82,Executive!B:B,Executive!D:D,,0) -> 5916 | D82: Executive Messages | E82: Trading Book | F82: Giao dịch pending
A83: =RPT -> 46290 | B83: tradingBookNotePrefix | C83: =_xlfn.XLOOKUP(B83,Executive!B:B,Executive!D:D,,0) -> Sau giảm trừ giao dịch bán chưa thanh toán và BO chưa xác nhận (~ | D83: Executive Messages | E83: Trading Book | F83: Note prefix
A84: =RPT -> 46290 | B84: tradingBookNoteSuffix | C84: =_xlfn.XLOOKUP(B84,Executive!B:B,Executive!D:D,,0) -> tỷ) | D84: Executive Messages | E84: Trading Book | F84: Note suffix
A85: =RPT -> 46290 | B85: tradingLimitTitle | C85: =_xlfn.XLOOKUP(B85,Executive!B:B,Executive!D:D,,0) -> Hạn mức Trading Book | D85: Executive Messages | E85: Trading Book | F85: Tiêu đề limit
A86: =RPT -> 46290 | B86: limitLabel | C86: =_xlfn.XLOOKUP(B86,Executive!B:B,Executive!D:D,,0) -> Limit | D86: Executive Messages | E86: Trading Book | F86: Limit
A87: =RPT -> 46290 | B87: usageLabel | C87: =_xlfn.XLOOKUP(B87,Executive!B:B,Executive!D:D,,0) -> Mức sử dụng | D87: Executive Messages | E87: Trading Book | F87: Mức sử dụng
A88: =RPT -> 46290 | B88: tradingBookLimit | C88: =_xlfn.XLOOKUP(B88,Executive!B:B,Executive!D:D,,0) -> 20000 | D88: Executive Messages | E88: Trading Book | F88: Limit
A89: =RPT -> 46290 | B89: tradingUtilization | C89: =_xlfn.XLOOKUP(B89,Executive!B:B,Executive!D:D,,0) -> 0.87565 | D89: Executive Messages | E89: Trading Book | F89: Mức sử dụng
A90: =RPT -> 46290 | B90: tradingLimitWarningComment | D90: Executive Messages | E90: Trading Book | F90: Ghi chú khi vượt hạn mức Trading Book
A91: =RPT -> 46290 | B91: mtmCardTitle | C91: =_xlfn.XLOOKUP(B91,Executive!B:B,Executive!D:D,,0) -> Lỗ MtM còn lại | D91: Executive Messages | E91: MtM | F91: Tiêu đề card
A92: =RPT -> 46290 | B92: mtmStatus | D92: Executive Messages | E92: MtM | F92: Status
A93: =RPT -> 46290 | B93: mtmLimitWarningComment | C93: =_xlfn.XLOOKUP(B93,Executive!B:B,Executive!D:D,,0) -> Lưu ý: Đang trong trạng thái phê duyệt ngoại lệ | D93: Executive Messages | E93: MtM | F93: Ghi chú limit
A94: =RPT -> 46290 | B94: mtmLoss | C94: =_xlfn.XLOOKUP(B94,Executive!B:B,Executive!D:D,,0) -> 1634 | D94: Executive Messages | E94: MtM | F94: Giá trị
A95: =RPT -> 46290 | B95: mtmLossChange | C95: =_xlfn.XLOOKUP(B95,Executive!B:B,Executive!D:D,,0) -> 0 | D95: Executive Messages | E95: MtM | F95: +/-
A96: =RPT -> 46290 | B96: mtmCardNote | C96: =_xlfn.XLOOKUP(B96,Executive!B:B,Executive!D:D,,0) -> Trading Book sau giảm trừ giao dịch đã bán chưa thanh toán | D96: Executive Messages | E96: MtM | F96: Note
A97: =RPT -> 46290 | B97: mtmLimitTitle | C97: =_xlfn.XLOOKUP(B97,Executive!B:B,Executive!D:D,,0) -> Hạn mức lỗ MtM | D97: Executive Messages | E97: MtM | F97: Tiêu đề limit
A98: =RPT -> 46290 | B98: mtmLossLimit | C98: =_xlfn.XLOOKUP(B98,Executive!B:B,Executive!D:D,,0) -> 500 | D98: Executive Messages | E98: MtM | F98: Limit
A99: =RPT -> 46290 | B99: mtmUtilization | C99: =_xlfn.XLOOKUP(B99,Executive!B:B,Executive!D:D,,0) -> 3.268 | D99: Executive Messages | E99: MtM | F99: Mức sử dụng
A100: =RPT -> 46290 | B100: worstCaseCardTitle | C100: =_xlfn.XLOOKUP(B100,Executive!B:B,Executive!D:D,,0) -> Kịch bản bất lợi với giao dịch BO chưa xác nhận | D100: Executive Messages | E100: BO chưa xác nhận | F100: Tiêu đề card
A101: =RPT -> 46290 | B101: worstCaseMtMStatus | C101: =_xlfn.XLOOKUP(B101,Executive!B:B,Executive!D:D,,0) -> Rủi ro trọng yếu | D101: Executive Messages | E101: BO chưa xác nhận | F101: Status
A102: =RPT -> 46290 | B102: worstCaseMtM | C102: =_xlfn.XLOOKUP(B102,Executive!B:B,Executive!D:D,,0) -> 2016 | D102: Executive Messages | E102: BO chưa xác nhận | F102: Giá trị
A103: =RPT -> 46290 | B103: worstCaseMtMChange | C103: =_xlfn.XLOOKUP(B103,Executive!B:B,Executive!D:D,,0) -> -287.58942 | D103: Executive Messages | E103: BO chưa xác nhận | F103: +/-
A104: =RPT -> 46290 | B104: worstCaseMtMNote | C104: =_xlfn.XLOOKUP(B104,Executive!B:B,Executive!D:D,,0) -> Lỗ MtM tiềm ẩn gia tăng nếu giao dịch BO chưa xác nhận có thể bị đối tác hủy khi thị trường bất lợi | D104: Executive Messages | E104: BO chưa xác nhận | F104: Note
... A110: =RPT -> 46290 | B110: estimatedNimLoss | C110: =_xlfn.XLOOKUP(B110,Executive!B:B,Executive!D:D,,0) -> 109.262 | D110: Executive Messages | E110: NIM | F110: Giá trị
A111: =RPT -> 46290 | B111: estimatedNimLossChange | D111: Executive Messages | E111: NIM | F111: +/-
A112: =RPT -> 46290 | B112: estimatedNimLossNotePrefix | C112: =_xlfn.XLOOKUP(B112,Executive!B:B,Executive!D:D,,0) -> NIM giảm bao nhiêu nếu CoF tăng thêm 1% | D112: Executive Messages | E112: NIM | F112: Note prefix
A113: =RPT -> 46290 | B113: fundingCost | D113: Executive Messages | E113: NIM | F113: Funding cost
A114: =RPT -> 46290 | B114: estimatedNimLossNoteMid | C114: =_xlfn.XLOOKUP(B114,Executive!B:B,Executive!D:D,,0) -> Từ tháng 9 đến YE2026, giả định danh mục không thay đổi (chỉ điều chỉnh các deal valuedate trong tương lai lần lượt chuyển từ ngoại bảng vào nội bảng), nếu COF tăng thêm | D114: Executive Messages | E114: NIM | F114: Note mid
A115: =RPT -> 46290 | B115: costIncreaseAssumption | C115: =_xlfn.XLOOKUP(B115,Executive!B:B,Executive!D:D,,0) -> 1% | D115: Executive Messages | E115: NIM | F115: Cost increase
A116: =RPT -> 46290 | B116: estimatedNimLossNoteSuffix | C116: =_xlfn.XLOOKUP(B116,Executive!B:B,Executive!D:D,,0) -> sẽ làm NIM giảm thêm ~ | D116: Executive Messages | E116: NIM | F116: Note suffix
A117: =RPT -> 46290 | B117: nimLossMonthlyIncrease | C117: =_xlfn.XLOOKUP(B117,Executive!B:B,Executive!D:D,,0) -> 26 | D117: Executive Messages | E117: NIM | F117: Lỗ/tháng
A118: =RPT -> 46290 | B118: estimatedNimLossNoteUnit | C118: =_xlfn.XLOOKUP(B118,Executive!B:B,Executive!D:D,,0) -> tỷ đồng/tháng. | D118: Executive Messages | E118: NIM | F118: Note unit
A119: =RPT -> 46290 | B119: bankingCardTitle | C119: =_xlfn.XLOOKUP(B119,Executive!B:B,Executive!D:D,,0) -> Banking Gbond được tài trợ bởi Tiền gửi Hệ thống | D119: Executive Messages | E119: Banking DCM | F119: Tiêu đề card
A120: =RPT -> 46290 | B120: bankingStatus | D120: Executive Messages | E120: Banking DCM | F120: Status
A121: =RPT -> 46290 | B121: bankingBookBalance | C121: =_xlfn.XLOOKUP(B121,Executive!B:B,Executive!D:D,,0) -> 12,000 | D121: Executive Messages | E121: Banking DCM | F121: Giá trị
A122: =RPT -> 46290 | B122: bankingBookBalanceChange | C122: =_xlfn.XLOOKUP(B122,Executive!B:B,Executive!D:D,,0) -> 0 | D122: Executive Messages | E122: Banking DCM | F122: +/-
A123: =RPT -> 46290 | B123: bankingBookNote | C123: =_xlfn.XLOOKUP(B123,Executive!B:B,Executive!D:D,,0) -> Hệ thống tài trợ 12k tỷ để dự phòng thanh khoản cho kịch bản rút tiền gửi, tương ứng 10.848 tỷ theo mệnh giá. | D123: Executive Messages | E123: Banking DCM | F123: Note
A124: =RPT -> 46290 | B124: bankingBookRiskWarningLabel | C124: =_xlfn.XLOOKUP(B124,Executive!B:B,Executive!D:D,,0) -> Lưu ý: | D124: Executive Messages | E124: Banking DCM | F124: Risk label
A125: =RPT -> 46290 | B125: bankingBookRiskWarning | C125: =_xlfn.XLOOKUP(B125,Executive!B:B,Executive!D:D,,0) -> Danh mục này có thể chịu các rủi ro tiềm ẩn IRRBB ở 02 khía cạnh sau :(1) Rủi ro tăng chi phí vốn tài trợ làm gia tăng chi phí thanh khoản phân bổ trong FTP ;(2) Rủi ro giảm giá trị: Mặc dù là Banking GBond nắm giữ để dự phòng thanh khoản, không phải để Trading, nhưng vẫn tiềm ẩn rủi ro Giảm giá trị (do đánh giá mtm) và có thể ghi nhận lỗ vào KQKD trong trường hợp buộc phải bán để đáp ứng nhu cầu thanh toán trong điều kiện căng thẳng thanh khoản. | D125: Executive Messages | E125: Banking DCM | F125: Risk warning
A126: =RPT -> 46290 | B126: bankingLimitTitle | C126: =_xlfn.XLOOKUP(B126,Executive!B:B,Executive!D:D,,0) -> Mức tài trợ từ Tiền gửi hệ thống (do ALCO phê duyệt) | D126: Executive Messages | E126: Banking DCM | F126: Limit title
A127: =RPT -> 46290 | B127: bankingBookLimit | C127: =_xlfn.XLOOKUP(B127,Executive!B:B,Executive!D:D,,0) -> 12,000 | D127: Executive Messages | E127: Banking DCM | F127: Limit
A128: =RPT -> 46290 | B128: bankingUtilization | C128: =_xlfn.XLOOKUP(B128,Executive!B:B,Executive!D:D,,0) -> 1 | D128: Executive Messages | E128: Banking DCM | F128: Mức sử dụng
A129: =RPT -> 46290 | B129: bankingLimitWarningComment | D129: Executive Messages | E129: Banking DCM | F129: Ghi chú khi vượt hạn mức Banking Book
A130: =RPT -> 46290 | B130: availableBankingCardTitle | C130: =_xlfn.XLOOKUP(B130,Executive!B:B,Executive!D:D,,0) -> Banking Gbond dự phòng thanh khoản | D130: Executive Messages | E130: Banking dự phòng | F130: Tiêu đề card
A131: =RPT -> 46290 | B131: availableBankingGbondStatus | D131: Executive Messages | E131: Banking dự phòng | F131: Status
A132: =RPT -> 46290 | B132: availableBankingGbond | C132: =_xlfn.XLOOKUP(B132,Executive!B:B,Executive!D:D,,0) -> 10769 | D132: Executive Messages | E132: Banking dự phòng | F132: Giá trị
A133: =RPT -> 46290 | B133: availableBankingGbondChange | C133: =_xlfn.XLOOKUP(B133,Executive!B:B,Executive!D:D,,0) -> -4560 | D133: Executive Messages | E133: Banking dự phòng | F133: +/-
A134: =RPT -> 46290 | B134: availableBankingGbondNote | C134: =_xlfn.XLOOKUP(B134,Executive!B:B,Executive!D:D,,0) -> Nguồn Gbond còn lại có thể sử dụng cho mục tiêu dự phòng thanh khoản | D134: Executive Messages | E134: Banking dự phòng | F134: Note
A135: =RPT -> 46290 | B135: availableBankingGbondLimitTitle | C135: =_xlfn.XLOOKUP(B135,Executive!B:B,Executive!D:D,,0) -> Mức dự phòng thanh khoản mục tiêu | D135: Executive Messages | E135: Banking dự phòng | F135: Limit title
A136: =RPT -> 46290 | B136: targetLabel | C136: =_xlfn.XLOOKUP(B136,Executive!B:B,Executive!D:D,,0) -> Target | D136: Executive Messages | E136: Banking dự phòng | F136: Target label
A137: =RPT -> 46290 | B137: liquidityReserveTarget | C137: =_xlfn.XLOOKUP(B137,Executive!B:B,Executive!D:D,,0) -> 10300 | D137: Executive Messages | E137: Banking dự phòng | F137: Target
A138: =RPT -> 46290 | B138: liquidityReserveWarningThresholdLabel | C138: =_xlfn.XLOOKUP(B138,Executive!B:B,Executive!D:D,,0) -> Ngưỡng cảnh báo | D138: Executive Messages | E138: Banking dự phòng | F138: WarningName
A139: =RPT -> 46290 | B139: liquidityReserveWarningThreshold | C139: =_xlfn.XLOOKUP(B139,Executive!B:B,Executive!D:D,,0) -> 8000 | D139: Executive Messages | E139: Banking dự phòng | F139: Ngưỡng
A140: =RPT -> 46290 | B140: reserveUsageLabel | C140: =_xlfn.XLOOKUP(B140,Executive!B:B,Executive!D:D,,0) -> Mức sử dụng so với mục tiêu | D140: Executive Messages | E140: Banking dự phòng | F140: Usage label
A141: =RPT -> 46290 | B141: availableBankingGbondUtilization | C141: =_xlfn.XLOOKUP(B141,Executive!B:B,Executive!D:D,,0) -> 1.045534 | D141: Executive Messages | E141: Banking dự phòng | F141: Mức đáp ứng
...

Sheet MR>>

Sheet Code
A1: Provider=SQLOLEDB.1;Password=msb@2019;Persist Security Info=True;User ID=sa;Initial Catalog=GS_RRTT;Data Source=10.1.77.53,8888;Use Procedure for Prepare=1;Auto Translate=True;Packet Size=4096;Workstation ID=QLRR-TRANGTTQ3;Use Encryption for Data=False;Tag with column collation when possible=False
A2: STT | B2: Sản phẩm | C2: Para1 | D2: Code | E2: Mục đích code | F2: Connection name
A3: 1 | B3: BOND | C3: select RptDate, Indicators, Class,Tenor_Value,Actual from GS_RRTT.dbo.Bond_Trading_Historical a where Indicators like '%Trang thai mo' and Tenor_Value = '' and Class = 'All' and Input_data = 'Spot' and Rptdate >= | D3: =C3&TEXT(Lastyear,"'yyyy-m-d'")&"order by RptDate desc" -> select RptDate, Indicators, Class,Tenor_Value,Actual from GS_RRTT.dbo.Bond_Trading_Historical a where Indicators like '%Trang thai mo' and Tenor_Value = '' and Class = 'All' and Input_data = 'Spot' and Rptdate >='2024-12-31'order by RptDate desc | E3: Trạng thái Trading book theo kỳ hạn, theo loại trái phiếu | F3: BOND.1
A4: 2 | B4: BOND | C4: select RptDate, Indicators,Class, Tenor_Value,Actual from GS_RRTT.dbo.Bond_Banking_Historical a where Indicators like '%Trang thai mo' and Rpt_Grp = '' and Input_data = 'Spot' and Tenor_Value = '' and Class = 'All' and Rptdate >= | D4: =C4&TEXT(Lastyear,"'yyyy-m-d'")&"order by RptDate desc" -> select RptDate, Indicators,Class, Tenor_Value,Actual from GS_RRTT.dbo.Bond_Banking_Historical a where Indicators like '%Trang thai mo' and Rpt_Grp = '' and Input_data = 'Spot' and Tenor_Value = '' and Class = 'All' and Rptdate >='2024-12-31'order by RptDate desc | E4: Trạng thái Banking book theo kỳ hạn, theo loại trái phiếu | F4: BOND.2
A5: 3 | B5: BOND | C5: select RptDate, Indicators, Tenor_Value,Actual from GS_RRTT.dbo.Bond_Trading_Historical a where Indicators = 'PV01' and Tenor_Value = '' and Class = 'All' and Input_data = 'Spot' and Rptdate >= | D5: =C5&TEXT(Lastmonth,"'yyyy-m-d'")&"order by RptDate desc" -> select RptDate, Indicators, Tenor_Value,Actual from GS_RRTT.dbo.Bond_Trading_Historical a where Indicators = 'PV01' and Tenor_Value = '' and Class = 'All' and Input_data = 'Spot' and Rptdate >='2026-8-28'order by RptDate desc | E5: PV01 Trading book theo kỳ hạn | F5: BOND.3
A6: 4 | B6: BOND | C6: select RptDate,Indicators,Tenor_Value, Rpt_Grp,Actual from GS_RRTT.dbo.Bond_Banking_Historical where Indicators = 'PV01' and Tenor_Value = '' and Class = 'All' and Input_data = 'Spot' and Rptdate >= | D6: =C6&TEXT(Lastmonth,"'yyyy-m-d'")&"order by RptDate desc" -> select RptDate,Indicators,Tenor_Value, Rpt_Grp,Actual from GS_RRTT.dbo.Bond_Banking_Historical where Indicators = 'PV01' and Tenor_Value = '' and Class = 'All' and Input_data = 'Spot' and Rptdate >='2026-8-28'order by RptDate desc | E6: PV01 Banking book theo kỳ hạn | F6: BOND.4
A7: 5 | B7: BOND | C7: select RptDate, Indicators,Tenor_Value, Actual from GS_RRTT.dbo.Bond_Trading_Historical a where Indicators = 'Unrealized_ItD_MtM_PnL' and Tenor_Value = '' and Class = 'All' and Input_data = 'Spot' and Rptdate >= | D7: =C7&TEXT(Lastmonth,"'yyyy-m-d'")&"order by RptDate desc" -> select RptDate, Indicators,Tenor_Value, Actual from GS_RRTT.dbo.Bond_Trading_Historical a where Indicators = 'Unrealized_ItD_MtM_PnL' and Tenor_Value = '' and Class = 'All' and Input_data = 'Spot' and Rptdate >='2026-8-28'order by RptDate desc | E7: ItD Unrealized PnL Trading theo kỳ hạn | F7: BOND.5
A8: 6 | B8: BOND | C8: select RptDate, Indicators,Tenor_Value, Actual from GS_RRTT.dbo.Bond_Banking_Historical a where Indicators = 'ItD Unrealized PnL' and Tenor_Value = '' and Class = 'All' and Input_data = 'Spot' and Rptdate >= | D8: =C8&TEXT(Lastmonth,"'yyyy-m-d'")&"order by RptDate desc" -> select RptDate, Indicators,Tenor_Value, Actual from GS_RRTT.dbo.Bond_Banking_Historical a where Indicators = 'ItD Unrealized PnL' and Tenor_Value = '' and Class = 'All' and Input_data = 'Spot' and Rptdate >='2026-8-28'order by RptDate desc | E8: ItD Unrealized PnL banking theo kỳ hạn | F8: BOND.6
A9: 7 | B9: BOND | C9: select RptDate,Indicators,Input_data,Class,Actual from GS_RRTT.dbo.Bond_Trading_Historical where Indicators in ('ON BS','OFF BS','NGOAI BS','YTM_ON BS') and Rptdate >= | D9: =C9&TEXT(Lastyear,"'yyyy-m-d'")&"order by RptDate desc" -> select RptDate,Indicators,Input_data,Class,Actual from GS_RRTT.dbo.Bond_Trading_Historical where Indicators in ('ON BS','OFF BS','NGOAI BS','YTM_ON BS') and Rptdate >='2024-12-31'order by RptDate desc | E9: ON_OFF_NGOAI BS | F9: BOND.7
A10: 8 | B10: BOND | C10: select RptDate, Indicators, Product, Actual from GS_RRTT.dbo.FIBond_Historical where Product in ('FI Bond', 'CD') and Indicators = 'Face value' and Issuer = '' and Tenor = '' and Rptdate >= | D10: =C10&TEXT(Lastyear,"'yyyy-m-d'")&"order by RptDate desc" -> select RptDate, Indicators, Product, Actual from GS_RRTT.dbo.FIBond_Historical where Product in ('FI Bond', 'CD') and Indicators = 'Face value' and Issuer = '' and Tenor = '' and Rptdate >='2024-12-31'order by RptDate desc | E10: Face value FIBond | F10: BOND.8
A11: 9 | B11: BOND | C11: select RptDate, Indicators, Product, Actual from GS_RRTT.dbo.FIBond_Historical where Indicators in ('Face value','YTM binh quan') and Product like '% BS' and Rptdate >= | D11: =C11&TEXT(Lastyear,"'yyyy-m-d'")&"order by RptDate desc" -> select RptDate, Indicators, Product, Actual from GS_RRTT.dbo.FIBond_Historical where Indicators in ('Face value','YTM binh quan') and Product like '% BS' and Rptdate >='2024-12-31'order by RptDate desc | E11: FIBond On/Off/Ngoai BS & YTM | F11: BOND.9
A12: 10 | B12: BOND | C12: select Date,Indicators,Value from QLRRTT.dbo.MSB_Report_AvailableBond where indicators in ('Face_HLA','Face_Secured_Unused','Face_SBV_Overdraft','Face_OMO_Available','Face_HMNR_NAPAS') and Date >= | D12: =C12&TEXT(Lastmonth,"'yyyy-m-d'")&"order by Date desc" -> select Date,Indicators,Value from QLRRTT.dbo.MSB_Report_AvailableBond where indicators in ('Face_HLA','Face_Secured_Unused','Face_SBV_Overdraft','Face_OMO_Available','Face_HMNR_NAPAS') and Date >='2026-8-28'order by Date desc | E12: Available bond - dữ liệu LR | F12: BOND.10
A13: 11 | B13: BOND | C13: select RptDate,Indicators,Actual from GS_RRTT.dbo.Bond_Trading_Historical where indicators like 'Est %' and Rptdate = | D13: =C13&TEXT(RPT,"'yyyy-m-d'")&"order by RptDate desc" -> select RptDate,Indicators,Actual from GS_RRTT.dbo.Bond_Trading_Historical where indicators like 'Est %' and Rptdate ='2026-9-25'order by RptDate desc | E13: Ước tính NIM: Trạng thái nội bảng + YTM ước tính | F13: BOND.11
A14: 12 | B14: BOND | C14: select RptDate,Indicators,Actual from GS_RRTT.dbo.Bond_Trading_Historical where indicators in ('Realized off BS', 'Realized ngoai BS') and Rptdate >= | D14: =C14&TEXT(Yesterday,"'yyyy-m-d'")&"order by RptDate desc" -> select RptDate,Indicators,Actual from GS_RRTT.dbo.Bond_Trading_Historical where indicators in ('Realized off BS', 'Realized ngoai BS') and Rptdate >='2026-9-24'order by RptDate desc | E14: Ước tính Realized off BS | F14: BOND.12
A15: 13 | B15: BOND | C15: select RptDate, Indicators,Actual from GS_RRTT.dbo.Bond_Trading_Historical a where Indicators = 'YTM' and Rptdate >= | D15: =C15&TEXT(Yesterday,"'yyyy-m-d'")&"order by RptDate desc" -> select RptDate, Indicators,Actual from GS_RRTT.dbo.Bond_Trading_Historical a where Indicators = 'YTM' and Rptdate >='2026-9-24'order by RptDate desc | E15: YTM Trading | F15: BOND.13
A16: 15 | B16: Market info | C16: select RptDate,Tenor,Average as 'Yield' from GS_RRTT.dbo.All_Marketdata_Historical where Indicators like 'VBMA%' and Indicators not like 'VBMA.%' and Rptdate >= | D16: =C16&TEXT(Lastyear,"'yyyy-m-d'")&"order by RptDate desc" -> select RptDate,Tenor,Average as 'Yield' from GS_RRTT.dbo.All_Marketdata_Historical where Indicators like 'VBMA%' and Indicators not like 'VBMA.%' and Rptdate >='2024-12-31'order by RptDate desc | E16: Chuỗi yield 1 năm | F16: MK.1
A17: 16 | B17: Market info | C17: select RptDate,Indicators,Average from GS_RRTT.dbo.All_Marketdata_Historical where Class = 'LNH' and Indicators like '%VND' and Rptdate >= | D17: =C17&TEXT(Lastyear,"'yyyy-m-d'")&"order by RptDate desc" -> select RptDate,Indicators,Average from GS_RRTT.dbo.All_Marketdata_Historical where Class = 'LNH' and Indicators like '%VND' and Rptdate >='2024-12-31'order by RptDate desc | E17: Chuỗi ls LNH đồng VND | F17: MK.2
A18: 17 | B18: Market info | C18: select Date,Indicators,Value from QLRRTT.dbo.MSB_Report_Other_Data where Indicators like '%OMO%' and Date >= | D18: =C18&TEXT(Lastyear,"'yyyy-m-d'")&"order by Date desc" -> select Date,Indicators,Value from QLRRTT.dbo.MSB_Report_Other_Data where Indicators like '%OMO%' and Date >='2024-12-31'order by Date desc | E18: Chuỗi thông tin OMO_Lay tu LR | F18: MK.3
A19: 18 | B19: Market info | C19: select RptDate,Average as 'TygiaUV' from GS_RRTT.dbo.All_Marketdata_Historical where Indicators like 'UV1' and RptDate >= | D19: =C19&TEXT(Lastyear,"'yyyy-m-d'")&"order by RptDate desc" -> select RptDate,Average as 'TygiaUV' from GS_RRTT.dbo.All_Marketdata_Historical where Indicators like 'UV1' and RptDate >='2024-12-31'order by RptDate desc | E19: Chuỗi tỷ giá USDVND | F19: MK.4

Sheet BOND
A1: 1. Trang thai bond trading | G1: 2. Trang thai bond banking | M1: 3. PV01 trading | R1: 4. PV01 banking | X1: 5. ItD Unrealized PnL trading | AA1: =AA4-#REF! -> #REF! | AC1: 6. ItD Unrealized PnL banking | AH1: 7. On, off BS - Trading book | AN1: 8. Trang thai FI Bond | AS1: 9. FIBond On/Off/Ngoai BS & YTM | AX1: 10. Available bond | BB1: 11. Ước tính NIM | BF1: 12. Realized chưa ghi nhận | BJ1: 13. YTM | BN1: 14. QLHS
A3: RptDate | B3: Indicators | C3: Class | D3: Tenor_Value | E3: Actual | G3: RptDate | H3: Indicators | I3: Class | J3: Tenor_Value | K3: Actual | M3: RptDate | N3: Indicators | O3: Tenor_Value | P3: Actual | R3: RptDate | S3: Indicators | T3: Tenor_Value | U3: Actual | V3: Rpt_Grp | X3: RptDate | Y3: Indicators | Z3: Tenor_Value | AA3: Actual | AC3: RptDate | AD3: Indicators | AE3: Tenor_Value | AF3: Actual | AH3: RptDate | AI3: Indicators | AJ3: Input_data | AK3: Class | AL3: Actual | AN3: RptDate | AO3: Indicators | AP3: Product | AQ3: Actual | AS3: RptDate | AT3: Indicators | AU3: Product | AV3: Actual | AX3: Date | AY3: Indicators | AZ3: Value | BB3: RptDate | BC3: Indicators | BD3: Actual | BF3: RptDate | BG3: Indicators | BH3: Actual | BJ3: RptDate | BK3: Indicators | BL3: Actual | BN3: Date | BO3: Desk | BP3: Indicator | BQ3: Actual
A4: 2026-09-28 | B4: Trang thai mo | C4: All | E4: 17513 | G4: 2026-09-28 | H4: Trang thai mo | I4: All | K4: 10858.311 | M4: 2026-09-28 | N4: PV01 | P4: -10.543406 | R4: 2026-09-28 | S4: PV01 | U4: -8.3967355 | X4: 2026-09-28 | Y4: Unrealized_ItD_MtM_PnL | AA4: -1631.9295 | AC4: 2026-09-28 | AD4: ItD Unrealized PnL | AF4: -1738.7219 | AH4: 2026-09-28 | AI4: ON BS | AJ4: Face | AK4: All | AL4: 33460.3 | AN4: 2026-09-28 | AO4: Face value | AP4: FI Bond | AQ4: 11965.192 | AS4: 2026-09-28 | AT4: Face value | AU4: CD On BS | AV4: 18899.1 | AX4: 46293 | AY4: Face_HLA | AZ4: 10769.311 | BB4: 2026-09-25 | BC4: Est YTM T9 | BD4: 4.2464765 | BF4: 2026-09-28 | BG4: Realized off BS | BH4: -32.480626 | BJ4: 2026-09-28 | BK4: YTM | BL4: 3.0511557 | BN4: 46052 | BO4: Trading bonds_Govbond | BP4: NIM | BQ4: -14.84306
A5: 2026-09-25 | B5: Trang thai mo | C5: All | E5: 17513 | G5: 2026-09-25 | H5: Trang thai mo | I5: All | K5: 10858.311 | M5: 2026-09-25 | N5: PV01 | P5: -10.551946 | R5: 2026-09-25 | S5: PV01 | U5: -8.4014384 | X5: 2026-09-25 | Y5: Unrealized_ItD_MtM_PnL | AA5: -1633.9373 | AC5: 2026-09-25 | AD5: ItD Unrealized PnL | AF5: -1740.2885 | AH5: 2026-09-28 | AI5: ON BS | AJ5: MtM | AK5: All | AL5: 33706.984 | AN5: 2026-09-28 | AO5: Face value | AP5: CD | AQ5: 27449.1 | AS5: 2026-09-28 | AT5: Face value | AU5: FI Bond Listed On BS | AV5: 397.6106 | AX5: 46293 | AY5: Face_Secured_Unused | AZ5: -800 | BB5: 2026-09-25 | BC5: Est YTM T8 | BD5: 0 | BF5: 2026-09-28 | BG5: Realized ngoai BS | BH5: -0.61667935 | BJ5: 2026-09-25 | BK5: YTM | BL5: 3.0511557 | BN5: 46052 | BO5: Trading bonds_Govbond | BP5: Realized PnL | BQ5: 2.8633123
A6: 2026-09-24 | B6: Trang thai mo | C6: All | E6: 17513 | G6: 2026-09-24 | H6: Trang thai mo | I6: All | K6: 10858.311 | M6: 2026-09-24 | N6: PV01 | P6: -10.554996 | R6: 2026-09-24 | S6: PV01 | U6: -8.403096 | X6: 2026-09-24 | Y6: Unrealized_ItD_MtM_PnL | AA6: -1634.2983 | AC6: 2026-09-24 | AD6: ItD Unrealized PnL | AF6: -1740.6871 | AH6: 2026-09-28 | AI6: ON BS | AJ6: PTCK | AK6: All | AL6: 1710.1846 | AN6: 2026-09-25 | AO6: Face value | AP6: FI Bond | AQ6: 11965.305 | AS6: 2026-09-28 | AT6: Face value | AU6: FI Bond Unlisted On BS | AV6: 11000 | AX6: 46293 | AY6: Face_SBV_Overdraft | AZ6: -1459 | BB6: 2026-09-25 | BC6: Est YTM T7 | BD6: 0 | BF6: 2026-09-25 | BG6: Realized off BS | BH6: -35.502497 | BJ6: 2026-09-24 | BK6: YTM | BL6: 3.0511557 | BN6: 46052 | BO6: Trading bonds_FI bond | BP6: NIM | BQ6: -14.723
A7: 2026-09-23 | B7: Trang thai mo | C7: All | E7: 17513 | G7: 2026-09-23 | H7: Trang thai mo | I7: All | K7: 10858.311 | M7: 2026-09-23 | N7: PV01 | P7: -10.557814 | R7: 2026-09-23 | S7: PV01 | U7: -8.4046858 | X7: 2026-09-23 | Y7: Unrealized_ItD_MtM_PnL | AA7: -1635.0999 | AC7: 2026-09-23 | AD7: ItD Unrealized PnL | AF7: -1741.1784 | AH7: 2026-09-28 | AI7: ON BS | AJ7: Diff | AK7: All | AL7: -1463.5005 | AN7: 2026-09-25 | AO7: Face value | AP7: CD | AQ7: 27449.1 | AS7: 2026-09-28 | AT7: Face value | AU7: CD Off BS | AV7: 0 | AX7: 46293 | AY7: Face_HMNR_NAPAS | AZ7: -605 | BB7: 2026-09-25 | BC7: Est YTM T6 | BD7: 0 | BF7: 2026-09-25 | BG7: Realized ngoai BS | BH7: -0.60485888 | BN7: 46052 | BO7: Trading bonds_FI bond | BP7: Realized PnL | BQ7: -2.222
A8: 2026-09-22 | B8: Trang thai mo | C8: All | E8: 17513 | G8: 2026-09-22 | H8: Trang thai mo | I8: All | K8: 10858.311 | M8: 2026-09-22 | N8: PV01 | P8: -10.559507 | R8: 2026-09-22 | S8: PV01 | U8: -8.4057128 | X8: 2026-09-22 | Y8: Unrealized_ItD_MtM_PnL | AA8: -1637.6918 | AC8: 2026-09-22 | AD8: ItD Unrealized PnL | AF8: -1742.2555 | AH8: 2026-09-28 | AI8: ON BS | AJ8: ItD | AK8: All | AL8: -1432.6245 | AN8: 2026-09-24 | AO8: Face value | AP8: FI Bond | AQ8: 11965.754 | AS8: 2026-09-28 | AT8: Face value | AU8: FI Bond Listed Off BS | AV8: 0 | AX8: 46293 | AY8: Face_OMO_Available | AZ8: 7392.8209 | BB8: 2026-09-25 | BC8: Est YTM T5 | BD8: 0 | BF8: 2026-09-24 | BG8: Realized off BS | BH8: -33.975479 | BN8: 46052 | BO8: Banking bonds_Govbond | BP8: NIM | BQ8: -11.038693
A9: 2026-09-21 | B9: Trang thai mo | C9: All | E9: 17513 | G9: 2026-09-21 | H9: Trang thai mo | I9: All | K9: 10858.311 | M9: 2026-09-21 | N9: PV01 | P9: -10.563334 | R9: 2026-09-21 | S9: PV01 | U9: -8.4082436 | X9: 2026-09-21 | Y9: Unrealized_ItD_MtM_PnL | AA9: -1637.0596 | AC9: 2026-09-21 | AD9: ItD Unrealized PnL | AF9: -1741.8634 | AH9: 2026-09-28 | AI9: OFF BS | AJ9: Face | AK9: All | AL9: -17794.7 | AN9: 2026-09-24 | AO9: Face value | AP9: CD | AQ9: 27449.1 | AS9: 2026-09-28 | AT9: Face value | AU9: FI Bond Unlisted Off BS | AV9: 0 | AX9: 46292 | AY9: Face_HLA | AZ9: 15329.311 | BB9: 2026-09-25 | BC9: Est YTM T4 | BD9: 0 | BF9: 2026-09-24 | BG9: Realized ngoai BS | BH9: -2.4092188 | BN9: 46052 | BO9: Banking bonds_Govbond | BP9: Realized PnL | BQ9: -0.003892796
A10: 2026-09-18 | B10: Trang thai mo | C10: All | E10: 17513 | G10: 2026-09-18 | H10: Trang thai mo | I10: All | K10: 10858.311 | M10: 2026-09-18 | N10: PV01 | P10: -10.573884 | R10: 2026-09-18 | S10: PV01 | U10: -8.4146508 | X10: 2026-09-18 | Y10: Unrealized_ItD_MtM_PnL | AA10: -1637.485 | AC10: 2026-09-18 | AD10: ItD Unrealized PnL | AF10: -1741.8966 | AH10: 2026-09-28 | AI10: OFF BS | AJ10: MtM | AK10: All | AL10: -19411.76 | AN10: 2026-09-23 | AO10: Face value | AP10: FI Bond | AQ10: 12965.527 | AS10: 2026-09-28 | AT10: Face value | AU10: CD Ngoai BS | AV10: 8550 | AX10: 46292 | AY10: Face_Secured_Unused | AZ10: -800 | BB10: 2026-09-25 | BC10: Est YTM T3 | BD10: 0 | BN10: 46080 | BO10: Banking bonds_Govbond | BP10: Realized PnL | BQ10: -0.003892796
A11: 2026-09-17 | B11: Trang thai mo | C11: All | E11: 17513 | G11: 2026-09-17 | H11: Trang thai mo | I11: All | K11: 10858.311 | M11: 2026-09-17 | N11: PV01 | P11: -10.577626 | R11: 2026-09-17 | S11: PV01 | U11: -8.4177501 | X11: 2026-09-17 | Y11: Unrealized_ItD_MtM_PnL | AA11: -1637.4335 | AC11: 2026-09-17 | AD11: ItD Unrealized PnL | AF11: -1740.9607 | AH11: 2026-09-28 | AI11: OFF BS | AJ11: PTCK | AK11: All | AL11: -1515.1092 | AN11: 2026-09-23 | AO11: Face value | AP11: CD | AQ11: 28149.1 | AS11: 2026-09-28 | AT11: Face value | AU11: FI Bond Listed Ngoai BS | AV11: 0 | AX11: 46292 | AY11: Face_SBV_Overdraft | AZ11: -1459 | BB11: 2026-09-25 | BC11: Est YTM T2 | BD11: 0 | BN11: 46080 | BO11: Banking bonds_Govbond | BP11: NIM | BQ11: -11.430737
A12: 2026-09-16 | B12: Trang thai mo | C12: All | E12: 17513 | G12: 2026-09-16 | H12: Trang thai mo | I12: All | K12: 10858.311 | M12: 2026-09-16 | N12: PV01 | P12: -10.581797 | R12: 2026-09-16 | S12: PV01 | U12: -8.4199731 | X12: 2026-09-16 | Y12: Unrealized_ItD_MtM_PnL | AA12: -1636.2583 | AC12: 2026-09-16 | AD12: ItD Unrealized PnL | AF12: -1740.7866 | AH12: 2026-09-28 | AI12: OFF BS | AJ12: Diff | AK12: All | AL12: -101.95033 | AN12: 2026-09-22 | AO12: Face value | AP12: FI Bond | AQ12: 12966.387 | AS12: 2026-09-28 | AT12: Face value | AU12: FI Bond Unlisted Ngoai BS | AV12: 0 | AX12: 46292 | AY12: Face_HMNR_NAPAS | AZ12: -605 | BB12: 2026-09-25 | BC12: Est YTM T12 | BD12: 3.5992079 | BN12: 46080 | BO12: Trading bonds_FI bond | BP12: Realized PnL | BQ12: 3.048
A13: 2026-09-15 | B13: Trang thai mo | C13: All | E13: 17513 | G13: 2026-09-15 | H13: Trang thai mo | I13: All | K13: 10858.311 | M13: 2026-09-15 | N13: PV01 | P13: -10.584026 | R13: 2026-09-15 | S13: PV01 | U13: -8.4211269 | X13: 2026-09-15 | Y13: Unrealized_ItD_MtM_PnL | AA13: -1638.5772 | AC13: 2026-09-15 | AD13: ItD Unrealized PnL | AF13: -1741.6388 | AH13: 2026-09-28 | AI13: OFF BS | AJ13: ItD | AK13: All | AL13: -101.95033 | AN13: 2026-09-22 | AO13: Face value | AP13: CD | AQ13: 28749.1 | AS13: 2026-09-28 | AT13: YTM binh quan | AU13: FI Bond On BS | AV13: 7.6809373 | AX13: 46292 | AY13: Face_OMO_Available | AZ13: 7392.8209 | BB13: 2026-09-25 | BC13: Est YTM T11 | BD13: 3.8006658 | BN13: 46080 | BO13: Trading bonds_Govbond | BP13: Realized PnL | BQ13: 9.8120631
A14: 2026-09-14 | B14: Trang thai mo | C14: All | E14: 17663 | G14: 2026-09-14 | H14: Trang thai mo | I14: All | K14: 10858.311 | M14: 2026-09-14 | N14: PV01 | P14: -10.665756 | R14: 2026-09-14 | S14: PV01 | U14: -8.4239771 | X14: 2026-09-14 | Y14: Unrealized_ItD_MtM_PnL | AA14: -1638.8987 | AC14: 2026-09-14 | AD14: ItD Unrealized PnL | AF14: -1741.0148 | AH14: 2026-09-28 | AI14: OFF BS | AJ14: Face | AK14: Deal buy | AL14: 4731.32 | AN14: 2026-09-21 | AO14: Face value | AP14: FI Bond | AQ14: 12966.025 | AS14: 2026-09-28 | AT14: YTM binh quan | AU14: CD On BS | AV14: 7.3566433 | AX14: 46289 | AY14: Face_HLA | AZ14: 15469.311 | BB14: 2026-09-25 | BC14: Est YTM T10 | BD14: 3.9499879 | BN14: 46080 | BO14: Trading bonds_Govbond | BP14: NIM | BQ14: -13.818341
A15: 2026-09-11 | B15: Trang thai mo | C15: All | E15: 17513 | G15: 2026-09-11 | H15: Trang thai mo | I15: All | K15: 10858.311 | M15: 2026-09-11 | N15: PV01 | P15: -10.595633 | R15: 2026-09-11 | S15: PV01 | U15: -8.4261398 | X15: 2026-09-11 | Y15: Unrealized_ItD_MtM_PnL | AA15: -1641.3731 | AC15: 2026-09-11 | AD15: ItD Unrealized PnL | AF15: -1744.6063 | AH15: 2026-09-28 | AI15: OFF BS | AJ15: ItD | AK15: Deal buy | AL15: -144.41234 | AN15: 2026-09-21 | AO15: Face value | AP15: CD | AQ15: 28749.1 | AS15: 2026-09-28 | AT15: YTM binh quan | AU15: Total On BS | AV15: 7.6020316 | AX15: 46289 | AY15: Face_Secured_Unused | AZ15: -800 | BB15: 2026-09-25 | BC15: Est YTM T1 | BD15: 0 | BN15: 46080 | BO15: Trading bonds_FI bond | BP15: NIM | BQ15: -56.599
A16: 2026-09-10 | B16: Trang thai mo | C16: All | E16: 17513 | G16: 2026-09-10 | H16: Trang thai mo | I16: All | K16: 10858.311 | M16: 2026-09-10 | N16: PV01 | P16: -10.602965 | R16: 2026-09-10 | S16: PV01 | U16: -8.43164 | X16: 2026-09-10 | Y16: Unrealized_ItD_MtM_PnL | AA16: -1637.3042 | AC16: 2026-09-10 | AD16: ItD Unrealized PnL | AF16: -1741.5353 | AH16: 2026-09-28 | AI16: OFF BS | AJ16: Face | AK16: Deal sell | AL16: 22526.02 | AN16: 2026-09-18 | AO16: Face value | AP16: FI Bond | AQ16: 12966.21 | AS16: 2026-09-25 | AT16: Face value | AU16: CD On BS | AV16: 18899.1 | AX16: 46289 | AY16: Face_SBV_Overdraft | AZ16: -1459 | BB16: 2026-09-25 | BC16: Est Posi onBS T9 | BD16: 34454.3 | BN16: 46112 | BO16: Trading bonds_Govbond | BP16: NIM | BQ16: -23.324771
A17: 2026-09-09 | B17: Trang thai mo | C17: All | E17: 18513 | G17: 2026-09-09 | H17: Trang thai mo | I17: All | K17: 10858.311 | M17: 2026-09-09 | N17: PV01 | P17: -11.388407 | R17: 2026-09-09 | S17: PV01 | U17: -8.4349222 | X17: 2026-09-09 | Y17: Unrealized_ItD_MtM_PnL | AA17: -1635.319 | AC17: 2026-09-09 | AD17: ItD Unrealized PnL | AF17: -1740.2686 | AH17: 2026-09-28 | AI17: OFF BS | AJ17: ItD | AK17: Deal sell | AL17: -42.462006 | AN17: 2026-09-18 | AO17: Face value | AP17: CD | AQ17: 28749.1 | AS17: 2026-09-25 | AT17: Face value | AU17: FI Bond Listed On BS | AV17: 397.6106 | AX17: 46289 | AY17: Face_HMNR_NAPAS | AZ17: -605 | BB17: 2026-09-25 | BC17: Est Posi onBS T8 | BD17: 0 | BN17: 46112 | BO17: Trading bonds_Govbond | BP17: Realized PnL | BQ17: 3.9186446
A18: 2026-09-08 | B18: Trang thai mo | C18: All | E18: 17513 | G18: 2026-09-08 | H18: Trang thai mo | I18: All | K18: 10858.311 | M18: 2026-09-08 | N18: PV01 | P18: -10.609883 | R18: 2026-09-08 | S18: PV01 | U18: -8.4350591 | X18: 2026-09-08 | Y18: Unrealized_ItD_MtM_PnL | AA18: -1637.0617 | AC18: 2026-09-08 | AD18: ItD Unrealized PnL | AF18: -1742.1945 | AH18: 2026-09-28 | AI18: NGOAI BS | AJ18: Face | AK18: All | AL18: 1847.4 | AN18: 2026-09-17 | AO18: Face value | AP18: FI Bond | AQ18: 12966.096 | AS18: 2026-09-25 | AT18: Face value | AU18: FI Bond Unlisted On BS | AV18: 11000 | AX18: 46289 | AY18: Face_OMO_Available | AZ18: 7692.8209 | BB18: 2026-09-25 | BC18: Est Posi onBS T7 | BD18: 0 | BN18: 46112 | BO18: Trading bonds_FI bond | BP18: NIM | BQ18: -6.892
A19: 2026-09-07 | B19: Trang thai mo | C19: All | E19: 17513 | G19: 2026-09-07 | H19: Trang thai mo | I19: All | K19: 10858.311 | M19: 2026-09-07 | N19: PV01 | P19: -10.612477 | R19: 2026-09-07 | S19: PV01 | U19: -8.4355926 | X19: 2026-09-07 | Y19: Unrealized_ItD_MtM_PnL | AA19: -1637.7748 | AC19: 2026-09-07 | AD19: ItD Unrealized PnL | AF19: -1743.5763 | AH19: 2026-09-28 | AI19: NGOAI BS | AJ19: MtM | AK19: All | AL19: 1705.8913 | AN19: 2026-09-17 | AO19: Face value | AP19: CD | AQ19: 28799.1 | AS19: 2026-09-25 | AT19: Face value | AU19: CD Off BS | AV19: 0 | AX19: 46288 | AY19: Face_HLA | AZ19: 12899.311 | BB19: 2026-09-25 | BC19: Est Posi onBS T6 | BD19: 0 | BN19: 46112 | BO19: Trading bonds_FI bond | BP19: Realized PnL | BQ19: -24.617
A20: 2026-09-04 | B20: Trang thai mo | C20: All | E20: 17513 | G20: 2026-09-04 | H20: Trang thai mo | I20: All | K20: 10858.311 | M20: 2026-09-04 | N20: PV01 | P20: -10.621377 | R20: 2026-09-04 | S20: PV01 | U20: -8.4413599 | X20: 2026-09-04 | Y20: Unrealized_ItD_MtM_PnL | AA20: -1639.6465 | AC20: 2026-09-04 | AD20: ItD Unrealized PnL | AF20: -1744.2174 | AH20: 2026-09-28 | AI20: NGOAI BS | AJ20: PTCK | AK20: All | AL20: -65.268159 | AN20: 2026-09-16 | AO20: Face value | AP20: FI Bond | AQ20: 12965.701 | AS20: 2026-09-25 | AT20: Face value | AU20: FI Bond Listed Off BS | AV20: 0 | AX20: 46288 | AY20: Face_Secured_Unused | AZ20: -800 | BB20: 2026-09-25 | BC20: Est Posi onBS T5 | BD20: 0 | BN20: 46112 | BO20: Banking bonds_Govbond | BP20: NIM | BQ20: -12.727281
A21: 2026-09-03 | B21: Trang thai mo | C21: All | E21: 17513 | G21: 2026-09-03 | H21: Trang thai mo | I21: All | K21: 10858.311 | M21: 2026-09-03 | N21: PV01 | P21: -10.62725 | R21: 2026-09-03 | S21: PV01 | U21: -8.4438313 | X21: 2026-09-03 | Y21: Unrealized_ItD_MtM_PnL | AA21: -1635.9934 | AC21: 2026-09-03 | AD21: ItD Unrealized PnL | AF21: -1743.7375 | AH21: 2026-09-28 | AI21: NGOAI BS | AJ21: Diff | AK21: All | AL21: -76.240517 | AN21: 2026-09-16 | AO21: Face value | AP21: CD | AQ21: 28799.1 | AS21: 2026-09-25 | AT21: Face value | AU21: FI Bond Unlisted Off BS | AV21: 0 | AX21: 46288 | AY21: Face_SBV_Overdraft | AZ21: -1459 | BB21: 2026-09-25 | BC21: Est Posi onBS T4 | BD21: 0 | BN21: 46112 | BO21: Banking bonds_Govbond | BP21: Realized PnL | BQ21: -0.003892796
A22: 2026-08-28 | B22: Trang thai mo | C22: All | E22: 17513 | G22: 2026-08-28 | H22: Trang thai mo | I22: All | K22: 10858.311 | M22: 2026-08-28 | N22: PV01 | P22: -10.64537 | R22: 2026-08-28 | S22: PV01 | U22: -8.4550612 | X22: 2026-08-28 | Y22: Unrealized_ItD_MtM_PnL | AA22: -1640.2643 | AC22: 2026-08-28 | AD22: ItD Unrealized PnL | AF22: -1745.4062 | AH22: 2026-09-28 | AI22: NGOAI BS | AJ22: ItD | AK22: All | AL22: -76.240517 | AN22: 2026-09-15 | AO22: Face value | AP22: FI Bond | AQ22: 12965.081 | AS22: 2026-09-25 | AT22: Face value | AU22: CD Ngoai BS | AV22: 8550 | AX22: 46288 | AY22: Face_HMNR_NAPAS | AZ22: -605 | BB22: 2026-09-25 | BC22: Est Posi onBS T3 | BD22: 0 | BN22: 46141 | BO22: Banking bonds_Govbond | BP22: NIM | BQ22: -10.589189
A23: 2026-08-27 | B23: Trang thai mo | C23: All | E23: 17513 | G23: 2026-08-27 | H23: Trang thai mo | I23: All | K23: 10858.311 | AH23: 2026-09-28 | AI23: NGOAI BS | AJ23: Face | AK23: Deal buy | AL23: 7763.4 | AN23: 2026-09-15 | AO23: Face value | AP23: CD | AQ23: 28799.1 | AS23: 2026-09-25 | AT23: Face value | AU23: FI Bond Listed Ngoai BS | AV23: 0 | AX23: 46288 | AY23: Face_OMO_Available | AZ23: 8042.8209 | BB23: 2026-09-25 | BC23: Est Posi onBS T2 | BD23: 0 | BN23: 46141 | BO23: Trading bonds_FI bond | BP23: Realized PnL | BQ23: -16.905
A24: 2026-08-26 | B24: Trang thai mo | C24: All | E24: 17513 | G24: 2026-08-26 | H24: Trang thai mo | I24: All | K24: 10858.311 | AH24: 2026-09-28 | AI24: NGOAI BS | AJ24: ItD | AK24: Deal buy | AL24: -478.75172 | AN24: 2026-09-14 | AO24: Face value | AP24: FI Bond | AQ24: 12965.496 | AS24: 2026-09-25 | AT24: Face value | AU24: FI Bond Unlisted Ngoai BS | AV24: 0 | AX24: 46287 | AY24: Face_HLA | AZ24: 11846.531 | BB24: 2026-09-25 | BC24: Est Posi onBS T12 | BD24: 28046.7 | BN24: 46141 | BO24: Banking bonds_Govbond | BP24: Realized PnL | BQ24: -0.003892796
A25: 2026-08-25 | B25: Trang thai mo | C25: All | E25: 17513 | G25: 2026-08-25 | H25: Trang thai mo | I25: All | K25: 10858.311 | AH25: 2026-09-28 | AI25: NGOAI BS | AJ25: Face | AK25: Deal sell | AL25: 5916 | AN25: 2026-09-14 | AO25: Face value | AP25: CD | AQ25: 28799.1 | AS25: 2026-09-25 | AT25: YTM binh quan | AU25: FI Bond On BS | AV25: 7.6807069 | AX25: 46287 | AY25: Face_Secured_Unused | AZ25: -800 | BB25: 2026-09-25 | BC25: Est Posi onBS T11 | BD25: 33845.7 | BN25: 46141 | BO25: Trading bonds_Govbond | BP25: Realized PnL | BQ25: 12.845423
A26: 2026-08-24 | B26: Trang thai mo | C26: All | E26: 17513 | G26: 2026-08-24 | H26: Trang thai mo | I26: All | K26: 10858.311 | AH26: 2026-09-28 | AI26: NGOAI BS | AJ26: ItD | AK26: Deal sell | AL26: -402.5112 | AN26: 2026-09-11 | AO26: Face value | AP26: FI Bond | AQ26: 12963.988 | AS26: 2026-09-25 | AT26: YTM binh quan | AU26: CD On BS | AV26: 7.3566433 | AX26: 46287 | AY26: Face_SBV_Overdraft | AZ26: -1459 | BB26: 2026-09-25 | BC26: Est Posi onBS T10 | BD26: 34767.7 | BN26: 46141 | BO26: Trading bonds_Govbond | BP26: NIM | BQ26: -9.994472
A27: 2026-08-21 | B27: Trang thai mo | C27: All | E27: 17513 | G27: 2026-08-21 | H27: Trang thai mo | I27: All | K27: 10858.311 | AH27: 2026-09-28 | AI27: YTM_ON BS | AJ27: Spot | AK27: All | AL27: 4.1229722 | AN27: 2026-09-11 | AO27: Face value | AP27: CD | AQ27: 28799.1 | AS27: 2026-09-25 | AT27: YTM binh quan | AU27: Total On BS | AV27: 7.6020316 | AX27: 46287 | AY27: Face_HMNR_NAPAS | AZ27: -605 | BB27: 2026-09-25 | BC27: Est Posi onBS T1 | BD27: 0 | BN27: 46141 | BO27: Trading bonds_FI bond | BP27: NIM | BQ27: -8.637
A28: 2026-08-20 | B28: Trang thai mo | C28: All | E28: 17513 | G28: 2026-08-20 | H28: Trang thai mo | I28: All | K28: 10858.311 | AH28: 2026-09-25 | AI28: YTM_ON BS | AJ28: Spot | AK28: All | AL28: 4.0940599 | AN28: 2026-09-10 | AO28: Face value | AP28: FI Bond | AQ28: 12963.804 | AS28: 2026-09-24 | AT28: Face value | AU28: CD On BS | AV28: 16599.1 | AX28: 46287 | AY28: Face_OMO_Available | AZ28: 8770.0403 | BN28: 46171 | BO28: Trading bonds_Govbond | BP28: NIM | BQ28: -14.006186
A29: 2026-08-19 | B29: Trang thai mo | C29: All | E29: 17513 | G29: 2026-08-19 | H29: Trang thai mo | I29: All | K29: 10858.311 | AH29: 2026-09-25 | AI29: ON BS | AJ29: Face | AK29: All | AL29: 38020.3 | AN29: 2026-09-10 | AO29: Face value | AP29: CD | AQ29: 27899.1 | AS29: 2026-09-24 | AT29: Face value | AU29: FI Bond Listed On BS | AV29: 397.6106 | AX29: 46286 | AY29: Face_HLA | AZ29: 15607.311 | BN29: 46171 | BO29: Trading bonds_Govbond | BP29: Realized PnL | BQ29: 12.177066
A30: 2026-08-18 | B30: Trang thai mo | C30: All | E30: 17513 | G30: 2026-08-18 | H30: Trang thai mo | I30: All | K30: 10858.311 | AH30: 2026-09-25 | AI30: ON BS | AJ30: MtM | AK30: All | AL30: 38033.784 | AN30: 2026-09-09 | AO30: Face value | AP30: FI Bond | AQ30: 12963.8 | AS30: 2026-09-24 | AT30: Face value | AU30: FI Bond Unlisted On BS | AV30: 11000 | AX30: 46286 | AY30: Face_Secured_Unused | AZ30: -800 | BN30: 46171 | BO30: Trading bonds_FI bond | BP30: NIM | BQ30: -31.377
A31: 2026-08-17 | B31: Trang thai mo | C31: All | E31: 17513 | G31: 2026-08-17 | H31: Trang thai mo | I31: All | K31: 10858.311 | AH31: 2026-09-25 | AI31: ON BS | AJ31: PTCK | AK31: All | AL31: 1658.4947 | AN31: 2026-09-09 | AO31: Face value | AP31: CD | AQ31: 27899.1 | AS31: 2026-09-24 | AT31: Face value | AU31: CD Off BS | AV31: 0 | AX31: 46286 | AY31: Face_SBV_Overdraft | AZ31: -1459 | BN31: 46171 | BO31: Trading bonds_FI bond | BP31: Realized PnL | BQ31: 5.733
A32: 2026-08-14 | B32: Trang thai mo | C32: All | E32: 17513 | G32: 2026-08-14 | H32: Trang thai mo | I32: All | K32: 10858.311 | AH32: 2026-09-25 | AI32: ON BS | AJ32: Diff | AK32: All | AL32: -1645.011 | AN32: 2026-09-08 | AO32: Face value | AP32: FI Bond | AQ32: 12965.259 | AS32: 2026-09-24 | AT32: Face value | AU32: FI Bond Listed Off BS | AV32: 0 | AX32: 46286 | AY32: Face_HMNR_NAPAS | AZ32: -605 | BN32: 46171 | BO32: Banking bonds_Govbond | BP32: NIM | BQ32: -12.61037
A33: 2026-08-13 | B33: Trang thai mo | C33: All | E33: 17513 | G33: 2026-08-13 | H33: Trang thai mo | I33: All | K33: 10858.311 | AH33: 2026-09-25 | AI33: ON BS | AJ33: ItD | AK33: All | AL33: -1614.1155 | AN33: 2026-09-08 | AO33: Face value | AP33: CD | AQ33: 28199.1 | AS33: 2026-09-24 | AT33: Face value | AU33: FI Bond Unlisted Off BS | AV33: 0 | AX33: 46286 | AY33: Face_OMO_Available | AZ33: 7952.8209 | BN33: 46171 | BO33: Banking bonds_Govbond | BP33: Realized PnL | BQ33: -0.003892796
A34: 2026-08-12 | B34: Trang thai mo | C34: All | E34: 17513 | G34: 2026-08-12 | H34: Trang thai mo | I34: All | K34: 10858.311 | AH34: 2026-09-25 | AI34: OFF BS | AJ34: Face | AK34: All | AL34: -24864.7 | AN34: 2026-09-07 | AO34: Face value | AP34: FI Bond | AQ34: 12966.251 | AS34: 2026-09-24 | AT34: Face value | AU34: CD Ngoai BS | AV34: 10850 | AX34: 46285 | AY34: Face_HLA | AZ34: 14261.311 | BN34: 46203 | BO34: Banking bonds_Govbond | BP34: Realized PnL | BQ34: -0.003892796
A35: 2026-08-11 | B35: Trang thai mo | C35: All | E35: 17513 | G35: 2026-08-11 | H35: Trang thai mo | I35: All | K35: 10858.311 | AH35: 2026-09-25 | AI35: OFF BS | AJ35: MtM | AK35: All | AL35: -26045.627 | AN35: 2026-09-07 | AO35: Face value | AP35: CD | AQ35: 27199.1 | AS35: 2026-09-24 | AT35: Face value | AU35: FI Bond Listed Ngoai BS | AV35: 0 | AX35: 46285 | AY35: Face_Secured_Unused | AZ35: -800 | BN35: 46203 | BO35: Trading bonds_FI bond | BP35: Realized PnL | BQ35: -5.246
A36: 2026-08-10 | B36: Trang thai mo | C36: All | E36: 17513 | G36: 2026-08-10 | H36: Trang thai mo | I36: All | K36: 10858.311 | AH36: 2026-09-25 | AI36: OFF BS | AJ36: PTCK | AK36: All | AL36: -1449.1643 | AN36: 2026-09-04 | AO36: Face value | AP36: FI Bond | AQ36: 12967.292 | AS36: 2026-09-24 | AT36: Face value | AU36: FI Bond Unlisted Ngoai BS | AV36: 0 | AX36: 46285 | AY36: Face_SBV_Overdraft | AZ36: -1459 | BN36: 46203 | BO36: Banking bonds_Govbond | BP36: NIM | BQ36: -11.352707
A37: 2026-08-07 | B37: Trang thai mo | C37: All | E37: 16370 | G37: 2026-08-07 | H37: Trang thai mo | I37: All | K37: 12001.311 | AH37: 2026-09-25 | AI37: OFF BS | AJ37: Diff | AK37: All | AL37: 268.23706 | AN37: 2026-09-04 | AO37: Face value | AP37: CD | AQ37: 27199.1 | AS37: 2026-09-24 | AT37: YTM binh quan | AU37: FI Bond On BS | AV37: 7.6808236 | AX37: 46285 | AY37: Face_HMNR_NAPAS | AZ37: -803 | BN37: 46203 | BO37: Trading bonds_Govbond | BP37: Realized PnL | BQ37: 17.012411
A38: 2026-08-06 | B38: Trang thai mo | C38: All | E38: 16370 | G38: 2026-08-06 | H38: Trang thai mo | I38: All | K38: 12001.311 | AH38: 2026-09-25 | AI38: OFF BS | AJ38: ItD | AK38: All | AL38: 268.23706 | AN38: 2026-09-03 | AO38: Face value | AP38: FI Bond | AQ38: 12967.996 | AS38: 2026-09-24 | AT38: YTM binh quan | AU38: CD On BS | AV38: 7.2133672 | AX38: 46285 | AY38: Face_OMO_Available | AZ38: 7254.8209 | BN38: 46203 | BO38: Trading bonds_Govbond | BP38: NIM | BQ38: -23.518877
A39: 2026-08-05 | B39: Trang thai mo | C39: All | E39: 16370 | G39: 2026-08-05 | H39: Trang thai mo | I39: All | K39: 12001.311 | AH39: 2026-09-25 | AI39: OFF BS | AJ39: Face | AK39: Deal buy | AL39: 500 | AN39: 2026-09-03 | AO39: Face value | AP39: CD | AQ39: 27199.1 | AS39: 2026-09-24 | AT39: YTM binh quan | AU39: Total On BS | AV39: 7.5349143 | AX39: 46282 | AY39: Face_HLA | AZ39: 10666.447 | BN39: 46203 | BO39: Trading bonds_FI bond | BP39: NIM | BQ39: -37.67
... A51: 2026-07-20 | B51: Trang thai mo | C51: All | E51: 11412 | G51: 2026-07-20 | H51: Trang thai mo | I51: All | K51: 16959.311 | AH51: 2026-09-25 | AI51: NGOAI BS | AJ51: ItD | AK51: Deal sell | AL51: -403.0263 | AN51: 2026-08-21 | AO51: Face value | AP51: CD | AQ51: 26949.1 | AS51: 2026-09-23 | AT51: YTM binh quan | AU51: Total On BS | AV51: 7.4414365 | AX51: 46280 | AY51: Face_SBV_Overdraft | AZ51: -1459 | BN51: 46262 | BO51: Banking bonds_Govbond | BP51: Realized PnL | BQ51: -0.003892796
A52: 2026-07-17 | B52: Trang thai mo | C52: All | E52: 11412 | G52: 2026-07-17 | H52: Trang thai mo | I52: All | K52: 16959.311 | AH52: 2026-09-24 | AI52: ON BS | AJ52: Face | AK52: All | AL52: 35910.3 | AN52: 2026-08-20 | AO52: Face value | AP52: FI Bond | AQ52: 10768.385 | AS52: 2026-09-22 | AT52: Face value | AU52: CD On BS | AV52: 14399.1 | AX52: 46280 | AY52: Face_HMNR_NAPAS | AZ52: -803
A53: 2026-07-16 | B53: Trang thai mo | C53: All | E53: 11412 | G53: 2026-07-16 | H53: Trang thai mo | I53: All | K53: 16959.311 | AH53: 2026-09-24 | AI53: ON BS | AJ53: MtM | AK53: All | AL53: 36110.781 | AN53: 2026-08-20 | AO53: Face value | AP53: CD | AQ53: 28449.1 | AS53: 2026-09-22 | AT53: Face value | AU53: FI Bond Listed On BS | AV53: 397.6106 | AX53: 46280 | AY53: Face_OMO_Available | AZ53: 6909.6335
A54: 2026-07-15 | B54: Trang thai mo | C54: All | E54: 11412 | G54: 2026-07-15 | H54: Trang thai mo | I54: All | K54: 16959.311 | AH54: 2026-09-24 | AI54: ON BS | AJ54: PTCK | AK54: All | AL54: 1673.7939 | AN54: 2026-08-19 | AO54: Face value | AP54: FI Bond | AQ54: 10769.74 | AS54: 2026-09-22 | AT54: Face value | AU54: FI Bond Unlisted On BS | AV54: 12000 | AX54: 46279 | AY54: Face_HLA | AZ54: 10355.613
A55: 2026-07-14 | B55: Trang thai mo | C55: All | E55: 11412 | G55: 2026-07-14 | H55: Trang thai mo | I55: All | K55: 16959.311 | AH55: 2026-09-24 | AI55: ON BS | AJ55: Diff | AK55: All | AL55: -1473.3126 | AN55: 2026-08-19 | AO55: Face value | AP55: CD | AQ55: 29449.1 | AS55: 2026-09-22 | AT55: Face value | AU55: CD Off BS | AV55: 0 | AX55: 46279 | AY55: Face_Secured_Unused | AZ55: -800
A56: 2026-07-13 | B56: Trang thai mo | C56: All | E56: 11412 | G56: 2026-07-13 | H56: Trang thai mo | I56: All | K56: 16959.311 | AH56: 2026-09-24 | AI56: ON BS | AJ56: ItD | AK56: All | AL56: -1442.4111 | AN56: 2026-08-18 | AO56: Face value | AP56: FI Bond | AQ56: 10769.827 | AS56: 2026-09-22 | AT56: Face value | AU56: FI Bond Listed Off BS | AV56: 0 | AX56: 46279 | AY56: Face_SBV_Overdraft | AZ56: -1459
A57: 2026-07-10 | B57: Trang thai mo | C57: All | E57: 11412 | G57: 2026-07-10 | H57: Trang thai mo | I57: All | K57: 16959.311 | AH57: 2026-09-24 | AI57: OFF BS | AJ57: Face | AK57: All | AL57: -18194.7 | AN57: 2026-08-18 | AO57: Face value | AP57: CD | AQ57: 29449.1 | AS57: 2026-09-22 | AT57: Face value | AU57: FI Bond Unlisted Off BS | AV57: 0 | AX57: 46279 | AY57: Face_HMNR_NAPAS | AZ57: -803
A58: 2026-07-09 | B58: Trang thai mo | C58: All | E58: 11412 | G58: 2026-07-09 | H58: Trang thai mo | I58: All | K58: 16959.311 | AH58: 2026-09-24 | AI58: OFF BS | AJ58: MtM | AK58: All | AL58: -19795.247 | AN58: 2026-08-17 | AO58: Face value | AP58: FI Bond | AQ58: 10770.409 | AS58: 2026-09-22 | AT58: Face value | AU58: CD Ngoai BS | AV58: 14350 | AX58: 46279 | AY58: Face_OMO_Available | AZ58: 6676.1225
A59: 2026-07-08 | B59: Trang thai mo | C59: All | E59: 11412 | G59: 2026-07-08 | H59: Trang thai mo | I59: All | K59: 16959.311 | AH59: 2026-09-24 | AI59: OFF BS | AJ59: PTCK | AK59: All | AL59: -1517.6289 | AN59: 2026-08-17 | AO59: Face value | AP59: CD | AQ59: 28950 | AS59: 2026-09-22 | AT59: Face value | AU59: FI Bond Listed Ngoai BS | AV59: 0 | AX59: 46278 | AY59: Face_HLA | AZ59: 11405.613
A60: 2026-07-07 | B60: Trang thai mo | C60: All | E60: 11412 | G60: 2026-07-07 | H60: Trang thai mo | I60: All | K60: 16959.311 | AH60: 2026-09-24 | AI60: OFF BS | AJ60: Diff | AK60: All | AL60: -82.918442 | AN60: 2026-08-14 | AO60: Face value | AP60: FI Bond | AQ60: 10768.799 | AS60: 2026-09-22 | AT60: Face value | AU60: FI Bond Unlisted Ngoai BS | AV60: 0 | AX60: 46278 | AY60: Face_Secured_Unused | AZ60: -800
A61: 2026-07-06 | B61: Trang thai mo | C61: All | E61: 11412 | G61: 2026-07-06 | H61: Trang thai mo | I61: All | K61: 16959.311 | AH61: 2026-09-24 | AI61: OFF BS | AJ61: ItD | AK61: All | AL61: -82.918442 | AN61: 2026-08-14 | AO61: Face value | AP61: CD | AQ61: 28050 | AS61: 2026-09-22 | AT61: YTM binh quan | AU61: FI Bond On BS | AV61: 7.6540452 | AX61: 46278 | AY61: Face_SBV_Overdraft | AZ61: -1459
A62: 2026-07-03 | B62: Trang thai mo | C62: All | E62: 11412 | G62: 2026-07-03 | H62: Trang thai mo | I62: All | K62: 16959.311 | AH62: 2026-09-24 | AI62: OFF BS | AJ62: Face | AK62: Deal buy | AL62: 2310 | AN62: 2026-08-13 | AO62: Face value | AP62: FI Bond | AQ62: 10767.415 | AS62: 2026-09-22 | AT62: YTM binh quan | AU62: CD On BS | AV62: 6.807317 | AX62: 46278 | AY62: Face_HMNR_NAPAS | AZ62: -803
A63: 2026-07-02 | B63: Trang thai mo | C63: All | E63: 11412 | G63: 2026-07-02 | H63: Trang thai mo | I63: All | K63: 16959.311 | AH63: 2026-09-24 | AI63: OFF BS | AJ63: ItD | AK63: Deal buy | AL63: -178.76949 | AN63: 2026-08-13 | AO63: Face value | AP63: CD | AQ63: 26650 | AS63: 2026-09-22 | AT63: YTM binh quan | AU63: Total On BS | AV63: 7.3295385 | AX63: 46278 | AY63: Face_OMO_Available | AZ63: 6676.1225
... A103: 2026-05-07 | B103: Trang thai mo | C103: All | E103: 6512 | G103: 2026-05-07 | H103: Trang thai mo | I103: All | K103: 16959.311 | AH103: 2026-09-22 | AI103: ON BS | AJ103: PTCK | AK103: All | AL103: 1693.6078 | AN103: 2026-07-16 | AO103: Face value | AP103: CD | AQ103: 28650 | AS103: 2026-09-16 | AT103: Face value | AU103: CD Off BS | AV103: 0 | AX103: 46265 | AY103: Face_OMO_Available | AZ103: 7020.0458
A104: 2026-05-06 | B104: Trang thai mo | C104: All | E104: 6612 | G104: 2026-05-06 | H104: Trang thai mo | I104: All | K104: 16959.311 | AH104: 2026-09-22 | AI104: ON BS | AJ104: Diff | AK104: All | AL104: -1422.4543 | AN104: 2026-07-15 | AO104: Face value | AP104: FI Bond | AQ104: 11388.899 | AS104: 2026-09-16 | AT104: Face value | AU104: FI Bond Listed Off BS | AV104: 0
A105: 2026-05-05 | B105: Trang thai mo | C105: All | E105: 6612 | G105: 2026-05-05 | H105: Trang thai mo | I105: All | K105: 16959.311 | AH105: 2026-09-22 | AI105: ON BS | AJ105: ItD | AK105: All | AL105: -1422.4543 | AN105: 2026-07-15 | AO105: Face value | AP105: CD | AQ105: 28650 | AS105: 2026-09-16 | AT105: Face value | AU105: FI Bond Unlisted Off BS | AV105: 0
A106: 2026-05-04 | B106: Trang thai mo | C106: All | E106: 6462 | G106: 2026-05-04 | H106: Trang thai mo | I106: All | K106: 16959.311 | AH106: 2026-09-22 | AI106: OFF BS | AJ106: Face | AK106: All | AL106: -18924.7 | AN106: 2026-07-14 | AO106: Face value | AP106: FI Bond | AQ106: 11388.923 | AS106: 2026-09-16 | AT106: Face value | AU106: CD Ngoai BS | AV106: 11250
A107: 2026-04-29 | B107: Trang thai mo | C107: All | E107: 6462 | G107: 2026-04-29 | H107: Trang thai mo | I107: All | K107: 16959.311 | AH107: 2026-09-22 | AI107: OFF BS | AJ107: MtM | AK107: All | AL107: -20445.473 | AN107: 2026-07-14 | AO107: Face value | AP107: CD | AQ107: 28650 | AS107: 2026-09-16 | AT107: Face value | AU107: FI Bond Listed Ngoai BS | AV107: 0
A108: 2026-04-28 | B108: Trang thai mo | C108: All | E108: 6412 | G108: 2026-04-28 | H108: Trang thai mo | I108: All | K108: 16959.311 | AH108: 2026-09-22 | AI108: OFF BS | AJ108: PTCK | AK108: All | AL108: -1500.291 | AN108: 2026-07-13 | AO108: Face value | AP108: FI Bond | AQ108: 11388.919 | AS108: 2026-09-16 | AT108: Face value | AU108: FI Bond Unlisted Ngoai BS | AV108: 0
A109: 2026-04-24 | B109: Trang thai mo | C109: All | E109: 6412 | G109: 2026-04-24 | H109: Trang thai mo | I109: All | K109: 16959.311 | AH109: 2026-09-22 | AI109: OFF BS | AJ109: Diff | AK109: All | AL109: -20.481782 | AN109: 2026-07-13 | AO109: Face value | AP109: CD | AQ109: 28650 | AS109: 2026-09-16 | AT109: YTM binh quan | AU109: FI Bond On BS | AV109: 7.6544979
A110: 2026-04-23 | B110: Trang thai mo | C110: All | E110: 6412 | G110: 2026-04-23 | H110: Trang thai mo | I110: All | K110: 16959.311 | AH110: 2026-09-22 | AI110: OFF BS | AJ110: ItD | AK110: All | AL110: -20.481782 | AN110: 2026-07-10 | AO110: Face value | AP110: FI Bond | AQ110: 11197.611 | AS110: 2026-09-16 | AT110: YTM binh quan | AU110: CD On BS | AV110: 6.8640687
A111: 2026-04-22 | B111: Trang thai mo | C111: All | E111: 6191 | G111: 2026-04-22 | H111: Trang thai mo | I111: All | K111: 16959.311 | AH111: 2026-09-22 | AI111: OFF BS | AJ111: Face | AK111: Deal buy | AL111: 1380 | AN111: 2026-07-10 | AO111: Face value | AP111: CD | AQ111: 28650 | AS111: 2026-09-16 | AT111: YTM binh quan | AU111: Total On BS | AV111: 7.31718
A112: 2026-04-21 | B112: Trang thai mo | C112: All | E112: 6141 | G112: 2026-04-21 | H112: Trang thai mo | I112: All | K112: 16959.311 | AH112: 2026-09-22 | AI112: OFF BS | AJ112: ItD | AK112: Deal buy | AL112: -110.68158 | AN112: 2026-07-09 | AO112: Face value | AP112: FI Bond | AQ112: 11197.611 | AS112: 2026-09-15 | AT112: Face value | AU112: CD On BS | AV112: 18849.1
A113: 2026-04-20 | B113: Trang thai mo | C113: All | E113: 6091 | G113: 2026-04-20 | H113: Trang thai mo | I113: All | K113: 16959.311 | AH113: 2026-09-22 | AI113: OFF BS | AJ113: Face | AK113: Deal sell | AL113: 20304.7 | AN113: 2026-07-09 | AO113: Face value | AP113: CD | AQ113: 28650 | AS113: 2026-09-15 | AT113: Face value | AU113: FI Bond Listed On BS | AV113: 397.6106
A114: 2026-04-17 | B114: Trang thai mo | C114: All | E114: 6241 | G114: 2026-04-17 | H114: Trang thai mo | I114: All | K114: 16959.311 | AH114: 2026-09-22 | AI114: OFF BS | AJ114: ItD | AK114: Deal sell | AL114: -90.199794 | AN114: 2026-07-08 | AO114: Face value | AP114: FI Bond | AQ114: 11197.611 | AS114: 2026-09-15 | AT114: Face value | AU114: FI Bond Unlisted On BS | AV114: 12000
A115: 2026-04-16 | B115: Trang thai mo | C115: All | E115: 6241 | G115: 2026-04-16 | H115: Trang thai mo | I115: All | K115: 16959.311 | AH115: 2026-09-22 | AI115: NGOAI BS | AJ115: Face | AK115: All | AL115: 3477.4 | AN115: 2026-07-08 | AO115: Face value | AP115: CD | AQ115: 28650 | AS115: 2026-09-15 | AT115: Face value | AU115: CD Off BS | AV115: 0
... A433: 2024-12-31 | B433: Trang thai mo | C433: All | E433: 17220 | G433: 2024-12-31 | H433: Trang thai mo | I433: All | K433: 11551.311 | AH433: 2026-09-03 | AI433: NGOAI BS | AJ433: Face | AK433: Deal sell | AL433: 2173.4 | AN433: 2025-11-13 | AO433: Face value | AP433: CD | AQ433: 24586.783 | AS433: 2026-08-05 | AT433: YTM binh quan | AU433: FI Bond On BS | AV433: 7.3870661
AH434: 2026-09-03 | AI434: NGOAI BS | AJ434: ItD | AK434: Deal sell | AL434: -96.180412 | AN434: 2025-11-12 | AO434: Face value | AP434: FI Bond | AQ434: 11397.611 | AS434: 2026-08-05 | AT434: YTM binh quan | AU434: CD On BS | AV434: 6.124166
AH435: 2026-09-03 | AI435: YTM_ON BS | AJ435: Spot | AK435: All | AL435: 4.0191262 | AN435: 2025-11-12 | AO435: Face value | AP435: CD | AQ435: 25486.783 | AS435: 2026-08-05 | AT435: YTM binh quan | AU435: Total On BS | AV435: 6.6958372
AH436: 2026-08-28 | AI436: ON BS | AJ436: Face | AK436: All | AL436: 39207.7 | AN436: 2025-11-11 | AO436: Face value | AP436: FI Bond | AQ436: 11397.611 | AS436: 2026-08-04 | AT436: Face value | AU436: CD On BS | AV436: 15315
AH437: 2026-08-28 | AI437: ON BS | AJ437: MtM | AK437: All | AL437: 39870.634 | AN437: 2025-11-11 | AO437: Face value | AP437: CD | AQ437: 18336.783 | AS437: 2026-08-04 | AT437: Face value | AU437: FI Bond Listed On BS | AV437: 397.6106
AH438: 2026-08-28 | AI438: ON BS | AJ438: PTCK | AK438: All | AL438: 2395.6394 | AN438: 2025-11-10 | AO438: Face value | AP438: FI Bond | AQ438: 11397.611 | AS438: 2026-08-04 | AT438: Face value | AU438: FI Bond Unlisted On BS | AV438: 11800
AH439: 2026-08-28 | AI439: ON BS | AJ439: Diff | AK439: All | AL439: -1732.7055 | AN439: 2025-11-10 | AO439: Face value | AP439: CD | AQ439: 19336.783 | AS439: 2026-08-04 | AT439: Face value | AU439: CD Off BS | AV439: 0
AH440: 2026-08-28 | AI440: ON BS | AJ440: ItD | AK440: All | AL440: -1732.7055 | AN440: 2025-11-07 | AO440: Face value | AP440: FI Bond | AQ440: 11397.611 | AS440: 2026-08-04 | AT440: Face value | AU440: FI Bond Listed Off BS | AV440: 0
AH441: 2026-08-28 | AI441: OFF BS | AJ441: Face | AK441: All | AL441: -23510.7 | AN441: 2025-11-07 | AO441: Face value | AP441: CD | AQ441: 21536.783 | AS441: 2026-08-04 | AT441: Face value | AU441: FI Bond Unlisted Off BS | AV441: 0
AH442: 2026-08-28 | AI442: OFF BS | AJ442: MtM | AK442: All | AL442: -25559.058 | AN442: 2025-11-06 | AO442: Face value | AP442: FI Bond | AQ442: 11397.611 | AS442: 2026-08-04 | AT442: Face value | AU442: CD Ngoai BS | AV442: 10935
AH443: 2026-08-28 | AI443: OFF BS | AJ443: PTCK | AK443: All | AL443: -2199.4167 | AN443: 2025-11-06 | AO443: Face value | AP443: CD | AQ443: 20741.454 | AS443: 2026-08-04 | AT443: Face value | AU443: FI Bond Listed Ngoai BS | AV443: 0
AH444: 2026-08-28 | AI444: OFF BS | AJ444: Diff | AK444: All | AL444: 151.05904 | AN444: 2025-11-05 | AO444: Face value | AP444: FI Bond | AQ444: 11397.611 | AS444: 2026-08-04 | AT444: Face value | AU444: FI Bond Unlisted Ngoai BS | AV444: 0
AH445: 2026-08-28 | AI445: OFF BS | AJ445: ItD | AK445: All | AL445: 151.05904 | AN445: 2025-11-05 | AO445: Face value | AP445: CD | AQ445: 21341.454 | AS445: 2026-08-04 | AT445: YTM binh quan | AU445: FI Bond On BS | AV445: 7.3870661
... AH755: 2026-08-11 | AI755: OFF BS | AJ755: MtM | AK755: All | AL755: -24365.68 | AN755: 2025-03-21 | AO755: Face value | AP755: CD | AQ755: 24796.384 | AS755: 2026-06-29 | AT755: Face value | AU755: FI Bond Listed Ngoai BS | AV755: 0
AH756: 2026-08-11 | AI756: OFF BS | AJ756: PTCK | AK756: All | AL756: -1903.6823 | AS756: 2026-06-29 | AT756: Face value | AU756: FI Bond Unlisted Ngoai BS | AV756: 0
AH757: 2026-08-11 | AI757: OFF BS | AJ757: Diff | AK757: All | AL757: 193.70229 | AS757: 2026-06-29 | AT757: YTM binh quan | AU757: FI Bond On BS | AV757: 7.2437978
AH758: 2026-08-11 | AI758: OFF BS | AJ758: ItD | AK758: All | AL758: 131.61486 | AS758: 2026-06-29 | AT758: YTM binh quan | AU758: CD On BS | AV758: 5.014925
AH759: 2026-08-11 | AI759: OFF BS | AJ759: Face | AK759: Deal buy | AL759: 230 | AS759: 2026-06-29 | AT759: YTM binh quan | AU759: Total On BS | AV759: 5.8320338
AH760: 2026-08-11 | AI760: OFF BS | AJ760: ItD | AK760: Deal buy | AL760: -4.4471288 | AS760: 2026-06-26 | AT760: Face value | AU760: CD On BS | AV760: 18123
AH761: 2026-08-11 | AI761: OFF BS | AJ761: Face | AK761: Deal sell | AL761: 22885.7 | AS761: 2026-06-26 | AT761: Face value | AU761: FI Bond Listed On BS | AV761: 397.6106
AH762: 2026-08-11 | AI762: OFF BS | AJ762: ItD | AK762: Deal sell | AL762: -136.06199 | AS762: 2026-06-26 | AT762: Face value | AU762: FI Bond Unlisted On BS | AV762: 13800
AH763: 2026-08-11 | AI763: NGOAI BS | AJ763: Face | AK763: All | AL763: -500 | AS763: 2026-06-26 | AT763: Face value | AU763: CD Off BS | AV763: 0
AH764: 2026-08-11 | AI764: NGOAI BS | AJ764: MtM | AK764: All | AL764: -1118.9026 | AS764: 2026-06-26 | AT764: Face value | AU764: FI Bond Listed Off BS | AV764: 0
AH765: 2026-08-11 | AI765: NGOAI BS | AJ765: PTCK | AK765: All | AL765: -823.78698 | AS765: 2026-06-26 | AT765: Face value | AU765: FI Bond Unlisted Off BS | AV765: 0
AH766: 2026-08-11 | AI766: NGOAI BS | AJ766: Diff | AK766: All | AL766: 204.88438 | AS766: 2026-06-26 | AT766: Face value | AU766: CD Ngoai BS | AV766: 8077
AH767: 2026-08-11 | AI767: NGOAI BS | AJ767: ItD | AK767: All | AL767: 15.169486 | AS767: 2026-06-26 | AT767: Face value | AU767: FI Bond Listed Ngoai BS | AV767: 0
... AH3484: 2026-02-26 | AI3484: ON BS | AJ3484: ItD | AK3484: All | AL3484: -995.80006 | AS3484: 2025-04-08 | AT3484: Face value | AU3484: CD Off BS | AV3484: 12320
AH3485: 2026-02-26 | AI3485: OFF BS | AJ3485: Face | AK3485: All | AL3485: -7232.5 | AM3485: =AL7+AL12+AL23 -> 6197.9491 | AS3485: 2025-04-08 | AT3485: Face value | AU3485: FI Bond Listed Off BS | AV3485: 300
AH3486: 2026-02-26 | AI3486: OFF BS | AJ3486: MtM | AK3486: All | AL3486: -9005.7969 | AS3486: 2025-04-08 | AT3486: Face value | AU3486: FI Bond Unlisted Off BS | AV3486: 0
AH3487: 2026-02-26 | AI3487: OFF BS | AJ3487: PTCK | AK3487: All | AL3487: -168.6346 | AS3487: 2025-04-04 | AT3487: Face value | AU3487: CD On BS | AV3487: 12976.384
AH3488: 2026-02-26 | AI3488: OFF BS | AJ3488: Diff | AK3488: All | AL3488: -1604.6623 | AS3488: 2025-04-04 | AT3488: Face value | AU3488: FI Bond Listed On BS | AV3488: 7100
AH3489: 2026-02-26 | AI3489: OFF BS | AJ3489: ItD | AK3489: All | AL3489: 153.34951 | AS3489: 2025-04-04 | AT3489: Face value | AU3489: FI Bond Unlisted On BS | AV3489: 1397.6106
AH3490: 2026-02-26 | AI3490: OFF BS | AJ3490: Face | AK3490: Deal buy | AL3490: 1423 | AS3490: 2025-04-04 | AT3490: Face value | AU3490: CD Off BS | AV3490: 11820
AH3491: 2026-02-26 | AI3491: OFF BS | AJ3491: ItD | AK3491: Deal buy | AL3491: -44.9468 | AS3491: 2025-04-04 | AT3491: Face value | AU3491: FI Bond Listed Off BS | AV3491: 300
AH3492: 2026-02-26 | AI3492: OFF BS | AJ3492: Face | AK3492: Deal sell | AL3492: 8655.5 | AS3492: 2025-04-04 | AT3492: Face value | AU3492: FI Bond Unlisted Off BS | AV3492: 0
AH3493: 2026-02-26 | AI3493: OFF BS | AJ3493: ItD | AK3493: Deal sell | AL3493: -198.29631 | AS3493: 2025-04-03 | AT3493: Face value | AU3493: CD On BS | AV3493: 13976.384
...

Sheet NIM
A1: Chỉ tiêu | B1: 46052 | C1: 46080 | D1: 46112 | E1: 46141 | F1: 46171 | G1: 46203 | H1: 46234 | I1: 46262 | J1: 46295 | K1: 46326 | L1: 46356 | M1: 46387 | N1: Estimate NII 2026
A2: I.Trạng thái rủi ro thị trường
A3: Trading book GBond | B3: =SUMIFS(BOND!$E:$E,BOND!$A:$A,B1) -> 8062 | C3: =SUMIFS(BOND!$E:$E,BOND!$A:$A,C1) -> 7802 | D3: =SUMIFS(BOND!$E:$E,BOND!$A:$A,D1) -> 6141 | E3: =SUMIFS(BOND!$E:$E,BOND!$A:$A,E1) -> 6462 | F3: =SUMIFS(BOND!$E:$E,BOND!$A:$A,F1) -> 6162 | G3: =SUMIFS(BOND!$E:$E,BOND!$A:$A,G1) -> 11412 | H3: =SUMIFS(BOND!$E:$E,BOND!$A:$A,H1) -> 16370 | I3: =SUMIFS(BOND!$E:$E,BOND!$A:$A,I1) -> 17513 | J3: =SUMIFS(BOND!$E:$E,BOND!$A:$A,RPT) -> 17513 | K3: =J3 -> 17513 | L3: =K3 -> 17513 | M3: =L3 -> 17513
A4: Banking book GBond | B4: =SUMIFS(BOND!$K:$K,BOND!$G:$G,B1) -> 16959.311 | C4: =SUMIFS(BOND!$K:$K,BOND!$G:$G,C1) -> 16959.311 | D4: =SUMIFS(BOND!$K:$K,BOND!$G:$G,D1) -> 16959.311 | E4: =SUMIFS(BOND!$K:$K,BOND!$G:$G,E1) -> 16959.311 | F4: =SUMIFS(BOND!$K:$K,BOND!$G:$G,F1) -> 16959.311 | G4: =SUMIFS(BOND!$K:$K,BOND!$G:$G,G1) -> 16959.311 | H4: =SUMIFS(BOND!$K:$K,BOND!$G:$G,H1) -> 12001.311 | I4: =SUMIFS(BOND!$K:$K,BOND!$G:$G,I1) -> 10858.311 | J4: =I4 -> 10858.311 | K4: =J4 -> 10858.311 | L4: =K4-300 -> 10558.311 | M4: =L4 -> 10558.311 | P4: chưa có cth, tháng 11 đáo hạn 300 tỷ
A5: FI bond | B5: =SUMIFS(BOND!$AQ:$AQ,BOND!$AN:$AN,B1) -> 34458.682 | C5: =SUMIFS(BOND!$AQ:$AQ,BOND!$AN:$AN,C1) -> 38969.947 | D5: =SUMIFS(BOND!$AQ:$AQ,BOND!$AN:$AN,D1) -> 27119.74 | E5: =SUMIFS(BOND!$AQ:$AQ,BOND!$AN:$AN,E1) -> 30669.469 | F5: =SUMIFS(BOND!$AQ:$AQ,BOND!$AN:$AN,F1) -> 35474.47 | G5: =SUMIFS(BOND!$AQ:$AQ,BOND!$AN:$AN,G1) -> 39497.611 | H5: =SUMIFS(BOND!$AQ:$AQ,BOND!$AN:$AN,H1) -> 39522.262 | I5: =SUMIFS(BOND!$AQ:$AQ,BOND!$AN:$AN,I1) -> 40166.528 | J5: =SUMIFS(BOND!$AQ:$AQ,BOND!$AN:$AN,RPT) -> 39414.405 | K5: =J5 -> 39414.405 | L5: =K5 -> 39414.405 | M5: =L5 -> 39414.405
A6: II.Trạng thái rủi ro IRRBB
A7: Trading book Gbond | B7: =SUMIFS(BOND!$AL:$AL,BOND!$AH:$AH,NIM!B1,BOND!$AI:$AI,"ON BS",BOND!$AJ:$AJ,"Face") -> 26803.3 | C7: =SUMIFS(BOND!$AL:$AL,BOND!$AH:$AH,NIM!C1,BOND!$AI:$AI,"ON BS",BOND!$AJ:$AJ,"Face") -> 30279 | D7: =SUMIFS(BOND!$AL:$AL,BOND!$AH:$AH,NIM!D1,BOND!$AI:$AI,"ON BS",BOND!$AJ:$AJ,"Face") -> 31928.3 | E7: =SUMIFS(BOND!$AL:$AL,BOND!$AH:$AH,NIM!E1,BOND!$AI:$AI,"ON BS",BOND!$AJ:$AJ,"Face") -> 35981.7 | F7: =SUMIFS(BOND!$AL:$AL,BOND!$AH:$AH,NIM!F1,BOND!$AI:$AI,"ON BS",BOND!$AJ:$AJ,"Face") -> 34368.7 | G7: =SUMIFS(BOND!$AL:$AL,BOND!$AH:$AH,NIM!G1,BOND!$AI:$AI,"ON BS",BOND!$AJ:$AJ,"Face") -> 36404.7 | H7: =SUMIFS(BOND!$AL:$AL,BOND!$AH:$AH,NIM!H1,BOND!$AI:$AI,"ON BS",BOND!$AJ:$AJ,"Face") -> 41024.2 | I7: =SUMIFS(BOND!$AL:$AL,BOND!$AH:$AH,NIM!I1,BOND!$AI:$AI,"ON BS",BOND!$AJ:$AJ,"Face") -> 39207.7 | J7: =_xlfn.XLOOKUP(J22,BOND!$BC:$BC,BOND!$BD:$BD,,0) -> 34454.3 | K7: =_xlfn.XLOOKUP(K22,BOND!$BC:$BC,BOND!$BD:$BD,,0) -> 34767.7 | L7: =_xlfn.XLOOKUP(L22,BOND!$BC:$BC,BOND!$BD:$BD,,0) -> 33845.7 | M7: =_xlfn.XLOOKUP(M22,BOND!$BC:$BC,BOND!$BD:$BD,,0) -> 28046.7
A8: Lợi suất bình quân | B8: 0.036272434 | C8: 0.037166247 | D8: 0.039292138 | E8: 0.039726522 | F8: 0.040102125 | G8: =SUMIFS(BOND!$AL:$AL,BOND!$AH:$AH,G1,BOND!$AI:$AI,"YTM_ON BS")/100 -> 0.040545139 | H8: =SUMIFS(BOND!$AL:$AL,BOND!$AH:$AH,H1,BOND!$AI:$AI,"YTM_ON BS")/100 -> 0.03940561 | I8: =SUMIFS(BOND!$AL:$AL,BOND!$AH:$AH,I1,BOND!$AI:$AI,"YTM_ON BS")/100 -> 0.040128409 | J8: =_xlfn.XLOOKUP(J23,BOND!$BC:$BC,BOND!$BD:$BD,,0)/100 -> 0.042464765 | K8: =_xlfn.XLOOKUP(K23,BOND!$BC:$BC,BOND!$BD:$BD,,0)/100 -> 0.039499879 | L8: =_xlfn.XLOOKUP(L23,BOND!$BC:$BC,BOND!$BD:$BD,,0)/100 -> 0.038006658 | M8: =_xlfn.XLOOKUP(M23,BOND!$BC:$BC,BOND!$BD:$BD,,0)/100 -> 0.035992079 | P8: thiếu công thức các tháng cũ
A9: Banking book Gbond | B9: =SUMIFS(BOND!$K:$K,BOND!$G:$G,B$1) -> 16959.311 | C9: =SUMIFS(BOND!$K:$K,BOND!$G:$G,C$1) -> 16959.311 | D9: =SUMIFS(BOND!$K:$K,BOND!$G:$G,D$1) -> 16959.311 | E9: =SUMIFS(BOND!$K:$K,BOND!$G:$G,E$1) -> 16959.311 | F9: =SUMIFS(BOND!$K:$K,BOND!$G:$G,F$1) -> 16959.311 | G9: =SUMIFS(BOND!$K:$K,BOND!$G:$G,G$1) -> 16959.311 | H9: =SUMIFS(BOND!$K:$K,BOND!$G:$G,H$1) -> 12001.311 | O9: tháng 11 đáo hạn 300 tỷ | P9: chưa có cth, tháng 11 đáo hạn 300 tỷ
A10: Lợi suất bình quân | B10: 0.026682072 | C10: 0.026682072 | D10: 0.026682072 | E10: 0.026682072 | F10: 0.026682072 | G10: 0.026682072 | H10: 0.026682072 | P10: chưa có cth, book BK fix nên số fix k sửa
A11: FI bond | B11: =SUMIFS(BOND!$AQ:$AQ,BOND!$AN:$AN,B1) -> 34458.682 | C11: =SUMIFS(BOND!$AQ:$AQ,BOND!$AN:$AN,C1) -> 38969.947 | D11: =SUMIFS(BOND!$AQ:$AQ,BOND!$AN:$AN,D1) -> 27119.74 | E11: =SUMIFS(BOND!$AQ:$AQ,BOND!$AN:$AN,E1) -> 30669.469 | F11: =SUMIFS(BOND!$AQ:$AQ,BOND!$AN:$AN,F1) -> 35474.47 | G11: =SUMIFS(BOND!$AQ:$AQ,BOND!$AN:$AN,G1) -> 39497.611 | H11: =SUMIFS(BOND!$AQ:$AQ,BOND!$AN:$AN,H1) -> 39522.262 | I11: =SUMIFS(BOND!$AQ:$AQ,BOND!$AN:$AN,I1) -> 40166.528 | J11: =I11 -> 40166.528 | K11: =J11 -> 40166.528 | L11: =K11 -> 40166.528 | M11: =L11 -> 40166.528 | P11: chưa có cth, chưa có ước tính, các tháng sau cho = số thực tế ngày báo cáo
A12: Lợi suất bình quân | B12: 0.057621928 | C12: 0.054484147 | D12: 0.05357593 | E12: 0.053719867 | F12: =SUMIFS(BOND!$AV:$AV,BOND!$AS:$AS,F1,BOND!$AU:$AU,"Total On BS")/100 -> 0.056270865 | G12: =SUMIFS(BOND!$AV:$AV,BOND!$AS:$AS,G1,BOND!$AU:$AU,"Total On BS")/100 -> 0.05894094 | H12: =SUMIFS(BOND!$AV:$AV,BOND!$AS:$AS,H1,BOND!$AU:$AU,"Total On BS")/100 -> 0.064706749 | I12: =SUMIFS(BOND!$AV:$AV,BOND!$AS:$AS,I1,BOND!$AU:$AU,"Total On BS")/100 -> 0.074070015 | J12: =I12 -> 0.074070015 | K12: =J12 -> 0.074070015 | L12: =K12 -> 0.074070015 | M12: =L12 -> 0.074070015 | P12: chưa có cth, chưa có ước tính, các tháng sau cho = số thực tế ngày báo cáo
A13: 1.Ước tính Biến động NII (L/s +1%) (*) | B13: =SUM(B14:B16) -> 40.604753 | C13: =SUM(C14:C16) -> 81.848077 | D13: =SUM(D14:D16) -> 42.944052 | E13: =SUM(E14:E16) -> 29.220661 | F13: =SUM(F14:F16) -> 57.993555 | G13: =SUM(G14:G16) -> 72.541583 | H13: =SUM(H14:H16) -> 29.619396 | I13: =SUM(I14:I16) -> 17.339183 | ... M13: =SUM(M14:M16) -> 56.844356 | N13: =SUM(B13:M13) -> 615.26169
A14: Trading book Gbond | B14: =-SUMIFS(BOND!$BQ:$BQ,BOND!$BN:$BN,B$1,BOND!$BO:$BO,"Trading bonds_Govbond",BOND!$BP:$BP,"NIM") -> 14.84306 | C14: =-SUMIFS(BOND!$BQ:$BQ,BOND!$BN:$BN,C$1,BOND!$BO:$BO,"Trading bonds_Govbond",BOND!$BP:$BP,"NIM") -> 13.818341 | D14: =-SUMIFS(BOND!$BQ:$BQ,BOND!$BN:$BN,D$1,BOND!$BO:$BO,"Trading bonds_Govbond",BOND!$BP:$BP,"NIM") -> 23.324771 | E14: =-SUMIFS(BOND!$BQ:$BQ,BOND!$BN:$BN,E$1,BOND!$BO:$BO,"Trading bonds_Govbond",BOND!$BP:$BP,"NIM") -> 9.994472 | F14: =-SUMIFS(BOND!$BQ:$BQ,BOND!$BN:$BN,F$1,BOND!$BO:$BO,"Trading bonds_Govbond",BOND!$BP:$BP,"NIM") -> 14.006186 | G14: =-SUMIFS(BOND!$BQ:$BQ,BOND!$BN:$BN,G$1,BOND!$BO:$BO,"Trading bonds_Govbond",BOND!$BP:$BP,"NIM") -> 23.518877 | H14: =-SUMIFS(BOND!$BQ:$BQ,BOND!$BN:$BN,H$1,BOND!$BO:$BO,"Trading bonds_Govbond",BOND!$BP:$BP,"NIM") -> 14.181213 | I14: =-SUMIFS(BOND!$BQ:$BQ,BOND!$BN:$BN,I$1,BOND!$BO:$BO,"Trading bonds_Govbond",BOND!$BP:$BP,"NIM") -> 20.181445 | J14: =J7*1%/12 -> 28.711917 | K14: =K7*1%/12 -> 28.973083 | L14: =L7*1%/12 -> 28.20475 | M14: =M7*1%/12 -> 23.37225 | N14: =SUM(B14:M14) -> 243.13036
A15: Banking book Gbond | B15: =-SUMIFS(BOND!$BQ:$BQ,BOND!$BN:$BN,B$1,BOND!$BO:$BO,"Banking bonds_Govbond",BOND!$BP:$BP,"NIM") -> 11.038693 | C15: =-SUMIFS(BOND!$BQ:$BQ,BOND!$BN:$BN,C$1,BOND!$BO:$BO,"Banking bonds_Govbond",BOND!$BP:$BP,"NIM") -> 11.430737 | D15: =-SUMIFS(BOND!$BQ:$BQ,BOND!$BN:$BN,D$1,BOND!$BO:$BO,"Banking bonds_Govbond",BOND!$BP:$BP,"NIM") -> 12.727281 | E15: =-SUMIFS(BOND!$BQ:$BQ,BOND!$BN:$BN,E$1,BOND!$BO:$BO,"Banking bonds_Govbond",BOND!$BP:$BP,"NIM") -> 10.589189 | F15: =-SUMIFS(BOND!$BQ:$BQ,BOND!$BN:$BN,F$1,BOND!$BO:$BO,"Banking bonds_Govbond",BOND!$BP:$BP,"NIM") -> 12.61037 | G15: =-SUMIFS(BOND!$BQ:$BQ,BOND!$BN:$BN,G$1,BOND!$BO:$BO,"Banking bonds_Govbond",BOND!$BP:$BP,"NIM") -> 11.352707 | H15: =-SUMIFS(BOND!$BQ:$BQ,BOND!$BN:$BN,H$1,BOND!$BO:$BO,"Banking bonds_Govbond",BOND!$BP:$BP,"NIM") -> 10.280184 | I15: =-SUMIFS(BOND!$BQ:$BQ,BOND!$BN:$BN,I$1,BOND!$BO:$BO,"Banking bonds_Govbond",BOND!$BP:$BP,"NIM") -> 7.2647387 | J15: =J9*1%/12 -> 0 | K15: =K9*1%/12 -> 0 | L15: =L9*1%/12 -> 0 | M15: =M9*1%/12 -> 0 | N15: =SUM(B15:M15) -> 87.293899
A16: FI bond | B16: =-SUMIFS(BOND!$BQ:$BQ,BOND!$BN:$BN,B$1,BOND!$BO:$BO,"Trading bonds_FI bond",BOND!$BP:$BP,"NIM") -> 14.723 | C16: =-SUMIFS(BOND!$BQ:$BQ,BOND!$BN:$BN,C$1,BOND!$BO:$BO,"Trading bonds_FI bond",BOND!$BP:$BP,"NIM") -> 56.599 | D16: =-SUMIFS(BOND!$BQ:$BQ,BOND!$BN:$BN,D$1,BOND!$BO:$BO,"Trading bonds_FI bond",BOND!$BP:$BP,"NIM") -> 6.892 | E16: =-SUMIFS(BOND!$BQ:$BQ,BOND!$BN:$BN,E$1,BOND!$BO:$BO,"Trading bonds_FI bond",BOND!$BP:$BP,"NIM") -> 8.637 | F16: =-SUMIFS(BOND!$BQ:$BQ,BOND!$BN:$BN,F$1,BOND!$BO:$BO,"Trading bonds_FI bond",BOND!$BP:$BP,"NIM") -> 31.377 | G16: =-SUMIFS(BOND!$BQ:$BQ,BOND!$BN:$BN,G$1,BOND!$BO:$BO,"Trading bonds_FI bond",BOND!$BP:$BP,"NIM") -> 37.67 | H16: =-SUMIFS(BOND!$BQ:$BQ,BOND!$BN:$BN,H$1,BOND!$BO:$BO,"Trading bonds_FI bond",BOND!$BP:$BP,"NIM") -> 5.158 | I16: =-SUMIFS(BOND!$BQ:$BQ,BOND!$BN:$BN,I$1,BOND!$BO:$BO,"Trading bonds_FI bond",BOND!$BP:$BP,"NIM") -> -10.107 | J16: =J11*1%/12 -> 33.472106 | K16: =K11*1%/12 -> 33.472106 | L16: =L11*1%/12 -> 33.472106 | M16: =M11*1%/12 -> 33.472106 | N16: =SUM(B16:M16) -> 284.83743
A17: 2.Ước tính Lỗ NIM (L/s duy trì 5%) (**) | B17: =SUM(B18:B20) -> 40.604753 | C17: =SUM(C18:C20) -> 81.848077 | D17: =SUM(D18:D20) -> 42.944052 | E17: =SUM(E18:E20) -> 29.220661 | F17: =SUM(F18:F20) -> 36.253555 | G17: =SUM(G18:G20) -> 44.508583 | H17: =SUM(H18:H20) -> 29.619396 | I17: =SUM(I18:I20) -> 17.339183 | ... M17: =SUM(M18:M20) -> 35.852519 | N17: =SUM(B17:M17) -> 453.41346
A18: Trading book | B18: =B14 -> 14.84306 | C18: =C14 -> 13.818341 | D18: =D14 -> 23.324771 | E18: =E14 -> 9.994472 | F18: =F14 -> 14.006186 | G18: =G14 -> 23.518877 | H18: =-SUMIFS(BOND!$BQ:$BQ,BOND!$BN:$BN,H$1,BOND!$BO:$BO,"Trading bonds_Govbond",BOND!$BP:$BP,"NIM") -> 14.181213 | I18: =-SUMIFS(BOND!$BQ:$BQ,BOND!$BN:$BN,I$1,BOND!$BO:$BO,"Trading bonds_Govbond",BOND!$BP:$BP,"NIM") -> 20.181445 | J18: =-J7*(J8-5%)/12 -> 21.635105 | K18: =-K7*(K8-5%)/12 -> 30.422088 | L18: =-L7*(L8-5%)/12 -> 33.826921 | M18: =-M7*(M8-5%)/12 -> 32.739663 | N18: =SUM(I18:M18) -> 138.80522
A19: Banking book | B19: =B15 -> 11.038693 | C19: =C15 -> 11.430737 | D19: =D15 -> 12.727281 | E19: =E15 -> 10.589189 | F19: =F15 -> 12.61037 | G19: =G15 -> 11.352707 | H19: =-SUMIFS(BOND!$BQ:$BQ,BOND!$BN:$BN,H$1,BOND!$BO:$BO,"Banking bonds_Govbond",BOND!$BP:$BP,"NIM") -> 10.280184 | I19: =-SUMIFS(BOND!$BQ:$BQ,BOND!$BN:$BN,I$1,BOND!$BO:$BO,"Banking bonds_Govbond",BOND!$BP:$BP,"NIM") -> 7.2647387 | J19: =-J9*(J10-5%)/12 -> 0 | K19: =-K9*(K10-5%)/12 -> 0 | L19: =-L9*(L10-5%)/12 -> 0 | M19: =-M9*(M10-5%)/12 -> 0 | N19: =SUM(I19:M19) -> 7.2647387
A20: FI bond | B20: 14.723 | C20: 56.599 | D20: 6.892 | E20: 8.637 | F20: 9.637 | G20: 9.637 | H20: =-SUMIFS(BOND!$BQ:$BQ,BOND!$BN:$BN,H$1,BOND!$BO:$BO,"Trading bonds_FI bond",BOND!$BP:$BP,"NIM") -> 5.158 | I20: =-SUMIFS(BOND!$BQ:$BQ,BOND!$BN:$BN,I$1,BOND!$BO:$BO,"Trading bonds_FI bond",BOND!$BP:$BP,"NIM") -> -10.107 | J20: =-J11*(J12-7.5%)/12 -> 3.112856 | K20: =-K11*(K12-7.5%)/12 -> 3.112856 | L20: =-L11*(L12-7.5%)/12 -> 3.112856 | M20: =-M11*(M12-7.5%)/12 -> 3.112856 | N20: =SUM(B20:M20) -> 113.62742
B22: Est Posi OnBS T1 | C22: Est Posi OnBS T2 | D22: Est Posi OnBS T3 | E22: Est Posi OnBS T4 | F22: Est Posi OnBS T5 | G22: Est Posi OnBS T6 | H22: Est Posi OnBS T7 | I22: Est Posi OnBS T8 | J22: Est Posi OnBS T9 | K22: Est Posi OnBS T10 | L22: Est Posi OnBS T11 | M22: Est Posi OnBS T12
B23: Est YTM T1 | C23: Est YTM T2 | D23: Est YTM T3 | E23: Est YTM T4 | F23: Est YTM T5 | G23: Est YTM T6 | H23: Est YTM T7 | I23: Est YTM T8 | J23: Est YTM T9 | K23: Est YTM T10 | L23: Est YTM T11 | M23: Est YTM T12

Sheet Market
A1: 1. Yield | E1: 2. Ls VND LNH | I1: 3. Thông tin OMO | M1: 4. Tỷ giá USDVND
A3: RptDate | B3: Tenor | C3: Yield | E3: RptDate | F3: Indicators | G3: Average | I3: Date | J3: Indicators | K3: Value | M3: RptDate | N3: TygiaUV
A4: 46293 | B4: 1Y | C4: 3.533 | E4: 46293 | F4: O/N_VND | G4: 0.5 | I4: 46293 | J4: OMO | K4: 8170238441064 | M4: 46293 | N4: 25970.6
A5: 46293 | B5: 2Y | C5: 3.638 | E5: 46293 | F5: 1W_VND | G5: 6.5 | I5: 46293 | J5: OMO_chao thau | K5: 1000 | M5: 46290 | N5: 25975.8
A6: 46293 | B6: 3Y | C6: 3.713 | E6: 46293 | F6: 2W_VND | G6: 5.9 | I6: 46293 | J6: OMO_ky han | K6: 7 | M6: 46289 | N6: 25996.4
A7: 46293 | B7: 4Y | C7: 4.002 | E7: 46293 | F7: 1M_VND | G7: 6.3 | I7: 46293 | J7: OMO_trung thau | K7: 1565 | M7: 46288 | N7: 25986
A8: 46293 | B8: 5Y | C8: 4.292 | E8: 46290 | F8: O/N_VND | G8: 0.7 | I8: 46293 | J8: OMO_LS trung thau | K8: 4.5 | M8: 46287 | N8: 26025.4
A9: 46293 | B9: 7Y | C9: 4.334 | E9: 46290 | F9: 1W_VND | G9: 5.6 | I9: 46293 | J9: OMO_dao han | K9: 46358.1 | M9: 46286 | N9: 26008.8
A10: 46293 | B10: 10Y | C10: 4.467 | E10: 46290 | F10: 2W_VND | G10: 5.75 | I10: 46293 | J10: OMO_Outstanding | K10: 142022.78 | M10: 46283 | N10: 26017.2
A11: 46293 | B11: 15Y | C11: 4.58 | E11: 46290 | F11: 1M_VND | G11: 6.2 | I11: 46293 | J11: Mature_next_week_OMO | K11: -50634.39 | M11: 46282 | N11: 26012
A12: 46293 | B12: 20Y | C12: 4.666 | E12: 46289 | F12: O/N_VND | G12: 1 | I12: 46293 | J12: OMO_thanhvien_trungthau | K12: 5 | M12: 46281 | N12: 25994
A13: 46293 | B13: 30Y | C13: 4.733 | E13: 46289 | F13: 1W_VND | G13: 5.1 | I13: 46293 | J13: OMO_thanhvien_thamgia | K13: 5 | M13: 46280 | N13: 25965.6
A14: 46290 | B14: 1Y | C14: 3.533 | E14: 46289 | F14: 2W_VND | G14: 5.2 | I14: 46292 | J14: OMO | K14: 8170238441064 | M14: 46279 | N14: 25984.6
A15: 46290 | B15: 2Y | C15: 3.638 | E15: 46289 | F15: 1M_VND | G15: 6.15 | I15: 46290 | J15: OMO_chao thau | K15: 1000 | M15: 46276 | N15: 25915.6
... A433: 46230 | B433: 3Y | C433: 3.642 | E433: 46134 | F433: 1W_VND | G433: 6.3 | I433: 46230 | J433: OMO_ky han | K433: 7 | M433: 45657 | N433: 25488.667
A434: 46227 | B434: 1Y | C434: 3.467 | E434: 46134 | F434: 2W_VND | G434: 7 | I434: 46230 | J434: OMO_trung thau | K434: 2195
A435: 46227 | B435: 2Y | C435: 3.571 | E435: 46134 | F435: 1M_VND | G435: 7.33 | I435: 46230 | J435: OMO_LS trung thau | K435: 4.5
A436: 46227 | B436: 3Y | C436: 3.625 | E436: 46133 | F436: O/N_VND | G436: 5.9 | I436: 46230 | J436: OMO_dao han | K436: 16382.57
A437: 46227 | B437: 4Y | C437: 3.917 | E437: 46133 | F437: 1W_VND | G437: 6.5 | I437: 46230 | J437: OMO_Outstanding | K437: 143018.39
A438: 46227 | B438: 5Y | C438: 4.209 | E438: 46133 | F438: 2W_VND | G438: 7 | I438: 46230 | J438: Mature_next_week_OMO | K438: -39088.48
A439: 46227 | B439: 7Y | C439: 4.27 | E439: 46133 | F439: 1M_VND | G439: 7.3 | I439: 46230 | J439: OMO_thanhvien_trungthau | K439: 7
A440: 46227 | B440: 10Y | C440: 4.405 | E440: 46132 | F440: O/N_VND | G440: 4.3 | I440: 46230 | J440: OMO_thanhvien_thamgia | K440: 7
A441: 46227 | B441: 15Y | C441: 4.578 | E441: 46132 | F441: 1W_VND | G441: 5.3 | I441: 46230 | J441: OMO | K441: 12315093015973
A442: 46227 | B442: 20Y | C442: 4.658 | E442: 46132 | F442: 2W_VND | G442: 7.05 | I442: 46229 | J442: OMO | K442: 12710714173165
A443: 46227 | B443: 30Y | C443: 4.724 | E443: 46132 | F443: 1M_VND | G443: 7.3 | I443: 46227 | J443: OMO_thanhvien_thamgia | K443: 8
A444: 46226 | B444: 1Y | C444: 3.467 | E444: 46129 | F444: O/N_VND | G444: 4 | I444: 46227 | J444: OMO_chao thau | K444: 1000
A445: 46226 | B445: 2Y | C445: 3.571 | E445: 46129 | F445: 1W_VND | G445: 5 | I445: 46227 | J445: OMO_ky han | K445: 7
... A1723: 46037 | B1723: 30Y | C1723: 4.35 | E1723: 45657 | F1723: 1M_VND | G1723: 5.3 | I1723: 46041 | J1723: OMO_Outstanding | K1723: 297529.28
A1724: 46036 | B1724: 1Y | C1724: 3.023 | I1724: 46041 | J1724: Mature_next_week_OMO | K1724: -45926.64
A1725: 46036 | B1725: 2Y | C1725: 3.096 | I1725: 46041 | J1725: OMO_thanhvien_trungthau | K1725: 9
A1726: 46036 | B1726: 3Y | C1726: 3.142 | I1726: 46041 | J1726: OMO_thanhvien_thamgia | K1726: 9
A1727: 46036 | B1727: 4Y | C1727: 3.374 | I1727: 46040 | J1727: OMO | K1727: 20490001316202
A1728: 46036 | B1728: 5Y | C1728: 3.607 | I1728: 46038 | J1728: OMO_chao thau | K1728: 1000
A1729: 46036 | B1729: 7Y | C1729: 3.65 | I1729: 46038 | J1729: OMO_ky han | K1729: 7
A1730: 46036 | B1730: 10Y | C1730: 4.14 | I1730: 46038 | J1730: OMO_trung thau | K1730: 2000
A1731: 46036 | B1731: 15Y | C1731: 4.245 | I1731: 46038 | J1731: OMO_LS trung thau | K1731: 4.5
A1732: 46036 | B1732: 20Y | C1732: 4.292 | I1732: 46038 | J1732: OMO_dao han | K1732: 8750
A1733: 46036 | B1733: 30Y | C1733: 4.338 | I1733: 46038 | J1733: OMO_Outstanding | K1733: 315248.51
A1734: 46035 | B1734: 1Y | C1734: 2.998 | I1734: 46038 | J1734: Mature_next_week_OMO | K1734: -58116.87
A1735: 46035 | B1735: 2Y | C1735: 3.077 | I1735: 46038 | J1735: OMO_thanhvien_trungthau | K1735: 7
... A4303: 45657 | B4303: 30Y | C4303: 3.267 | I4303: 45665 | J4303: OMO_Outstanding | K4303: 38997.19
I4304: 45665 | J4304: Mature_next_week_OMO | K4304: -38997.19
I4305: 45665 | J4305: OMO_thanhvien_trungthau | K4305: 9
I4306: 45665 | J4306: OMO_thanhvien_thamgia | K4306: 9
I4307: 45665 | J4307: OMO | K4307: 5504843264590
I4308: 45664 | J4308: OMO_chao thau | K4308: 5000
I4309: 45664 | J4309: OMO_ky han | K4309: 7
I4310: 45664 | J4310: OMO_trung thau | K4310: 5000
I4311: 45664 | J4311: OMO_LS trung thau | K4311: 4
I4312: 45664 | J4312: OMO_dao han | K4312: 16989
I4313: 45664 | J4313: OMO_Outstanding | K4313: 46997.18
I4314: 45664 | J4314: Mature_next_week_OMO | K4314: -46997.18
I4315: 45664 | J4315: OMO_thanhvien_trungthau | K4315: 5
... I4358: 45657 | J4358: OMO | K4358: 8194415088942

Sheet Executive
A1: Section | B1: Key | C1: Field/Label | D1: Current HTML Value
A2: Thông tin chung | B2: reportMainTitle | C2: Header báo cáo | D2: Market & Liquidity Risk Report (Market II)
A3: Thông tin chung | B3: reportSubtitle | C3: Header báo cáo | D3: Rủi ro thị trường - thanh khoản | Danh mục Gbond Banking Book & Trading Book | Theo dõi MtM, PV01, NIM và tín hiệu thị trường
A4: Header | B4: reportDate | C4: Tiêu đề module Executive | D4: =RPT -> 46290
A5: Header | B5: moduleExecutiveTitle | C5: Tiêu đề module Executive | D5: ='Run Tool'!H2 -> Executive Messages: (1) Chỉ số lỗ MtM của danh mục Bond Trading giữ mức 1.634 tỷ. Nếu yield tăng thêm 1 bps (~0.01%) ở tất cả các kỳ hạn, mức lỗ sẽ gia tăng thêm 11 tỷ. (2) Trạng thái danh mục GBond duy trì mức 17.513 tỷ - 88% hạn mức; Trạng thái danh mục FIBond & CD (bao gồm cả TPCP nước ngoài Kyrgyzstan) duy trì mức 39.414 tỷ - 88% hạn mức. (3) Lãi suất LNH kỳ ON tiếp tục giảm xuống 0.7% trong khi các kỳ dài hơn từ 1W-1M vẫn quanh mức 5-6%. Lưu ý rủi ro lỗ NIM vẫn tiềm ẩn do lãi suất có khả năng biến động mạnh. (4) Khe hở thanh khoản lũy kế - Gap 3M đang ở mức -25,2k tỷ, có xu hướng tăng chiều âm trong tháng 9, chủ yếu do giảm cho vay LNH kì 1-3M trong khi tăng huy động LNH kì dưới 3M
A6: Header | B6: moduleExecutiveStatus | C6: Trạng thái module Executive | D6: NGOẠI LỆ HẠN MỨC LỖ MtM & RỦI RO LỖ KÉP
A7: Thông điệp trọng tâm | B7: executiveMessageSectionTitle | C7: Tiêu đề section | D7: 1. Thông điệp trọng tâm
A8: Thông điệp trọng tâm | B8: msg1Title | C8: Tiêu đề 1 | D8: ='Run Tool'!H3 -> Phân tách lại danh mục TD và BK GovBond
A9: Thông điệp trọng tâm | B9: msg1Body | C9: Nội dung 1 | D9: ='Run Tool'!H4 -> Kể từ ngày báo cáo 10/08/2026, QLRR đã điều chỉnh danh mục Trading và Banking book theo bóc tách lại phần Danh mục Banking Gbond phù hợp với số vốn được Pool tài trợ 12k tỷ) từ DCM. Theo đó: (1) Danh mục theo mệnh giá của Trading book và Banking book tương ứng là: 17.413 tỷ và 10.848 tỷ. (2) Ngay tại thời điểm bóc tách lại (10/08), Lỗ MtM của danh mục Trading điều chỉnh tăng thêm 23 tỷ.
A10: Thông điệp trọng tâm | B10: msg2Title | C10: Tiêu đề 2 | D10: ='Run Tool'!H5 -> Thay đổi ngưỡng mục tiêu bộ đệm thanh khoản
A11: Thông điệp trọng tâm | B11: msg2Body | C11: Nội dung 2 | D11: ='Run Tool'!H6 -> Sau bóc tách lại danh mục TD & BK, ngưỡng mục tiêu bộ đệm thanh khoản điều chỉnh từ 11.440 tỷ về 10.400 tỷ. QLRR lưu ý: (1) Banking Gbond dự phòng cần được sử dụng/tối ưu có chọn lọc trong điều kiện bình thường, nhằm tránh làm suy giảm năng lực ứng phó khi thị trường xuất hiện cú sốc nguồn vốn.
A12: Thông điệp trọng tâm | B12: msg3Title | C12: Tiêu đề 3 | D12: ='Run Tool'!H7 -> Giám sát tình trạng NGOẠI LỆ vượt hạn mức lỗ mtm
A13: Thông điệp trọng tâm | B13: msg3Body | C13: Nội dung 3 | D13: ='Run Tool'!H8 -> Danh mục Trading Gbond hiện ghi nhận lỗ MtM quanh 1.640 tỷ đồng (xu hướng tăng gần đây do yield tăng liên tục tuần qua) trên quy mô trạng thái rủi ro 17.413 tỷ đồng, vượt hạn mức 400 tỷ đồng và đang trong quá trình phê duyệt ngoại lệ. => QLRR khuyến nghị FI/DCM duy trì báo cáo định kỳ cấp có thẩm quyền, vẫn tiếp tục tìm kiếm các biện pháp giảm thiểu/xử lý lỗ và kiểm soát không để rủi ro tiếp tục gia tăng; báo cáo xin ý kiến cấp có thẩm quyền trong t/h phát sinh các nhân tố có thể làm leo thang đáng kể tình trạng lỗ mtm.
A14: Thông điệp trọng tâm | B14: msg4Title | C14: Tiêu đề 4 | D14: ='Run Tool'!H9 -> Rủi ro LỖ KÉP tiếp tục là ÁP LỰC CHÍNH
A15: Thông điệp trọng tâm | B15: msg4Body | C15: Nội dung 4 | D15: ='Run Tool'!H10 -> Trong bối cảnh lợi suất trái phiếu tăng từ đầu tháng và chi phí vốn duy trì ở mức cao, các danh mục Banking Gbond, FIBond và Trading Gbond đang chịu đồng thời hai áp lực: lỗ đánh giá lại MtM và suy giảm NIM => Đây không chỉ là rủi ro thị trường ngắn hạn, mà là vấn đề cần được cân nhắc trong chiến lược phân bổ bảng cân đối (danh quy mô DM đầu tư) và tối ưu hiệu quả vốn.
A16: KPI Gbond | B16: executiveGbondSectionTitle | C16: Tiêu đề nhóm | D16: Tình hình rủi ro Danh mục Trái phiếu chính phủ
A17: Trading Book | B17: tradingCardTitle | C17: Tiêu đề card | D17: Trading Book chịu rủi ro thị trường
A18: Trading Book | B18: tradingStatus | C18: Status
A19: Trading Book | B19: tradingExposure | C19: Giá trị | D19: =SUMIFS(BOND!$E:$E,BOND!$C:$C,"All",BOND!$A:$A,RPT) -> 17513
A20: Trading Book | B20: tradingExposureChange | C20: +/- | D20: 0 | E20: bỏ
A21: Trading Book | B21: tradingPortfolioRateLabel | C21: Label lãi suất | D21: Lãi suất DM:
A22: Trading Book | B22: tradingPortfolioRate | C22: Lãi suất DM | D22: =SUMIFS(BOND!BL:BL,BOND!BJ:BJ,RPT)/100 -> 0.030511557
A23: Trading Book | B23: pendingTradeAmount | C23: Giao dịch pending | D23: =ROUND(SUMIFS(BOND!$AL:$AL,BOND!$AJ:$AJ,"Face",BOND!$AI:$AI,"NGOAI BS",BOND!$AK:$AK,"Deal sell",BOND!$AH:$AH,RPT),0) -> 5916
A24: Trading Book | B24: tradingBookNotePrefix | C24: Note prefix | D24: Sau giảm trừ giao dịch bán chưa thanh toán và BO chưa xác nhận (~
A25: Trading Book | B25: tradingBookNoteSuffix | C25: Note suffix | D25: tỷ)
A26: Trading Book | B26: tradingLimitTitle | C26: Tiêu đề limit | D26: Hạn mức Trading Book
A27: Trading Book | B27: limitLabel | C27: limitLabel | D27: Limit
A28: Trading Book | B28: usageLabel | C28: usageLabel | D28: Mức sử dụng
A29: Trading Book | B29: tradingBookLimit | C29: Limit | D29: 20000
A30: Trading Book | B30: tradingUtilization | C30: Mức sử dụng | D30: =D19/D29 -> 0.87565
A31: Trading Book | B31: tradingLimitWarningComment | C31: tradingLimitWarningComment
A32: MtM | B32: mtmCardTitle | C32: Tiêu đề card | D32: Lỗ MtM còn lại
A33: MtM | B33: mtmStatus | C33: Status
A34: MtM | B34: mtmLimitWarningComment | C34: Ghi chú limit | D34: Lưu ý: Đang trong trạng thái phê duyệt ngoại lệ
A35: MtM | B35: mtmLoss | C35: Giá trị | D35: =ROUND(-SUMIFS(BOND!$AA:$AA,BOND!$Z:$Z,"",BOND!$X:$X,RPT),0) -> 1634
A36: MtM | B36: mtmLossChange | C36: +/- | D36: =ROUND(SUMIFS(BOND!$AA:$AA,BOND!$Z:$Z,"",BOND!$X:$X,RPT)-SUMIFS(BOND!$AA:$AA,BOND!$Z:$Z,"",BOND!$X:$X,Yesterday),0) -> 0
A37: MtM | B37: mtmCardNote | C37: Note | D37: Trading Book sau giảm trừ giao dịch đã bán chưa thanh toán
A38: MtM | B38: mtmLimitTitle | C38: Tiêu đề limit | D38: Hạn mức lỗ MtM
A39: MtM | B39: mtmLossLimit | C39: Limit | D39: 500
A40: MtM | B40: mtmUtilization | C40: Mức sử dụng | D40: =D35/D39 -> 3.268
A41: BO chưa xác nhận | B41: worstCaseCardTitle | C41: Tiêu đề card | D41: Kịch bản bất lợi với giao dịch BO chưa xác nhận
A42: BO chưa xác nhận | B42: worstCaseMtMStatus | C42: Status | D42: Rủi ro trọng yếu
A43: BO chưa xác nhận | B43: worstCaseMtM | C43: Giá trị | D43: =ROUND(ABS(SUMIFS(BOND!$AL:$AL,BOND!$AJ:$AJ,"ItD",BOND!$AK:$AK,"All",BOND!$AI:$AI,"ON BS",BOND!$AH:$AH,RPT) +SUMIFS(BOND!AL:AL,BOND!AH:AH,RPT,BOND!AJ:AJ,"ItD",BOND!AK:AK,"Deal buy") -SUMIFS(BOND!AL:AL,BOND!AH:AH,RPT,BOND!AJ:AJ,"ItD",BOND!AK:AK,"Deal sell",BOND!AI:AI,"OFF BS")),0) -> 2016
A44: BO chưa xác nhận | B44: worstCaseMtMChange | C44: +/- | D44: =D43- ABS(SUMIFS(BOND!$AL:$AL,BOND!$AJ:$AJ,"ItD",BOND!$AK:$AK,"All",BOND!$AI:$AI,"ON BS",BOND!$AH:$AH,RPT) +SUMIFS(BOND!$BH:$BH,BOND!$BF:$BF,Yesterday,BOND!$BG:$BG,"Itd_Unrealized Book DCM tu fund") +SUMIFS(BOND!AL:AL,BOND!AH:AH,Yesterday,BOND!AJ:AJ,"ItD",BOND!AK:AK,"Deal buy") -SUMIFS(BOND!AL:AL,BOND!AH:AH,Yesterday,BOND!AJ:AJ,"ItD",BOND!AK:AK,"Deal sell",BOND!AI:AI,"OFF BS")) -> -287.58942
A45: BO chưa xác nhận | B45: worstCaseMtMNote | C45: Note | D45: Lỗ MtM tiềm ẩn gia tăng nếu giao dịch BO chưa xác nhận có thể bị đối tác hủy khi thị trường bất lợi
A46: BO chưa xác nhận | B46: unsettledSoldTradePnLPrefix | C46: PnL prefix | D46: T/h các giao dịch này thực hiện thanh toán thành công thì ngân hàng sẽ ghi nhận bổ sung vào KQKD phần lãi (+)/lỗ (-) là
A47: BO chưa xác nhận | B47: unsettledSoldTradePnL | C47: PnL | D47: =SUMIFS(BOND!BH:BH,BOND!BF:BF,RPT) -> -36.107355
A48: BO chưa xác nhận | B48: unsettledSoldTradePnLUnit | C48: PnL unit | D48: tỷ.
A49: NIM | B49: nimCardTitle | C49: Tiêu đề card | D49: Áp lực suy giảm NIM 2026
A50: NIM | B50: estimatedNimLossStatus | C50: Status | D50: Độ nhạy NIM
A51: NIM | B51: estimatedNimLoss | C51: Giá trị | D51: =SUM(NIM!J14:M14) -> 109.262
A52: NIM | B52: estimatedNimLossChange | C52: +/-
A53: NIM | B53: estimatedNimLossNotePrefix | C53: Note prefix | D53: NIM giảm bao nhiêu nếu CoF tăng thêm 1%
A54: NIM | B54: fundingCost | C54: Funding cost
A55: NIM | B55: estimatedNimLossNoteMid | C55: Note mid | D55: Từ tháng 9 đến YE2026, giả định danh mục không thay đổi (chỉ điều chỉnh các deal valuedate trong tương lai lần lượt chuyển từ ngoại bảng vào nội bảng), nếu COF tăng thêm
A56: NIM | B56: costIncreaseAssumption | C56: Cost increase | D56: 1%
A57: NIM | B57: estimatedNimLossNoteSuffix | C57: Note suffix | D57: sẽ làm NIM giảm thêm ~
A58: NIM | B58: nimLossMonthlyIncrease | C58: Lỗ/tháng | D58: =ROUND(AVERAGE(NIM!I14:M14),0) -> 26
A59: NIM | B59: estimatedNimLossNoteUnit | C59: Note unit | D59: tỷ đồng/tháng.
A60: Banking DCM | B60: bankingCardTitle | C60: Tiêu đề card | D60: Banking Gbond được tài trợ bởi Tiền gửi Hệ thống
A61: Banking DCM | B61: bankingStatus | C61: Status
A62: Banking DCM | B62: bankingBookBalance | C62: Giá trị | D62: 12,000
A63: Banking DCM | B63: bankingBookBalanceChange | C63: +/- | D63: 0
A64: Banking DCM | B64: bankingBookNote | C64: Note | D64: ='Run Tool'!H11 -> Hệ thống tài trợ 12k tỷ để dự phòng thanh khoản cho kịch bản rút tiền gửi, tương ứng 10.848 tỷ theo mệnh giá.
A65: Banking DCM | B65: bankingBookRiskWarningLabel | C65: Risk label | D65: Lưu ý:
A66: Banking DCM | B66: bankingBookRiskWarning | C66: Risk warning | D66: Danh mục này có thể chịu các rủi ro tiềm ẩn IRRBB ở 02 khía cạnh sau :(1) Rủi ro tăng chi phí vốn tài trợ làm gia tăng chi phí thanh khoản phân bổ trong FTP ;(2) Rủi ro giảm giá trị: Mặc dù là Banking GBond nắm giữ để dự phòng thanh khoản, không phải để Trading, nhưng vẫn tiềm ẩn rủi ro Giảm giá trị (do đánh giá mtm) và có thể ghi nhận lỗ vào KQKD trong trường hợp buộc phải bán để đáp ứng nhu cầu thanh toán trong điều kiện căng thẳng thanh khoản.
A67: Banking DCM | B67: bankingLimitTitle | C67: Limit title | D67: Mức tài trợ từ Tiền gửi hệ thống (do ALCO phê duyệt)
A68: Banking DCM | B68: bankingBookLimit | C68: Limit | D68: 12,000
A69: Banking DCM | B69: bankingUtilization | C69: Mức sử dụng | D69: =D62/D68 -> 1
A70: Banking DCM | B70: bankingLimitWarningComment | C70: Ghi chú khi vượt hạn mức Banking Book
A71: Banking dự phòng | B71: availableBankingCardTitle | C71: Tiêu đề card | D71: Banking Gbond dự phòng thanh khoản
A72: Banking dự phòng | B72: availableBankingGbondStatus | C72: Status
A73: Banking dự phòng | B73: availableBankingGbond | C73: Giá trị | D73: =ROUND(SUMIFS(BOND!$AZ:$AZ,BOND!$AY:$AY,"Face_HLA",BOND!$AX:$AX,RPT_LR),0) -> 10769
A74: Banking dự phòng | B74: availableBankingGbondChange | C74: +/- | D74: =ROUND(SUMIFS(BOND!$AZ:$AZ,BOND!$AY:$AY,"Face_HLA",BOND!$AX:$AX,RPT_LR)-SUMIFS(BOND!$AZ:$AZ,BOND!$AY:$AY,"Face_HLA",BOND!$AX:$AX,RPT_LR1),0) -> -4560
A75: Banking dự phòng | B75: availableBankingGbondNote | C75: Note | D75: Nguồn Gbond còn lại có thể sử dụng cho mục tiêu dự phòng thanh khoản
A76: Banking dự phòng | B76: availableBankingGbondLimitTitle | C76: Limit title | D76: Mức dự phòng thanh khoản mục tiêu
A77: Banking dự phòng | B77: targetLabel | C77: Target label | D77: Target
A78: Banking dự phòng | B78: liquidityReserveTarget | C78: Target | D78: =ROUND(SUMIFS(BOND!K:K,BOND!G:G,RPT)-(-SUMIFS(BOND!$AZ:$AZ,BOND!$AY:$AY,"Face_HMNR_NAPAS",BOND!$AX:$AX,RPT_LR)),-2) -> 10300
A79: Banking dự phòng | B79: liquidityReserveWarningThresholdLabel | C79: WarningName | D79: Ngưỡng cảnh báo
A80: Banking dự phòng | B80: liquidityReserveWarningThreshold | C80: Ngưỡng | D80: 8000
A81: Banking dự phòng | B81: reserveUsageLabel | C81: Usage label | D81: Mức sử dụng so với mục tiêu
A82: Banking dự phòng | B82: availableBankingGbondUtilization | C82: Mức đáp ứng | D82: =D73/D78 -> 1.045534
A83: Banking dự phòng | B83: reserveThresholdGood | C83: Threshold good | D83: >=100%: Xanh - Đáp ứng tốt
A84: Banking dự phòng | B84: reserveThresholdWatch | C84: Threshold watch | D84: <100%: Vàng - Thiếu hụt so với mục tiêu
A85: Banking dự phòng | B85: reserveThresholdBad | C85: Threshold bad | D85: <70%: Đỏ - Cảnh báo suy giảm năng lực ứng phó căng thẳng thanh khoản (tương đương Ngưỡng cảnh báo 8.000 tỷ theo y/c của ALCO
A86: Banking dự phòng | B86: availableBankingGbondReserveWarningHtml | C86: Warning HTML | D86: <b>Lưu ý:</b> Danh mục đã về trên ngưỡng cảnh báo 8.000 tỷ nhưng vẫn thấp hơn mức target (là mức được tài trợ từ TT1 để dự phòng các kịch bản rút tiền gửi đột xuất/nghiêm trọng).<br><span style="color:#344054;font-weight:500;">Theo đó <b>việc tối ưu Banking book</b> trong điều kiện bình thường (nếu có) chỉ nên được cân đối ngắn hạn và cần điều chỉnh các kế hoạch cân nguồn để đưa Giá trị danh mục về mức mục tiêu</span>
A87: Banking dự phòng | B87: availableBankingGbondLimitWarningComment | C87: Ghi chú khi vượt ngưỡng Banking Gbond còn lại
A88: MtM Banking | B88: bankingMtMCardTitle | C88: Tiêu đề card | D88: Mức giảm giá theo MtM - Banking Gbond
A89: MtM Banking | B89: bankingMtMDiscountStatus | C89: Status | D89: Áp lực đánh giá lại
A90: MtM Banking | B90: bankingMtMDiscount | C90: Giá trị | D90: =-SUMIFS(BOND!AF:AF,BOND!AC:AC,RPT) -> 1740.2885
A91: MtM Banking | B91: bankingMtMDiscountChange | C91: +/- | D91: 0
A92: MtM Banking | B92: bankingMtMDiscountNote | C92: Note | D92: Mức suy giảm giá trị theo MtM của danh mục Banking Gbond
A93: MtM Banking | B93: bankingMtMWarningMainHtml | C93: Warning main | D93: <b>CẢNH BÁO:</b> Việc giảm giá MtM đối với danh mục này có thể tác động vào lãi/lỗ kinh doanh trong kịch bản MSB phải bán (thay vì cầm cố/repo/OMO) Gbond Banking Book để đáp ứng nhu cầu thanh khoản trong các kịch bản căng thẳng/rút tiền gửi lớn.
A94: MtM Banking | B94: bankingMtMWarningMutedPrefix | C94: Warning prefix | D94: Khuyến nghị DCM/ALM đề xuất Cấp có thẩm quyền phương án quản lý:
A95: MtM Banking | B95: bankingMtMWarningLine1 | C95: Warning line 1 | D95: (i) Phòng ngừa rủi ro giảm giá MtM gia tăng của danh mục Banking Gbond;
A96: MtM Banking | B96: bankingMtMWarningLine2 | C96: Warning line 2 | D96: (ii) Xem xét phương án phân bổ vào chi phí thanh khoản nói chung (nếu cần) để giảm tác động tiêu cực vào PnL trong tương lai nếu buộc phải bán để đáp ứng thanh khoản.
A97: FI Bond&CD | B97: executiveFiSectionTitle | C97: Tiêu đề nhóm | D97: Tình hình rủi ro Danh mục Trái phiếu TCTD
A98: FI Bond&CD | B98: fiBondCdCardTitle | C98: Tiêu đề card | D98: Trạng thái rủi ro Bond&CD-FI
A99: FI Bond&CD | B99: fiBondCdStatus | C99: Status
A100: FI Bond&CD | B100: fiBondCdExposure | C100: Giá trị | D100: =ROUND(SUMIFS(BOND!$AQ:$AQ,BOND!$AN:$AN,RPT),0) -> 39414
...

Sheet Thị trường
A1: Thông tin thị trường - Daily Input
A2: Section | B2: Key | C2: Current HTML Value
A3: Thông tin thị trường | B3: marketUpdateTime | C3: =Executive!D4 -> 46290
A4: Thông tin thị trường | B4: moduleHeading_market | C4: Thông tin thị trường
A5: Thông tin thị trường | B5: moduleDesc_market | C5: Theo dõi biến động DTD/WTD/MTD/YTD của lãi suất, lợi suất TPCP, tỷ giá và tín hiệu OMO/SBV phục vụ đánh giá rủi ro thị trường.
A6: Thông tin thị trường | B6: moduleDesc_marketUpdateLabel | C6: Cập nhật:
A7: Thông tin thị trường | B7: marketRiskSignal | C7: Theo dõi biến động lợi suất
A8: Thông tin thị trường | B8: marketCommentary | C8: Lợi suất TPCP và chi phí vốn ngắn hạn được dự báo tăng. Cần tiếp tục kiểm soát trạng thái Trading Book, theo dõi sát lỗ MtM và đánh giá lại mức độ phù hợp của danh mục Banking Gbond phục vụ dự phòng thanh khoản.
A9: Thông tin thị trường | B9: gbondYield2Y | C9: =SUMIFS(Market!C:C,Market!B:B,"2Y",Market!A:A,RPT)/100 -> 0.03638
A10: Thông tin thị trường | B10: gbondYield2YDTD | C10: =10000*(C9-SUMIFS(Market!C:C,Market!B:B,"2Y",Market!A:A,Yesterday)/100) -> 0
A11: Thông tin thị trường | B11: gbondYield2YWTD | C11: =10000*(C9-SUMIFS(Market!C:C,Market!B:B,"2Y",Market!A:A,Lastweek)/100) -> 0
A12: Thông tin thị trường | B12: gbondYield2YMTD | C12: =10000*(C9-SUMIFS(Market!C:C,Market!B:B,"2Y",Market!A:A,Lastmonth)/100) -> 0
A13: Thông tin thị trường | B13: gbondYield2YYTD | C13: =10000*(C9-SUMIFS(Market!C:C,Market!B:B,"2Y",Market!A:A,Lastyear)/100) -> 165
A14: Thông tin thị trường | B14: gbondYield5Y | C14: =SUMIFS(Market!C:C,Market!B:B,"5Y",Market!A:A,RPT)/100 -> 0.04296
A15: Thông tin thị trường | B15: gbondYield5YDTD | C15: =10000*(C14-SUMIFS(Market!C:C,Market!B:B,"5Y",Market!A:A,Yesterday)/100) -> 0.4
A16: Thông tin thị trường | B16: gbondYield5YWTD | C16: =10000*(C14-SUMIFS(Market!C:C,Market!B:B,"5Y",Market!A:A,Lastweek)/100) -> -0.3
A17: Thông tin thị trường | B17: gbondYield5YMTD | C17: =10000*(C14-SUMIFS(Market!C:C,Market!B:B,"5Y",Market!A:A,Lastmonth)/100) -> -0.6
A18: Thông tin thị trường | B18: gbondYield5YYTD | C18: =10000*(C14-SUMIFS(Market!C:C,Market!B:B,"5Y",Market!A:A,Lastyear)/100) -> 200.5
A19: Thông tin thị trường | B19: gbondYield10Y | C19: =SUMIFS(Market!C:C,Market!B:B,"10Y",Market!A:A,RPT)/100 -> 0.04467
A20: Thông tin thị trường | B20: gbondYield10YDTD | C20: =10000*(C19-SUMIFS(Market!C:C,Market!B:B,"10Y",Market!A:A,Yesterday)/100) -> 0
A21: Thông tin thị trường | B21: gbondYield10YWTD | C21: =10000*(C19-SUMIFS(Market!C:C,Market!B:B,"10Y",Market!A:A,Lastweek)/100) -> 0.5
A22: Thông tin thị trường | B22: gbondYield10YMTD | C22: =10000*(C19-SUMIFS(Market!C:C,Market!B:B,"10Y",Market!A:A,Lastmonth)/100) -> 1.8
A23: Thông tin thị trường | B23: gbondYield10YYTD | C23: =10000*(C19-SUMIFS(Market!C:C,Market!B:B,"10Y",Market!A:A,Lastyear)/100) -> 149.8
A24: Thông tin thị trường | B24: interbankON | C24: =SUMIFS(Market!G:G,Market!F:F,"O/N_VND",Market!E:E,RPT)/100 -> 0.007
A25: Thông tin thị trường | B25: interbankONDTD | C25: =10000*(C24-SUMIFS(Market!G:G,Market!F:F,"O/N_VND",Market!E:E,Yesterday)/100) -> -30
A26: Thông tin thị trường | B26: interbankONWTD | C26: =10000*(C24-SUMIFS(Market!G:G,Market!F:F,"O/N_VND",Market!E:E,Lastweek)/100) -> -380
A27: Thông tin thị trường | B27: interbankONMTD | C27: =10000*(C24-SUMIFS(Market!G:G,Market!F:F,"O/N_VND",Market!E:E,Lastmonth)/100) -> -680
A28: Thông tin thị trường | B28: interbankONYTD | C28: =10000*(C24-SUMIFS(Market!G:G,Market!F:F,"O/N_VND",Market!E:E,Lastyear)/100) -> -327
A29: Thông tin thị trường | B29: interbank1W | C29: =SUMIFS(Market!G:G,Market!F:F,"1W_VND",Market!E:E,RPT)/100 -> 0.056
A30: Thông tin thị trường | B30: interbank1WDTD | C30: =10000*(C29-SUMIFS(Market!G:G,Market!F:F,"1W_VND",Market!E:E,Yesterday)/100) -> 50
A31: Thông tin thị trường | B31: interbank1WWTD | C31: =10000*(C29-SUMIFS(Market!G:G,Market!F:F,"1W_VND",Market!E:E,Lastweek)/100) -> 80
A32: Thông tin thị trường | B32: interbank1WMTD | C32: =10000*(C29-SUMIFS(Market!G:G,Market!F:F,"1W_VND",Market!E:E,Lastmonth)/100) -> -165
A33: Thông tin thị trường | B33: interbank1WYTD | C33: =10000*(C29-SUMIFS(Market!G:G,Market!F:F,"1W_VND",Market!E:E,Lastyear)/100) -> 63
A34: Thông tin thị trường | B34: interbank2W | C34: =SUMIFS(Market!G:G,Market!F:F,"2W_VND",Market!E:E,RPT)/100 -> 0.0575
A35: Thông tin thị trường | B35: interbank2WDTD | C35: =10000*(C34-SUMIFS(Market!G:G,Market!F:F,"2W_VND",Market!E:E,Yesterday)/100) -> 55
A36: Thông tin thị trường | B36: interbank2WWTD | C36: =10000*(C34-SUMIFS(Market!G:G,Market!F:F,"2W_VND",Market!E:E,Lastweek)/100) -> -25
A37: Thông tin thị trường | B37: interbank2WMTD | C37: =10000*(C34-SUMIFS(Market!G:G,Market!F:F,"2W_VND",Market!E:E,Lastmonth)/100) -> -85
A38: Thông tin thị trường | B38: interbank2WYTD | C38: =10000*(C34-SUMIFS(Market!G:G,Market!F:F,"2W_VND",Market!E:E,Lastyear)/100) -> 57
A39: Thông tin thị trường | B39: interbank1M | C39: =SUMIFS(Market!G:G,Market!F:F,"1M_VND",Market!E:E,RPT)/100 -> 0.062
A40: Thông tin thị trường | B40: interbank1MDTD | C40: =10000*(C39-SUMIFS(Market!G:G,Market!F:F,"1M_VND",Market!E:E,Yesterday)/100) -> 5
A41: Thông tin thị trường | B41: interbank1MWTD | C41: =10000*(C39-SUMIFS(Market!G:G,Market!F:F,"1M_VND",Market!E:E,Lastweek)/100) -> 20
A42: Thông tin thị trường | B42: interbank1MMTD | C42: =10000*(C39-SUMIFS(Market!G:G,Market!F:F,"1M_VND",Market!E:E,Lastmonth)/100) -> -35
A43: Thông tin thị trường | B43: interbank1MYTD | C43: =10000*(C39-SUMIFS(Market!G:G,Market!F:F,"1M_VND",Market!E:E,Lastyear)/100) -> 90
A44: Thông tin thị trường | B44: usdVnd | C44: =ROUND(SUMIFS(Market!N:N,Market!M:M,RPT),0) -> 25976
A45: Thông tin thị trường | B45: usdVndDTD | C45: =C44-SUMIFS(Market!N:N,Market!M:M,Yesterday) -> -20.4
A46: Thông tin thị trường | B46: usdVndWTD | C46: =C44-SUMIFS(Market!N:N,Market!M:M,Lastweek) -> -41.2
A47: Thông tin thị trường | B47: usdVndMTD | C47: =C44-SUMIFS(Market!N:N,Market!M:M,Lastmonth) -> -97
A48: Thông tin thị trường | B48: usdVndYTD | C48: =C44-SUMIFS(Market!N:N,Market!M:M,Lastyear) -> 487.33333
A49: Thông tin thị trường | B49: omoOutstanding | C49: =ROUND(SUMIFS(Market!K:K,Market!J:J,"OMO_Outstanding",Market!I:I,RPT),0) -> 186816
A50: Thông tin thị trường | B50: omoOutstandingDtd | C50: =ROUND(C49-SUMIFS(Market!K:K,Market!J:J,"OMO_Outstanding",Market!I:I,Yesterday),0) -> -5301
A51: Thông tin thị trường | B51: omoNetToday | C51: =ROUND(C49-SUMIFS(Market!K:K,Market!J:J,"OMO_Outstanding",Market!I:I,Yesterday),0) -> -5301
A52: Thông tin thị trường | B52: omoNetWeek | C52: =ROUND(C49-SUMIFS(Market!K:K,Market!J:J,"OMO_Outstanding",Market!I:I,Lastweek),0) -> 34330
A53: Thông tin thị trường | B53: omoNetMonth | C53: =ROUND(C49-SUMIFS(Market!K:K,Market!J:J,"OMO_Outstanding",Market!I:I,Lastmonth),0) -> -50430
A54: Thông tin thị trường | B54: omoNetYear | C54: =ROUND(C49-SUMIFS(Market!K:K,Market!J:J,"OMO_Outstanding",Market!I:I,Lastyear),0) -> 109827
A55: Thông tin thị trường | B55: omoMaturity7D | C55: =ROUND(-SUMIFS(Market!K:K,Market!J:J,"Mature_next_week_OMO",Market!I:I,RPT),0) -> 78615

Sheet Chi tiết DM
A1: Bảng 2 & 3 - Thông tin chi tiết Danh mục
A2: Section | B2: Key | C2: Current HTML Value
A3: Bảng 2 - Tổng quan rủi ro | B3: riskOverviewTitle | C3: 2. Tổng quan các nội dung rủi ro trọng yếu
A4: Bảng 2 - Tổng quan rủi ro | B4: riskOverviewHeaderRisk | C4: Nội dung rủi ro
A5: Bảng 2 - Tổng quan rủi ro | B5: riskOverviewHeaderStatus | C5: Trạng thái
A6: Bảng 2 - Tổng quan rủi ro | B6: riskOverviewHeaderMeaning | C6: Diễn giải theo ngôn ngữ quản trị
A7: Bảng 2 - Tổng quan rủi ro | B7: riskOverview1Risk | C7: Trạng thái Gbond Trading
A8: Bảng 2 - Tổng quan rủi ro | B8: riskOverview1Status | C8: Cần theo dõi
A9: Bảng 2 - Tổng quan rủi ro | B9: riskOverview1Meaning | C9: Trạng thái chịu RRTT đã giảm, nhưng trên cơ sở giả định các giao dịch bán chưa thanh toán và BO chưa valid sẽ được thực hiện thành công trong tương lai.
A10: Bảng 2 - Tổng quan rủi ro | B10: riskOverview2Risk | C10: MtM / capital impact
A11: Bảng 2 - Tổng quan rủi ro | B11: riskOverview2Status | C11: Cần theo dõi
A12: Bảng 2 - Tổng quan rủi ro | B12: riskOverview2Meaning | C12: ="Lỗ MtM còn lại khoảng "&ROUND(Executive!D35,0)&" tỷ; trong kịch bản bất lợi có thể lên khoảng "&Executive!D43&" nếu phần giao dịch chưa valid quay lại danh mục." -> Lỗ MtM còn lại khoảng 1634 tỷ; trong kịch bản bất lợi có thể lên khoảng 2016 nếu phần giao dịch chưa valid quay lại danh mục.
A13: Bảng 2 - Tổng quan rủi ro | B13: riskOverview3Risk | C13: Yield shock risk
A14: Bảng 2 - Tổng quan rủi ro | B14: riskOverview3Status | C14: Cảnh báo trong kịch bản bất lợi
A15: Bảng 2 - Tổng quan rủi ro | B15: riskOverview3Meaning | C15: Một số kịch bản yield 10Y cao làm vượt hạn mức ItD unrealized PnL; kịch bản NCKT cao có thể khiến tổng lỗ + lỗ tiềm ẩn tăng mạnh.
A16: Bảng 2 - Tổng quan rủi ro | B16: riskOverview4Risk | C16: Funding cost / NIM drag
A17: Bảng 2 - Tổng quan rủi ro | B17: riskOverview4Status | C17: Cần theo dõi
A18: Bảng 2 - Tổng quan rủi ro | B18: riskOverview4Meaning | C18: Danh mục Bond không chỉ chịu rủi ro giảm giá khi lợi suất tăng mà còn chịu áp lực từ chi phí vốn duy trì ở mức cao, làm gia tăng tác động đồng thời lên lỗ đánh giá lại, vốn yêu cầu và hiệu quả sinh lời.
A19: Bảng 2 - Tổng quan rủi ro | B19: riskOverview5Risk | C19: Banking Book economic loss
A20: Bảng 2 - Tổng quan rủi ro | B20: riskOverview5Status | C20: Cần theo dõi
A21: Bảng 2 - Tổng quan rủi ro | B21: riskOverview5Meaning | C21: Banking Book không ghi nhận lỗ giá theo PnL, nhưng vẫn có lỗ kinh tế và lỗ NIM; cần xin ý kiến ALCO về cơ chế quản lý phù hợp.
A22: Bảng 3 - Thuật ngữ/ngôn ngữ rủi ro | B22: termsTitle | C22: 3. Diễn giải một số thuật ngữ/ngôn ngữ rủi ro
A23: Bảng 3 - Thuật ngữ/ngôn ngữ rủi ro | B23: termsHeaderTerm | C23: Thuật ngữ/chỉ tiêu
A24: Bảng 3 - Thuật ngữ/ngôn ngữ rủi ro | B24: termsHeaderTechnical | C24: Cách hiểu kỹ thuật
... A27: Bảng 3 - Thuật ngữ/ngôn ngữ rủi ro | B27: term1TechnicalPrefix | C27: PV01 Trading =
A28: Bảng 3 - Thuật ngữ/ngôn ngữ rủi ro | B28: tradingPV01 | C28: =ROUND(SUMIFS(BOND!$P:$P,BOND!$M:$M,RPT),1) -> -10.6
A29: Bảng 3 - Thuật ngữ/ngôn ngữ rủi ro | B29: term1TechnicalMid | C29: , Banking =
A30: Bảng 3 - Thuật ngữ/ngôn ngữ rủi ro | B30: bankingPV01 | C30: =ROUND(SUMIFS(BOND!U:U,BOND!R:R,RPT),1) -> -8.4
A31: Bảng 3 - Thuật ngữ/ngôn ngữ rủi ro | B31: term1MeaningPrefix | C31: Kịch bản nếu yield tăng
A32: Bảng 3 - Thuật ngữ/ngôn ngữ rủi ro | B32: yieldShockPct | C32: 0.0026
A33: Bảng 3 - Thuật ngữ/ngôn ngữ rủi ro | B33: term1MeaningMid1 | C33: , giá trị danh mục Trading Book giảm khoảng
A34: Bảng 3 - Thuật ngữ/ngôn ngữ rủi ro | B34: tradingYieldLoss | C34: =ROUND(C28*C32*10^4,0) -> -276
A35: Bảng 3 - Thuật ngữ/ngôn ngữ rủi ro | B35: term1MeaningMid2 | C35: tỷ
A36: Bảng 3 - Thuật ngữ/ngôn ngữ rủi ro | B36: bankingYieldLoss | C36: và giá trị danh mục Banking Book giảm khoảng
A37: Bảng 3 - Thuật ngữ/ngôn ngữ rủi ro | B37: term1MeaningSuffix | C37: =ROUND(C30*C32*10^4,0) &" tỷ." -> -218 tỷ.
A38: Bảng 3 - Thuật ngữ/ngôn ngữ rủi ro | B38: term2Name | C38: Unrealized MtM
A39: Bảng 3 - Thuật ngữ/ngôn ngữ rủi ro | B39: term2TechnicalPrefix | C39: ItD Unrealized PnL -
A40: Bảng 3 - Thuật ngữ/ngôn ngữ rủi ro | B40: mtmLoss | C40: 1593
A41: Bảng 3 - Thuật ngữ/ngôn ngữ rủi ro | B41: term2Meaning | C41: Đây là phần lỗ kinh tế chưa hiện thực hóa; nếu bán/giảm trạng thái sai thời điểm có thể chuyển thành lỗ thực.
A42: Bảng 3 - Thuật ngữ/ngôn ngữ rủi ro | B42: term3Name | C42: BO valid / unvalid
A43: Bảng 3 - Thuật ngữ/ngôn ngữ rủi ro | B43: term3Technical | C43: Giao dịch bán chưa được BO xác nhận
A44: Bảng 3 - Thuật ngữ/ngôn ngữ rủi ro | B44: term3Meaning | C44: Rủi ro xử lý: nếu giao dịch chưa hoàn tất pháp lý/vận hành, trạng thái rủi ro có thể quay lại danh mục.
A45: Bảng 3 - Thuật ngữ/ngôn ngữ rủi ro | B45: term4NamePrefix | C45: Funding rate
A46: Bảng 3 - Thuật ngữ/ngôn ngữ rủi ro | B46: fundingCost | C46: 5%
A47: Bảng 3 - Thuật ngữ/ngôn ngữ rủi ro | B47: term4Technical | C47: Lỗ NIM theo giả định lãi suất fund
A48: Bảng 3 - Thuật ngữ/ngôn ngữ rủi ro | B48: term4Meaning | C48: Carry trade trái phiếu đang chịu áp lực vì chi phí vốn cao hơn lợi suất danh mục.
A49: Bảng 3 - Thuật ngữ/ngôn ngữ rủi ro | B49: term5Name | C49: Yield scenario
... A51: Bảng 3 - Thuật ngữ/ngôn ngữ rủi ro | B51: term5Meaning | C51: Nếu mặt bằng yield tiếp tục tăng, ngân hàng chịu áp lực đồng thời về vốn, PnL và định hướng giảm trạng thái.

Sheet LR>>
A1: RptDate | B1: TygiaUV
A2: 46281 | B2: 1438000
A3: 46280 | B3: 1439200
A4: 46279 | B4: 1444000
A5: 46276 | B5: 1445400
A6: 46275 | B6: 1451000
A7: 46274 | B7: 1443000
A8: 46273 | B8: 1453000
A9: 46272 | B9: 1458000
A10: 46269 | B10: 1470000
A11: 46268 | B11: 1465500
A12: 46262 | B12: 1485000
A13: 46261 | B13: 1486500
... A423: 45657 | B423: 835000

Sheet Available rpt
A1: a. Cơ cấu sử dụng TPTKC | B1: Giá trị ngày báo cáo | E1: Dự báo | H1: b. Cơ cấu dự trữ TPTKC | I1: Mệnh giá | J1: HLA in Normal | K1: +/- | L1: HLA in Stress
B2: =RPT_LR -> 46293 | C2: =RPT_LR1 -> 46292 | D2: +/- | E2: Giao dịch dự kiến thực hiện | F2: Tổng TPTKC | H2: 1. TP Lưu ký mở HM Thấu chi SBV | I2: 1459 | J2: 1492 | K2: 0 | L2: 1492 | M2: TP sử dụng để vay thấu chi với SBV
A3: 1. Available Bond 1M | B3: 9633.5738 | C3: 14171.043 | D3: -4537.4692 | E3: 6588.2569 | F3: 16221.831 | H3: 2. TP lưu ký được cầm cố mở HM với TCTD khác | I3: 800 | J3: 712.82 | K3: 0 | L3: 712.82 | M3: TP sử dụng để vay cầm cố cho KH tại SBV + VSD chưa sử dụng
A4: 1.1 Danh mục DT TPCP | B4: 44318.611 | C4: 48878.611 | D4: -4560 | E4: 4731.32 | F4: 49049.931 | H4: 3. TP lưu ký đặt tại SBV sẵn sàng tham gia OMO | I4: 7392.8209 | J4: 6363.3929 | K4: 0.76367655 | L4: 6363.3929 | M4: TP sử dụng để vay OMO với SBV nhưng chưa sử dụng
A5: 1.2 (+) TPCP nhận về từ GD Reversed-repo | B5: 0 | C5: 0 | D5: 0 | E5: 0 | F5: 0 | H5: 4. TP tại VSD đã cam kết bán/repo | I5: 767.4904 | J5: 774.2699 | K5: -4538.2666 | L5: 774.2699 | M5: Là Bond available (chưa sử dụng) nhưng đã ký cam kết bán/repo
A6: 1.3 (-) Sử dụng để vay Repo | B6: -23578.3 | C6: -23578.3 | D6: 0 | E6: 0 | F6: -23578.3 | H6: 5. TP lưu ký sẵn sàng khác tại VSD | I6: 350 | J6: 291.09105 | K6: 0.03375 | L6: 274.91933 | M6: Số dư khả dụng còn lại (chưa cam kết)
A7: 1.4 (-) Sử dụng để vay OMO | B7: -9366 | C7: -9366 | D7: 0 | E7: 660.7075 | F7: -8705.2925 | H7: 6. Tổng Trái phiếu thanh khoản cao | I7: 10769.311 | J7: 9633.5738 | K7: -4537.4692 | L7: 9617.4021
A8: 1.5 (-) Sử dụng để cầm cố tại TCTD khác | B8: 0 | C8: 0 | D8: 0 | E8: 0 | F8: 0 | H8: Net Unrealized [Buy (+)/Sell (-)] cho T+1 | I8: -15947.3
A9: 1.6 (-) Cầm cố cho HMNR + NAPAS | B9: -605 | C9: -605 | D9: 0 | E9: 0 | F9: -605 | H9: Total Sell_Unrealized | I9: -28442.02
A10: 2. Chênh lệch giá trị vốn hóa và facevalue | B10: -1135.7375 | C10: -1158.2683 | D10: 22.530834 | E10: 1196.2294 | F10: 60.491925 | H10: Total Buy_Unrealized | I10: 12494.72
A11: Tổng giá trị mệnh giá | B11: 10769.311 | C11: 15329.311 | D11: -4560
A12: 3. Danh mục Unrealized [Buy (+)/Sell (-)] | B12: -15947.3
A13: 3.1 (-) Unrealized Sell | B13: -28442.02
A14: 3.2 (+) Unrealized Buy | B14: 12494.72

Sheet BK Gbond
A1: Thông tin chi tiết Danh mục - Bảng 1.1 và 1.2
A3: Key | B3: Nội dung | C3: Value
A4: detailPortfolioTitle | B4: Tiêu đề module | C4: Thông tin chi tiết Danh mục GBond
A5: detailPortfolioDesc | B5: Mô tả module | C5: Tổng hợp cơ cấu Banking Gbond còn lại sẵn sàng sử dụng, tổng quan rủi ro trọng yếu và diễn giải thuật ngữ rủi ro.
A6: bankingGbondPledgeSectionTitle | B6: Tiêu đề bảng 1.1 | C6: 1.1 Cơ cấu sử dụng Banking Gbond được tài trợ bởi hệ thống
A7: bankingGbondPledgeHeaderMetric | B7: Header 1.1 - Chỉ tiêu | C7: Chỉ tiêu
A8: bankingGbondPledgeHeaderValue | B8: Header 1.1 - Giá trị | C8: Giá trị
A9: bankingGbondPledgeHeaderDtd | B9: Header 1.1 - +/- Dtd | C9: +/- Dtd
A10: bankingGbondPledgeHeaderRatio | B10: Header 1.1 - Tỷ trọng | C10: Tỷ trọng trong Banking Gbond hệ thống
A11: bankingGbondPledgeHeaderUsage | B11: Header 1.1 - Mức độ sử dụng | C11: Mức độ sử dụng
A12: availableGbondSectionTitle | B12: Tiêu đề bảng 1.2 | C12: 1.2 Cơ cấu Banking Gbond còn lại sẵn sàng sử dụng
A13: availableGbondHeaderComponent | B13: Header 1.2 - Cấu phần | C13: Cấu phần
A14: availableGbondHeaderValue | B14: Header 1.2 - Giá trị | C14: Giá trị
... A17: availableGbondHeaderMeaning | B17: Header 1.2 - Diễn giải quản trị | C17: Diễn giải quản trị
A19: 1.1 Cơ cấu sử dụng Banking Gbond được tài trợ bởi hệ thống
A20: Key gốc | B20: Loại dòng | C20: Chỉ tiêu | D20: Giá trị (tỷ) | E20: +/- Dtd | F20: Tỷ trọng | G20: Ghi chú
A21: systemFundedBankingGbond | B21: positive | C21: (+) Banking Gbond được tài trợ bởi Hệ thống | D21: ='Available rpt'!B4 -> 44318.611 | E21: ='Available rpt'!D4 -> -4560 | F21: =IFERROR(ABS(D21)/SUM(D21:D22),"") -> 1 | G21: Dòng dấu (+), thuộc mẫu số
A22: reverseRepoReceivedGbond | B22: positive | C22: (+) Gbond đã nhận trong giao dịch Reverse Repo | D22: ='Available rpt'!B5 -> 0 | E22: ='Available rpt'!D5 -> 0 | F22: =IFERROR(ABS(D22)/SUM(D21:D22),"") -> 0 | G22: Dòng dấu (+), thuộc mẫu số
A23: pledgedNapasBankingGbond | B23: negative | C23: (-) Đã cầm cố kênh thanh toán Hạn mức nợ ròng/Napas | D23: =-'Available rpt'!B9 -> 605 | E23: =-'Available rpt'!D9 -> 0 | F23: =IFERROR(ABS(D23)/SUM(D21:D22),"") -> 0.01365115 | G23: Tự tính trên tổng các dòng dấu (+)
A24: pledgedOMOBankingGbond | B24: negative | C24: (-) Đã sử dụng để vay OMO | D24: =-'Available rpt'!B7 -> 9366 | E24: =-'Available rpt'!D7 -> 0 | F24: =IFERROR(ABS(D24)/SUM(D21:D22),"") -> 0.21133334 | G24: Tự tính trên tổng các dòng dấu (+)
A25: pledgedRepoBankingGbond | B25: negative | C25: (-) Đã sử dụng để vay REPO | D25: =-'Available rpt'!B6 -> 23578.3 | E25: =-'Available rpt'!D6 -> 0 | F25: =IFERROR(ABS(D25)/SUM(D21:D22),"") -> 0.53201802 | G25: Tự tính trên tổng các dòng dấu (+)
A26: pledgedSecuredTCTDBankingGbond | B26: negative | C26: (-) Đã cầm cố vay có đảm bảo tại TCTD khác | D26: =-'Available rpt'!B8 -> 0 | E26: =-'Available rpt'!D8 -> 0 | F26: =IFERROR(ABS(D26)/SUM(D21:D22),"") -> 0 | G26: Tự tính trên tổng các dòng dấu (+)
A27: remainingAvailableBankingGbond | B27: remaining | C27: Banking Gbond còn lại sẵn sàng sử dụng | D27: ='Available rpt'!B11 -> 10769.311 | E27: ='Available rpt'!D11 -> -4560 | F27: =IFERROR(ABS(D27)/SUM(D21:D22),"") -> 0.24299749 | G27: Tự tính trên tổng các dòng dấu (+)
A29: 1.2 Cơ cấu Banking Gbond còn lại sẵn sàng sử dụng
A30: Key gốc | B30: Loại dòng | C30: Cấu phần | D30: Giá trị (tỷ) | E30: Tỷ trọng | F30: Diễn giải quản trị | G30: Cảnh báo/Ghi chú
A31: availableGbondTotal | B31: main | C31: Available Gbond | D31: ='Available rpt'!I7 -> 10769.311 | E31: =IFERROR(ABS(D31)/ABS(D31),"") -> 1 | F31: Bộ đệm thanh khoản có thể sử dụng qua bán, repo, OMO hoặc cầm cố.
A32: availableGbondSBVOverdraft | B32: sub | C32: Đặt mở Thấu chi SBV | D32: ='Available rpt'!I2 -> 1459 | E32: =IFERROR(ABS(D32)/ABS(D31),"") -> 0.13547756 | F32: Phần đã bố trí để mở/duy trì khả năng tiếp cận thấu chi tại NHNN; hỗ trợ nhu cầu thanh khoản trong ngày.
A33: availableGbondCreditLine | B33: sub | C33: Đặt tại Bank khác mở Credit line | D33: ='Available rpt'!I3 -> 800 | E33: =IFERROR(ABS(D33)/ABS(D31),"") -> 0.074285159 | F33: Phần Gbond dùng để hỗ trợ mở/duy trì hạn mức thanh khoản với ngân hàng khác.
A34: availableGbondOMO | B34: sub | C34: Đặt tại OMO | D34: ='Available rpt'!I4 -> 7392.8209 | E34: =IFERROR(ABS(D34)/ABS(D31),"") -> 0.68647109 | F34: Phần đã sẵn sàng cho kênh OMO/cầm cố với NHNN, giúp đáp ứng nhu cầu thanh khoản ngay khi cần.
A35: availableGbondRemaining | B35: sub | C35: Bond còn lại | D35: ='Available rpt'!I5+'Available rpt'!I6 -> 1117.4904 | E35: =IFERROR(ABS(D35)/ABS(D31),"") -> 0.10376619 | F35: Phần trái phiếu còn lại có thể linh hoạt sử dụng tùy trạng thái thị trường. | G35: Lưu ý: Nếu cấu phần này duy trì thấp sẽ ảnh hưởng trọng yếu đến năng lực cân nguồn cho các kịch bản thanh khoản bất thường

Sheet BS_TT2
C1: Ngày báo cáo | E1: Biến động số dư BS TT2 | H1: Số dư BS TT2 | K1: ="Phân bố kỳ thanh khoản BS tại "&TEXT(C2,"dd/mm/yyyy") -> Phân bố kỳ thanh khoản BS tại 28/09/2026 | P1: Bình quân
A2: Stt | C2: 46293 | D2: Tỷ trọng | E2: DtD | F2: MtD | G2: YtD | H2: 46292 | I2: 46265 | J2: 46022 | K2: 1M | L2: 1-3M | M2: 3-6M | N2: 6-12M | O2: 12M | P2: Kỳ hạn | Q2: Lãi suất bình quân
A3: 1 | B3: Gbond_Trading (On BS) | C3: 33.46061 | D3: 0.28803445 | E3: -4.56 | F3: -5.7474 | G3: 8.5494987 | H3: 38.02061 | I3: 39.20801 | J3: 24.911111 | K3: 20.890678 | L3: 12.569932 | M3: 0 | N3: 0 | O3: 0 | P3: 1.0634954
A4: 2 | B4: Gbond_Banking (On BS) | C4: 10.858 | D4: 0.093467456 | E4: 0 | F4: 0 | G4: -6.101 | H4: 10.858 | I4: 10.858 | J4: 16.959 | K4: 0 | L4: 0 | M4: 0 | N4: 0 | O4: 10.858 | P4: 12
A5: 3 | B5: Gbond_Phụ trội chiết khấu | C5: 2.6192872 | D5: 0.022547257 | E5: 0.052490881 | F5: -0.70047829 | G5: -1.3064951 | H5: 2.5667963 | I5: 3.3197655 | J5: 3.9257823 | K5: 2.6192872 | L5: 0 | M5: 0 | N5: 0 | O5: 0 | P5: 0.5
A6: 4 | B6: FIBond | C6: 37.35304 | D6: 0.32154113 | E6: -0.011470677 | F6: 1.011235 | G6: -3.1022748 | H6: 37.36451 | I6: 36.341805 | J6: 40.455314 | K6: 1.3 | L6: 8.95 | M6: 2.4426106 | N6: 20.9041 | O6: 3.7563296 | P6: 7.0016604
A7: 5 | B7: Interbank Lending | C7: 29.339813 | D7: 0.25256196 | E7: 0.30224423 | F7: -1.1548003 | G7: 2.2328521 | H7: 29.037569 | I7: 30.494614 | J7: 27.106961 | K7: 18.113425 | L7: 4.3246352 | M7: 1.1305102 | N7: 5.7712431 | O7: 0 | P7: 2.5279374
A8: 6 | B8: Mproduct Lending | C8: 1.9792985 | D8: 0.017038128 | E8: 0 | F8: 0.49618669 | G8: 1.200703 | H8: 1.9792985 | I8: 1.4831118 | J8: 0.77859548 | K8: 0.12250666 | L8: 0.44077959 | M8: 0.75740698 | N8: 0.65860526 | O8: 0 | P8: 5.0017154
A9: 7 | B9: Other Assets | C9: 0.55872743 | D9: 0.0048096179 | E9: -2.8246564 | F9: -4.9072412 | G9: -2.3884126 | H9: 3.3833839 | I9: 5.4659686 | J9: 2.94714 | K9: 0.55872743 | L9: 0 | M9: 0 | N9: 0 | O9: 0 | P9: 0.5
A10: I | B10: TOTAL ASSETS (USE OF FUNDING) | C10: 116.16878 | D10: 1 | E10: -7.041392 | F10: -11.002498 | G10: -0.91512874 | H10: 123.21017 | I10: 127.17127 | J10: 117.0839 | K10: 43.604624 | L10: 26.285347 | M10: 4.3305278 | N10: 27.333948 | O10: 14.61433 | P10: 4.4166137
A11: 1 | B11: Repo & OMO | C11: 33.646305 | D11: 0.28963295 | E11: 0 | F11: -4.7187959 | G11: 4.8173048 | H11: 33.646305 | I11: 38.365101 | J11: 28.829 | K11: 21.076372 | L11: 12.569932 | M11: 0 | N11: 0 | O11: 0 | P11: 1.0603854
A12: 2 | B12: Interbank borrowing | C12: 35.604341 | D12: 0.30648804 | E12: -4.0463448 | F12: -1.6009998 | G12: 1.3599637 | H12: 39.650686 | I12: 37.205341 | J12: 34.244377 | K12: 18.768216 | L12: 9.0459224 | M12: 6.1381288 | N12: 1.6520736 | O12: 0 | P12: 1.8789038
A13: 3 | B13: Casa Fund FI | C13: 11.124225 | D13: 0.095759166 | E13: -0.00028364257 | F13: -3.6962692 | G13: -2.329709 | H13: 11.124509 | I13: 14.820494 | J13: 13.453934 | K13: 1.6004018 | L13: 9.5238233 | M13: 0 | N13: 0 | O13: 0 | P13: 1.7842005
A14: 4 | B14: PHGTCG | C14: 6.5 | D14: 0.055953073 | E14: 0 | F14: 0 | G14: -4.4 | H14: 6.5 | I14: 6.5 | J14: 10.9 | K14: 2 | L14: 3.5 | M14: 0 | N14: 1 | O14: 0 | P14: 2.6153846
A15: 5 | B15: Other Liabilities | C15: 2.6985933 | D15: 0.023229937 | E15: -0.16380556 | F15: 0.329087 | G15: -0.44534364 | H15: 2.8623989 | I15: 2.3695063 | J15: 3.143937 | K15: 2.6985933 | L15: 0 | M15: 0 | N15: 0 | O15: 0 | P15: 0.5
A16: 6 | B16: Vốn TT1 tài trợ Gbond Banking | C16: 12 | D16: 0.10329798 | E16: 0 | F16: 0 | G16: 0 | H16: 12 | I16: 12 | J16: 12 | K16: 0 | L16: 0 | M16: 0 | N16: 0 | O16: 12 | P16: 12
A17: II | B17: TOTAL LIABILITIES (FUNDING SOURCES) | C17: 101.57346 | D17: 0.87436115 | E17: -4.210434 | F17: -9.686978 | G17: -0.99778413 | H17: 105.7839 | I17: 111.26044 | J17: 102.57125 | K17: 46.143583 | L17: 34.639678 | M17: 6.1381288 | N17: 2.6520736 | O17: 12 | P17: 2.8036095
A18: III | B18: EXCESS DEPOSIT FROM TT1 (được TT2 hấp thụ tự động hàng ngày như là nguồn tài trợ (đối với Balancesheet FI và sẽ được cân đối để phân bổ vào các tài sản thanh khoản của TT2) | C18: 14.595312 | D18: 0.12563885 | E18: -2.830958 | F18: -1.31552 | G18: 0.082655396 | H18: 17.42627 | I18: 15.910832 | J18: 14.512657 | K18: 7.595312 | L18: 7 | M18: 0 | N18: 0 | O18: 0 | P18: 1.2194091
A19: IV | B19: Liquidity GAP (theo tính chất thanh khoản) | C19: -10.134272 | E19: -0.26793685 | F19: -5.615009 | G19: 6.691208 | H19: -9.8663349 | I19: -4.5192627 | J19: -16.82548 | K19: -10.134272 | L19: -15.354331 | M19: -1.807601 | N19: 24.681875 | O19: 2.6143296
A20: 1 | B20: Liquidity GAP_Lũy kế (nếu giả định nguồn dư thừa TT1 tài trợ theo kỳ hạn phân bổ tại chỉ tiêu III như trên) | C20: -10.134272 | E20: -0.26793685 | F20: -5.615009 | G20: 6.691208 | H20: -9.8663349 | I20: -4.5192627 | J20: -16.82548 | K20: -10.134272 | L20: -25.488603 | M20: -27.296204 | N20: -2.614329 | O20: 5.8005919e-07
A21: 2 | B21: Liquidity GAP_Lũy kế (nếu giả định nguồn dư thừa TT1 hỗ trợ ổn định dài hạn) | C21: -2.5389598 | E21: -3.0988949 | F21: -6.930529 | G21: 6.7738634 | H21: 0.5599351 | I21: 4.3915693 | J21: -9.3128232 | K21: -2.5389598 | L21: -10.893291 | M21: -12.700892 | N21: 11.980983 | O21: 14.595313
A22: V | B22: Repricing GAP (theo kỳ Tái định giá lãi suất, không bao gồm RRLSSNH của Danh mục Gbond Trading và Banking) | C22: -10.134272 | E22: -0.26793685 | F22: -5.615009 | G22: 6.691208 | H22: -9.8663349 | I22: -4.5192627 | J22: -16.82548 | K22: -10.134272 | L22: -15.354331 | M22: -1.807601 | N22: 24.681875 | O22: 2.6143296
A23: 1 | B23: Repricing GAP_lũy kế (theo kỳ Tái định giá lãi suất, không bao gồm RRLSSNH của Danh mục Gbond Trading và Banking) | C23: -10.134272 | E23: -0.26793685 | F23: -5.615009 | G23: 6.691208 | H23: -9.8663349 | I23: -4.5192627 | J23: -16.82548 | K23: -10.134272 | L23: -25.488603 | M23: -27.296204 | N23: -2.614329 | O23: 5.8005919e-07
A24: 2 | B24: Ước tính Giảm NII trong 3M tới (đv: tỷ VND) Nếu giả định lãi suất LNH bình quân tăng 1% và giữ ổn định kể từ ngày mai (tỷ VND) | C24: -33.908342 | E24: -0.56139228 | F24: -13.502623 | G24: 17.133583 | H24: -33.34695 | I24: -20.405719 | J24: -51.041925 | K24: -21.113066 | L24: -12.795276 | M24: 0 | N24: 0 | O24: 0
A25: 2 | B25: Ước tính Giảm NII trong 3M tới (đv: tỷ VND) Nếu giả định lãi suất LNH bình quân tăng 2% và giữ ổn định kể từ ngày mai (tỷ VND) | C25: -67.816684 | E25: -1.1227846 | F25: -27.005245 | G25: 34.267166 | H25: -66.693899 | I25: -40.811439 | J25: -102.08385 | K25: -42.226132 | L25: -25.590552 | M25: 0 | N25: 0 | O25: 0
A26: 4 | B26: Ước tính Giảm NII trong 6M tới (đv: tỷ VND) Nếu giả định lãi suất LNH bình quân tăng 1% và giữ ổn định kể từ ngày mai (tỷ VND) | C26: -100.64252 | E26: -1.2370237 | F26: -31.999067 | G26: 1.0418223 | H26: -99.405493 | I26: -68.64345 | J26: -101.68434 | K26: -46.448746 | L26: -51.181103 | M26: -3.0126684 | N26: 0 | O26: 0
A27: 3 | B27: Ước tính Giảm NII trong 6M tới (đv: tỷ VND) Nếu giả định lãi suất LNH bình quân tăng 2% và giữ ổn định kể từ ngày mai (tỷ VND) | C27: -201.28503 | E27: -2.4740475 | F27: -63.998134 | G27: 2.0836447 | H27: -198.81099 | I27: -137.2869 | J27: -203.36868 | K27: -92.897491 | L27: -102.36221 | M27: -6.0253367 | N27: 0 | O27: 0
A31: Note
A32: Nhập Asset và Liability từ Excessive mà BSM gửi update nhất hàng ngày
A33: Trừ ngược với các giá trị xác định được từ báo cáo để ra phần Other Assets và Other Liability
A34: -> Đảm bảo dư thừa khớp Excessive của BSM

Sheet Market II_BS FI
A1: Cơ cấu dòng tiền Market II
A3: Key | B3: Nội dung | C3: Value
A4: marketIISummaryTitle | B4: Tiêu đề module | C4: Cơ cấu dòng tiền thanh khoản - Market II
A5: marketIISummarySub | B5: Mô tả module | C5: Tóm tắt các điểm nghẽn dòng tiền Market II theo kỳ hạn; đơn vị bảng là nghìn tỷ VND, riêng tác động NII là tỷ VND.
A6: marketII_period | B6: Kỳ báo cáo | C6: =TEXT(B25,"dd/mm/yyyy") -> 28/09/2026
A8: KPI Market II
A9: KPI | B9: Title | C9: Subtitle | D9: Value | E9: Unit | F9: Target | G9: Target Label | H9: Target Unit | I9: Note | J9: No Limit | K9: Status Override | L9: Usage Override | M9: Auto fields
A10: KPI 1 | B10: Khe hở thanh khoản lũy kế 1M | D10: =VALUE(H64) -> -10.1 | E10: Nghìn tỷ VND | F10: -22 | G10: Mục tiêu theo dõi tối đa | H10: nghìn tỷ VND | J10: false | M10: Status/Usage để trống nếu muốn HTML tự tính
A11: KPI 2 | B11: Khe hở thanh khoản lũy kế 3M | D11: =VALUE(H64+I64) -> -25.5 | E11: Nghìn tỷ VND | F11: -30 | G11: Mục tiêu theo dõi tối đa | H11: nghìn tỷ VND | J11: false | M11: Status/Usage để trống nếu muốn HTML tự tính
A12: KPI 3 | B12: Khe hở tái định giá lũy kế 1M | D12: =VALUE(H66) -> -10.1 | E12: Nghìn tỷ VND | I12: Không áp dụng limit; chỉ theo dõi xu hướng nhạy cảm lãi suất. | J12: true | M12: Status/Usage để trống nếu muốn HTML tự tính
A13: KPI 4 | B13: Khe hở tái định giá lũy kế 3M | D13: =VALUE(I66) -> -25.5 | E13: Nghìn tỷ VND | I13: Không áp dụng limit; chỉ theo dõi xu hướng nhạy cảm lãi suất. | J13: true | M13: Status/Usage để trống nếu muốn HTML tự tính
A14: KPI 5 | B14: Kịch bản dự báo biến động NII trong 3M | C14: (nếu Lãi suất funding tăng thêm 2% so với hiện tại và duy trì trong 3M tới) | D14: =H67+I67 -> -67.8 | E14: Tỷ VND | F14: -100 | G14: Mục tiêu theo dõi | H14: tỷ VND | J14: false | M14: Status/Usage để trống nếu muốn HTML tự tính
A16: Insight Market II
A17: Insight | B17: Title | C17: Body | D17: Ghi chú
A18: Insight 1 | B18: Thanh khoản lũy kế | C18: Khe hở thanh khoản gap 3M có xu hướng tăng chiều âm trong tháng 9 chủ yếu do giảm cho vay LNH kì 1-3M trong khi tăng huy động LNH kì dưới 3M | D18: Text tùy biến
A19: Insight 2 | B19: Tái định giá lũy kế | C19: Repricing GAP lũy kế 3M xu hướng mở rộng từ tuần trước, mức độ nhạy cảm với biến động lãi suất ngắn hạn tăng | D19: Text tùy biến
A20: Insight 3 | B20: Tác động NII | C20: Nếu lãi suất funding tăng thêm 2% so với hiện tại và duy trì trong 3M tới, biến động NII ước tính lỗ về NIM theo quy mô như chỉ số hiện tại | D20: Text tùy biến
A22: Key | B22: Value | C22: Module | D22: Group | E22: Note | F22: Auto | G22: Auto Rule
A23: marketII_tableTitle | B23: Bảng chi tiết Cơ cấu dòng tiền Market II | C23: Cơ cấu dòng tiền Market II | D23: Bảng chi tiết Cơ cấu dòng tiền Market II | E23: Tiêu đề bảng chi tiết Market II | F23: INPUT
A24: marketII_tableSubtitle | B24: Trình bày đầy đủ các nhóm số dư BS TT2, phân bổ kỳ hạn, phân bổ kỳ thanh khoản và kỳ hạn/lãi suất bình quân. | C24: Cơ cấu dòng tiền Market II | D24: Bảng chi tiết Cơ cấu dòng tiền Market II | E24: Subtitle/mô tả dưới tiêu đề bảng chi tiết Market II | F24: INPUT
A25: marketII_tablePeriod | B25: =B31 -> 28/09/2026 | C25: Cơ cấu dòng tiền Market II | D25: Bảng chi tiết Cơ cấu dòng tiền Market II | E25: Kỳ báo cáo hiển thị trên pill của bảng; có thể đồng bộ với marketII_period | F25: INPUT
A26: marketII_tableUnit | B26: Nghìn tỷ VND | C26: Cơ cấu dòng tiền Market II | D26: Bảng chi tiết Cơ cấu dòng tiền Market II | E26: Đơn vị hiển thị trên pill và header chỉ tiêu | F26: INPUT
A27: marketII_tableCol_stt | B27: STT | C27: Cơ cấu dòng tiền Market II | D27: Bảng chi tiết Cơ cấu dòng tiền Market II | E27: Header cột STT | F27: INPUT
A28: marketII_tableCol_item | B28: Chỉ tiêu | C28: Cơ cấu dòng tiền Market II | D28: Bảng chi tiết Cơ cấu dòng tiền Market II | E28: Header cột Chỉ tiêu | F28: INPUT
A29: marketII_tableCol_itemUnit | B29: Nghìn tỷ VND | C29: Cơ cấu dòng tiền Market II | D29: Bảng chi tiết Cơ cấu dòng tiền Market II | E29: Đơn vị nhỏ trong header cột Chỉ tiêu | F29: INPUT
A30: marketII_tableCol_balanceGroup | B30: Số dư BS TT2 | C30: Cơ cấu dòng tiền Market II | D30: Bảng chi tiết Cơ cấu dòng tiền Market II | E30: Header nhóm Số dư BS TT2 | F30: INPUT
A31: marketII_tableCol_balanceDate | B31: =TEXT(C47,"dd/mm/yyyy") -> 28/09/2026 | C31: Cơ cấu dòng tiền Market II | D31: Bảng chi tiết Cơ cấu dòng tiền Market II | E31: Header cột ngày số dư BS TT2 | F31: INPUT
A32: marketII_tableCol_weight | B32: Tỷ trọng | C32: Cơ cấu dòng tiền Market II | D32: Bảng chi tiết Cơ cấu dòng tiền Market II | E32: Header cột Tỷ trọng | F32: INPUT
A33: marketII_tableCol_tenorGroup | B33: Biến động số dư BS | C33: Cơ cấu dòng tiền Market II | D33: Bảng chi tiết Cơ cấu dòng tiền Market II | E33: Header nhóm Phân bổ kỳ hạn | F33: INPUT
A34: marketII_tableCol_mtd | B34: =E47 -> +/- 27/9/2026 | C34: Cơ cấu dòng tiền Market II | D34: Bảng chi tiết Cơ cấu dòng tiền Market II | E34: Header cột biến động MTD | F34: INPUT
A35: marketII_tableCol_qtd | B35: =F47 -> +/- 31/8/2026 | C35: Cơ cấu dòng tiền Market II | D35: Bảng chi tiết Cơ cấu dòng tiền Market II | E35: Header cột biến động QTD | F35: INPUT
A36: marketII_tableCol_ytd | B36: =G47 -> +/- 31/12/2025 | C36: Cơ cấu dòng tiền Market II | D36: Bảng chi tiết Cơ cấu dòng tiền Market II | E36: Header cột biến động YTD | F36: INPUT
A37: marketII_tableCol_liquidityGroup | B37: ="Phân bổ kỳ thanh khoản BS tại "&TEXT(DATE(YEAR(B31), MONTH(B31),DAY(B31)),"dd/mm/yyyy") -> Phân bổ kỳ thanh khoản BS tại 28/09/2026 | C37: Cơ cấu dòng tiền Market II | D37: Bảng chi tiết Cơ cấu dòng tiền Market II | E37: Header nhóm Phân bổ kỳ thanh khoản BS | F37: INPUT
A38: marketII_tableCol_lt1m | B38: =H47 -> 1M | C38: Cơ cấu dòng tiền Market II | D38: Bảng chi tiết Cơ cấu dòng tiền Market II | E38: Header bucket thanh khoản dưới 1 tháng | F38: INPUT
A39: marketII_tableCol_m1_3 | B39: =I47 -> 1-3M | C39: Cơ cấu dòng tiền Market II | D39: Bảng chi tiết Cơ cấu dòng tiền Market II | E39: Header bucket thanh khoản 1-3 tháng | F39: INPUT
A40: marketII_tableCol_m3_6 | B40: =J47 -> 3-6M | C40: Cơ cấu dòng tiền Market II | D40: Bảng chi tiết Cơ cấu dòng tiền Market II | E40: Header bucket thanh khoản 3-6 tháng | F40: INPUT
A41: marketII_tableCol_m6_12 | B41: =K47 -> 6-12M | C41: Cơ cấu dòng tiền Market II | D41: Bảng chi tiết Cơ cấu dòng tiền Market II | E41: Header bucket thanh khoản 6-12 tháng | F41: INPUT
A42: marketII_tableCol_gt12 | B42: =L47 -> 12M | C42: Cơ cấu dòng tiền Market II | D42: Bảng chi tiết Cơ cấu dòng tiền Market II | E42: Header bucket thanh khoản trên 12 tháng | F42: INPUT
A43: marketII_tableCol_avgTenor | B43: =M47 -> Kỳ hạn bình quân | C43: Cơ cấu dòng tiền Market II | D43: Bảng chi tiết Cơ cấu dòng tiền Market II | E43: Header cột Kỳ hạn bình quân | F43: INPUT
A44: marketII_tableCol_avgRate | B44: =N47 -> Lãi suất bình quân | C44: Cơ cấu dòng tiền Market II | D44: Bảng chi tiết Cơ cấu dòng tiền Market II | E44: Header cột Lãi suất bình quân | F44: INPUT
A46: Bảng chi tiết Cơ cấu dòng tiền Market II
A47: STT | B47: Chỉ tiêu (Nghìn tỷ VND) | C47: =BS_TT2!C2 -> 46293 | D47: =BS_TT2!D2 -> Tỷ trọng | E47: ="+/- "&TEXT(BS_TT2!H2,"d/m/yyyy") -> +/- 27/9/2026 | F47: ="+/- "&TEXT(BS_TT2!I2,"d/m/yyyy") -> +/- 31/8/2026 | G47: ="+/- "&TEXT(BS_TT2!J2,"d/m/yyyy") -> +/- 31/12/2025 | H47: =BS_TT2!K2 -> 1M | I47: =BS_TT2!L2 -> 1-3M | J47: =BS_TT2!M2 -> 3-6M | K47: =BS_TT2!N2 -> 6-12M | L47: =BS_TT2!O2 -> 12M | M47: =BS_TT2!P2&" bình quân" -> Kỳ hạn bình quân | N47: =BS_TT2!Q2 -> Lãi suất bình quân | O47: Loại dòng (helper)
A48: 1 | B48: Gbond_Trading (On BS) | C48: =_xlfn.VALUETOTEXT(ROUND(BS_TT2!C3,1),0) -> 33.5 | D48: =BS_TT2!D3 -> 0.28803445 | E48: =_xlfn.VALUETOTEXT(ROUND(BS_TT2!E3,1),0) -> -4.6 | F48: =_xlfn.VALUETOTEXT(ROUND(BS_TT2!F3,1),0) -> -5.7 | G48: =_xlfn.VALUETOTEXT(ROUND(BS_TT2!G3,1),0) -> 8.5 | H48: =_xlfn.VALUETOTEXT(ROUND(BS_TT2!K3,1),0) -> 20.9 | I48: =_xlfn.VALUETOTEXT(ROUND(BS_TT2!L3,1),0) -> 12.6 | J48: =_xlfn.VALUETOTEXT(ROUND(BS_TT2!M3,1),0) -> 0 | K48: =_xlfn.VALUETOTEXT(ROUND(BS_TT2!N3,1),0) -> 0 | L48: =_xlfn.VALUETOTEXT(ROUND(BS_TT2!O3,1),0) -> 0 | M48: =_xlfn.VALUETOTEXT(ROUND(BS_TT2!P3,1),0) -> 1.1 | N48: Updating… | O48: normal
A49: 2 | B49: Gbond_Banking (On BS) | C49: =_xlfn.VALUETOTEXT(ROUND(BS_TT2!C4,1),0) -> 10.9 | D49: =BS_TT2!D4 -> 0.093467456 | E49: =_xlfn.VALUETOTEXT(ROUND(BS_TT2!E4,1),0) -> 0 | F49: =_xlfn.VALUETOTEXT(ROUND(BS_TT2!F4,1),0) -> 0 | G49: =_xlfn.VALUETOTEXT(ROUND(BS_TT2!G4,1),0) -> -6.1 | H49: =_xlfn.VALUETOTEXT(ROUND(BS_TT2!K4,1),0) -> 0 | I49: =_xlfn.VALUETOTEXT(ROUND(BS_TT2!L4,1),0) -> 0 | J49: =_xlfn.VALUETOTEXT(ROUND(BS_TT2!M4,1),0) -> 0 | K49: =_xlfn.VALUETOTEXT(ROUND(BS_TT2!N4,1),0) -> 0 | L49: =_xlfn.VALUETOTEXT(ROUND(BS_TT2!O4,1),0) -> 10.9 | M49: =_xlfn.VALUETOTEXT(ROUND(BS_TT2!P4,1),0) -> 12 | N49: Updating… | O49: normal
A50: 3 | B50: Gbond_Phụ trội chiết khấu | C50: =_xlfn.VALUETOTEXT(ROUND(BS_TT2!C5,1),0) -> 2.6 | D50: =BS_TT2!D5 -> 0.022547257 | E50: =_xlfn.VALUETOTEXT(ROUND(BS_TT2!E5,1),0) -> 0.1 | F50: =_xlfn.VALUETOTEXT(ROUND(BS_TT2!F5,1),0) -> -0.7 | G50: =_xlfn.VALUETOTEXT(ROUND(BS_TT2!G5,1),0) -> -1.3 | H50: =_xlfn.VALUETOTEXT(ROUND(BS_TT2!K5,1),0) -> 2.6 | I50: =_xlfn.VALUETOTEXT(ROUND(BS_TT2!L5,1),0) -> 0 | J50: =_xlfn.VALUETOTEXT(ROUND(BS_TT2!M5,1),0) -> 0 | K50: =_xlfn.VALUETOTEXT(ROUND(BS_TT2!N5,1),0) -> 0 | L50: =_xlfn.VALUETOTEXT(ROUND(BS_TT2!O5,1),0) -> 0 | M50: =_xlfn.VALUETOTEXT(ROUND(BS_TT2!P5,1),0) -> 0.5 | N50: Updating… | O50: normal
A51: 4 | B51: FIBond (including PTCK) | C51: =_xlfn.VALUETOTEXT(ROUND(BS_TT2!C6,1),0) -> 37.4 | D51: =BS_TT2!D6 -> 0.32154113 | E51: =_xlfn.VALUETOTEXT(ROUND(BS_TT2!E6,1),0) -> 0 | F51: =_xlfn.VALUETOTEXT(ROUND(BS_TT2!F6,1),0) -> 1 | G51: =_xlfn.VALUETOTEXT(ROUND(BS_TT2!G6,1),0) -> -3.1 | H51: =_xlfn.VALUETOTEXT(ROUND(BS_TT2!K6,1),0) -> 1.3 | I51: =_xlfn.VALUETOTEXT(ROUND(BS_TT2!L6,1),0) -> 9 | J51: =_xlfn.VALUETOTEXT(ROUND(BS_TT2!M6,1),0) -> 2.4 | K51: =_xlfn.VALUETOTEXT(ROUND(BS_TT2!N6,1),0) -> 20.9 | L51: =_xlfn.VALUETOTEXT(ROUND(BS_TT2!O6,1),0) -> 3.8 | M51: =_xlfn.VALUETOTEXT(ROUND(BS_TT2!P6,1),0) -> 7 | N51: Updating… | O51: normal
A52: 5 | B52: Interbank Lending | C52: =_xlfn.VALUETOTEXT(ROUND(BS_TT2!C7,1),0) -> 29.3 | D52: =BS_TT2!D7 -> 0.25256196 | E52: =_xlfn.VALUETOTEXT(ROUND(BS_TT2!E7,1),0) -> 0.3 | F52: =_xlfn.VALUETOTEXT(ROUND(BS_TT2!F7,1),0) -> -1.2 | G52: =_xlfn.VALUETOTEXT(ROUND(BS_TT2!G7,1),0) -> 2.2 | H52: =_xlfn.VALUETOTEXT(ROUND(BS_TT2!K7,1),0) -> 18.1 | I52: =_xlfn.VALUETOTEXT(ROUND(BS_TT2!L7,1),0) -> 4.3 | J52: =_xlfn.VALUETOTEXT(ROUND(BS_TT2!M7,1),0) -> 1.1 | K52: =_xlfn.VALUETOTEXT(ROUND(BS_TT2!N7,1),0) -> 5.8 | L52: =_xlfn.VALUETOTEXT(ROUND(BS_TT2!O7,1),0) -> 0 | M52: =_xlfn.VALUETOTEXT(ROUND(BS_TT2!P7,1),0) -> 2.5 | N52: Updating… | O52: normal
A53: 6 | B53: Mproduct Lending | C53: =_xlfn.VALUETOTEXT(ROUND(BS_TT2!C8,1),0) -> 2 | D53: =BS_TT2!D8 -> 0.017038128 | E53: =_xlfn.VALUETOTEXT(ROUND(BS_TT2!E8,1),0) -> 0 | F53: =_xlfn.VALUETOTEXT(ROUND(BS_TT2!F8,1),0) -> 0.5 | G53: =_xlfn.VALUETOTEXT(ROUND(BS_TT2!G8,1),0) -> 1.2 | H53: =_xlfn.VALUETOTEXT(ROUND(BS_TT2!K8,1),0) -> 0.1 | I53: =_xlfn.VALUETOTEXT(ROUND(BS_TT2!L8,1),0) -> 0.4 | J53: =_xlfn.VALUETOTEXT(ROUND(BS_TT2!M8,1),0) -> 0.8 | K53: =_xlfn.VALUETOTEXT(ROUND(BS_TT2!N8,1),0) -> 0.7 | L53: =_xlfn.VALUETOTEXT(ROUND(BS_TT2!O8,1),0) -> 0 | M53: =_xlfn.VALUETOTEXT(ROUND(BS_TT2!P8,1),0) -> 5 | N53: Updating… | O53: normal
A54: 7 | B54: Other Assets | C54: =_xlfn.VALUETOTEXT(ROUND(BS_TT2!C9,1),0) -> 0.6 | D54: =BS_TT2!D9 -> 0.0048096179 | E54: =_xlfn.VALUETOTEXT(ROUND(BS_TT2!E9,1),0) -> -2.8 | F54: =_xlfn.VALUETOTEXT(ROUND(BS_TT2!F9,1),0) -> -4.9 | G54: =_xlfn.VALUETOTEXT(ROUND(BS_TT2!G9,1),0) -> -2.4 | H54: =_xlfn.VALUETOTEXT(ROUND(BS_TT2!K9,1),0) -> 0.6 | I54: =_xlfn.VALUETOTEXT(ROUND(BS_TT2!L9,1),0) -> 0 | J54: =_xlfn.VALUETOTEXT(ROUND(BS_TT2!M9,1),0) -> 0 | K54: =_xlfn.VALUETOTEXT(ROUND(BS_TT2!N9,1),0) -> 0 | L54: =_xlfn.VALUETOTEXT(ROUND(BS_TT2!O9,1),0) -> 0 | M54: =_xlfn.VALUETOTEXT(ROUND(BS_TT2!P9,1),0) -> 0.5 | N54: Updating… | O54: normal
A55: I | B55: Total Assets | C55: =_xlfn.VALUETOTEXT(ROUND(BS_TT2!C10,1),0) -> 116.2 | D55: =BS_TT2!D10 -> 1 | E55: =_xlfn.VALUETOTEXT(ROUND(BS_TT2!E10,1),0) -> -7 | F55: =_xlfn.VALUETOTEXT(ROUND(BS_TT2!F10,1),0) -> -11 | G55: =_xlfn.VALUETOTEXT(ROUND(BS_TT2!G10,1),0) -> -0.9 | H55: =_xlfn.VALUETOTEXT(ROUND(BS_TT2!K10,1),0) -> 43.6 | I55: =_xlfn.VALUETOTEXT(ROUND(BS_TT2!L10,1),0) -> 26.3 | J55: =_xlfn.VALUETOTEXT(ROUND(BS_TT2!M10,1),0) -> 4.3 | K55: =_xlfn.VALUETOTEXT(ROUND(BS_TT2!N10,1),0) -> 27.3 | L55: =_xlfn.VALUETOTEXT(ROUND(BS_TT2!O10,1),0) -> 14.6 | M55: =_xlfn.VALUETOTEXT(ROUND(BS_TT2!P10,1),0) -> 4.4 | N55: Updating… | O55: total
A56: 1 | B56: Repo/OMO | C56: =_xlfn.VALUETOTEXT(ROUND(BS_TT2!C11,1),0) -> 33.6 | D56: =BS_TT2!D11 -> 0.28963295 | E56: =_xlfn.VALUETOTEXT(ROUND(BS_TT2!E11,1),0) -> 0 | F56: =_xlfn.VALUETOTEXT(ROUND(BS_TT2!F11,1),0) -> -4.7 | G56: =_xlfn.VALUETOTEXT(ROUND(BS_TT2!G11,1),0) -> 4.8 | H56: =_xlfn.VALUETOTEXT(ROUND(BS_TT2!K11,1),0) -> 21.1 | I56: =_xlfn.VALUETOTEXT(ROUND(BS_TT2!L11,1),0) -> 12.6 | J56: =_xlfn.VALUETOTEXT(ROUND(BS_TT2!M11,1),0) -> 0 | K56: =_xlfn.VALUETOTEXT(ROUND(BS_TT2!N11,1),0) -> 0 | L56: =_xlfn.VALUETOTEXT(ROUND(BS_TT2!O11,1),0) -> 0 | M56: =_xlfn.VALUETOTEXT(ROUND(BS_TT2!P11,1),0) -> 1.1 | N56: Updating… | O56: normal
A57: 2 | B57: Interbank borrowing | C57: =_xlfn.VALUETOTEXT(ROUND(BS_TT2!C12,1),0) -> 35.6 | D57: =BS_TT2!D12 -> 0.30648804 | E57: =_xlfn.VALUETOTEXT(ROUND(BS_TT2!E12,1),0) -> -4 | F57: =_xlfn.VALUETOTEXT(ROUND(BS_TT2!F12,1),0) -> -1.6 | G57: =_xlfn.VALUETOTEXT(ROUND(BS_TT2!G12,1),0) -> 1.4 | H57: =_xlfn.VALUETOTEXT(ROUND(BS_TT2!K12,1),0) -> 18.8 | I57: =_xlfn.VALUETOTEXT(ROUND(BS_TT2!L12,1),0) -> 9 | J57: =_xlfn.VALUETOTEXT(ROUND(BS_TT2!M12,1),0) -> 6.1 | K57: =_xlfn.VALUETOTEXT(ROUND(BS_TT2!N12,1),0) -> 1.7 | L57: =_xlfn.VALUETOTEXT(ROUND(BS_TT2!O12,1),0) -> 0 | M57: =_xlfn.VALUETOTEXT(ROUND(BS_TT2!P12,1),0) -> 1.9 | N57: Updating… | O57: normal
A58: 3 | B58: Casa FD Fund FI | C58: =_xlfn.VALUETOTEXT(ROUND(BS_TT2!C13,1),0) -> 11.1 | D58: =BS_TT2!D13 -> 0.095759166 | E58: =_xlfn.VALUETOTEXT(ROUND(BS_TT2!E13,1),0) -> 0 | F58: =_xlfn.VALUETOTEXT(ROUND(BS_TT2!F13,1),0) -> -3.7 | G58: =_xlfn.VALUETOTEXT(ROUND(BS_TT2!G13,1),0) -> -2.3 | H58: =_xlfn.VALUETOTEXT(ROUND(BS_TT2!K13,1),0) -> 1.6 | I58: =_xlfn.VALUETOTEXT(ROUND(BS_TT2!L13,1),0) -> 9.5 | J58: =_xlfn.VALUETOTEXT(ROUND(BS_TT2!M13,1),0) -> 0 | K58: =_xlfn.VALUETOTEXT(ROUND(BS_TT2!N13,1),0) -> 0 | L58: =_xlfn.VALUETOTEXT(ROUND(BS_TT2!O13,1),0) -> 0 | M58: =_xlfn.VALUETOTEXT(ROUND(BS_TT2!P13,1),0) -> 1.8 | N58: Updating… | O58: normal
A59: 4 | B59: PHGTCG | C59: =_xlfn.VALUETOTEXT(ROUND(BS_TT2!C14,1),0) -> 6.5 | D59: =BS_TT2!D14 -> 0.055953073 | E59: =_xlfn.VALUETOTEXT(ROUND(BS_TT2!E14,1),0) -> 0 | F59: =_xlfn.VALUETOTEXT(ROUND(BS_TT2!F14,1),0) -> 0 | G59: =_xlfn.VALUETOTEXT(ROUND(BS_TT2!G14,1),0) -> -4.4 | H59: =_xlfn.VALUETOTEXT(ROUND(BS_TT2!K14,1),0) -> 2 | I59: =_xlfn.VALUETOTEXT(ROUND(BS_TT2!L14,1),0) -> 3.5 | J59: =_xlfn.VALUETOTEXT(ROUND(BS_TT2!M14,1),0) -> 0 | K59: =_xlfn.VALUETOTEXT(ROUND(BS_TT2!N14,1),0) -> 1 | L59: =_xlfn.VALUETOTEXT(ROUND(BS_TT2!O14,1),0) -> 0 | M59: =_xlfn.VALUETOTEXT(ROUND(BS_TT2!P14,1),0) -> 2.6 | N59: Updating… | O59: normal
... A63: III | B63: Excess Deposit from TT1 | C63: =_xlfn.VALUETOTEXT(ROUND(BS_TT2!C18,1),0) -> 14.6 | D63: =BS_TT2!D18 -> 0.12563885 | E63: =_xlfn.VALUETOTEXT(ROUND(BS_TT2!E18,1),0) -> -2.8 | F63: =_xlfn.VALUETOTEXT(ROUND(BS_TT2!F18,1),0) -> -1.3 | G63: =_xlfn.VALUETOTEXT(ROUND(BS_TT2!G18,1),0) -> 0.1 | H63: =_xlfn.VALUETOTEXT(ROUND(BS_TT2!K18,1),0) -> 7.6 | I63: =_xlfn.VALUETOTEXT(ROUND(BS_TT2!L18,1),0) -> 7 | J63: =_xlfn.VALUETOTEXT(ROUND(BS_TT2!M18,1),0) -> 0 | K63: =_xlfn.VALUETOTEXT(ROUND(BS_TT2!N18,1),0) -> 0 | L63: =_xlfn.VALUETOTEXT(ROUND(BS_TT2!O18,1),0) -> 0 | M63: =_xlfn.VALUETOTEXT(ROUND(BS_TT2!P18,1),0) -> 1.2 | N63: Updating… | O63: total
A64: IV | B64: Liquidity GAP (theo tính chất thanh khoản) | C64: =_xlfn.VALUETOTEXT(ROUND(BS_TT2!C19,1),0) -> -10.1 | D64: =BS_TT2!D19 -> 0 | E64: =_xlfn.VALUETOTEXT(ROUND(BS_TT2!E19,1),0) -> -0.3 | F64: =_xlfn.VALUETOTEXT(ROUND(BS_TT2!F19,1),0) -> -5.6 | G64: =_xlfn.VALUETOTEXT(ROUND(BS_TT2!G19,1),0) -> 6.7 | H64: =_xlfn.VALUETOTEXT(ROUND(BS_TT2!K19,1),0) -> -10.1 | I64: =_xlfn.VALUETOTEXT(ROUND(BS_TT2!L19,1),0) -> -15.4 | J64: =_xlfn.VALUETOTEXT(ROUND(BS_TT2!M19,1),0) -> -1.8 | K64: =_xlfn.VALUETOTEXT(ROUND(BS_TT2!N19,1),0) -> 24.7 | L64: =_xlfn.VALUETOTEXT(ROUND(BS_TT2!O19,1),0) -> 2.6 | N64: Updating… | O64: gap
A65: V | B65: Repricing GAP (theo kỳ Tái định giá lãi suất) | C65: =_xlfn.VALUETOTEXT(ROUND(BS_TT2!C22,1),0) -> -10.1 | D65: =BS_TT2!D22 -> 0 | E65: =_xlfn.VALUETOTEXT(ROUND(BS_TT2!E22,1),0) -> -0.3 | F65: =_xlfn.VALUETOTEXT(ROUND(BS_TT2!F22,1),0) -> -5.6 | G65: =_xlfn.VALUETOTEXT(ROUND(BS_TT2!G22,1),0) -> 6.7 | H65: =_xlfn.VALUETOTEXT(ROUND(BS_TT2!K22,1),0) -> -10.1 | I65: =_xlfn.VALUETOTEXT(ROUND(BS_TT2!L22,1),0) -> -15.4 | J65: =_xlfn.VALUETOTEXT(ROUND(BS_TT2!M22,1),0) -> -1.8 | K65: =_xlfn.VALUETOTEXT(ROUND(BS_TT2!N22,1),0) -> 24.7 | L65: =_xlfn.VALUETOTEXT(ROUND(BS_TT2!O22,1),0) -> 2.6 | N65: Updating… | O65: gap
A66: 1 | B66: Repricing GAP_lũy kế (theo kỳ Tái định giá lãi suất) | C66: =_xlfn.VALUETOTEXT(ROUND(BS_TT2!C23,1),0) -> -10.1 | D66: =BS_TT2!D23 -> 0 | E66: =_xlfn.VALUETOTEXT(ROUND(BS_TT2!E23,1),0) -> -0.3 | F66: =_xlfn.VALUETOTEXT(ROUND(BS_TT2!F23,1),0) -> -5.6 | G66: =_xlfn.VALUETOTEXT(ROUND(BS_TT2!G23,1),0) -> 6.7 | H66: =_xlfn.VALUETOTEXT(ROUND(BS_TT2!K23,1),0) -> -10.1 | I66: =_xlfn.VALUETOTEXT(ROUND(BS_TT2!L23,1),0) -> -25.5 | J66: =_xlfn.VALUETOTEXT(ROUND(BS_TT2!M23,1),0) -> -27.3 | K66: =_xlfn.VALUETOTEXT(ROUND(BS_TT2!N23,1),0) -> -2.6 | L66: =_xlfn.VALUETOTEXT(ROUND(BS_TT2!O23,1),0) -> 0 | N66: Updating… | O66: gap
A67: 2 | B67: Biến động NII nếu ls thay đổi 2% trong 3M tới (tỷ VND) | C67: =_xlfn.VALUETOTEXT(ROUND(BS_TT2!C25,1),0) -> -67.8 | D67: =BS_TT2!D25 -> 0 | E67: =_xlfn.VALUETOTEXT(ROUND(BS_TT2!E25,1),0) -> -1.1 | F67: =_xlfn.VALUETOTEXT(ROUND(BS_TT2!F25,1),0) -> -27 | G67: =_xlfn.VALUETOTEXT(ROUND(BS_TT2!G25,1),0) -> 34.3 | H67: =_xlfn.VALUETOTEXT(ROUND(BS_TT2!K25,1),0) -> -42.2 | I67: =_xlfn.VALUETOTEXT(ROUND(BS_TT2!L25,1),0) -> -25.6 | J67: =_xlfn.VALUETOTEXT(ROUND(BS_TT2!M25,1),0) -> 0 | K67: =_xlfn.VALUETOTEXT(ROUND(BS_TT2!N25,1),0) -> 0 | L67: =_xlfn.VALUETOTEXT(ROUND(BS_TT2!O25,1),0) -> 0 | N67: Updating… | O67: gap
A68: 3 | B68: Biến động NII nếu ls thay đổi 2% trong 6M tới (tỷ VND) | C68: =_xlfn.VALUETOTEXT(ROUND(BS_TT2!C27,1),0) -> -201.3 | D68: =BS_TT2!D27 -> 0 | E68: =_xlfn.VALUETOTEXT(ROUND(BS_TT2!E27,1),0) -> -2.5 | F68: =_xlfn.VALUETOTEXT(ROUND(BS_TT2!F27,1),0) -> -64 | G68: =_xlfn.VALUETOTEXT(ROUND(BS_TT2!G27,1),0) -> 2.1 | H68: =_xlfn.VALUETOTEXT(ROUND(BS_TT2!K27,1),0) -> -92.9 | I68: =_xlfn.VALUETOTEXT(ROUND(BS_TT2!L27,1),0) -> -102.4 | J68: =_xlfn.VALUETOTEXT(ROUND(BS_TT2!M27,1),0) -> -6 | K68: =_xlfn.VALUETOTEXT(ROUND(BS_TT2!N27,1),0) -> 0 | L68: =_xlfn.VALUETOTEXT(ROUND(BS_TT2!O27,1),0) -> 0 | N68: Updating… | O68: gap

Sheet Market II Input
A1: Cơ cấu dòng tiền Market II
A3: Key | B3: Nội dung | C3: Value
A4: marketIISummaryTitle | B4: Tiêu đề module | C4: Cơ cấu dòng tiền thanh khoản - Market II
A5: marketIISummarySub | B5: Mô tả module | C5: Tóm tắt các điểm nghẽn dòng tiền Market II theo kỳ hạn; đơn vị bảng là nghìn tỷ VND, riêng tác động NII là tỷ VND.
A6: marketII_period | B6: Kỳ báo cáo | C6: =TEXT(B27,"dd/mm/yyyy") -> 28/09/2026
A9: KPI Market II
A10: KPI | B10: Title | C10: Subtitle | D10: Value | E10: Unit | F10: Target | G10: Target Label | H10: Target Unit | I10: Note | J10: No Limit | K10: Status Override | L10: Usage Override | M10: Auto fields
A11: KPI 1 | B11: Khe hở thanh khoản lũy kế 1M | D11: =VALUE(H66) -> -10.13 | E11: Nghìn tỷ VND | F11: -22 | G11: Mục tiêu theo dõi tối đa | H11: nghìn tỷ VND | J11: false | M11: Status/Usage để trống nếu muốn HTML tự tính
A12: KPI 2 | B12: Khe hở thanh khoản lũy kế 3M | D12: =H66+I66 -> -35.62 | E12: Nghìn tỷ VND | F12: -30 | G12: Mục tiêu theo dõi tối đa | H12: nghìn tỷ VND | J12: false | M12: Status/Usage để trống nếu muốn HTML tự tính
A13: KPI 3 | B13: Khe hở tái định giá lũy kế 1M | D13: =VALUE(H68) -> -21.11 | E13: Nghìn tỷ VND | I13: Không áp dụng limit; chỉ theo dõi xu hướng nhạy cảm lãi suất. | J13: true | M13: Status/Usage để trống nếu muốn HTML tự tính
A14: KPI 4 | B14: Khe hở tái định giá lũy kế 3M | D14: =VALUE(I68) -> -12.8 | E14: Nghìn tỷ VND | I14: Không áp dụng limit; chỉ theo dõi xu hướng nhạy cảm lãi suất. | J14: true | M14: Status/Usage để trống nếu muốn HTML tự tính
A15: KPI 5 | B15: Kịch bản dự báo biến động NII trong 3M | C15: (nếu Lãi suất funding tăng thêm 2% so với hiện tại và duy trì trong 3M tới) | D15: =H69+I69 -> -97.6 | E15: Tỷ VND | F15: -100 | G15: Mục tiêu theo dõi | H15: tỷ VND | J15: false | M15: Status/Usage để trống nếu muốn HTML tự tính
A18: Insight Market II
A19: Insight | B19: Title | C19: Body | D19: Ghi chú
A20: Insight 1 | B20: Thanh khoản lũy kế | C20: Khe hở thanh khoản lũy kế 3M có xu hướng tăng chiều âm do tăng huy động LNH kì ngắn. | D20: Text tùy biến
A21: Insight 2 | B21: Tái định giá lũy kế | C21: Repricing GAP lũy kế 3M mở rộng trong phiên, mức độ nhạy cảm với biến động lãi suất ngắn hạn theo đó cũng tăng | D21: Text tùy biến
A22: Insight 3 | B22: Tác động NII | C22: Nếu lãi suất funding tăng thêm 2% so với hiện tại và duy trì trong 3M tới, biến động NII ước tính lỗ về NIM theo quy mô như chỉ số hiện tại | D22: Text tùy biến
A24: Key | B24: Value | C24: Module | D24: Group | E24: Note | F24: Auto | G24: Auto Rule
A25: marketII_tableTitle | B25: Bảng chi tiết Cơ cấu dòng tiền Market II | C25: Cơ cấu dòng tiền Market II | D25: Bảng chi tiết Cơ cấu dòng tiền Market II | E25: Tiêu đề bảng chi tiết Market II | F25: INPUT
A26: marketII_tableSubtitle | B26: Trình bày đầy đủ các nhóm số dư BS TT2, phân bổ kỳ hạn, phân bổ kỳ thanh khoản và kỳ hạn/lãi suất bình quân. | C26: Cơ cấu dòng tiền Market II | D26: Bảng chi tiết Cơ cấu dòng tiền Market II | E26: Subtitle/mô tả dưới tiêu đề bảng chi tiết Market II | F26: INPUT
A27: marketII_tablePeriod | B27: =B33 -> 28/09/2026 | C27: Cơ cấu dòng tiền Market II | D27: Bảng chi tiết Cơ cấu dòng tiền Market II | E27: Kỳ báo cáo hiển thị trên pill của bảng; có thể đồng bộ với marketII_period | F27: INPUT
A28: marketII_tableUnit | B28: Nghìn tỷ VND | C28: Cơ cấu dòng tiền Market II | D28: Bảng chi tiết Cơ cấu dòng tiền Market II | E28: Đơn vị hiển thị trên pill và header chỉ tiêu | F28: INPUT
A29: marketII_tableCol_stt | B29: STT | C29: Cơ cấu dòng tiền Market II | D29: Bảng chi tiết Cơ cấu dòng tiền Market II | E29: Header cột STT | F29: INPUT
A30: marketII_tableCol_item | B30: Chỉ tiêu | C30: Cơ cấu dòng tiền Market II | D30: Bảng chi tiết Cơ cấu dòng tiền Market II | E30: Header cột Chỉ tiêu | F30: INPUT
A31: marketII_tableCol_itemUnit | B31: Nghìn tỷ VND | C31: Cơ cấu dòng tiền Market II | D31: Bảng chi tiết Cơ cấu dòng tiền Market II | E31: Đơn vị nhỏ trong header cột Chỉ tiêu | F31: INPUT
A32: marketII_tableCol_balanceGroup | B32: Số dư BS TT2 | C32: Cơ cấu dòng tiền Market II | D32: Bảng chi tiết Cơ cấu dòng tiền Market II | E32: Header nhóm Số dư BS TT2 | F32: INPUT
A33: marketII_tableCol_balanceDate | B33: =TEXT(C49,"dd/mm/yyyy") -> 28/09/2026 | C33: Cơ cấu dòng tiền Market II | D33: Bảng chi tiết Cơ cấu dòng tiền Market II | E33: Header cột ngày số dư BS TT2 | F33: INPUT
A34: marketII_tableCol_weight | B34: Tỷ trọng | C34: Cơ cấu dòng tiền Market II | D34: Bảng chi tiết Cơ cấu dòng tiền Market II | E34: Header cột Tỷ trọng | F34: INPUT
A35: marketII_tableCol_tenorGroup | B35: Biến động số dư BS | C35: Cơ cấu dòng tiền Market II | D35: Bảng chi tiết Cơ cấu dòng tiền Market II | E35: Header nhóm Phân bổ kỳ hạn | F35: INPUT
A36: marketII_tableCol_mtd | B36: =E49 -> DtD | C36: Cơ cấu dòng tiền Market II | D36: Bảng chi tiết Cơ cấu dòng tiền Market II | E36: Header cột biến động MTD | F36: INPUT
A37: marketII_tableCol_qtd | B37: =F49 -> MtD | C37: Cơ cấu dòng tiền Market II | D37: Bảng chi tiết Cơ cấu dòng tiền Market II | E37: Header cột biến động QTD | F37: INPUT
A38: marketII_tableCol_ytd | B38: =G49 -> YtD | C38: Cơ cấu dòng tiền Market II | D38: Bảng chi tiết Cơ cấu dòng tiền Market II | E38: Header cột biến động YTD | F38: INPUT
A39: marketII_tableCol_liquidityGroup | B39: ="Phân bổ kỳ thanh khoản BS tại "&TEXT(DATE(YEAR(B33), MONTH(B33),DAY(B33)),"dd/mm/yyyy") -> Phân bổ kỳ thanh khoản BS tại 28/09/2026 | C39: Cơ cấu dòng tiền Market II | D39: Bảng chi tiết Cơ cấu dòng tiền Market II | E39: Header nhóm Phân bổ kỳ thanh khoản BS | F39: INPUT
A40: marketII_tableCol_lt1m | B40: =H49 -> 1M | C40: Cơ cấu dòng tiền Market II | D40: Bảng chi tiết Cơ cấu dòng tiền Market II | E40: Header bucket thanh khoản dưới 1 tháng | F40: INPUT
A41: marketII_tableCol_m1_3 | B41: =I49 -> 1-3M | C41: Cơ cấu dòng tiền Market II | D41: Bảng chi tiết Cơ cấu dòng tiền Market II | E41: Header bucket thanh khoản 1-3 tháng | F41: INPUT
A42: marketII_tableCol_m3_6 | B42: =J49 -> 3-6M | C42: Cơ cấu dòng tiền Market II | D42: Bảng chi tiết Cơ cấu dòng tiền Market II | E42: Header bucket thanh khoản 3-6 tháng | F42: INPUT
A43: marketII_tableCol_m6_12 | B43: =K49 -> 6-12M | C43: Cơ cấu dòng tiền Market II | D43: Bảng chi tiết Cơ cấu dòng tiền Market II | E43: Header bucket thanh khoản 6-12 tháng | F43: INPUT
A44: marketII_tableCol_gt12 | B44: =L49 -> 12M | C44: Cơ cấu dòng tiền Market II | D44: Bảng chi tiết Cơ cấu dòng tiền Market II | E44: Header bucket thanh khoản trên 12 tháng | F44: INPUT
A45: marketII_tableCol_avgTenor | B45: =M49 -> Kỳ hạn | C45: Cơ cấu dòng tiền Market II | D45: Bảng chi tiết Cơ cấu dòng tiền Market II | E45: Header cột Kỳ hạn bình quân | F45: INPUT
A46: marketII_tableCol_avgRate | B46: =N49 -> Lãi suất bình quân | C46: Cơ cấu dòng tiền Market II | D46: Bảng chi tiết Cơ cấu dòng tiền Market II | E46: Header cột Lãi suất bình quân | F46: INPUT
A48: Bảng chi tiết Cơ cấu dòng tiền Market II
A49: STT | B49: Chỉ tiêu (Nghìn tỷ VND) | C49: =TEXT(BS_TT2!C2,"dd/mm/yy") -> 28/09/26 | D49: =BS_TT2!D2 -> Tỷ trọng | E49: =BS_TT2!E2 -> DtD | F49: =BS_TT2!F2 -> MtD | G49: =BS_TT2!G2 -> YtD | H49: =BS_TT2!K2 -> 1M | I49: =BS_TT2!L2 -> 1-3M | J49: =BS_TT2!M2 -> 3-6M | K49: =BS_TT2!N2 -> 6-12M | L49: =BS_TT2!O2 -> 12M | M49: =BS_TT2!P2 -> Kỳ hạn | N49: =BS_TT2!Q2 -> Lãi suất bình quân | O49: Loại dòng (helper)
A50: 1 | B50: Gbond_Trading (On BS) | C50: =_xlfn.VALUETOTEXT(ROUND(BS_TT2!C3,1),0) -> 33.5 | D50: =BS_TT2!D3 -> 0.28803445 | E50: =_xlfn.VALUETOTEXT(ROUND(BS_TT2!E3,1),0) -> -4.6 | F50: =_xlfn.VALUETOTEXT(ROUND(BS_TT2!F3,1),0) -> -5.7 | G50: =_xlfn.VALUETOTEXT(ROUND(BS_TT2!G3,1),0) -> 8.5 | H50: =_xlfn.VALUETOTEXT(ROUND(BS_TT2!K3,1),0) -> 20.9 | I50: =_xlfn.VALUETOTEXT(ROUND(BS_TT2!L3,1),0) -> 12.6 | J50: =_xlfn.VALUETOTEXT(ROUND(BS_TT2!M3,1),0) -> 0 | K50: =_xlfn.VALUETOTEXT(ROUND(BS_TT2!N3,1),0) -> 0 | L50: =_xlfn.VALUETOTEXT(ROUND(BS_TT2!O3,1),0) -> 0 | M50: =_xlfn.VALUETOTEXT(ROUND(BS_TT2!P3,1),0) -> 1.1 | N50: Updating… | O50: normal
A51: 2 | B51: Gbond_Banking (On BS) | C51: =_xlfn.VALUETOTEXT(ROUND(BS_TT2!C4,1),0) -> 10.9 | D51: =BS_TT2!D4 -> 0.093467456 | E51: =_xlfn.VALUETOTEXT(ROUND(BS_TT2!E4,1),0) -> 0 | F51: =_xlfn.VALUETOTEXT(ROUND(BS_TT2!F4,1),0) -> 0 | G51: =_xlfn.VALUETOTEXT(ROUND(BS_TT2!G4,1),0) -> -6.1 | H51: =_xlfn.VALUETOTEXT(ROUND(BS_TT2!K4,1),0) -> 0 | I51: =_xlfn.VALUETOTEXT(ROUND(BS_TT2!L4,1),0) -> 0 | J51: =_xlfn.VALUETOTEXT(ROUND(BS_TT2!M4,1),0) -> 0 | K51: =_xlfn.VALUETOTEXT(ROUND(BS_TT2!N4,1),0) -> 0 | L51: =_xlfn.VALUETOTEXT(ROUND(BS_TT2!O4,1),0) -> 10.9 | M51: =_xlfn.VALUETOTEXT(ROUND(BS_TT2!P4,1),0) -> 12 | N51: Updating… | O51: normal
A52: 3 | B52: Gbond_Phụ trội chiết khấu | C52: =_xlfn.VALUETOTEXT(ROUND(BS_TT2!C5,1),0) -> 2.6 | D52: =BS_TT2!D5 -> 0.022547257 | E52: =_xlfn.VALUETOTEXT(ROUND(BS_TT2!E5,1),0) -> 0.1 | F52: =_xlfn.VALUETOTEXT(ROUND(BS_TT2!F5,1),0) -> -0.7 | G52: =_xlfn.VALUETOTEXT(ROUND(BS_TT2!G5,1),0) -> -1.3 | H52: =_xlfn.VALUETOTEXT(ROUND(BS_TT2!K5,1),0) -> 2.6 | I52: =_xlfn.VALUETOTEXT(ROUND(BS_TT2!L5,1),0) -> 0 | J52: =_xlfn.VALUETOTEXT(ROUND(BS_TT2!M5,1),0) -> 0 | K52: =_xlfn.VALUETOTEXT(ROUND(BS_TT2!N5,1),0) -> 0 | L52: =_xlfn.VALUETOTEXT(ROUND(BS_TT2!O5,1),0) -> 0 | M52: =_xlfn.VALUETOTEXT(ROUND(BS_TT2!P5,1),0) -> 0.5 | N52: Updating… | O52: normal
A53: 4 | B53: FIBond (including PTCK) | C53: =_xlfn.VALUETOTEXT(ROUND(BS_TT2!C6,1),0) -> 37.4 | D53: =BS_TT2!D6 -> 0.32154113 | E53: =_xlfn.VALUETOTEXT(ROUND(BS_TT2!E6,1),0) -> 0 | F53: =_xlfn.VALUETOTEXT(ROUND(BS_TT2!F6,1),0) -> 1 | G53: =_xlfn.VALUETOTEXT(ROUND(BS_TT2!G6,1),0) -> -3.1 | H53: =_xlfn.VALUETOTEXT(ROUND(BS_TT2!K6,1),0) -> 1.3 | I53: =_xlfn.VALUETOTEXT(ROUND(BS_TT2!L6,1),0) -> 9 | J53: =_xlfn.VALUETOTEXT(ROUND(BS_TT2!M6,1),0) -> 2.4 | K53: =_xlfn.VALUETOTEXT(ROUND(BS_TT2!N6,1),0) -> 20.9 | L53: =_xlfn.VALUETOTEXT(ROUND(BS_TT2!O6,1),0) -> 3.8 | M53: =_xlfn.VALUETOTEXT(ROUND(BS_TT2!P6,1),0) -> 7 | N53: Updating… | O53: normal
A54: 5 | B54: Interbank Lending | C54: =_xlfn.VALUETOTEXT(ROUND(BS_TT2!C7,1),0) -> 29.3 | D54: =BS_TT2!D7 -> 0.25256196 | E54: =_xlfn.VALUETOTEXT(ROUND(BS_TT2!E7,1),0) -> 0.3 | F54: =_xlfn.VALUETOTEXT(ROUND(BS_TT2!F7,1),0) -> -1.2 | G54: =_xlfn.VALUETOTEXT(ROUND(BS_TT2!G7,1),0) -> 2.2 | H54: =_xlfn.VALUETOTEXT(ROUND(BS_TT2!K7,1),0) -> 18.1 | I54: =_xlfn.VALUETOTEXT(ROUND(BS_TT2!L7,1),0) -> 4.3 | J54: =_xlfn.VALUETOTEXT(ROUND(BS_TT2!M7,1),0) -> 1.1 | K54: =_xlfn.VALUETOTEXT(ROUND(BS_TT2!N7,1),0) -> 5.8 | L54: =_xlfn.VALUETOTEXT(ROUND(BS_TT2!O7,1),0) -> 0 | M54: =_xlfn.VALUETOTEXT(ROUND(BS_TT2!P7,1),0) -> 2.5 | N54: Updating… | O54: normal
A55: 6 | B55: Mproduct Lending | C55: =_xlfn.VALUETOTEXT(ROUND(BS_TT2!C9,1),0) -> 0.6 | D55: =BS_TT2!D8 -> 0.017038128 | E55: =_xlfn.VALUETOTEXT(ROUND(BS_TT2!E9,1),0) -> -2.8 | F55: =_xlfn.VALUETOTEXT(ROUND(BS_TT2!F9,1),0) -> -4.9 | G55: =_xlfn.VALUETOTEXT(ROUND(BS_TT2!G9,1),0) -> -2.4 | H55: =_xlfn.VALUETOTEXT(ROUND(BS_TT2!K9,1),0) -> 0.6 | I55: =_xlfn.VALUETOTEXT(ROUND(BS_TT2!L9,1),0) -> 0 | J55: =_xlfn.VALUETOTEXT(ROUND(BS_TT2!M9,1),0) -> 0 | K55: =_xlfn.VALUETOTEXT(ROUND(BS_TT2!N9,1),0) -> 0 | L55: =_xlfn.VALUETOTEXT(ROUND(BS_TT2!O9,1),0) -> 0 | M55: =_xlfn.VALUETOTEXT(ROUND(BS_TT2!P9,1),0) -> 0.5 | N55: Updating… | O55: normal
A56: 7 | B56: Other Assets | C56: =_xlfn.VALUETOTEXT(ROUND(BS_TT2!C10,1),0) -> 116.2 | D56: =BS_TT2!D9 -> 0.0048096179 | E56: =_xlfn.VALUETOTEXT(ROUND(BS_TT2!E10,1),0) -> -7 | F56: =_xlfn.VALUETOTEXT(ROUND(BS_TT2!F10,1),0) -> -11 | G56: =_xlfn.VALUETOTEXT(ROUND(BS_TT2!G10,1),0) -> -0.9 | H56: =_xlfn.VALUETOTEXT(ROUND(BS_TT2!K10,1),0) -> 43.6 | I56: =_xlfn.VALUETOTEXT(ROUND(BS_TT2!L10,1),0) -> 26.3 | J56: =_xlfn.VALUETOTEXT(ROUND(BS_TT2!M10,1),0) -> 4.3 | K56: =_xlfn.VALUETOTEXT(ROUND(BS_TT2!N10,1),0) -> 27.3 | L56: =_xlfn.VALUETOTEXT(ROUND(BS_TT2!O10,1),0) -> 14.6 | M56: =_xlfn.VALUETOTEXT(ROUND(BS_TT2!P10,1),0) -> 4.4 | N56: Updating… | O56: normal
A57: I | B57: Total Assets | C57: =_xlfn.VALUETOTEXT(ROUND(BS_TT2!C11,1),0) -> 33.6 | D57: =BS_TT2!D10 -> 1 | E57: =_xlfn.VALUETOTEXT(ROUND(BS_TT2!E11,1),0) -> 0 | F57: =_xlfn.VALUETOTEXT(ROUND(BS_TT2!F11,1),0) -> -4.7 | G57: =_xlfn.VALUETOTEXT(ROUND(BS_TT2!G11,1),0) -> 4.8 | H57: =_xlfn.VALUETOTEXT(ROUND(BS_TT2!K11,1),0) -> 21.1 | I57: =_xlfn.VALUETOTEXT(ROUND(BS_TT2!L11,1),0) -> 12.6 | J57: =_xlfn.VALUETOTEXT(ROUND(BS_TT2!M11,1),0) -> 0 | K57: =_xlfn.VALUETOTEXT(ROUND(BS_TT2!N11,1),0) -> 0 | L57: =_xlfn.VALUETOTEXT(ROUND(BS_TT2!O11,1),0) -> 0 | M57: =_xlfn.VALUETOTEXT(ROUND(BS_TT2!P11,1),0) -> 1.1 | N57: Updating… | O57: total
A58: 1 | B58: Repo/OMO | C58: =_xlfn.VALUETOTEXT(ROUND(BS_TT2!C12,1),0) -> 35.6 | D58: =BS_TT2!D11 -> 0.28963295 | E58: =_xlfn.VALUETOTEXT(ROUND(BS_TT2!E12,1),0) -> -4 | F58: =_xlfn.VALUETOTEXT(ROUND(BS_TT2!F12,1),0) -> -1.6 | G58: =_xlfn.VALUETOTEXT(ROUND(BS_TT2!G12,1),0) -> 1.4 | H58: =_xlfn.VALUETOTEXT(ROUND(BS_TT2!K12,1),0) -> 18.8 | I58: =_xlfn.VALUETOTEXT(ROUND(BS_TT2!L12,1),0) -> 9 | J58: =_xlfn.VALUETOTEXT(ROUND(BS_TT2!M12,1),0) -> 6.1 | K58: =_xlfn.VALUETOTEXT(ROUND(BS_TT2!N12,1),0) -> 1.7 | L58: =_xlfn.VALUETOTEXT(ROUND(BS_TT2!O12,1),0) -> 0 | M58: =_xlfn.VALUETOTEXT(ROUND(BS_TT2!P12,1),0) -> 1.9 | N58: Updating… | O58: normal
A59: 2 | B59: Interbank borrowing | C59: =_xlfn.VALUETOTEXT(ROUND(BS_TT2!C13,1),0) -> 11.1 | D59: =BS_TT2!D12 -> 0.30648804 | E59: =_xlfn.VALUETOTEXT(ROUND(BS_TT2!E13,1),0) -> 0 | F59: =_xlfn.VALUETOTEXT(ROUND(BS_TT2!F13,1),0) -> -3.7 | G59: =_xlfn.VALUETOTEXT(ROUND(BS_TT2!G13,1),0) -> -2.3 | H59: =_xlfn.VALUETOTEXT(ROUND(BS_TT2!K13,1),0) -> 1.6 | I59: =_xlfn.VALUETOTEXT(ROUND(BS_TT2!L13,1),0) -> 9.5 | J59: =_xlfn.VALUETOTEXT(ROUND(BS_TT2!M13,1),0) -> 0 | K59: =_xlfn.VALUETOTEXT(ROUND(BS_TT2!N13,1),0) -> 0 | L59: =_xlfn.VALUETOTEXT(ROUND(BS_TT2!O13,1),0) -> 0 | M59: =_xlfn.VALUETOTEXT(ROUND(BS_TT2!P13,1),0) -> 1.8 | N59: Updating… | O59: normal
A60: 3 | B60: Casa FD Fund FI | C60: =_xlfn.VALUETOTEXT(ROUND(BS_TT2!C14,1),0) -> 6.5 | D60: =BS_TT2!D13 -> 0.095759166 | E60: =_xlfn.VALUETOTEXT(ROUND(BS_TT2!E14,1),0) -> 0 | F60: =_xlfn.VALUETOTEXT(ROUND(BS_TT2!F14,1),0) -> 0 | G60: =_xlfn.VALUETOTEXT(ROUND(BS_TT2!G14,1),0) -> -4.4 | H60: =_xlfn.VALUETOTEXT(ROUND(BS_TT2!K14,1),0) -> 2 | I60: =_xlfn.VALUETOTEXT(ROUND(BS_TT2!L14,1),0) -> 3.5 | J60: =_xlfn.VALUETOTEXT(ROUND(BS_TT2!M14,1),0) -> 0 | K60: =_xlfn.VALUETOTEXT(ROUND(BS_TT2!N14,1),0) -> 1 | L60: =_xlfn.VALUETOTEXT(ROUND(BS_TT2!O14,1),0) -> 0 | M60: =_xlfn.VALUETOTEXT(ROUND(BS_TT2!P14,1),0) -> 2.6 | N60: Updating… | O60: normal
A61: 4 | B61: PHGTCG | C61: =_xlfn.VALUETOTEXT(ROUND(BS_TT2!C15,1),0) -> 2.7 | D61: =BS_TT2!D14 -> 0.055953073 | E61: =_xlfn.VALUETOTEXT(ROUND(BS_TT2!E15,1),0) -> -0.2 | F61: =_xlfn.VALUETOTEXT(ROUND(BS_TT2!F15,1),0) -> 0.3 | G61: =_xlfn.VALUETOTEXT(ROUND(BS_TT2!G15,1),0) -> -0.4 | H61: =_xlfn.VALUETOTEXT(ROUND(BS_TT2!K15,1),0) -> 2.7 | I61: =_xlfn.VALUETOTEXT(ROUND(BS_TT2!L15,1),0) -> 0 | J61: =_xlfn.VALUETOTEXT(ROUND(BS_TT2!M15,1),0) -> 0 | K61: =_xlfn.VALUETOTEXT(ROUND(BS_TT2!N15,1),0) -> 0 | L61: =_xlfn.VALUETOTEXT(ROUND(BS_TT2!O15,1),0) -> 0 | M61: =_xlfn.VALUETOTEXT(ROUND(BS_TT2!P15,1),0) -> 0.5 | N61: Updating… | O61: normal
A62: 5 | B62: Other Liabilities | C62: =_xlfn.VALUETOTEXT(ROUND(BS_TT2!C16,1),0) -> 12 | D62: =BS_TT2!D15 -> 0.023229937 | E62: =_xlfn.VALUETOTEXT(ROUND(BS_TT2!E16,1),0) -> 0 | F62: =_xlfn.VALUETOTEXT(ROUND(BS_TT2!F16,1),0) -> 0 | G62: =_xlfn.VALUETOTEXT(ROUND(BS_TT2!G16,1),0) -> 0 | H62: =_xlfn.VALUETOTEXT(ROUND(BS_TT2!K16,1),0) -> 0 | I62: =_xlfn.VALUETOTEXT(ROUND(BS_TT2!L16,1),0) -> 0 | J62: =_xlfn.VALUETOTEXT(ROUND(BS_TT2!M16,1),0) -> 0 | K62: =_xlfn.VALUETOTEXT(ROUND(BS_TT2!N16,1),0) -> 0 | L62: =_xlfn.VALUETOTEXT(ROUND(BS_TT2!O16,1),0) -> 12 | M62: =_xlfn.VALUETOTEXT(ROUND(BS_TT2!P16,1),0) -> 12 | N62: Updating… | O62: normal
A63: 6 | B63: Vốn TT1 tài trợ Gbond Banking | C63: =_xlfn.VALUETOTEXT(ROUND(BS_TT2!C17,1),0) -> 101.6 | D63: =BS_TT2!D16 -> 0.10329798 | E63: =_xlfn.VALUETOTEXT(ROUND(BS_TT2!E17,1),0) -> -4.2 | F63: =_xlfn.VALUETOTEXT(ROUND(BS_TT2!F17,1),0) -> -9.7 | G63: =_xlfn.VALUETOTEXT(ROUND(BS_TT2!G17,1),0) -> -1 | H63: =_xlfn.VALUETOTEXT(ROUND(BS_TT2!K17,1),0) -> 46.1 | I63: =_xlfn.VALUETOTEXT(ROUND(BS_TT2!L17,1),0) -> 34.6 | J63: =_xlfn.VALUETOTEXT(ROUND(BS_TT2!M17,1),0) -> 6.1 | K63: =_xlfn.VALUETOTEXT(ROUND(BS_TT2!N17,1),0) -> 2.7 | L63: =_xlfn.VALUETOTEXT(ROUND(BS_TT2!O17,1),0) -> 12 | M63: =_xlfn.VALUETOTEXT(ROUND(BS_TT2!P17,1),0) -> 2.8 | N63: Updating… | O63: normal
A64: II | B64: Total Liabilities | C64: =_xlfn.VALUETOTEXT(ROUND(BS_TT2!C18,1),0) -> 14.6 | D64: =BS_TT2!D17 -> 0.87436115 | E64: =_xlfn.VALUETOTEXT(ROUND(BS_TT2!E18,1),0) -> -2.8 | F64: =_xlfn.VALUETOTEXT(ROUND(BS_TT2!F18,1),0) -> -1.3 | G64: =_xlfn.VALUETOTEXT(ROUND(BS_TT2!G18,1),0) -> 0.1 | H64: =_xlfn.VALUETOTEXT(ROUND(BS_TT2!K18,1),0) -> 7.6 | I64: =_xlfn.VALUETOTEXT(ROUND(BS_TT2!L18,1),0) -> 7 | J64: =_xlfn.VALUETOTEXT(ROUND(BS_TT2!M18,1),0) -> 0 | K64: =_xlfn.VALUETOTEXT(ROUND(BS_TT2!N18,1),0) -> 0 | L64: =_xlfn.VALUETOTEXT(ROUND(BS_TT2!O18,1),0) -> 0 | M64: =_xlfn.VALUETOTEXT(ROUND(BS_TT2!P18,1),0) -> 1.2 | N64: Updating… | O64: total
A65: III | B65: Excess Deposit from TT1 | C65: =_xlfn.VALUETOTEXT(ROUND(BS_TT2!C19,1),0) -> -10.1 | D65: =BS_TT2!D18 -> 0.12563885 | E65: =_xlfn.VALUETOTEXT(ROUND(BS_TT2!E19,1),0) -> -0.3 | F65: =_xlfn.VALUETOTEXT(ROUND(BS_TT2!F19,1),0) -> -5.6 | G65: =_xlfn.VALUETOTEXT(ROUND(BS_TT2!G19,1),0) -> 6.7 | H65: =_xlfn.VALUETOTEXT(ROUND(BS_TT2!K19,1),0) -> -10.1 | I65: =_xlfn.VALUETOTEXT(ROUND(BS_TT2!L19,1),0) -> -15.4 | J65: =_xlfn.VALUETOTEXT(ROUND(BS_TT2!M19,1),0) -> -1.8 | K65: =_xlfn.VALUETOTEXT(ROUND(BS_TT2!N19,1),0) -> 24.7 | L65: =_xlfn.VALUETOTEXT(ROUND(BS_TT2!O19,1),0) -> 2.6 | M65: =_xlfn.VALUETOTEXT(ROUND(BS_TT2!P19,1),0) -> 0 | N65: Updating… | O65: total
A66: IV | B66: Liquidity GAP (theo tính chất thanh khoản) | C66: =_xlfn.VALUETOTEXT(ROUND(BS_TT2!C20,1),0) -> -10.1 | E66: =_xlfn.VALUETOTEXT(ROUND(BS_TT2!E20,1),0) -> -0.3 | F66: =_xlfn.VALUETOTEXT(ROUND(BS_TT2!F20,1),0) -> -5.6 | G66: =_xlfn.VALUETOTEXT(ROUND(BS_TT2!G20,1),0) -> 6.7 | H66: =_xlfn.VALUETOTEXT(ROUND(BS_TT2!K20,2),0) -> -10.13 | I66: =_xlfn.VALUETOTEXT(ROUND(BS_TT2!L20,2),0) -> -25.49 | J66: =_xlfn.VALUETOTEXT(ROUND(BS_TT2!M20,1),0) -> -27.3 | K66: =_xlfn.VALUETOTEXT(ROUND(BS_TT2!N20,1),0) -> -2.6 | L66: =_xlfn.VALUETOTEXT(ROUND(BS_TT2!O20,1),0) -> 0 | M66: =_xlfn.VALUETOTEXT(ROUND(BS_TT2!P20,1),0) -> 0 | N66: Updating… | O66: gap
A67: V | B67: Repricing GAP (theo kỳ Tái định giá lãi suất) | C67: =_xlfn.VALUETOTEXT(ROUND(BS_TT2!C21,1),0) -> -2.5 | E67: =_xlfn.VALUETOTEXT(ROUND(BS_TT2!E21,1),0) -> -3.1 | F67: =_xlfn.VALUETOTEXT(ROUND(BS_TT2!F21,1),0) -> -6.9 | G67: =_xlfn.VALUETOTEXT(ROUND(BS_TT2!G21,1),0) -> 6.8 | H67: =_xlfn.VALUETOTEXT(ROUND(BS_TT2!K23,2),0) -> -10.13 | I67: =_xlfn.VALUETOTEXT(ROUND(BS_TT2!L23,2),0) -> -25.49 | J67: =_xlfn.VALUETOTEXT(ROUND(BS_TT2!M23,1),0) -> -27.3 | K67: =_xlfn.VALUETOTEXT(ROUND(BS_TT2!N23,1),0) -> -2.6 | L67: =_xlfn.VALUETOTEXT(ROUND(BS_TT2!O23,1),0) -> 0 | M67: =_xlfn.VALUETOTEXT(ROUND(BS_TT2!P23,1),0) -> 0 | N67: Updating… | O67: gap
A68: 1 | B68: Repricing GAP_lũy kế (theo kỳ Tái định giá lãi suất) | C68: =_xlfn.VALUETOTEXT(ROUND(BS_TT2!C23,1),0) -> -10.1 | E68: =_xlfn.VALUETOTEXT(ROUND(BS_TT2!E23,1),0) -> -0.3 | F68: =_xlfn.VALUETOTEXT(ROUND(BS_TT2!F23,1),0) -> -5.6 | G68: =_xlfn.VALUETOTEXT(ROUND(BS_TT2!G23,1),0) -> 6.7 | H68: =_xlfn.VALUETOTEXT(ROUND(BS_TT2!K24,2),0) -> -21.11 | I68: =_xlfn.VALUETOTEXT(ROUND(BS_TT2!L24,2),0) -> -12.8 | J68: =_xlfn.VALUETOTEXT(ROUND(BS_TT2!M24,1),0) -> 0 | K68: =_xlfn.VALUETOTEXT(ROUND(BS_TT2!N24,1),0) -> 0 | L68: =_xlfn.VALUETOTEXT(ROUND(BS_TT2!O24,1),0) -> 0 | M68: =_xlfn.VALUETOTEXT(ROUND(BS_TT2!P24,1),0) -> 0 | N68: Updating… | O68: gap
A69: 2 | B69: Biến động NII nếu ls thay đổi 2% trong 3M tới (tỷ VND) | C69: =_xlfn.VALUETOTEXT(ROUND(BS_TT2!C26,1),0) -> -100.6 | E69: =_xlfn.VALUETOTEXT(ROUND(BS_TT2!E26,1),0) -> -1.2 | F69: =_xlfn.VALUETOTEXT(ROUND(BS_TT2!F26,1),0) -> -32 | G69: =_xlfn.VALUETOTEXT(ROUND(BS_TT2!G26,1),0) -> 1 | H69: =_xlfn.VALUETOTEXT(ROUND(BS_TT2!K26,1),0) -> -46.4 | I69: =_xlfn.VALUETOTEXT(ROUND(BS_TT2!L26,1),0) -> -51.2 | J69: =_xlfn.VALUETOTEXT(ROUND(BS_TT2!M26,1),0) -> -3 | K69: =_xlfn.VALUETOTEXT(ROUND(BS_TT2!N26,1),0) -> 0 | L69: =_xlfn.VALUETOTEXT(ROUND(BS_TT2!O26,1),0) -> 0 | M69: =_xlfn.VALUETOTEXT(ROUND(BS_TT2!P26,1),0) -> 0 | N69: Updating… | O69: gap
A70: 3 | B70: Biến động NII nếu ls thay đổi 2% trong 6M tới (tỷ VND) | C70: =_xlfn.VALUETOTEXT(ROUND(BS_TT2!C28,1),0) -> 0 | E70: =_xlfn.VALUETOTEXT(ROUND(BS_TT2!E28,1),0) -> 0 | F70: =_xlfn.VALUETOTEXT(ROUND(BS_TT2!F28,1),0) -> 0 | G70: =_xlfn.VALUETOTEXT(ROUND(BS_TT2!G28,1),0) -> 0 | H70: =_xlfn.VALUETOTEXT(ROUND(BS_TT2!K28,1),0) -> 0 | I70: =_xlfn.VALUETOTEXT(ROUND(BS_TT2!L28,1),0) -> 0 | J70: =_xlfn.VALUETOTEXT(ROUND(BS_TT2!M28,1),0) -> 0 | K70: =_xlfn.VALUETOTEXT(ROUND(BS_TT2!N28,1),0) -> 0 | L70: =_xlfn.VALUETOTEXT(ROUND(BS_TT2!O28,1),0) -> 0 | M70: =_xlfn.VALUETOTEXT(ROUND(BS_TT2!P28,1),0) -> 0 | N70: Updating… | O70: gap

Sheet AI Input>>

Sheet AI module
A1: Key | B1: Value | C1: Group | D1: Description | E1: How to use | F1: Module | G1: Field name | H1: Type | I1: Auto | K1: Loại key | L1: Ví dụ giá trị hợp lệ | M1: Ghi chú
A2: moduleNav_aiRecommend | B2: Góc tham khảo: AI sẽ nói gì về MLIR hôm nay :)? | C2: AI Module | D2: Tên tab menu module AI | E2: Sửa cột Value rồi import sheet Data Import vào HTML. Các key format dùng giá trị CSS như #RRGGBB, px, số độ đậm, hoặc font-family. | F2: Navigation | G2: Tên tab menu module AI | H2: Text | I2: Manual | K2: Color | L2: #F04438 | M2: Dùng mã màu HEX để kiểm soát màu chữ/viền/nhấn.
A3: aiRecommendModuleTitle | B3: AI khuyến nghị hành động trong ngày | C3: AI Module | D3: Tên module AI | E3: Sửa cột Value rồi import sheet Data Import vào HTML. Các key format dùng giá trị CSS như #RRGGBB, px, số độ đậm, hoặc font-family. | F3: Module Header | G3: Tên module AI | H3: Text | I3: Manual | K3: Font family | L3: Inter, Arial, sans-serif | M3: Nên giữ font fallback sau dấu phẩy.
A4: aiRecommendModuleDesc | B4: Tự động rà soát dữ liệu hiện có sau import để tạo checklist ngắn gọn theo từng góc nhìn quản trị. | C4: AI Module | D4: Mô tả module AI | E4: Sửa cột Value rồi import sheet Data Import vào HTML. Các key format dùng giá trị CSS như #RRGGBB, px, số độ đậm, hoặc font-family. | F4: Module Header | G4: Tiêu đề phụ / mô tả module | H4: Text | I4: Manual | K4: Font size | L4: 13px / 14px / 20px | M4: Dùng đơn vị px để HTML nhận chính xác.
A5: aiRecommendModuleBadge | B5: Market Risk AI | C5: AI Module | D5: Badge nhỏ trong module AI | E5: Sửa cột Value rồi import sheet Data Import vào HTML. Các key format dùng giá trị CSS như #RRGGBB, px, số độ đậm, hoặc font-family. | F5: Module Header | G5: Badge module | H5: Text | I5: Manual | K5: Font weight | L5: 400 / 500 / 600 / 700 / 850 / 900 | M5: Số càng lớn chữ càng đậm.
A6: aiRecommendTitle | B6: What does AI recommend for risk Today? | C6: AI Module | D6: Tiêu đề chính trước khi gen checklist | E6: Sửa cột Value rồi import sheet Data Import vào HTML. Các key format dùng giá trị CSS như #RRGGBB, px, số độ đậm, hoặc font-family. | F6: Hero | G6: Tiêu đề chính trước khi gen checklist | H6: Text | I6: Manual | K6: Gradient | L6: linear-gradient(90deg,#F04438,#F79009) | M6: Chỉ dùng cho key hỗ trợ gradient.
A7: aiRecommendDisclaimerHtml | B7: <b>Disclaimer:</b> Đây là nội dung gen tự động từ AI, chỉ để người đọc trải nghiệm và tham khảo thông tin gợi ý/lưu ý từ góc nhìn của AI. Không phải là khuyến nghị chính thức của QLRRTT&TK | C7: AI Module | D7: Nội dung disclaimer; HTML chỉ bôi đỏ/đậm chữ Disclaimer nếu HTML có CSS tương ứng | E7: Sửa cột Value rồi import sheet Data Import vào HTML. Các key format dùng giá trị CSS như #RRGGBB, px, số độ đậm, hoặc font-family. | F7: Hero | G7: Disclaimer dưới tiêu đề chính | H7: HTML | I7: Manual | K7: Disclaimer | L7: <b>Disclaimer:</b> ... | M7: Chỉ phần nằm trong thẻ <b>...</b> được HTML bôi đỏ/đậm nếu CSS hỗ trợ.
A8: aiRecommendSubtitle | B8: Mỗi lần bấm Generate, module sẽ rà soát lại dữ liệu đang hiển thị về Trading Gbond, MtM, Banking Gbond, Bond&CD-FI, Market II, thị trường và OMO để tạo checklist mới, không dùng lại checklist đã lưu trước đó. | C8: AI Module | D8: Subtitle module AI | E8: Sửa cột Value rồi import sheet Data Import vào HTML. Các key format dùng giá trị CSS như #RRGGBB, px, số độ đậm, hoặc font-family. | F8: Hero | G8: Tiêu đề phụ dưới disclaimer | H8: Text | I8: Manual
A9: aiRecommendBackButton | B9: Back | C9: AI Module | D9: Nút quay lại checklist trước | E9: Sửa cột Value rồi import sheet Data Import vào HTML. Các key format dùng giá trị CSS như #RRGGBB, px, số độ đậm, hoặc font-family. | F9: Controls | G9: Nút quay lại checklist trước | H9: Text | I9: Manual
A10: aiRecommendViewLeadership | B10: View lãnh đạo | C10: AI Module | D10: Tên view lãnh đạo | E10: Sửa cột Value rồi import sheet Data Import vào HTML. Các key format dùng giá trị CSS như #RRGGBB, px, số độ đậm, hoặc font-family. | F10: Controls | G10: Nút view lãnh đạo | H10: Text | I10: Manual
A11: aiRecommendViewSupervision | B11: View giám sát/khuyến nghị | C11: AI Module | D11: Tên view giám sát/khuyến nghị | E11: Sửa cột Value rồi import sheet Data Import vào HTML. Các key format dùng giá trị CSS như #RRGGBB, px, số độ đậm, hoặc font-family. | F11: Controls | G11: Nút view giám sát/khuyến nghị | H11: Text | I11: Manual
A12: aiRecommendViewExecution | B12: View đơn vị thực hiện | C12: AI Module | D12: Tên view đơn vị thực hiện | E12: Sửa cột Value rồi import sheet Data Import vào HTML. Các key format dùng giá trị CSS như #RRGGBB, px, số độ đậm, hoặc font-family. | F12: Controls | G12: Nút view đơn vị thực hiện | H12: Text | I12: Manual
A13: aiRecommendClearButton | B13: Xóa checklist hiện tại | C13: AI Module | D13: Nút xóa checklist hiện tại | E13: Sửa cột Value rồi import sheet Data Import vào HTML. Các key format dùng giá trị CSS như #RRGGBB, px, số độ đậm, hoặc font-family. | F13: Controls | G13: Nút xóa checklist hiện tại | H13: Text | I13: Manual
A14: aiRecommendGenerateButton | B14: Generate new risk recommendation | C14: AI Module | D14: Nút gen checklist mới | E14: Sửa cột Value rồi import sheet Data Import vào HTML. Các key format dùng giá trị CSS như #RRGGBB, px, số độ đậm, hoặc font-family. | F14: Controls | G14: Nút Generate checklist mới | H14: Text | I14: Manual
A15: aiRecommendStatusIdle | B15: Chưa sinh khuyến nghị | C15: AI Module | D15: Trạng thái ban đầu | E15: Sửa cột Value rồi import sheet Data Import vào HTML. Các key format dùng giá trị CSS như #RRGGBB, px, số độ đậm, hoặc font-family. | F15: Status | G15: Trạng thái khi chưa gen | H15: Text | I15: Manual
A16: aiRecommendStatusCleared | B16: Đã xóa checklist hiện tại | C16: AI Module | D16: Trạng thái sau khi xóa checklist | E16: Sửa cột Value rồi import sheet Data Import vào HTML. Các key format dùng giá trị CSS như #RRGGBB, px, số độ đậm, hoặc font-family. | F16: Status | G16: Trạng thái sau khi xóa | H16: Text | I16: Manual
A17: aiRecommendEmptyText | B17: Chưa có checklist trong phiên hiện tại. | C17: AI Module | D17: Nội dung empty state | E17: Sửa cột Value rồi import sheet Data Import vào HTML. Các key format dùng giá trị CSS như #RRGGBB, px, số độ đậm, hoặc font-family. | F17: Status | G17: Thông báo vùng output trống | H17: Text | I17: Manual
A18: aiRecommendScanLabel | B18: Rà soát mới | C18: AI Module | D18: Nhãn thời điểm scan | E18: Sửa cột Value rồi import sheet Data Import vào HTML. Các key format dùng giá trị CSS như #RRGGBB, px, số độ đậm, hoặc font-family. | F18: Generated View Labels | G18: Nhãn box góc nhìn rà soát | H18: Text | I18: Manual
A19: aiRecommendViewLabel | B19: View | C19: AI Module | D19: Nhãn lựa chọn view | E19: Sửa cột Value rồi import sheet Data Import vào HTML. Các key format dùng giá trị CSS như #RRGGBB, px, số độ đậm, hoặc font-family. | F19: Generated View Labels | G19: Nhãn view trong kết quả | H19: Text | I19: Manual
... A26: aiRecommendSnapshotMarketIINii | B26: Market II NII | C26: AI Module | D26: Nhãn box highlight Market II NII | E26: Sửa cột Value rồi import sheet Data Import vào HTML. Các key format dùng giá trị CSS như #RRGGBB, px, số độ đậm, hoặc font-family. | F26: Highlight Boxes | G26: Tên box highlight Market II NII | H26: Text | I26: Manual
A27: executiveTitleColor | B27: #F04438 | C27: Executive Format | D27: Màu chữ tiêu đề Executive Messages | E27: Sửa cột Value rồi import sheet Data Import vào HTML. Các key format dùng giá trị CSS như #RRGGBB, px, số độ đậm, hoặc font-family.
A28: executiveTitleFontFamily | B28: Inter, Arial, sans-serif | C28: Executive Format | D28: Font chữ tiêu đề Executive Messages | E28: Sửa cột Value rồi import sheet Data Import vào HTML. Các key format dùng giá trị CSS như #RRGGBB, px, số độ đậm, hoặc font-family.
A29: executiveTitleFontSize | B29: 20px | C29: Executive Format | D29: Cỡ chữ tiêu đề Executive Messages | E29: Sửa cột Value rồi import sheet Data Import vào HTML. Các key format dùng giá trị CSS như #RRGGBB, px, số độ đậm, hoặc font-family.
A30: executiveTitleFontWeight | B30: 900 | C30: Executive Format | D30: Độ đậm tiêu đề Executive Messages | E30: Sửa cột Value rồi import sheet Data Import vào HTML. Các key format dùng giá trị CSS như #RRGGBB, px, số độ đậm, hoặc font-family.
A31: executiveHeadingDetailGradient | B31: linear-gradient(90deg,#F04438,#F79009) | C31: Executive Format | D31: Màu/gradient phần thông tin nhấn sau dấu ':' trong Executive Messages | E31: Sửa cột Value rồi import sheet Data Import vào HTML. Các key format dùng giá trị CSS như #RRGGBB, px, số độ đậm, hoặc font-family.
A32: executiveHeadingDetailFontSize | B32: 14px | C32: Executive Format | D32: Cỡ chữ phần thông tin nhấn sau dấu ':' | E32: Sửa cột Value rồi import sheet Data Import vào HTML. Các key format dùng giá trị CSS như #RRGGBB, px, số độ đậm, hoặc font-family.
A33: executiveHeadingDetailFontWeight | B33: 600 | C33: Executive Format | D33: Độ đậm phần thông tin nhấn sau dấu ':' | E33: Sửa cột Value rồi import sheet Data Import vào HTML. Các key format dùng giá trị CSS như #RRGGBB, px, số độ đậm, hoặc font-family.
A34: executiveMessageTitleColor | B34: #B42318 | C34: Executive Format | D34: Màu chữ tiêu đề các thông điệp trọng tâm | E34: Sửa cột Value rồi import sheet Data Import vào HTML. Các key format dùng giá trị CSS như #RRGGBB, px, số độ đậm, hoặc font-family.
A35: executiveMessageTitleFontFamily | B35: Inter, Arial, sans-serif | C35: Executive Format | D35: Font chữ tiêu đề các thông điệp trọng tâm | E35: Sửa cột Value rồi import sheet Data Import vào HTML. Các key format dùng giá trị CSS như #RRGGBB, px, số độ đậm, hoặc font-family.
A36: executiveMessageTitleFontSize | B36: 15px | C36: Executive Format | D36: Cỡ chữ tiêu đề các thông điệp trọng tâm | E36: Sửa cột Value rồi import sheet Data Import vào HTML. Các key format dùng giá trị CSS như #RRGGBB, px, số độ đậm, hoặc font-family.
A37: executiveMessageTitleFontWeight | B37: 850 | C37: Executive Format | D37: Độ đậm tiêu đề các thông điệp trọng tâm | E37: Sửa cột Value rồi import sheet Data Import vào HTML. Các key format dùng giá trị CSS như #RRGGBB, px, số độ đậm, hoặc font-family.
A38: executiveMessageBodyColor | B38: #344054 | C38: Executive Format | D38: Màu chữ nội dung thông điệp trọng tâm | E38: Sửa cột Value rồi import sheet Data Import vào HTML. Các key format dùng giá trị CSS như #RRGGBB, px, số độ đậm, hoặc font-family.
... A51: importQualityStatusDone | B51: Done | C51: Import AI Check | D51: Trạng thái lỗi đã hết sau lần scan lại | E51: Sửa cột Value rồi import sheet Data Import vào HTML. Các key format dùng giá trị CSS như #RRGGBB, px, số độ đậm, hoặc font-family.

Sheet Module name
A1: Key | B1: Value | C1: Module | D1: Group | E1: Note | F1: Auto | G1: Auto Rule
A2: moduleNavLabel | B2: Menu báo cáo | C2: Thông tin chung | D2: Tên module | E2: Label thanh menu module | F2: INPUT
A3: moduleNav_executive | B3: Executive Messages | C3: Thông tin chung | D3: Tên module | E3: Tên tab module Executive Messages | F3: INPUT
A4: moduleNav_detailPortfolio | B4: Thông tin chi tiết Danh mục | C4: Thông tin chung | D4: Tên module | E4: Tên tab module Thông tin chi tiết Danh mục | F4: INPUT
A5: moduleNav_market | B5: Thông tin thị trường | C5: Thông tin chung | D5: Tên module | E5: Tên tab module Thông tin thị trường | F5: INPUT
A6: moduleNav_marketII | B6: Cơ cấu dòng tiền thanh khoản - Market II | C6: Thông tin chung | D6: Tên module | E6: Tên tab module Cơ cấu dòng tiền Market II | F6: INPUT
A7: moduleNav_import | B7: 🔒 Import Data | C7: Thông tin chung | D7: Tên module | E7: Tên tab module Import Data | F7: INPUT
A8: moduleNav_print | B8: In / PDF | C8: Thông tin chung | D8: Tên module | E8: Tên nút In / PDF trên thanh menu | F8: INPUT

Sheet Import module
A1: Key | B1: Value | C1: Module | E1: Note | F1: Auto
A2: moduleHeading_import | B2: Import Data | C2: Import Data | E2: Tiêu đề heading module Import Data | F2: INPUT
A3: moduleDesc_import | B3: Module dành cho Report Maker cập nhật dữ liệu đầu vào và đồng bộ lên giao diện báo cáo. | C3: Import Data | D3: Current HTML Value | E3: Mô tả heading module Import Data | F3: INPUT
A4: moduleImportBadge | B4: Report Maker | C4: Import Data | D4: 2. Tổng quan các nội dung rủi ro trọng yếu | E4: Badge heading module Import Data | F4: INPUT
A5: moduleImportDataTitle | B5: 7. Data Import - Cập nhật số liệu báo cáo | C5: Import Data | D5: Nội dung rủi ro | E5: Tiêu đề khối Data Import trong module Import | F5: INPUT
